Workbook

Sheet Matrice RISQUES (2)
L2: RISQUE
B3: 6 | C3: 12 | D3: 18 | E3: 24 | F3: 30 | G3: 36 | L3: Critique | M3: Le risque est jugé critique avec une qualité de contrôle interne non maitrisé (la situation est telle que les objectifs initiaux ne pourront vraisemblablement pas être atteints)
B4: 5 | C4: 10 | D4: 15 | E4: 20 | F4: 25 | G4: 30 | L4: Fort | M4: Le risque est jugé fort avec une qualité de contrôle interne insatisfaisant (des manquements et/ou défaillances sérieux existent qui pourraient mettre en danger le fait d’atteindre les objectifs)
B5: 4 | C5: 8 | D5: 12 | E5: 16 | F5: 20 | G5: 24 | L5: Moderé | M5: Risque jugé moderé avec une qualité de contrôle interne satisfaisante (système de contrôle interne globalement adéquat mais un certain nombre de constatations révèlent des faiblesses dans les contrôles. Ces constatations requièrent l’attention du management)
B6: 3 | C6: 6 | D6: 9 | E6: 12 | F6: 15 | G6: 18 | L6: Faible | M6: Risque jugé faible avec une qualité de contrôle interne très satisfaisant (Des possibilités d'améliorations existent, mais les faiblesses et défaillances constatées sont insignifiant)
B7: 2 | C7: 4 | D7: 6 | E7: 8 | F7: 10 | G7: 12
B8: 1 | C8: 2 | D8: 3 | E8: 4 | F8: 5 | G8: 6

Sheet Synthèse Exceptions & risqu (2
A2: N° | B2: PROCESSUS | C2: RATIO | D2: SOUS PROCESSUS | E2: Risques Majeurs | F2: gravité | G2: probabilité | H2: Risque Résiduel (Rb) | I2: Niveau de RISQUE
F3: G | G3: P | H3: est égal à GxP
A4: 1 | B4: Exploitation | C4: 0.2 | D4: Gestion clientèle (ouverture de compte, Remise chèque, Gestion opérationnelle des produits) | E4: - Identification du client (921 comptes sans Photo & 641 comptes sans signature dans le système NAFA) - Ouverture incomplète des comptes dans NAFA (531 comptes en instance d'ouverture) - Compte fermé ou à fermer (statut ''demande de cloture'') avec un solde non nul (21 comptes) - Non prelevement des frais sur les produits (Engagement par signature, ...) | F4: 4 | G4: 5 | H4: =+F4*G4 -> 20 | I4: CRITIQUE
D5: Octroi de crédit | E5: - Dossier de demande de crédit incomplet (Tous les dossiers de crédit du produit 3 en 1 établis sur la période de juin à aout étaient incomplet à la date de revue, pas de checklist des éléments composititifs du dossier, absence du plan de localisation du client, ...) - Octroi de crédit avec deblocage des fonds sans mise à disposition des fonds aux clients - Découverts non autorisés et forçage de compte (en dehors des lignes de crédits mis en place et des contrats d'avance sur chèques) - Baisse des marges d'interet (Meme Cible clientèle que les banques) | F5: 5 | G5: 5 | H5: =+F5*G5 -> 25 | I5: CRITIQUE
D6: Suivi du portefeuille | E6: - Modification de la structure initiale du crédit (rééchelonnement, restructuration, décalage d'échéance) non autorisée par les organes habilités - Non respect du niveau de Portefeuille A Risque (PAR) 0 | F6: 4 | G6: 4 | H6: =+F6*G6 -> 16 | I6: ELEVE
D7: Recouvrement | E7: Clients non correctement identifié et localisé (clients injoignables) - 243 clients injoignables | F7: 5 | G7: 5 | H7: =+F7*G7 -> 25 | I7: CRITIQUE
D8: EVALUATION EXPLOITATION | F8: =+ROUND(IFERROR(AVERAGE(F4:F7),0),0) -> 5 | G8: =+ROUND(IFERROR(AVERAGE(G4:G7),0),0) -> 5 | H8: =+F8*G8 -> 25 | I8: CRITIQUE
A9: 2 | B9: Risques crédit & suivi du portefeuille | C9: 0.2 | D9: Octroi de credit & Monitoring / Gestion du Portefeuille | E9: - Erreur d'analyse dans l'étude des dossiers des crédits (Pas de senior analyste crédit, ) - Non réalisation systématique des visites et contre-visite terrain permettant de localiser l'activité ou le domicile du client, de constater visuellement l'existence des biens présentés en garantie et d'évaluer la capacité de remboursement du client - Dossier restructuré tombé en impayé | F9: 5 | G9: 5 | H9: =+F9*G9 -> 25 | I9: CRITIQUE
D10: Gestion des impayés & Pré-Contentieux | E10: Non respect des niveaux de PAR (30, 90, 180) | F10: 5 | G10: 5 | H10: =+F10*G10 -> 25 | I10: CRITIQUE
D11: EVALUATION RISQUE & SUIVI DU PORTEFEUILLE | F11: =+ROUND(IFERROR(AVERAGE(F9:F10),0),0) -> 5 | G11: =+ROUND(IFERROR(AVERAGE(G9:G10),0),0) -> 5 | H11: =+F11*G11 -> 25 | I11: CRITIQUE
A12: 3 | B12: Système d'information | C12: 0.15 | D12: Gestion des systèmes | E12: Indisponibilité du SI et défaillances SI (dysfonctionnement) identifiées non corrigées | F12: 5 | G12: 4 | H12: =+F12*G12 -> 20 | I12: CRITIQUE
D13: Gestion des changements Système et Réseau | E13: Non respect de la procédure des changements, des configurations et des mises en production (Un changement consiste à modifier, créer ou supprimer un des composants de l'infrastructure du système d'information) | F13: 4 | G13: 3 | H13: =+F13*G13 -> 12 | I13: ELEVE
D14: Gestion des comptes et habilitations | E14: Accès non autorisé et inadéquation des accès à la fonction ou poste occupé (Profil CC peut faire des decalages) | F14: 4 | G14: 3 | H14: =+F14*G14 -> 12 | I14: ELEVE
D15: Administration des bases de données | E15: - Corruption de la base de données - Non sauvegarde des données et pas de site de secours | F15: 4 | G15: 5 | H15: =+F15*G15 -> 20 | I15: CRITIQUE
D16: EVALUATION SYSTEME D'INFORMATION | F16: =+ROUND(IFERROR(AVERAGE(F12:F15),0),0) -> 4 | G16: =+ROUND(IFERROR(AVERAGE(G12:G15),0),0) -> 4 | H16: =+F16*G16 -> 16 | I16: ELEVE
A17: 4 | B17: Opérations | C17: 0.15 | D17: Opération de caisse | E17: - Non réalisation du pointage systèmatique des tickets de caisses et de l'inventaire des espèces quotidiennement par un staff autre que le caissier lui-même. - Dépassement de la limite d'encaisse journalière autorisée - daily overnight limit - Rechargement fictif des cartes prépayées dans la plateforme - Différence de caisse | F17: 4 | G17: 4 | H17: =+F17*G17 -> 16 | I17: ELEVE
D18: Back office Opérations | E18: - Comptabilisation des remises chèques sans attendre le sort définitif du chèque par la banque - Non comptabilisation des fiches d'imputations comptables et/ou erreur d'imputation des fiches comptables, des mise en place de prets, des virements reçus et des remises chèques sur les comptes appropriés du bon montant déterminé - Non établissement des reconciliations des commissions de transferts d'argent et/ou non comptabilisation des commissions de transferts - Non établissement des états de rapprochements bancaires périodiques | F18: 4 | G18: 4 | H18: =+F18*G18 -> 16 | I18: ELEVE
D19: EVALUATION OPERATION | F19: =+ROUND(IFERROR(AVERAGE(F17:F18),0),0) -> 4 | G19: =+ROUND(IFERROR(AVERAGE(G17:G18),0),0) -> 4 | H19: =+F19*G19 -> 16 | I19: ELEVE
A20: 5 | B20: Finance & reporting | C20: 0.15 | D20: Arrêté & clôture périodique comptable | E20: - Longs suspens de plus de 90 jours sur les comptes internes et les rapprochements bancaires - Non justification des opérations comptabilisées dans le système par des pièces probantes - Déséquilibre de la balance à une date d'arrêté donnée - Absence de calcul et de comptabilisation de la réévaluation de la position de change Arrêté & clôture périodique comptable | F20: 5 | G20: 5 | H20: =+F20*G20 -> 25 | I20: CRITIQUE
D21: Reporting financier (groupe - bailleurs) / Règlementaire (Tutelle-DRS-BCEAO-COBAC-BCRG) | E21: - Sanctions règlementaires du fait du non respect systématique des normes de gestion (limitation des risques, couverture des emplois, limitation des prêts aux dirigeants, limitation des risques par signature, coefficient de liquidité, constitution de la réserve générale, capitalisation,....) du dispositif prudentiel instaurées par l'Institution - Non automatisation des reporting reglementaire, financier et métier | F21: 4 | G21: 2 | H21: =+F21*G21 -> 8 | I21: MODERE
D22: Fiscalité | E22: - Absence ou retard de déclaration/paiement des impots, taxes et redevances et/ou erreur de calcul dans la détermination des impots, taxes et redevances à payer - Redressement fiscal et social | F22: 4 | G22: 3 | H22: =+F22*G22 -> 12 | I22: ELEVE
D23: Trésorerie / ALM | E23: Risque de liquidité, de taux d'intéret et de taux de change et respect des ratios reglementaires | F23: 5 | G23: 3 | H23: =+F23*G23 -> 15 | I23: ELEVE
D24: EVALUATION FINANCE & REPORTING | F24: =+ROUND(IFERROR(AVERAGE(F20:F23),0),0) -> 5 | G24: =+ROUND(IFERROR(AVERAGE(G20:G23),0),0) -> 3 | H24: =+F24*G24 -> 15 | I24: ELEVE
A25: 6 | B25: Gouvernance & Contrôle interne (Gouv & CI) | C25: 0.05 | D25: Gouvernance | E25: - Non respecte des dispositions légales et Réglementaires relatives à la gouvernance (Respect de la loi sur les microfinances, des instructions, des statuts) - Conformité des statuts avec la législation - Bon fonctionnement des organes d'administration et de direction et de contrôle | F25: 4 | G25: 4 | H25: =+F25*G25 -> 16 | I25: ELEVE
D26: Contrôle interne | E26: - Existance, accessibilité et Connaissance des politiques et procédures écrites en vigueur - Bonne séparation des taches (maker & checker) - Réalisation systématique des contrôle de premier niveau - Politique de lutte antiblanchiment - Mise en place et fonctionnement d'un comité d'audit - Cartographie des risques (identification et cotation des risques inhérents, évaluation du contrôle interne, cotation des risques résiduels) | F26: 4 | G26: 4 | H26: =+F26*G26 -> 16 | I26: ELEVE
D27: EVALUATION CI & GOUVERNANCE | F27: =+ROUND(IFERROR(AVERAGE(F25:F26),0),0) -> 4 | G27: =+ROUND(IFERROR(AVERAGE(G25:G26),0),0) -> 4 | H27: =+F27*G27 -> 16 | I27: ELEVE
A28: 7 | B28: Juridique & contentieux | C28: 0.05 | D28: Gestion du Contentieux | E28: Non utisation de tous les recours contentieux et Pilotage, suivi inapproprié de la performance reporting Recouvrement en raison d'une absence de tableaux de bord et d'indicateurs dédiés au suivi formel du recouvrement | F28: 3 | G28: 3 | H28: =+F28*G28 -> 9 | I28: MODERE
D29: Gestion des contrats et Etudes juridiques | E29: Modification abusive ou non autorisée des contrats de crédit par les entités opérationnelles et/ou contrat non établi ou vérifié par le juridique | F29: 5 | G29: 2 | H29: =+F29*G29 -> 10 | I29: MODERE
D30: Gestion des garanties | E30: Impossibilité d'exécuter la garantie entièrement en cas de besoin : Non mise à jour des valeurs des garanties en raison d'une détérioration normale et/ou de sinistre impactant de manière significative la valeur de l'actif (incendie, dégât des eaux, etc.), mauvaise localisation du bien garanti, immeubles construits sur des titres précaires, perte d'emploi pour des particuliers salariés, garantie pris sur des actifs non éligibles par la règlementation | F30: 3 | G30: 2 | H30: =+F30*G30 -> 6 | I30: MODERE
D31: Gestion des Avis à Tiers Détenteur ou ATD, des saisies attributions et saisies conservatoires | E31: Traitement inapproprié ou hors délai des Avis à Tiers Détenteur ou ATD, des saisies attributions et saisies conservatoires | F31: 3 | G31: 2 | H31: =+F31*G31 -> 6 | I31: MODERE
D32: EVALUATION JURIDIQUE & CONTENTIEUX | F32: =+ROUND(IFERROR(AVERAGE(F28:F31),0),0) -> 4 | G32: =+ROUND(IFERROR(AVERAGE(G28:G31),0),0) -> 2 | H32: =+F32*G32 -> 8 | I32: MODERE
A33: 8 | B33: Ressources Humaines | C33: 0.025 | D33: Gestion administrative du personnel & Affaires sociales | E33: - Dossier du personnel incomplet - Non respect des obligations légales en matière de santé et sécurité au travail et des engagements de l’organisation | F33: 4 | G33: 3 | H33: =+F33*G33 -> 12 | I33: ELEVE
D34: Politique de rémunération et Paie | E34: - Non-conformité règlementaire des traitements salariaux - Non justification des variations de la masse salariale (modifications frauduleuses des données de la paie, Erreur de calcul ou d'imputation des salaires, écart sur paiement des salaires) - Non détermination des provisions pour congé et retraite et/ou non comptabilisations des provisions pour congé et retraite - Absence de déclarations fiscales et sociales et/ou erreur dans les déclarations fiscales et sociales liées à la paie - Absence d'un outil de gestion de la paie | F34: 4 | G34: 3 | H34: =+F34*G34 -> 12 | I34: ELEVE
D35: Appréciation des performance - Evaluation | E35: - Non respect du processus d'évaluation - Non évaluation des staffs et/ou Critères d’évaluation non définis ou non adéquats - Evaluation non objective | F35: 3 | G35: 4 | H35: =+F35*G35 -> 12 | I35: ELEVE
D36: EVALUATION RH | F36: =+ROUND(IFERROR(AVERAGE(F33:F35),0),0) -> 4 | G36: =+ROUND(IFERROR(AVERAGE(G33:G35),0),0) -> 3 | H36: =+F36*G36 -> 12 | I36: ELEVE
A37: 9 | B37: Administration, Achats & Logistique | C37: 0.025 | D37: Planification & Administration des achats | E37: - Non respect de la politique d'achat - Réalisation de dépenses non-autorisées - Absence ou Pertes de pièces jusificatives des achats (Non justification des achats) | F37: 3 | G37: 3 | H37: =+F37*G37 -> 9 | I37: MODERE
D38: Logistique & moyens généraux | E38: - Perte / vol / et dégradation du patrimoine immobilier, mobilier et consommables - Inadequation des systèmes de sécurité incendie et absence de plan d'évacuation des locaux | F38: 3 | G38: 3 | H38: =+F38*G38 -> 9 | I38: MODERE
D39: Gestion administrative | E39: Perte de valeurs et de courriers due à une conservation ou un mode d'acheminement ou un traitement inapproprié | F39: 3 | G39: 3 | H39: =+F39*G39 -> 9 | I39: MODERE
D40: EVALUATION ACHAT LOGISTIQUE | F40: =+ROUND(IFERROR(AVERAGE(F37:F39),0),0) -> 3 | G40: =+ROUND(IFERROR(AVERAGE(G37:G39),0),0) -> 3 | H40: =+F40*G40 -> 9 | I40: MODERE
C42: =+SUM(C4:C40) -> 1 | D42: EVALUATION GLOBALE - NOTE FINALE | F42: =ROUND(+F8*$C4+F11*$C9+F24*$C20+F16*$C12+F19*$C17+F40*$C37+F36*$C33+F32*$C28+F27*$C25,0) -> 5 | G42: =ROUND(+G8*$C4+G11*$C9+G24*$C20+G16*$C12+G19*$C17+G40*$C37+G36*$C33+G32*$C28+G27*$C25,0) -> 4 | H42: =+G42*F42 -> 20 | I42: CRITIQUE
C44: =+SUM(C4:C25) -> 0.9 | D44: EVALUATION GLOBALE - NOTE FINALE | F44: =ROUND(IFERROR(AVERAGE(F4:F7)*$C4,0)+IFERROR(AVERAGE(F9:F10)*$C9,0)+IFERROR(AVERAGE(F20:F23)*$C20,0)+IFERROR(AVERAGE(F12:F15)*$C12,0)+IFERROR(AVERAGE(F17:F18)*$C17,0),+IFERROR(AVERAGE(F37:F39)*$C37,0)+IFERROR(AVERAGE(F33:F35)*$C33,0)+IFERROR(AVERAGE(F28:F31)*$C28,0)+IFERROR(AVERAGE(F25:F26)*$C25,0)*0) -> 4 | G44: =ROUND(IFERROR(AVERAGE(G4:G7)*$C4,0)+IFERROR(AVERAGE(G9:G10)*$C9,0)+IFERROR(AVERAGE(G20:G23)*$C20,0)+IFERROR(AVERAGE(G12:G15)*$C12,0)+IFERROR(AVERAGE(G17:G18)*$C17,0),+IFERROR(AVERAGE(G37:G39)*$C37,0)+IFERROR(AVERAGE(G33:G35)*$C33,0)+IFERROR(AVERAGE(G28:G31)*$C28,0)+IFERROR(AVERAGE(G25:G26)*$C25,0)*0) -> 4 | H44: =+G44*F44 -> 16

Sheet DASHBOARD

Sheet HOME

Sheet Définition & Objectifs

Sheet Préambule

Sheet Principes
B2: PRINCIPES | C2: ENONCE DU PRINCIPE | D2: EXPLICATIONS
B3: Principe 1 | C3: Objectivité et rationnalité de l'évaluation des risques | D3: Un exercice de cette nature expose naturellement les acteurs à un risque d'erreur de jugement ou d'appréciation sur l'analyse du risque. Ce biais peut être lié à des facteurs personnels ou psychologiques (syndrome "alarmiste" ou "paranoïaque") ou à un élément de l'environnement interne ("conflits internes et considérations crypto-personnelles"). Les fiches d'évaluation prévoient un champ "Commentaires" permettant à l'évaluateur (ou groupe d'évaluateurs) de justifier ses évaluations jugées extrêmes (entre 5 et 6).
B4: Principe 2 | C4: Objectif de l'évaluation (évaluation du risque inhérent ou risque brut et de la maturité des contrôles) | D4: Dans le cadre de cet atelier, il vous est demandé de procéder d'une part à l'évaluation des risques inhérents (risques bruts) c'est-à-dire de faire fi des dispositifs de contrôle en vigueur. L'évaluation du risque inhérent permet d'appréhender de manière globale l'exposition de la filiale sur les différents process cible.
B5: Principe 3 | C5: Principe de corrélation de l'évaluation des risques avec les objectifs stratégiques et opérationnels | D5: Il est demandé à chaque évaluateur de procéder à cette exercice en corrélation avec les objectifs opérationnels de ses processus ou sous processus
B6: Principe 4 | C6: Probabilité du risque est différente de la fréquence de survenance de l'incident | D6: Un risque jamais survenu peut présenter une probabilité de survenance élevée et vice-versa. L'évaluateur devra donc avoir à l'esprit que les facteurs rendant possibles la survenance du risque.
B7: Principe 5 | C7: Evaluation de la gravité | D7: L’appréciation de la gravité est une estimation très fine des impacts supposés de la survenance du risque sur la réalisation des objectifs de l’organisation. Il conviendra de ne pas surestimer des risques dont les impacts ne seraient que « locaux ». De même, il faudra veiller à ne pas sous estimer des risques dont l'impact est plus général. L'exercice d'évaluation requiert un élargissement de la perspective au-delà de votre simple domaine (direction, cellule, process, activité).

Sheet Echelle P & G
A1: CRITERE DE QUANTIFICATION DE LA PROBABILITE D'OCCURRENCE ET DE L'IMPACT DU RISQUE OPERATIONNEL
A2: Gravité | B2: Qualification de l'échelle | C2: Explication de l'échelle de gravité
A3: 1 | B3: Inoffensif (aucun impact) | C3: Ne présente aucune forme d'impact sur l'activité ou les objectifs
A4: 2 | B4: Faible impact | C4: Un niveau d'impact sur les activités ou les objectifs stratégiques ou opérationnels est perceptible mais ne gêne pas le déroulement des opérations
A5: 3 | B5: Impact sérieux sur process secondaires | C5: Des niveaux d'impact circonscris à des processus (importants mais non critiques ont été notés. Il s'agit de processus non liés directement à la qualité de service
A6: 4 | B6: Impact sérieux sur process métiers | C6: Il s'agit soit de processus critiques fortement impactées et de manière durable. soit de désagréments perceptibles en interne ou par le membre sur des processus liés directement à la qualité de service
A7: 5 | B7: Fort impact (généralisé) | C7: Niveau de risque impactant de manière significative et durable l'ensemble des activités du l'entité ainsi que ses objectifs stratégiques et opérationnels
A8: 6 | B8: Crise majeure / Arrêt de l'exploitation | C8: Niveau de risque impactant de manière absolue et durable la continuité de l'activité et autres processus critiques de l'entité
A11: Probabilité | B11: Qualification de l'échelle | C11: Explication de l'échelle de probabilité
A12: 1 | B12: Quasi impossible | C12: Ce niveau de l'échelle correspond au risque pour lesquels aucun facteur indiquant une possible survenance n'a été identifiée ni au niveau interne, ni externe
A13: 2 | B13: Eventuelle / possible | C13: Le risque est plausible et, un ou des facteurs internes ou externes le rendent tout à fait réalisable
A14: 3 | B14: Vraisemblable | C14: Plusieurs facteurs précis ont été identifiés au niveau interne ou externe favorisant la survenance du risque. Par exemple, une vague de démissions au niveau du support informatique doublée ou non d'une augmentation exponentielle du nombre de sollicitations par les membres rendra assez probable le risque de dégradation de la qualité du support (qualité des traitements, délai de résolution des problèmes, etc.)
A15: 4 | B15: Probable | C15: Un nombre important de facteurs potentiels ont été identifiés au niveau interne ou externe favorisant la survenance du risque. Par exemple, une vague de démissions au niveau du support informatique + une augmentation exponentielle du nombre de sollicitations par les services + dégradation des outils de traitement + démotivation + etc. rendra extrêmement probable le risque de dégradation de la qualité du support (qualité des interventions, délai de résolution des problèmes, etc.). Les facteurs indiquent une survenance qui pourrait être différée.
A16: 5 | B16: Hautement probable | C16: Ce niveau de risque correspond à l'identification de plusieurs signes confirmés qui indiquent une survenance probable et imminente
A17: 6 | B17: Evènement certain | C17: Aucun doute sur la survenance du risque. Tout indique que le risque se réalisera de manière certaine. Toutes les conditions sont réunies pour que le risque survienne à tout moment.

Sheet Echelle de contrôle
B3: Niveau de l'échelle | C3: Qualification de l'échelle | D3: Explicitation de l'échelle | E3: Maturité du contrôle
B4: 1 | C4: Initial | D4: Dispositif de contrôle jugé "embryonnaire" | E4: Inexistant
B5: 2 | C5: Aléatoire | D5: Pratique de contrôle identifié mais présentant un caractère aléatoire et fortement conditionné par la disponibilité et la volonté de certaines individualités (prépondérance du facteur humain) | E5: Informel
B6: 3 | C6: Opérationnel | D6: Contrôle opérationnel et mis en œuvre manuellement ou de manière semi-automatique, conceptuellement satisfaisant mais ne présentant aucune garantie de mise en œuvre | E6: Opérationnel
B7: 4 | C7: Standardisé | D7: Dispositf de contrôle indépendant du facteur humain, testé périodiquement avec des résultats globalement concluants et un système d'archivage des preuves assurant une parfaite traçabilité des tests | E7: Standardisé
B8: 5 | C8: Optimisé | D8: Contrôle paramétré de manière automatique ne nécessitant pas d'intervention humaine. Un contrôle des paramètres est néanmoins effectué suivant une périodicité définie (contrôles de type applicatif ou "embarqué" par un SI) | E8: Optimisé

Sheet Matrice RISQUES
L2: Lexique
B3: 6 | C3: 12 | D3: 18 | E3: 24 | F3: 30 | G3: 36 | L3: Critique | M3: Le risque est jugé critique (la situation est tellement grave que l'organisation est face à la faillite ou à une dégradation accrue de sa réputation ou image)
B4: 5 | C4: 10 | D4: 15 | E4: 20 | F4: 25 | G4: 30 | L4: Très Elevé | M4: Le risque est jugé très élevé (des fraudes sérieuses existent telles que les objectifs initiaux ne pourront vraisemblablement pas être atteints)
B5: 4 | C5: 8 | D5: 12 | E5: 16 | F5: 20 | G5: 24 | L5: Elevé | M5: Le risque est jugé élevé (des manquements et/ou défaillances sérieux existent qui pourraient mettre en danger le fait d’atteindre les objectifs)
B6: 3 | C6: 6 | D6: 9 | E6: 12 | F6: 15 | G6: 18 | L6: Moderé | M6: Risque jugé moderé (un certain nombre de constatations révèlent des faiblesses dans les contrôles. Ces constatations requièrent l’attention du management)
B7: 2 | C7: 4 | D7: 6 | E7: 8 | F7: 10 | G7: 12 | L7: Faible | M7: Risque jugé faible (Des possibilités d'améliorations existent, mais les faiblesses et défaillances constatées sont insignifiants)
B8: 1 | C8: 2 | D8: 3 | E8: 4 | F8: 5 | G8: 6 | L8: Non significatif | M8: Risque jugé insignifiant par rapport aux process métier

Sheet Constats Détaillés
A2: N° | B2: PROCESSUS | C2: RATIO | D2: SOUS PROCESSUS | E2: RISQUES | F2: gravité | G2: probabilité | H2: Risque Résiduel (Rb)
F3: G | G3: P | H3: est égal à GxP
A4: 1 | B4: Exploitation | C4: 0.25 | D4: Gestion clientèle (ouverture de compte, Remise chèque, Gestion opérationnelle des produits) | E4: Dossier d'ouverture de compte clientèle incomplet et/ou mauvaise identification du client | H4: =+F4*G4 -> 0
E5: Absence des signatures et photos scannées des clients dans le système NAFA | H5: =+F5*G5 -> 0
E6: Mauvaise gestion opérationnelle des produits (Non prelevement de frais, non traitement des requetes clients) | H6: =+F6*G6 -> 0
D7: Octroi de crédit | E7: Dossier de demande de crédit incomplèt et/ou contenant des pièces non authentiques | H7: =+F7*G7 -> 0
E8: Non respect des limites des comités de crédits et des seniors credit officers | H8: =+F8*G8 -> 0
E9: Mauvaise évaluation de la capacité de remboursement (capacité financière) du client et/ou mauvaise identification du besoin du client | H9: =+F9*G9 -> 0
E10: Découverts non autorisés et forçage de comptes | H10: =+F10*G10 -> 0
D11: Suivi du portefeuille | E11: Non évaluation du portefeuille à risque (PAR) et/ou évaluation erronée à travers une sous estimation du PAR | H11: =+F11*G11 -> 0
E12: Modification de la structure initiale du crédit (Rééchelonnement, restructuration, décalage d'échéance) non autorisée par les organes habilétés | H12: =+F12*G12 -> 0
D13: Recouvrement | E13: Clients non correctement identifié et localisé (clients injoignables) | H13: =+F13*G13 -> 0
E14: Détournement des recouvrements de créances par les agents en charge du recouvrement | H14: =+F14*G14 -> 0
D15: EVALUATION EXPLOITATION | F15: =+ROUND(IFERROR(AVERAGE(F4:F14),0),0) -> 0 | G15: =+ROUND(IFERROR(AVERAGE(G4:G14),0),0) -> 0 | H15: =+F15*G15 -> 0
A16: 2 | B16: Risques & suivi du portefeuille | C16: 0.2 | D16: Monitoring / Gestion du Portefeuille | E16: Risque de contrepartie due à la méconnaissance de la situation globale du client par les analystes risques (total des engagements, cautions, absence d'analyse sectorielle, situation financière du client, etc.) | H16: =+F16*G16 -> 0
D17: Monitoring / Gestion du Portefeuille | E17: Dossier restructuré tombé en impayé | H17: =+F17*G17 -> 0
D18: Gestion des impayés & Pré-Contentieux | E18: Non respect des niveaux de PAR (30, 90, 180) | H18: =+F18*G18 -> 0
D19: EVALUATION RISQUE & SUIVI DU PORTEFEUILLE | F19: =+ROUND(IFERROR(AVERAGE(F16:F18),0),0) -> 0 | G19: =+ROUND(IFERROR(AVERAGE(G16:G18),0),0) -> 0 | H19: =+F19*G19 -> 0
A20: 4 | B20: Finance & reporting | C20: 0.15 | D20: Contrôle de gestion | E20: Non justification des écarts budgétaires et/ou mauvaise analyse desdits écarts - les entités opérationnelles (directions, services, agence et siège) ne procèdent pas à des analyses de fond mais s'inscrivent plus dans une logique de justification sans entrer dans une dynamique de plans d'actions correctifs. La non mise en œuvre des actions arrêtées en M-1 ne sont pas expliquées. | H20: =+F20*G20 -> 0
D21: Arrêté & clôture comptable | E21: Non justification des soldes des comptes internes (y compris soldes bancaires) à une date d'arrêté donnée (Non établissement des proofs et/ou proofs mal établis ou proofs présentant des écarts de rapprochement non justifiés) | H21: =+F21*G21 -> 0
D22: Arrêté & clôture comptable | E22: Longs suspens de plus de 90 jours sur les comptes internes et les rapprochements bancaires | H22: =+F22*G22 -> 0
D23: Arrêté & clôture comptable | E23: Non justification des opérations comptabilisées dans le système par des pièces probantes | H23: =+F23*G23 -> 0
D24: Arrêté & clôture comptable | E24: Déséquilibre de la balance à une date d'arrêté donnée | H24: =+F24*G24 -> 0
D25: Arrêté & clôture comptable | E25: Absence de calcul et de comptabilisation de la réévaluation de la position de change à la date de clôture | H25: =+F25*G25 -> 0
D26: Reporting financier (groupe - bailleurs) / Règlementaire (Tutelle-DRS-BCEAO-COBAC-BCRG) | E26: Sanctions règlementaires du fait du non respect systématique des normes de gestion (limitation des risques, couverture des emplois, limitation des prêts aux dirigeants, limitation des risques par signature, coefficient de liquidité, constitution de la réserve générale, capitalisation,....) du dispositif prudentiel instaurées par l'Institution | H26: =+F26*G26 -> 0
D27: Fiscalité | E27: Absence ou retard de déclaration/paiement des impots, taxes et redevances et/ou erreur de calcul dans la détermination des impots, taxes et redevances à payer | H27: =+F27*G27 -> 0
D28: Trésorerie / ALM | E28: Risque de liquidité de taux et de change et respect des ratios reglementaires | H28: =+F28*G28 -> 0
D29: EVALUATION FINANCE & REPORTING | F29: =+ROUND(IFERROR(AVERAGE(F20:F28),0),0) -> 0 | G29: =+ROUND(IFERROR(AVERAGE(G20:G28),0),0) -> 0 | H29: =+F29*G29 -> 0
A30: 3 | B30: Système d'information | C30: 0.1 | D30: Gestion des systèmes | E30: Indisponibilité du SI et défaillances SI (dysfonctionnement) identifiées non corrigées | H30: =+F30*G30 -> 0
D31: Gestion des changements Système et Réseau | E31: Non respect de la procédure des changements, des configurations et des mises en production (Un changement consiste à modifier, créer ou supprimer un des composants de l'infrastructure du système d'information) | H31: =+F31*G31 -> 0
D32: Gestion des comptes et habilitations | E32: Accès non autorisé et inadéquation des accès à la fonction ou poste occupé | H32: =+F32*G32 -> 0
D33: Gestion du parc & Maintenance physique et système | E33: Absence d'inventaire physique périodique du parc informatique et de maintenance dudit parc | H33: =+F33*G33 -> 0
D34: Administration des bases de données | E34: Risque de perte de données d'exploitation liée à la non sauvegarde des données et pas de site de secours | H34: =+F34*G34 -> 0
E35: Risque de corruption de la base de données | H35: =+F35*G35 -> 0
E36: Risque de non fonctionnement des serveurs de base de données tant au niveau de la conception des bases, des tests de validation, de la coordination des intervenants, de l'exploitation, de la protection et du contrôle d'utilisation | H36: =+F36*G36 -> 0
D37: Sécurité logique et accès physiques des systèmes d'information | E37: Les utilisateurs non identifiés peuvent faire des changements non autorisés dans les programmes et les données | H37: =+F37*G37 -> 0
E38: Transactions non autorisées par les utilisateurs dont l’accès n’a pas été authentifié | H38: =+F38*G38 -> 0
D39: Gestion des incidents | E39: Diagnostic des incidents non réalisé ou réalisé tardivement et Clôture d'un incident non résolu | H39: =+F39*G39 -> 0
D40: EVALUATION SYSTEME D'INFORMATION | F40: =+ROUND(IFERROR(AVERAGE(F30:F39),0),0) -> 0 | G40: =+ROUND(IFERROR(AVERAGE(G30:G39),0),0) -> 0 | H40: =+F40*G40 -> 0
A41: 5 | B41: Opérations | C41: 0.1 | D41: Opération de caisse | E41: Non réalisation du pointage systèmatique des tickets de caisses et de l'inventaire des espèces quotidiennement par un staff autre que le caissier lui-même. | H41: =+F41*G41 -> 0
D42: Opération de caisse | E42: Signature non conforme et retrait non autorisé (sans ordre de retrait dument signé conforme par le client) | H42: =+F42*G42 -> 0
D43: Opération de caisse | E43: Dépassement de la limite d'encaisse journalière autorisée - daily overnight limit | H43: =+F43*G43 -> 0
D44: Opération de caisse | E44: Rechargement fictif des cartes prépayées dans la plateforme | H44: =+F44*G44 -> 0
D45: Opération de caisse | E45: Envois fictifs dans les plateforme de transferts d'argent | H45: =+F45*G45 -> 0
D46: Opération de caisse | E46: Conservation des fonds et transport (convoyage) des fonds | H46: =+F46*G46 -> 0
D47: Back office Opérations | E47: Non établissement des états de rapprochements bancaires | H47: =+F47*G47 -> 0
D48: Back office Opérations | E48: Remise Chèque rejetée par la banque du tiré avec un crédit effectif sur le compte du client bénéficiaire dans nos livres | H48: =+F48*G48 -> 0
D49: Back office Opérations | E49: Non établissement des reconciliations des commissions de transferts d'argent et/ou non comptabilisation des commissions de transferts | H49: =+F49*G49 -> 0
D50: Back office Opérations | E50: Comptabilisation d'opération dans NAFA ou les plateforme de cartes magnétiques sans support comptable probant (Pas de pièce justificatives des transactions) | H50: =+F50*G50 -> 0
D51: Back office Opérations | E51: Non comptabilisation des fiches d'imputations comptables et/ou erreur d'imputation des fiches comptables, des mise en place de prets, des virements reçus et des remises chèques sur les comptes appropriés du bon montant déterminé | H51: =+F51*G51 -> 0
D52: EVALUATION OPERATION | F52: =+ROUND(IFERROR(AVERAGE(F41:F51),0),0) -> 0 | G52: =+ROUND(IFERROR(AVERAGE(G41:G51),0),0) -> 0 | H52: =+F52*G52 -> 0
A53: 6 | B53: Administration, Achats & Logistique | C53: 0.05 | D53: Planification & Administration des achats | E53: Réalisation de dépenses non-autorisées | H53: =+F53*G53 -> 0
E54: Risque de pertes de pièces jusificatives des achats ou d'absence des pièces justificatives | H54: =+F54*G54 -> 0
D55: Logistique & moyens généraux | E55: Perte / vol / et dégradation du patrimoine immobilier, mobilier et consommables | H55: =+F55*G55 -> 0
E56: Inadequation des systèmes de sécurité incendie et absence de plan d'évacuation des locaux | H56: =+F56*G56 -> 0
D57: Gestion administrative | E57: Perte de courrier (notamment des valeurs) due à une conservation ou un mode d'acheminement ou un traitement inapproprié | H57: =+F57*G57 -> 0
D58: EVALUATION ACHAT LOGISTIQUE | F58: =+ROUND(IFERROR(AVERAGE(F53:F57),0),0) -> 0 | G58: =+ROUND(IFERROR(AVERAGE(G53:G57),0),0) -> 0 | H58: =+F58*G58 -> 0
A59: 7 | B59: Ressources Humaines | C59: 0.05 | D59: Gestion administrative du personnel & Affaires sociales | E59: Dossier du personnel incomplet | H59: =+F59*G59 -> 0
D60: Gestion administrative du personnel & Affaires sociales | E60: Non-respect des obligations légales en matière de santé et sécurité au travail et des engagements de l’organisation | H60: =+F60*G60 -> 0
D61: Politique de rémunération et Paie | E61: Non-conformité règlementaire dans la détermination des salaires | H61: =+F61*G61 -> 0
D62: Politique de rémunération et Paie | E62: Non justification des variations de la masse salariale (modifications frauduleuses des données de la paie, Erreur de calcul ou d'imputation des salaires, écart sur paiement des salaires) | H62: =+F62*G62 -> 0
D63: Politique de rémunération et Paie | E63: Non détermination des provisions pour congé et retraite et/ou non comptabilisations des provisions pour congé et retraite | H63: =+F63*G63 -> 0
D64: Politique de rémunération et Paie | E64: Absence de déclarations fiscales et sociales et/ou erreur dans les déclarations fiscales et sociales liées à la paie | H64: =+F64*G64 -> 0
D65: Politique de rémunération et Paie | E65: Elaboration manuel de la paie (Paie traité sur fichier Excel) | H65: =+F65*G65 -> 0
D66: Appréciation des performance - Evaluation | E66: Non évaluation des staffs et/ou Critères d’évaluation non définis ou non adéquats | H66: =+F66*G66 -> 0
D67: Appréciation des performance - Evaluation | E67: Processus d'évaluation non respecté et/ou évaluation non objective | H67: =+F67*G67 -> 0
D68: EVALUATION ACHAT LOGISTIQUE | F68: =+ROUND(IFERROR(AVERAGE(F59:F67),0),0) -> 0 | G68: =+ROUND(IFERROR(AVERAGE(G59:G67),0),0) -> 0 | H68: =+F68*G68 -> 0
A69: 8 | B69: Juridique & contentieux | C69: 0.05 | D69: Gestion du Contentieux | E69: Non utisation de tous les recours contentieux et Pilotage, suivi inapproprié de la performance reporting Recouvrement en raison d'une absence de tableaux de bord et d'indicateurs dédiés au suivi formel du recouvrement | H69: =+F69*G69 -> 0
D70: Gestion des contrats et Etudes juridiques | E70: Modification abusive ou non autorisée des contrats de crédit par les entités opérationnelles et/ou contrat non établi ou vérifié par le juridique | H70: =+F70*G70 -> 0
D71: Gestion des garanties | E71: Impossibilité d'exécuter la garantie entièrement en cas de besoin : Non mise à jour des valeurs des garanties en raison d'une détérioration normale et/ou de sinistre impactant de manière significative la valeur de l'actif (incendie, dégât des eaux, etc.), mauvaise localisation du bien garanti, immeubles construits sur des titres précaires, perte d'emploi pour des particuliers salariés, garantie pris sur des actifs non éligibles par la règlementation | H71: =+F71*G71 -> 0
D72: Gestion des Avis à Tiers Détenteur ou ATD | E72: Traitement inapproprié ou hors délai des Avis à Tiers Détenteur ou ATD | H72: =+F72*G72 -> 0
D73: Gestion des Saisies Attribution | E73: Traitement inapproprié ou hors délai des Saisies Attribution | H73: =+F73*G73 -> 0
D74: Gestion des saisies conservatoires | E74: Traitement inapproprié ou hors délai des saisies conservatoires | H74: =+F74*G74 -> 0
D75: EVALUATION ACHAT LOGISTIQUE | F75: =+ROUND(IFERROR(AVERAGE(F69:F74),0),0) -> 0 | G75: =+ROUND(IFERROR(AVERAGE(G69:G74),0),0) -> 0 | H75: =+F75*G75 -> 0
A76: 9 | B76: Communication & Marketing | C76: 0.05 | D76: Communication | E76: Risque réputationnel et communication d'informations erronées | H76: =+F76*G76 -> 0
D77: Marketing & Produits | E77: Non respect du catalogue produit et non mise à jour dudit catalogue des nouveaux produits autorisés | H77: =+F77*G77 -> 0
D78: EVALUATION ACHAT LOGISTIQUE | F78: =+ROUND(IFERROR(AVERAGE(F76:F77),0),0) -> 0 | G78: =+ROUND(IFERROR(AVERAGE(G76:G77),0),0) -> 0 | H78: =+F78*G78 -> 0
C80: =+SUM(C4:C78) -> 1 | D80: EVALUATION GLOBALE - NOTE FINALE | F80: =ROUND(+F15*$C4+F19*$C16+F29*$C20+F40*$C30+F52*$C41+F58*$C53+F68*$C59+F75*$C69+F78*$C76,0) -> 0 | G80: =ROUND(+G15*$C4+G19*$C16+G29*$C20+G40*$C30+G52*$C41+G58*$C53+G68*$C59+G75*$C69+G78*$C76,0) -> 0 | H80: =+G80*F80 -> 0
C82: =+SUM(C4:C76) -> 1 | D82: EVALUATION GLOBALE - NOTE FINALE | F82: =ROUND(IFERROR(AVERAGE(F4:F14)*$C4,0)+IFERROR(AVERAGE(F16:F18)*$C16,0)+IFERROR(AVERAGE(F20:F28)*$C20,0)+IFERROR(AVERAGE(F30:F39)*$C30,0)+IFERROR(AVERAGE(F41:F51)*$C41,0),+IFERROR(AVERAGE(F53:F57)*$C53,0)+IFERROR(AVERAGE(F59:F67)*$C59,0)+IFERROR(AVERAGE(F69:F74)*$C69,0)+IFERROR(AVERAGE(F76:F77)*$C76,0)*0) -> 0 | G82: =ROUND(IFERROR(AVERAGE(G4:G14)*$C4,0)+IFERROR(AVERAGE(G16:G18)*$C16,0)+IFERROR(AVERAGE(G20:G28)*$C20,0)+IFERROR(AVERAGE(G30:G39)*$C30,0)+IFERROR(AVERAGE(G41:G51)*$C41,0),+IFERROR(AVERAGE(G53:G57)*$C53,0)+IFERROR(AVERAGE(G59:G67)*$C59,0)+IFERROR(AVERAGE(G69:G74)*$C69,0)+IFERROR(AVERAGE(G76:G77)*$C76,0)*0) -> 0 | H82: =+G82*F82 -> 0

Sheet DMCC
A1: ANALYSE DES RISQUES OPERATIONNELS - MARKETING & PRODUITS
A2: N° | B2: PROCESSUS | C2: RATIO | D2: SOUS PROCESSUS | E2: EXCEPTIONS MAJEURES CONSTATEES | F2: RISQUES CORRELES | G2: FAMILLE DU RISQUE | H2: Gravité | I2: Probabilité | J2: Risque brut (Rb) | K2: Justification de l'évaluation en cas de risque jugé critique | L2: DISPOSITIF DE PREVENTION ET DE CONTRÔLE | P2: Gravité résiduelle | Q2: Probabilité résiduelle | R2: Risque résiduel (Rr)
H4: G | I4: P | J4: est égal à GxP | L4: Description du dispositif à mettre en œuvre | M4: Dispositif existant ou Non | N4: Owner du Contrôle | O4: Efficacité du dispositif | P4: G | Q4: Pr | R4: est égal à GxP
A5: 1 | B5: MARKETING PRODUITS | C5: 0.025 | D5: Gestion clientèle | E5: • Absence de plan d'action commerciale et stratégique pour le développement des produits de COFINA | F5: Risque lié à la mission commerciale Risque de concurrence | G5: Risque stratégique | H5: 4 | I5: 2 | J5: =H5*I5 -> 8 | L5: Mise en placed d' un plan action annuel avec des revue d'étape | M5: OUI | N5: DEX | O5: 2 | P5: =H5 -> 4 | Q5: =I5/O5 -> 1 | R5: =P5*Q5 -> 4
E6: Absence de suivi sur la gestion des réclamations clients | F6: Risque lié à la mission commerciale Risque opérationnel Risque de non-conformité | G6: Risque stratégique | H6: 3 | I6: 3 | J6: =H6*I6 -> 9 | L6: Existence d'un disposirtif de suivi des réclamations | M6: OUI | N6: R.MCC | O6: 2 | P6: =H6 -> 3 | Q6: =I6/O6 -> 1.5 | R6: =P6*Q6 -> 4.5
E7: Dysfonctionnement/obsolescence des enseignes et totems | F7: Risque d'image | G7: Risque stratégique | H7: 4 | I7: 3 | J7: =H7*I7 -> 12 | L7: En plus des remontées des chefs d'agence des revues semestrielle sont faites | M7: OUI | N7: R.MCC | O7: 2 | P7: =H7 -> 4 | Q7: =I7/O7 -> 1.5 | R7: =P7*Q7 -> 6
E8: Non-affichage des conditions générales à jour dans les agences | F8: Risque de non-conformité réglementaire | G8: Risque réglementaire | H8: 3 | I8: 2 | J8: =H8*I8 -> 6 | L8: Revue semestriel sur l'affichage des conditions générales | M8: OUI | N8: R.MCC/Chef d'agence | O8: 2 | P8: =H8 -> 3 | Q8: =I8/O8 -> 1 | R8: =P8*Q8 -> 3
E9: • Défaut constatée sur la qualité de service délivrée en Agence | F9: Risque lié à la mission commerciale | G9: Risque stratégique | H9: 4 | I9: 3 | J9: =H9*I9 -> 12 | L9: Mise en plance d'un planning annuel de formation de remise à niveau | M9: OUI | N9: DEX/R.MCC/Chef d'agence | O9: 2 | P9: =H9 -> 4 | Q9: =I9/O9 -> 1.5 | R9: =P9*Q9 -> 6
D10: Gestion des produits | E10: • Défaut de communication des produits | F10: Risque lié à la mission sociale | G10: Risque stratégique | H10: 3 | I10: 3 | J10: =H10*I10 -> 9 | L10: Existence d'un plannig de formation sur 2026 | M10: OUI | N10: RMCC | O10: 2 | P10: =H10 -> 3 | Q10: =I10/O10 -> 1.5 | R10: =P10*Q10 -> 4.5
E11: Absence de mise à jour des conditions générales conformément aux pratiques | F11: Risque de non-conformité | G11: Risque opérationnel | H11: 4 | I11: 2 | J11: =H11*I11 -> 8 | L11: Mise a jour systématique à chaque modification | M11: OUI | N11: RMCC | O11: 2 | P11: =H11 -> 4 | Q11: =I11/O11 -> 1 | R11: =P11*Q11 -> 4
E12: Non réalisation d'une étude de marché préalable à la création d'un nouveau produit/service et nécessaire à la compréhension du besoin identifié et l’identification des pistes et options des solutions | F12: Risque de perte financière Risque lié à la mission commerciale | G12: Risque stratégique | H12: 4 | I12: 3 | J12: =H12*I12 -> 12 | L12: Réaliser une étude de marché avant toute mise en place d'un nouveau produit/service | M12: NON | N12: DEX/R.MCC | O12: 1 | P12: 4
E13: Absence de fiche de produit validée pour une nouvelle offre de produit/service | F13: Risque opérationnel | G13: Risque opérationnel | H13: 4 | I13: 2 | J13: =H13*I13 -> 8 | L13: Existence d'un dispositif encadré par une politique de lancement de nouveau produit | M13: OUI | N13: DEX/R.MCC | O13: 3 | P13: 4
E14: Absence de formation des utilisateurs (INTERNES)d'un nouveau produit/service | F14: Risque de fraude Risque opérationnel | G14: Risque opérationnel | H14: 4 | I14: 3 | J14: =H14*I14 -> 12 | M14: NON | N14: DEX/R.MCC | O14: 2 | P14: 4
E15: Absence de Protection de la proprièté intellectuelle | F15: Risque d'image Risque de litiges | G15: Risque stratégique | H15: 4 | I15: 2 | J15: =H15*I15 -> 8 | L15: Protéger les noms des produits et les enregistrer à l'OAPI | N15: RMCC | O15: 2 | P15: =H15 -> 4 | Q15: =I15/O15 -> 1 | R15: =P15*Q15 -> 4
E16: Absence de contrôle de conformité ou validation lors du lancement d'un nouveau produit | F16: Risque de non-conformité Risque opérationnel | G16: Risque opérationnel | H16: 4 | I16: 2 | J16: =H16*I16 -> 8 | L16: Validation systématique de la conformié | M16: NON | N16: RMCC | O16: 2 | P16: =H16 -> 4 | Q16: =I16/O16 -> 1 | R16: =P16*Q16 -> 4
D17: Evénements & Relations avec les tiers | E17: Non-Conformité relative aux prises de parole publique. | F17: Risque d'image Risque de réputation | G17: Risque stratégique | H17: 4 | I17: 2 | J17: =H17*I17 -> 8 | L17: Procedure encadrant la prise de parole | M17: OUI | N17: RMCC | O17: 2 | P17: =H17 -> 4 | Q17: =I17/O17 -> 1 | R17: =P17*Q17 -> 4
E18: Absence de validation par les personnes habilitées d'une création graphique | F18: Risque de perte financière Risque lié à la mission commerciale | G18: Risque stratégique | H18: 3 | I18: 3 | J18: 9 | L18: Procedure encadrant la prise de parole | M18: OUI | N18: MCC | O18: 2 | P18: 3
E19: Mauvaise gestion des supports de communication et matériels promotionnels | F19: Risque de perte, vols, dégradation | G19: Risque opérationnel | H19: 3 | I19: 2 | J19: 6 | L19: Faire un suivi adéquat des supports de communication et matériels promotionnels | M19: OUI | N19: MCC | O19: 3 | P19: 3
E20: Absence de politique en matière RSE | F20: Risque d'image, Risque de non-conformité | G20: Risque stratégique | H20: 4 | I20: 3 | J20: 12 | L20: Existence d'une politique de formation | M20: NON | N20: DEX/R.MCC | O20: 1 | P20: 4
D21: Organisation d'événements d'entreprise | E21: Non respect des Processs événementiels (dépassement budget, benchmarking inexistant, proposition non autorisée…) | F21: Risque d'image, Perte financière | G21: Risque stratégique | H21: 4 | I21: 2 | J21: =H21*I21 -> 8 | L21: Mise en place d'un système de mémo avec validation dela direction générale et finance | N21: RMCC | O21: 2 | P21: =H21 -> 4 | Q21: =I21/O21 -> 1 | R21: =P21*Q21 -> 4
D22: Respect de la réglementation relative à la communication | E22: Non Respect du droit d'auteur | F22: Risque d'image, Risque de non-conformité | G22: Risque stratégique | H22: 3 | I22: 2 | J22: =H22*I22 -> 6 | L22: Existence d'une fiche de cesssion de droit d'image | N22: RMCC | O22: 2 | P22: =H22 -> 3 | Q22: =I22/O22 -> 1 | R22: =P22*Q22 -> 3
A23: MARKETING & PRODUITS | E23: EVALUATION INTRINSEQUE | H23: =+ROUND(IFERROR(AVERAGE(H5:H22),0),0) -> 4 | I23: =+ROUND(IFERROR(AVERAGE(I5:I22),0),0) -> 2 | J23: =H23*I23 -> 8 | L23: EVALUATION RESIDUELLE | O23: =+ROUND(IFERROR(AVERAGE(O5:O22),0),0) -> 2 | P23: =+ROUND(IFERROR(AVERAGE(P5:P22),0),0) -> 4 | Q23: =+ROUND(IFERROR(AVERAGE(Q5:Q22),0),0) -> 1 | R23: =+ROUND(IFERROR(AVERAGE(R5:R11),0),0) -> 5
F25: Risque de Fraude | G25: =COUNTIF(G5:G22,F25) -> 0
F26: Risque opérationnel | G26: =COUNTIF(G5:G22,F26) -> 5
F27: Risque stratégique | G27: =COUNTIF(G5:G22,F27) -> 12
F28: Risque de crédit | G28: =COUNTIF(G5:G22,F28) -> 0
F29: Risque réglementaire | G29: =COUNTIF(G5:G22,F29) -> 1
F30: Risque de liquidité | G30: =COUNTIF(G5:G22,F30) -> 0
F31: Risque exogéne | G31: =COUNTIF(G5:G22,F31) -> 0

Sheet AGENCES
A1: ANALYSE DES RISQUES OPERATIONNELS - DIRECTION EXPLOITATION
A2: N° | B2: PROCESSUS | C2: RATIO | D2: SOUS PROCESSUS | E2: EXCEPTIONS MAJEURES CONSTATEES | F2: RISQUES CORRELES | G2: FAMILLE DE RISQUE | H2: Gravité | I2: Probabilité | J2: Risque brut (Rb) | K2: Justification de l'évaluation en cas de risque jugé critique | L2: DISPOSITIF DE PREVENTION ET DE CONTRÔLE | P2: Gravité résiduelle | Q2: Probabilité résiduelle | R2: Risque résiduel (Rr)
H4: G | I4: P | J4: est égal à GxP | L4: Description du dispositif | M4: Dispositif existant ou Non | N4: Owner du Contrôle | O4: Efficacité du dispositif | P4: G | Q4: Pr | R4: est égal à GxP
B5: AGENCES | C5: 0.1 | D5: Gestion clientèle (ouverture de compte, Gestion opérationnelle des produits) | E5: • Identification du client (comptes sans Photo & comptes sans signature dans le système FLEXCUB) | F5: Risque opérationnel Risque de non-conformité | G5: Risque opérationnel | H5: 4 | I5: 3 | J5: =H5*I5 -> 12 | L5: Ne pas procéder à l'ouverture du compte dans le SI en cas d'absence de photo ou signature | M5: OUI | N5: CC / RR / CA | O5: 2 | P5: =H5 -> 4 | Q5: =I5/O5 -> 1.5 | R5: =P5*Q5 -> 6
E6: • Défaut dans la conformité des piéces d'identité (Présence de clients ayant plusieurs pièces différentes) | F6: Risque de non-conformité Risque de fraude | G6: Risque de Fraude | H6: 5 | I6: 1 | J6: =H6*I6 -> 5 | L6: Vérifier l'authenticité des pièces d'identité et s'assurer qu'elles ne sont pas expirées | N6: CC / RR / CA | O6: 2 | P6: =H6 -> 5 | Q6: =I6/O6 -> 0.5 | R6: =P6*Q6 -> 2.5
E7: • Absence de prélévement des frais de tenue de compte pour défaut de provision (Manque de suivi sur la gestion de la clientèle), Perte de revenus | F7: Risque de pertes financières Risque opérationnel | G7: Risque opérationnel | H7: 4 | I7: 1 | J7: =H7*I7 -> 4 | L7: Prélèvement automatique des FTC paramétré dans le système | M7: oui | N7: CC / RR / CA IT | O7: 2 | P7: =H7 -> 4 | Q7: =I7/O7 -> 0.5 | R7: =P7*Q7 -> 2
E8: Vérification originaux des statuts et pv nomination du gérant ou du Directeur Général pour les SA ; SARL ; SUARL | F8: Risque de non-conformité Risque de fraude | G8: Risque de Fraude | H8: 3 | I8: 3 | J8: =H8*I8 -> 9 | L8: Type de document à receuillir déjà préétabli a l'aide d'une checklist | M8: oui | N8: CC / RR / CA | O8: 2 | P8: =H8 -> 3 | Q8: =I8/O8 -> 1.5 | R8: =P8*Q8 -> 4.5
E9: Incomplétude des dossiers d'ouverture de compte | F9: Risque opérationnel Risque de non-conformité | G9: Risque opérationnel | H9: 4 | I9: 1 | J9: 8 | L9: Mise en place d'une cheklist recensant les documents à fournir | M9: OUI | N9: CC/CA | O9: 3 | P9: 4 | Q9: =I9/O9 -> 0.33333333 | R9: =P9*Q9 -> 1.3333333
E10: Absence de liste des clients décédés | F10: Risque opérationnel Risque de non-conformité | G10: Risque opérationnel | H10: 4 | I10: 4 | J10: 16 | L10: Mettre en place une liste exhaustive des clients décédés | M10: NON | N10: AGENCE/OPS RISQUE | O10: 1 | P10: 4 | Q10: =I10/O10 -> 4 | R10: =P10*Q10 -> 16
E11: Mauvaise gestion des comptes des clients décédés | F11: Risque de fraude | G11: Risque de Fraude | H11: 4 | I11: 3 | J11: 12 | L11: Procedure de gestion des comptes des cleints décédés retracant les dispositions à mettre en œuvre | M11: OUI | N11: AGENCE/OPS/CONTRÔLE/ RISQUE | O11: 2 | P11: 4 | Q11: =I11/O11 -> 1.5 | R11: =P11*Q11 -> 6
E12: Fraude sur l'enrolement des produits digitaux et les cartes prépayées (Exemple : Création de profil, Modification des informations personnelles…) | F12: Risque opérationnel Risque de fraude | G12: Risque de Fraude | H12: 4 | I12: 3 | J12: =H12*I12 -> 12 | L12: Procedure a double validation mis en place avec initiateur et validateur | M12: Oui | N12: CC / RR / CA/ MONETIQUE | O12: 2 | P12: =H12 -> 4 | Q12: =I12/O12 -> 1.5 | R12: =P12*Q12 -> 6
E13: • Modification de type de compte dans le SI (Compte courant en compte épargne) | F13: Risque de conformité Risque de fraude | G13: Risque de Fraude | H13: 4 | I13: 1 | J13: =H13*I13 -> 4 | L13: Rendre impossible dans le SI, la modification du type de compte. | M13: OUI | N13: CC / RR / CA | O13: 2 | P13: =H13 -> 4 | Q13: =I13/O13 -> 0.5 | R13: =P13*Q13 -> 2
E14: Défaut dans la modification des packs (fiche non signée, frais non prélevés, code catégorie non modifié…) | F14: Risque opérationnel Perte financière | G14: Risque opérationnel | H14: 4 | I14: 2 | J14: =H14*I14 -> 8 | L14: Respecter vigoureusement la procédure de modification de pack | M14: NON | N14: CC / RR / CA | O14: 2 | P14: =H14 -> 4 | Q14: =I14/O14 -> 1 | R14: =P14*Q14 -> 4
E15: Défaut dans l'établissement des procurations liées aux comptes mandataires | F15: Risque opérationnel Risque de fraude | G15: Risque de Fraude | H15: 4 | I15: 3 | J15: =H15*I15 -> 12 | L15: Blocage de la création des mandataires en l'absence de procuration reçues | M15: OUI | N15: CC / RR / CA | O15: 2 | P15: =H15 -> 4 | Q15: =I15/O15 -> 1.5 | R15: =P15*Q15 -> 6
E16: • Ouverture ou fermeture incomplète des comptes dans Flexcub (comptes en instance d'ouverture, comptes à valider, demande clôture, à clôturer) | F16: Risque de conformité | G16: Risque opérationnel | H16: 4 | I16: 2 | J16: =H16*I16 -> 8 | L16: Existence de procedure d'ouverture ou de fermeture de compte | M16: OUI | N16: CC / RR / CA | O16: 2 | P16: =H16 -> 4 | Q16: =I16/O16 -> 1 | R16: =P16*Q16 -> 4
E17: • Mauvais archivage des dossiers d'ouverture de compte | F17: Risque de pertes de document | G17: Risque opérationnel | H17: 4 | I17: 1 | J17: =H17*I17 -> 4 | L17: Création du service archve | M17: OUI | N17: CC / RR / CA/Archive | O17: 2 | P17: =H17 -> 4 | Q17: =I17/O17 -> 0.5 | R17: =P17*Q17 -> 2
E18: • Manque de suivi des fermetures de compte Client | F18: Risque opérationnel Risque de conformité | G18: Risque opérationnel | H18: 4 | I18: 4 | J18: =H18*I18 -> 16 | L18: Mise en place d'une procédure de fermeture de compte | M18: NON | N18: CC / RR / CA/IT | O18: 2 | P18: =H18 -> 4 | Q18: =I18/O18 -> 2 | R18: =P18*Q18 -> 8
E19: Non-respect des horaires d'ouverture des agences | F19: Risque d'image | G19: Risque stratégique | H19: 4 | I19: 1 | J19: =H19*I19 -> 4 | L19: Procedure d'ouverture et de fermeture des agences | M19: OUI | N19: CC / RR / CA | O19: 2 | P19: =H19 -> 4 | Q19: =I19/O19 -> 0.5 | R19: =P19*Q19 -> 2
E20: Insuffisance dans les mesures de modification de signature et de numéro de téléphone | F20: Risque de fraude | G20: Risque de Fraude | H20: 4 | I20: 2 | J20: =H20*I20 -> 8 | L20: Création d'une fiche de modification des informations du client | M20: OUI | N20: CC / RR / CA | O20: 2 | P20: =H20 -> 4 | Q20: =I20/O20 -> 1 | R20: =P20*Q20 -> 4
E21: • Non prise en charge des demandes de prêt en agence | F21: Mauvaise qualité de service Risque lié à la mission commerciale | G21: Risque stratégique | H21: 4 | I21: 1 | J21: =H21*I21 -> 4 | L21: Assurer un suivi ou monitoring via Tracking crédit de toutes les demandes de prêt | M21: OUI | N21: CC / RR / CA | O21: 1 | P21: =H21 -> 4 | Q21: =I21/O21 -> 1 | R21: =P21*Q21 -> 4
E22: • Non prélèvement des frais de demande de prêt | F22: Risque de pertes financières Risque opérationnel | G22: Risque opérationnel | H22: 4 | I22: 2 | J22: =H22*I22 -> 8 | L22: Veiller à respecter rigoureusement la procédure mise en place | M22: OUI | N22: CC / RR / CA | O22: 2 | P22: =H22 -> 4 | Q22: =I22/O22 -> 1 | R22: =P22*Q22 -> 4
E23: Non réalisation/matérialisation du call back au client lors de la validation d'un ordre de virement | F23: Risque de fraude | G23: Risque de Fraude | H23: 5 | I23: 2 | J23: =H23*I23 -> 10 | L23: Veiller respecter rigoureusement la procédure de traitement des ordres de virement | M23: OUI | N23: CC / RR / CA/ CREDIT | O23: 2 | P23: =H23 -> 5 | Q23: =I23/O23 -> 1 | R23: =P23*Q23 -> 5
... E27: • Défaut sur la qualité de service délivrée en Agence | F27: Risque lié à la mission commerciale | G27: Risque stratégique | H27: 4 | I27: 1 | J27: =H27*I27 -> 4 | L27: S'assurer d'une bonne qualité des ressources humaines / favoriser des formations et sensibilisations régulières | M27: OUI | N27: CC / RR / CA | O27: 2 | P27: =H27 -> 4 | Q27: =I27/O27 -> 0.5 | R27: =P27*Q27 -> 2
D28: Gestion des caisses | E28: • Non réalisation du pointage systématique des tickets de caisses et de l'inventaire des espèces quotidiennement par un staff autre que le caissier lui-même. | F28: Risque opérationnel | G28: Risque opérationnel | H28: 3 | I28: 2 | J28: =H28*I28 -> 6 | L28: Mise en place du contrôle de niveau 1 | M28: OUI | N28: Chef D'agence / Chef Caisse | O28: 1 | P28: =H28 -> 3 | Q28: =I28/O28 -> 2 | R28: =P28*Q28 -> 6
E29: • Dépassement de la limite d'encaisse journalière autorisée – ‘’daily overnight limit’’ | F29: Risque opérationnel Risque de pertes financières en cas de sinistre | G29: Risque opérationnel | H29: 4 | I29: 2 | J29: =H29*I29 -> 8 | L29: Diffusion d'une note de service fixant les plafond d'encaisse | M29: OUI | N29: Chef D'agence / Chef Caisse | O29: 2 | P29: =H29 -> 4 | Q29: =I29/O29 -> 1 | R29: =P29*Q29 -> 4
E30: Mauvaise gestion des approvisionnements et délestages en banque | F30: Risque de fraude | G30: Risque de Fraude | H30: 5 | I30: 4 | J30: =H30*I30 -> 20 | L30: Respect strict du montant limite par convoi et présence obligatoire d'un garde national | M30: OUI(la frèquence de l'approvisionnement des caisses est faible) | N30: OPS/Chef D'agence / Chef Caisse | O30: 2 | P30: =H30 -> 5 | Q30: =I30/O30 -> 2 | R30: =P30*Q30 -> 10
E31: • Retrait fictif sur compte client | F31: Risque de fraude | G31: Risque de Fraude | H31: 5 | I31: 2 | J31: =H31*I31 -> 10 | L31: Systéme alerte sms fonctionnel pour tous les comptes clients. | M31: OUI (mais l'alerte SMS n'est pas fonctionnel pour le moment) | N31: Chef D'agence / Chef Caisse | O31: 2 | P31: =H31 -> 5 | Q31: =I31/O31 -> 1 | R31: =P31*Q31 -> 5
E32: • Non détection des cas de faux billets | F32: Risque de fraude Risque de pertes financières | G32: Risque de Fraude | H32: 5 | I32: 3 | J32: =H32*I32 -> 15 | L32: Mise a disposition de detecteurde faux billet au niveau de chaque caisse | M32: NON | N32: Chef D'agence / Chef Caisse | O32: 2 | P32: =H32 -> 5 | Q32: =I32/O32 -> 1.5 | R32: =P32*Q32 -> 7.5
E33: Absence de validation des annulations d'opèrations de caisse | F33: Risque de fraude/Vol | G33: Risque de Fraude | H33: 4 | I33: 3 | J33: =H33*I33 -> 12 | L33: Validation système paramétré au niveaudu chef d'agence pour chaque opération | M33: NON | N33: Contrôle Interne/Chef agence | O33: 3 | P33: =H33 -> 4 | Q33: =I33/O33 -> 1 | R33: =P33*Q33 -> 4
E34: • Différence de caisse | F34: Risque de pertes financières Risque opérationnel | G34: Risque de Fraude | H34: 5 | I34: 2 | J34: =H34*I34 -> 10 | L34: suivi quotidien des caisses et des contrôles inopinés de caisse | M34: OUI | N34: Chef D'agence / Superviseur/ Contrôle | O34: 3 | P34: =H34 -> 5 | Q34: =I34/O34 -> 0.66666667 | R34: =P34*Q34 -> 3.3333333
D35: Gestion de la sécurité et Assurance | E35: • Absence d'alarme anti-intruision | F35: Risque de vol | G35: Risque opérationnel | H35: 3 | I35: 1 | J35: =H35*I35 -> 3 | L35: Mettre en place des alarmes anti-intruision | M35: OUI | N35: IT | O35: 2 | P35: =H35 -> 3 | Q35: =I35/O35 -> 0.5 | R35: =P35*Q35 -> 1.5
E36: • Absence détecteur de fumée et extincteur | F36: Risque de perte de données | G36: Risque opérationnel | H36: 3 | I36: 1 | J36: =H36*I36 -> 3 | L36: Mettre en place des détecteurs de fumée et extincteur | M36: OUI (Dysfonctionnement du dispositif de détecteur de fumée en place (Inventaire en cours pour régulariser le dysfonctionnement) | N36: IT/Achat Logistique | O36: 1 | P36: =H36 -> 3 | Q36: =I36/O36 -> 1 | R36: =P36*Q36 -> 3
E37: • Gestion des clés du coffre-fort ou accès coffre effectuée par une seule personne | F37: Risque opérationnel Risque de vol, fraude | G37: Risque de Fraude | H37: 5 | I37: 2 | J37: =H37*I37 -> 10 | L37: Procédure de gestion des clés du coffre et l'accès au coffre. | M37: OUI | N37: Contrôle interne/CA | O37: 2 | P37: =H37 -> 5 | Q37: =I37/O37 -> 1 | R37: =P37*Q37 -> 5
E38: Absence de politique de sécurité physique et locaux sensibles. | F38: Risque de pertes financières en cas de sinistre | G38: Risque opérationnel | H38: 4 | I38: 2 | J38: =H38*I38 -> 8 | L38: Veiller à ce que les exigences liées au dispositif de sécurité sont en place. | M38: NON | N38: Contrôle interne | O38: 2 | P38: =H38 -> 4 | Q38: =I38/O38 -> 1 | R38: =P38*Q38 -> 4
E39: • Absence d'agent de sécurité armé en agence | F39: Risque opérationnel | G39: Risque opérationnel | H39: 5 | I39: 2 | J39: =H39*I39 -> 10 | L39: Veiller à ce que les agents armés soient présent en agence pour veiller à la sécurité des biens et des personnes | M39: OUI(il faudra vérifier si c'est disponible dans tous les agences) | N39: Contrôle interne | O39: 2 | P39: =H39 -> 5 | Q39: =I39/O39 -> 1 | R39: =P39*Q39 -> 5
A40: AGENCES | E40: EVALUATION INTRINSEQUE | H40: =+ROUND(IFERROR(AVERAGE(H5:H39),0),0) -> 4 | I40: =+ROUND(IFERROR(AVERAGE(I5:I39),0),0) -> 2 | J40: =H40*I40 -> 8 | L40: EVALUATION RESIDUELLE | O40: =+ROUND(IFERROR(AVERAGE(O5:O39),0),0) -> 2 | P40: =+ROUND(IFERROR(AVERAGE(P5:P39),0),0) -> 4 | Q40: =+ROUND(IFERROR(AVERAGE(Q5:Q39),0),0) -> 1 | R40: =+ROUND(IFERROR(AVERAGE(R5:R39),0),0) -> 5
F43: Risque de Fraude | G43: =COUNTIF(G5:G40,F43) -> 17
F44: Risque opérationnel | G44: =COUNTIF(G5:G40,F44) -> 15
F45: Risque stratégique | G45: =COUNTIF(G5:G40,F45) -> 3
F46: Risque de crédit | G46: =COUNTIF(G5:G40,F46) -> 0
F47: Risque réglementaire | G47: =COUNTIF(G5:G40,F47) -> 0
F48: Risque de liquidité | G48: =COUNTIF(G5:G40,F48) -> 0
F49: Risque exogéne | G49: =COUNTIF(G5:G40,F49) -> 0

Sheet Feuil2
A1: Risque de Fraude
A2: Risque opérationnel
A3: Risque stratégique
A4: Risque de crédit
A5: Risque de liquidité
A6: Risque réglementaire
A7: Risque exogéne

Sheet RESSOURCES HUMAINES
A1: ANALYSE DES RISQUES OPERATIONNELS - RESSOURCES HUMAINES
A2: N° | B2: PROCESSUS | C2: RATIO | D2: SOUS PROCESSUS | E2: EXCEPTIONS MAJEURES CONSTATEES | F2: RISQUES CORRELES | G2: FAMILLE DE RISQUE | H2: Gravité | I2: Probabilité | J2: Risque brut (Rb) | K2: Justification de l'évaluation en cas de risque jugé critique | L2: DISPOSITIF DE PREVENTION ET DE CONTRÔLE | P2: Gravité résiduelle | Q2: Probabilité résiduelle | R2: Risque résiduel (Rr)
H4: G | I4: P | J4: est égal à GxP | L4: Description du dispositif | M4: Dispositif existant ou Non | N4: Owner du Contrôle | O4: Efficacité du dispositif | P4: G | Q4: Pr | R4: est égal à GxP
A5: 8 | B5: RESSOURCES HUMAINES | C5: 0.05 | D5: Gestion administrative du personnel & Affaires sociales | E5: '• Dossier du personnel incomplet | F5: Faiblesse dans l'identification du staff Risque de document fictif | G5: Risque opérationnel | H5: 3 | I5: 1 | J5: =H5*I5 -> 3 | L5: Contrôle systématique du dossier de personnel pour le nouveau entrant | M5: OUI | N5: CONTRÔLE INTERNE | O5: 2 | P5: =H5 -> 3 | Q5: =I5/O5 -> 0.5 | R5: =P5*Q5 -> 1.5
E6: Mauvais archivage des dossiers du personnel | F6: Risque de perte Risque de divulgation d'informations sensibles | G6: Risque opérationnel | H6: 3 | I6: 2 | J6: =H6*I6 -> 6 | L6: Classement chronologique mis en place avec stokage dans unenarmoire unifuge | M6: OUI | N6: RRH | O6: 2 | P6: =H6 -> 3 | Q6: =I6/O6 -> 1 | R6: =P6*Q6 -> 3
E7: • Non-respect du processus de recrutement | F7: Risque d'inadéquation entre le profil recherché et le besoin réel Risque de recrutement arbitraire | G7: Risque opérationnel | H7: 4 | I7: 2 | J7: =H7*I7 -> 8 | L7: Procedue de gestion du recritement existant | M7: OUI | N7: RRH | O7: 2 | P7: =H7 -> 4 | Q7: =I7/O7 -> 1 | R7: =P7*Q7 -> 4
E8: Non-conformité des dossiers du personnel | F8: Risque de fraude | G8: Risque de Fraude | H8: 4 | I8: 2 | J8: =H8*I8 -> 8 | L8: Mis en place d'une checklist des documents a fournir avant le démarrage | N8: RRH | O8: 2 | P8: =H8 -> 4 | Q8: =I8/O8 -> 1 | R8: =P8*Q8 -> 4
E9: Défaut de provisionnement des indemnités de départ à la retraite | F9: Risque de non-conformité | G9: Risque opérationnel | H9: 4 | I9: 2 | J9: =H9*I9 -> 8 | L9: S'assurer que les provisions de départ à la retraite sont constituées | N9: RRH | O9: 2 | P9: =H9 -> 4 | Q9: =I9/O9 -> 1 | R9: =P9*Q9 -> 4
E10: Non respect de la procédure des avances/accomptes sur salaires | F10: Risque opérationnel | G10: Risque opérationnel | H10: 3 | I10: 1 | J10: =H10*I10 -> 3 | L10: Mise en plae d'une politique encadrant l'activité | N10: RRH | O10: 2 | P10: =H10 -> 3 | Q10: =I10/O10 -> 0.5 | R10: =P10*Q10 -> 1.5
E11: Absence de mise à jour du registre de l'employeur | F11: Risque de non-conformité | G11: Risque opérationnel | H11: 3 | I11: 1 | J11: =H11*I11 -> 3 | L11: Mettre à jour systématiquement le registre d'employeur | M11: OUI | N11: RRH | O11: 3 | P11: 4 | Q11: =I11/O11 -> 0.33333333 | R11: =P11*Q11 -> 1.3333333
E12: Défaut de réalisation du PIC pour les nouveaux entrants | F12: Risque opérationnel | G12: Risque opérationnel | H12: 4 | I12: 3 | J12: =H12*I12 -> 12 | L12: Etablir et exécuter un planning d'immersion pour les nouveaux rentrants | M12: OUI | N12: RRH | O12: 3 | P12: 4 | Q12: =I12/O12 -> 1 | R12: =P12*Q12 -> 4
E13: Mauvaise gestion des prêts octroyés au personnel (non respect de la quotité cessible, échéance non prélevée…) | F13: Risque opérationnel | G13: Risque opérationnel | H13: 5 | I13: 3 | J13: =H13*I13 -> 15 | L13: Mise en plae d'une politique encadrant l'activité | M13: OUI | N13: RRH | O13: 2 | P13: 5 | Q13: =I13/O13 -> 1.5 | R13: =P13*Q13 -> 7.5
E14: Non-respect du dress code par le personnel | F14: Risque opérationnel, d'image | G14: Risque opérationnel | H14: 3 | I14: 3 | J14: =H14*I14 -> 9 | L14: Sensibiliser le personnel sur le respect du dress code/Faire des sessions de rappel | M14: NON | N14: RRH | O14: 1 | P14: 4 | Q14: =I14/O14 -> 3 | R14: =P14*Q14 -> 12
E15: Recrutement du personnel non budgétisé | F15: Risque de recrutement arbitraire | G15: Risque opérationnel | H15: 3 | I15: 3 | J15: =H15*I15 -> 9 | L15: Mettre en place une procédure de recrutement non budgétisé | M15: NON | N15: RRH | O15: 2 | P15: 4 | Q15: =I15/O15 -> 1.5 | R15: =P15*Q15 -> 6
D16: Gestion des départs | E16: Non restitution des outils et matériels de travail lors des départs (check-list départ non réalisé) | F16: Risque de vol | G16: Risque de Fraude | H16: 2 | I16: 2 | J16: =H16*I16 -> 4 | L16: Mise en place check-list départ systématiquement avec materiel a rendre | M16: OUI | N16: RRH | O16: 2 | P16: =+H16 -> 2 | Q16: =I16/O16 -> 1 | R16: =P16*Q16 -> 2
E17: Non désactivation des accès (messagerie, système, autres…) du staff sortant | F17: Risque opérationnel Risque de fraude | G17: Risque de Fraude | H17: 2 | I17: 2 | J17: =H17*I17 -> 4 | L17: Communication systématique sur les départ aux IT et Contrôle interne | M17: OUI | N17: RRH | O17: 2 | P17: =H17 -> 2 | Q17: =I17/O17 -> 1 | R17: =P17*Q17 -> 2
E18: Non-suppression du staff du logiciel de paie | F18: Risque opérationnel Risque de fraude | G18: Risque de Fraude | H18: 5 | I18: 2 | J18: =H18*I18 -> 10 | L18: Supprimer le staff sortant du logiciel de paie | M18: OUI | N18: RRH | O18: 2 | P18: =H18 -> 5 | Q18: =I18/O18 -> 1 | R18: =P18*Q18 -> 5
D19: Politique de rémunération et Paie | E19: • Non-conformité règlementaire des traitements salariaux (grille convention collective APSFD) | F19: Risque de non exhaustivité de la paie | G19: Risque réglementaire | H19: 4 | I19: 2 | J19: =H19*I19 -> 8 | L19: S'assurer de la conformité des traitements de salaire | M19: OUI | N19: RRH | O19: 2 | P19: =H19 -> 4 | Q19: =I19/O19 -> 1 | R19: =P19*Q19 -> 4
E20: • Non détermination des provisions pour congé et retraite et/ou non comptabilisation des provisions pour congé et retraite | F20: Risque de redressement | G20: Risque réglementaire | H20: 4 | I20: 2 | J20: =H20*I20 -> 8 | L20: S'assurer de la conformité des traitements de congés | M20: OUI | N20: RRH | O20: 2 | P20: =H20 -> 4 | Q20: =I20/O20 -> 1 | R20: =P20*Q20 -> 4
E21: • Absence de déclarations fiscales et sociales et/ou erreur dans les déclarations fiscales et sociales liées à la paie | F21: Risque de redressement | G21: Risque réglementaire | H21: 4 | I21: 2 | J21: =H21*I21 -> 8 | L21: S'assurer de la conformité des déclarations sociales effectuées. | M21: OUI | N21: RRH | O21: 2 | P21: =H21 -> 4 | Q21: =I21/O21 -> 1 | R21: =P21*Q21 -> 4
E22: Manque de confidentialité des données de la paie | F22: Conflit d'intérêts | G22: Risque stratégique | H22: 3 | I22: 3 | J22: =H22*I22 -> 9 | L22: S'assurer que l'accès au logiciel de la paie est restreint dans le système et le dossier du personnel | M22: NON | N22: RRH | O22: 2 | P22: =H22 -> 3 | Q22: =I22/O22 -> 1.5 | R22: =P22*Q22 -> 4.5
E23: • Absence d'un outil de gestion de la paie | F23: Risque d'erreur opérationnelle | G23: Risque opérationnel | H23: 3 | I23: 3 | J23: =H23*I23 -> 9 | L23: Existence d'un outils de gestion de la paie | M23: OUI | N23: RRH | O23: 2 | P23: =H23 -> 3 | Q23: =I23/O23 -> 1.5 | R23: =P23*Q23 -> 4.5
D24: Appréciation des performance - Evaluation | E24: '• Non-respect du processus d'évaluation | F24: Conflit d'intérêts | G24: Risque stratégique | H24: 1 | I24: 1 | J24: =H24*I24 -> 1 | L24: Mise n place d'une procedure d'évaluataion | M24: OUI | N24: RRH | O24: 2 | P24: =H24 -> 1 | Q24: =I24/O24 -> 0.5 | R24: =P24*Q24 -> 0.5
E25: • Non évaluation des staffs et/ou Critères d’évaluation non définis ou non adéquats | F25: Méconnaissance des critéres d'évaluation | G25: Risque opérationnel | H25: 1 | I25: 1 | J25: =H25*I25 -> 1 | L25: Suivi semestriel sur les évaluations | M25: OUI | N25: RRH | O25: 2 | P25: =H25 -> 1 | Q25: =I25/O25 -> 0.5 | R25: =P25*Q25 -> 0.5
E26: • Evaluation non objective | F26: Conflit d'intérêts | G26: Risque stratégique | H26: 4 | I26: 2 | J26: =H26*I26 -> 8 | L26: Procedure des gestion des évaluation mis en place prenant en compte ce point | M26: OUI | N26: RRH | O26: 2 | P26: =H26 -> 4 | Q26: =I26/O26 -> 1 | R26: =P26*Q26 -> 4
D27: Gestion des congés | E27: Exixtance de solde de congés supérieurs à la norme | F27: Perturbation/baisse de rendement | G27: Risque opérationnel | H27: 5 | I27: 3 | J27: =H27*I27 -> 15 | P27: =H27 -> 5
E28: Non élaboration d'un fichier annuel de suivi des congés | F28: Risque opérationnel | G28: Risque opérationnel | H28: 2 | I28: 2 | J28: =H28*I28 -> 4 | L28: Outils de gestion des congés existant | M28: OUI | N28: RRH | O28: 2 | P28: =H28 -> 2 | Q28: =I28/O28 -> 1 | R28: =P28*Q28 -> 2
D29: Formation | E29: Non évaluation annuelle et suivi des besoins de formation du personnel | F29: Non renforcement des compétences Démotivation du personnel | G29: Risque stratégique | H29: 4 | I29: 4 | J29: =H29*I29 -> 16 | L29: Mettre en place un tableau de suivi des formations et les exécuter au cours de l'année | M29: OUI | N29: RRH | O29: 2 | P29: =H29 -> 4 | Q29: =I29/O29 -> 2 | R29: =P29*Q29 -> 8
D30: Gestions des carrières | E30: Absence d'une politique de conservation ou rétention du personnel | F30: Risque d'image , Risque réputationnel | G30: Risque stratégique | H30: 4 | I30: 4 | J30: =H30*I30 -> 16 | L30: Respect de la politique de la Gestion prévisionnelle des emplois et des carrières ( GPEC ) | M30: NON | N30: RRH | O30: 2 | P30: =H30 -> 4 | Q30: =I30/O30 -> 2 | R30: =P30*Q30 -> 8
E31: Absence d'une politique de développement du personnel (formation, suivi managérial) | F31: Risque d'image , Risque réputationnel | G31: Risque stratégique | H31: 3 | I31: 2 | J31: =H31*I31 -> 6 | L31: S'assurer de la MEP d'une politique de capacitation du personnel | M31: NON | N31: RRH | O31: 2 | P31: =H31 -> 3 | Q31: =I31/O31 -> 1 | R31: =P31*Q31 -> 3
D32: Bien être au travail/Qualité de vie au travail | E32: Harcellement (violence physique ou verbale) | F32: Risque de départ; Risque de dégradation de la santé mentale Risque d'image de l'Intitution | G32: Risque stratégique | H32: 4 | I32: 2 | J32: =H32*I32 -> 8 | L32: Politique de sanction mis en place | M32: oui | N32: RRH | O32: 3 | P32: =H32 -> 4 | Q32: =I32/O32 -> 0.66666667 | R32: =P32*Q32 -> 2.6666667
E33: Qualité du mobilier | F33: Risque de dégradation de la santé physique des collaborateurs | G33: Risque stratégique | H33: 4 | I33: 4 | J33: =H33*I33 -> 16 | L33: Mis en place d'un comité d'hygiène et de sécurité | N33: RRH | O33: 2 | P33: =H33 -> 4 | Q33: =I33/O33 -> 2 | R33: =P33*Q33 -> 8
E34: Manque d'hygiène | F34: Risque de maladie | G34: Risque opérationnel | H34: 4 | I34: 4 | J34: =H34*I34 -> 16 | L34: Mis en place d'un comité d'hygiène et de sécurité | N34: RRH | O34: 2 | P34: =H34 -> 4 | Q34: =I34/O34 -> 2 | R34: =P34*Q34 -> 8
E35: Climent social inappropprié | F35: Risque baisse de productivité et de la performance | G35: Risque stratégique | H35: 3 | I35: 2 | J35: =H35*I35 -> 6 | L35: Mis en place d'un comité d'hygiène et de sécurité | N35: RRH | O35: 2 | P35: =H35 -> 3 | Q35: =I35/O35 -> 1 | R35: =P35*Q35 -> 3
A37: RESSOURCES HUMAINES | E37: EVALUATION INTRINSEQUE | H37: =+ROUND(IFERROR(AVERAGE(H5:H29),0),0) -> 3 | I37: =+ROUND(IFERROR(AVERAGE(I5:I29),0),0) -> 2 | J37: =H37*I37 -> 6 | L37: EVALUATION RESIDUELLE | O37: =+ROUND(IFERROR(AVERAGE(O5:O26),0),0) -> 2 | P37: =+ROUND(IFERROR(AVERAGE(P5:P26),0),0) -> 3 | Q37: =+ROUND(IFERROR(AVERAGE(Q5:Q26),0),0) -> 1 | R37: =P37*Q37 -> 3
F40: Risque de Fraude | G40: =COUNTIF(G5:G35,F40) -> 4
F41: Risque stratégique | G41: =COUNTIF(G5:G35,F41) -> 9
F42: Risque de crédit | G42: =COUNTIF(G5:G35,F42) -> 0
F43: Risque réglementaire | G43: =COUNTIF(G5:G35,F43) -> 3
F44: Risque de liquidité | G44: =COUNTIF(G5:G35,F44) -> 0
F45: Risque exogéne | G45: =COUNTIF(G5:G35,F45) -> 0
E51: Exixtance de solde de congés supérieurs à la norme | F51: Perturbation/baisse de rendement | G51: Risque opérationnel | H51: 4 | I51: 4

Sheet OPERATIONS
A1: ANALYSE DES RISQUES OPERATIONNELS - SERVICE OPERATIONS
A2: N° | B2: PROCESSUS | C2: RATIO | D2: SOUS PROCESSUS | E2: EXCEPTIONS MAJEURES CONSTATEES | F2: RISQUES | G2: FAMILLE DE RISQUE | H2: Gravité | I2: Probabilité | J2: Risque brut (Rb) | K2: Justification de l'évaluation en cas de risque jugé critique | L2: Dispositif de prévention et contrôle | P2: Gravité résiduelle | Q2: Probabilité résiduelle | R2: Risque résiduel (Rr)
H4: G | I4: P | J4: est égal à GxP | L4: Description du dispositif | M4: Dispositif existant ou non | N4: Owner du Contrôle | O4: Efficacité du dispositif | P4: G | Q4: Pr | R4: est égal à GxP
B5: OPERATIONS | C5: 0.1 | D5: Back office Opérations | E5: • Rejet tardif de la banque partenaire sur le sort d'un cheque apres comptabilisation dans nos livres | F5: Risques d'impayés Risque de fraude Risque de pertes financières | G5: Risque de Fraude | H5: 4 | I5: 4 | J5: =H5*I5 -> 16 | L5: Procedue de remise exitant
E6: • Absence de prélévements des frais de remises cheques | F6: Risques de pertes financieres | G6: Risques de pertes financieres | H6: 4 | I6: 4 | J6: =H6*I6 -> 16 | L6: Contrôle de 1e niveau a J pour toutes les operations de remise cheque | M6: Non (le contrôle n'est fait a la validation de la comptabilisation dans le SI | N6: resp .OPS | O6: 2
A7: 4 | E7: • Comptabilisation des remises chèques sans attendre le sort définitif du chèque par la banque (OD) | F7: Risques d'impayés Risque de fraude Risque de pertes financières | G7: Risque de Fraude | H7: 5 | I7: 2 | J7: =H8*I8 -> 9 | L7: Contrôle de 1e niveau à J pour toutes les opérations de remise de chéque | M7: NON ( LE CONTRÖLE EST FAIT MAIS PAS J) UN CONTRÔLE N'est PAS FAIT LORS DE LA VALIDATION DE L'INTEGRATION | N7: CONTRÔLE INTERNE | O7: 2 | P7: =H7 -> 5 | Q7: =I7/O7 -> 1 | R7: =P7*Q7 -> 5
E8: • Non prélévement des frais de mise en place de prêts, des virements émis ou reçus et des remises chèques sur les comptes. | F8: Risque de pertes financières | G8: Risque opérationnel | H8: 3 | I8: 3 | J8: =H8*I8 -> 9 | L8: Contrôle de 2e niveau à J pour toutes les opérations de virement et remises | M8: NON ( LE CONTRÖLE EST FAIT MAIS PAS J) | N8: CONTRÔLE INTERNE | O8: 2 | P8: =H8 -> 3 | Q8: =I8/O8 -> 1.5 | R8: =P8*Q8 -> 4.5
E9: '• Longs suspens de plus de 90 jours sur les comptes internes et les rapprochements bancaires | F9: Risque de pertes financières Risque de fraude | G9: Risque de Fraude | H9: 5 | I9: 3 | J9: =H9*I9 -> 15 | L9: Assurer un suivi hebdomadaire de l'analyse de tous les comptes internes et veiller à l'appurement des suspens | M9: OUI | N9: Resp. OPS/FINANCES | O9: 2 | P9: =H9 -> 5 | Q9: =I9/O9 -> 1.5 | R9: =P9*Q9 -> 7.5
E10: • Comptabilisation d’opérations frauduleuses | F10: Pertes opérationnelles, Fraude,risques financiers | G10: Risque de Fraude | H10: 5 | I10: 2 | J10: =H10*I10 -> 10 | L10: Contrôle de 1er niveau à J pour toutes les opérations passées dans le SI | M10: OUI | N10: Resp. OPS/FINANCES | O10: 2 | P10: =H10 -> 5 | Q10: =I10/O10 -> 1 | R10: =P10*Q10 -> 5
E11: • Mauvaise imputation comptable sur un compte inapproprié | F11: Risque opérationnel | G11: Risque opérationnel | H11: 4 | I11: 3 | J11: =H11*I11 -> 12 | L11: Contrôle de 1er niveau à J pour toutes les opérations passées dans le SI/le système ne permet plus de loger un virement dans un compte inapproprie si le code agence est different;mise en place d'un compte de desequilibre du bilan | M11: OUI | N11: Resp. OPS | O11: 2 | P11: =H11 -> 4 | Q11: =I11/O11 -> 1.5 | R11: =P11*Q11 -> 6
E12: • Absence de pièces justificatives comptables | F12: Risque opérationnel | G12: Risque opérationnel | H12: 1 | I12: 1 | J12: =H12*I12 -> 1 | L12: Contrôle de 1er niveau à J pour toutes les opérations passées dans le SI | M12: OUI | N12: Resp. OPS | O12: 2 | P12: =H12 -> 1 | Q12: =I12/O12 -> 0.5 | R12: =P12*Q12 -> 0.5
E13: • Erreur de saisie des opérations | F13: Risque opérationnel, Risque de pertes | G13: Risque opérationnel | H13: 4 | I13: 3 | J13: =H13*I13 -> 12 | L13: Contrôle de 1er niveau à J+1 pour toutes les opérations passées dans le SI | M13: OUI | N13: Resp. OPS | O13: 2 | P13: =H13 -> 4 | Q13: =I13/O13 -> 1.5 | R13: =P13*Q13 -> 6
E14: • Libération dépôt de garantie ou DAT sans respecter la procédure | F14: Risque de fraude Risque de pertes financières | G14: Risque de Fraude | H14: 5 | I14: 1 | J14: =H14*I14 -> 5 | L14: Contrôle de 2e niveau à J+1 pour toutes les Libérations de dépôt effectués dans le SI | M14: NON ( LE CONTRÖLE EST FAIT MAIS PAS J) | N14: Resp. OPS/CREDIT | O14: 2 | P14: =H14 -> 5 | Q14: =I14/O14 -> 0.5 | R14: =P14*Q14 -> 2.5
E15: • Report d'échéances sans respecter la procédure | F15: Risque de fraude Risque de pertes financières | G15: Risque de Fraude | H15: 5 | I15: 1 | J15: =H15*I15 -> 5 | L15: Contrôle de 2e niveau à J pour tou décalage effectués dans le SI | M15: NON ( LE CONTRÖLE EST FAIT MAIS PAS J) | N15: Resp. OPS | O15: 2 | P15: =H15 -> 5 | Q15: =I15/O15 -> 0.5 | R15: =P15*Q15 -> 2.5
E16: Absence d'analyse des comptes internes | F16: Risque de fraude Risque de pertes financières | G16: Risque de Fraude | H16: 5 | I16: 3 | J16: =H16*I16 -> 15 | L16: Analyse de compte élaborer chque mois | M16: OUI | N16: Resp. OPS | O16: 2 | P16: =H16 -> 5 | Q16: =I16/O16 -> 1.5 | R16: =P16*Q16 -> 7.5
E17: Levée non autorisée des réservations de fonds | F17: Risque de fraude Risque de pertes financières | G17: Risque de Fraude | H17: 5 | I17: 1 | J17: =H17*I17 -> 5 | L17: Contrôle systématique de toute levée de réservation de fonds | M17: OUI | N17: Resp. OPS | O17: 2 | P17: =H17 -> 5 | Q17: =I17/O17 -> 0.5 | R17: =P17*Q17 -> 2.5
E18: Absence de suivi sur les déblocages de crédit en attente dans le SI | F18: Risque de fraude | G18: Risque de Fraude | H18: 4 | I18: 3 | J18: =H18*I18 -> 12 | L18: Revue des crédits en instance de déblocage journalière | M18: OUI | N18: Resp. OPS | O18: 2 | P18: =H18 -> 4 | Q18: =I18/O18 -> 1.5 | R18: =P18*Q18 -> 6
E19: Absence de procédure et de suivi des virements et versements bancaires reçus | F19: Risque de fraude Risque de pertes financières | G19: Risque de Fraude | H19: 4 | I19: 1 | J19: =H19*I19 -> 4 | L19: S'assurer de l'existance et l'application de la procédure des virements et versements bancaires | M19: NON | N19: Resp. OPS | O19: 2 | P19: =H19 -> 4 | Q19: =I19/O19 -> 0.5 | R19: =P19*Q19 -> 2
E20: Usurpation d'identité sur les escomptes de traite | F20: Risque de fraude Risque de pertes financières | G20: Risque de Fraude | H20: 5 | I20: 1 | J20: =H20*I20 -> 5 | L20: Veiller à la conformité des traites et s'assurer de l'absence de faux homonymes | M20: OUI | N20: Resp. OPS | O20: 2 | P20: =H20 -> 5 | Q20: =I20/O20 -> 0.5 | R20: =P20*Q20 -> 2.5
E21: Duplicata d'une traite avalisée dans le but de l'escompter sur plusieurs banques différentes | F21: Risque de fraude Risque de pertes financières | G21: Risque de Fraude | H21: 5 | I21: 1 | J21: =H21*I21 -> 5 | L21: Veiller à la conformité des traites et s'assurer de l'absence de faux homonymes.Calls back effectué | N21: Resp. OPS | O21: 2 | P21: =H21 -> 5 | Q21: =I21/O21 -> 0.5 | R21: =P21*Q21 -> 2.5
E22: Réactivation non autorisée des comptes dormants | F22: Risque de fraude | G22: Risque de Fraude | H22: 5 | I22: 1 | J22: =H22*I22 -> 5 | L22: Procedure de gestion des comptes dormant existant | M22: OUI | N22: Resp. OPS | O22: 2 | P22: =H22 -> 5 | Q22: =I22/O22 -> 0.5 | R22: =P22*Q22 -> 2.5
E23: Absence de réconciliations sur les transactions B2W /W2B | F23: Risque opérationnel, fraude | G23: Risque de Fraude | H23: 4 | I23: 2 | J23: 12 | L23: Réaliser les reconciliations quotidiennement | M23: OUI | N23: OPS/CONTRÔLE INTERNE | O23: 3 | P23: 4 | Q23: =I23/O23 -> 0.66666667 | R23: =P23*Q23 -> 2.6666667
E24: Absence de réconciliation des transactions OM/WAVE | F24: Risque opérationnel, fraude | G24: Risque de Fraude | H24: 4 | I24: 2 | J24: 12 | L24: Réaliser les reconciliations quotidiennement | M24: OUI | N24: OPS/CONTRÔLE INTERNE | O24: 1 | P24: 4 | Q24: =I24/O24 -> 2 | R24: =P24*Q24 -> 8
E25: Traitement d'un ordre de virement sans preuve de réalisation du call back de l'agence au client | F25: Risque de fraude | G25: Risque de Fraude | H25: 5 | I25: 1 | J25: =H25*I25 -> 5 | L25: S'assurer que tous les ordres de virements soit validés par le chef d'agence | M25: OUI | N25: Resp. OPS | O25: 2 | P25: =H25 -> 5 | Q25: =I25/O25 -> 0.5 | R25: =P25*Q25 -> 2.5
E26: Absence de gestion des comptes débiteurs | F26: Risque de pertes financières Risque de fraude | G26: Risque de Fraude | H26: 5 | I26: 1 | J26: =H26*I26 -> 5 | L26: Contrôle de niveau 1 et 2 mis en place | M26: OUI | N26: Resp. OPS | O26: 3 | P26: =H26 -> 5 | Q26: =I26/O26 -> 0.33333333 | R26: =P26*Q26 -> 1.6666667
E27: • Mauvaise comptabilisation des DAT dans le SI | F27: Risque opérationnel Absence de conformité des données du SI | G27: Risque opérationnel | H27: 5 | I27: 1 | J27: =H27*I27 -> 5 | L27: Contrôle de 1e niveau à J pour la saisies des garanties ;verifier le taux pour toutes les Libérations de DAT effectués dans le SI | M27: NON ( LE CONTRÖLE EST FAIT MAIS PAS J) | N27: Resp. OPS | O27: 2 | P27: =H27 -> 5 | Q27: =I27/O27 -> 0.5 | R27: =P27*Q27 -> 2.5
D28: Gestion des espèces | E28: Absence de politique de convoyage des fonds (approvisionnement et délestage). | F28: Risque de vol Risque de pertes financières | G28: Risque de Fraude | H28: 4 | I28: 3 | J28: =H28*I28 -> 12 | L28: Existence d'une note deservice encadrant le convoyage de fond | M28: OUI | N28: Resp. OPS | O28: 2 | P28: =H28 -> 4 | Q28: =I28/O28 -> 1.5 | R28: =P28*Q28 -> 6
E29: Conservation des espèces | F29: Risque opérationnel, fraude | G29: Risque de Fraude | H29: 4 | I29: 1 | J29: =H29*I29 -> 4 | L29: Procedure de gestion des coffres et caisse disponible | M29: OUI | N29: Resp. OPS | O29: 2 | P29: =H29 -> 4 | Q29: =I29/O29 -> 0.5 | R29: =P29*Q29 -> 2
D30: Transfert d'argent | E30: Absence de certificat ou clé token de sécurité sur la connexion des applications de transfert | F30: Risque de fraude | G30: Risque de Fraude | H30: 4 | I30: 3 | J30: =H30*I30 -> 12 | L30: Installation d'un certificat de sécurité relié à l'adresse IP | M30: OUI | N30: Resp. OPS | O30: 2 | P30: =H30 -> 4 | Q30: =I30/O30 -> 1.5 | R30: =P30*Q30 -> 6
E31: • Non établissement des réconciliations des commissions de transferts d'argent et/ou non comptabilisation des commissions de transferts | F31: Risque de pertes financières | G31: Risque opérationnel | H31: 5 | I31: 2 | J31: =H31*I31 -> 10 | L31: Contrôle de 1er et 2e niveau à J pour toutes les opérations de réconciliation | M31: OUI | N31: Resp. OPS | O31: 2 | P31: =H31 -> 5 | Q31: =I31/O31 -> 1 | R31: =P31*Q31 -> 5
A32: OPERATIONS | E32: EVALUATION INTRINSEQUE | H32: =+ROUND(IFERROR(AVERAGE(H7:H31),0),0) -> 4 | I32: =+ROUND(IFERROR(AVERAGE(I7:I31),0),0) -> 2 | J32: =H32*I32 -> 8 | L32: EVALUATION RESIDUELLE | O32: =+ROUND(IFERROR(AVERAGE(O7:O31),0),0) -> 2 | P32: =+ROUND(IFERROR(AVERAGE(P7:P31),0),0) -> 4 | Q32: =+ROUND(IFERROR(AVERAGE(Q7:Q31),0),0) -> 1 | R32: =P32*Q32 -> 4
F35: Risque de Fraude | G35: =COUNTIF(G7:G31,F35) -> 19
F36: Risque opérationnel | G36: =COUNTIF(G7:G31,F36) -> 6
F37: Risque stratégique | G37: =COUNTIF(G7:G31,F37) -> 0
F38: Risque de crédit | G38: =COUNTIF(G7:G31,F38) -> 0
F39: Risque réglementaire | G39: =COUNTIF(G7:G31,F39) -> 0
F40: Risque de liquidité | G40: =COUNTIF(G7:G31,F40) -> 0
F41: Risque exogéne | G41: =COUNTIF(G7:G31,F41) -> 0

Sheet CREDIT
A1: ANALYSE DES RISQUES OPERATIONNELS - CREDIT & RISQUES
A2: N° | B2: PROCESSUS | C2: RATIO | D2: SOUS PROCESSUS | E2: EXCEPTIONS MAJEURES CONSTATEES | F2: RISQUES CORRELES | G2: FAMILLE DE RISQUES | H2: Gravité | I2: Probabilité | J2: Risque brut (Rb) | K2: Justification de l'évaluation en cas de risque jugé critique | L2: DISPOSITIF DE PREVENTION ET DE CONTRÔLE | P2: gravité résiduelle | Q2: Probabilité résiduelle | R2: Risque résiduel (Rr)
H4: G | I4: P | J4: est égal à GxP | L4: Description du dispositif | M4: Dispositif existant ou non | N4: Owner du Contrôle | O4: Efficacité du dispositif | P4: G | Q4: Pr | R4: est égal à GxP
A5: 2 | B5: CREDIT & RISQUES | C5: 0.4 | D5: Gestion des dossiers de crédit et mise en place | E5: • Dossiers de crédit incomplets (Absence de la convention, contrat cautionnement, certificat de résidence, géolocalisation, Fiche CAT...) | F5: Risque de crédit Risque de non-conformité | G5: Risque de crédit | H5: 4 | I5: 4 | J5: =H5*I5 -> 16 | L5: 1er niveau de vérification au niveau des admin crédit ; 2e niveau de contrôle systématique à J+1 par les vérificateurs post-déblocage; Checklist des documents disponible | M5: OUI | N5: D. CREDIT | O5: 2 | P5: =H5 -> 4 | Q5: =I5/O5 -> 2 | R5: =P5*Q5 -> 8
E6: • Non respect du seuil de validation crédit par SCO | F6: Risque de non-conformité | G6: Risque de crédit | H6: 4 | I6: 4 | J6: =H6*I6 -> 16 | L6: Les seuils de validation sont paramétrés dans créditflow par Crédit Officers à l'exception des restructurations dont la cinématique n'est pas pris en compte | M6: OUI | N6: D. CREDIT | O6: 2 | P6: =H6 -> 4 | Q6: =I6/O6 -> 2 | R6: =P6*Q6 -> 8
E7: Prêts débloqués non décaissés sur une balance agée de plus de 3 mois | F7: Risque opérationnel Risque de fraude Risque de non-conformité | G7: Risque de Fraude | H7: 5 | I7: 4 | J7: =H7*I7 -> 20 | L7: Veiller à procéder aux annulations de prêt ayant une ancienneté de plus de 3 mois pour éviter l'enregistrement des produits fictifs | M7: OUI | N7: D. CREDIT | O7: 2 | P7: =H7 -> 5 | Q7: =I7/O7 -> 2 | R7: =P7*Q7 -> 10
E8: Absence de communication et de validation préalable avec le client sur les condtions du crédit avant la mise en place | F8: Risque de crédit Risque de conformité | G8: risque de crédit Risque de conformité | H8: 5 | I8: 3 | J8: =H8*I8 -> 15 | L8: Mis a jour du contrat avec toutes les informations relatives au crédit | M8: Oui | N8: D. CREDIT | O8: 2 | P8: 5 | Q8: =I8/O8 -> 1.5 | R8: =P8*Q8 -> 7.5
E9: Mise en place crédit sans plan de décaissement | F9: Risque d'image | G9: Risque d'image | H9: 3 | I9: 2 | J9: =H9*I9 -> 6 | O9: 2 | P9: 2 | Q9: =I9/O9 -> 1 | R9: =P9*Q9 -> 2
E10: Absence de visibilité de la Direction crédit sur les dossiers niveau agence et RZ | F10: Risque de crédit Risque de conformité | G10: risque de crédit Risque de conformité | H10: 4 | I10: 4 | J10: =H10*I10 -> 16 | M10: NON | O10: 1 | P10: 4 | Q10: =I10/O10 -> 4 | R10: =P10*Q10 -> 16
E11: Mise en place de COFI-EXPRESS ou SPOT dans le but de solder une partie d'impayés d'un crédit classique | F11: Risque opérationnel Risque de fraude Risque de non-conformité | G11: Risque de Fraude | H11: 5 | I11: 4 | J11: =H11*I11 -> 20 | L11: Le niveau de validation de ces produits est réservé exclusivement au DG; Exclusion des clients en impayés pour ces produits; Exclusion des clients n'ayant pas encore remboursé au moins 30% de l'encours du crédit classique; Refonte du dispositif d'octroi des cofi-express (30% pour cofi-express et 40% pour spot) | M11: OUI | N11: D. CREDIT | O11: 2 | P11: =H11 -> 5 | Q11: =I11/O11 -> 2 | R11: =P11*Q11 -> 10
E12: Mise en place de crédit fictif (Activité inexistante, Escompte de facture déjà payée avec complicité du payeur final…) | F12: Risque opérationnel Risque de fraude Risque de non-conformité | G12: Risque de Fraude | H12: 5 | I12: 4 | J12: =H12*I12 -> 20 | L12: Existence d'un dispositif de vérification auprés du payeur final Visite terrain par le contrôle de 1e, 2e et 3e niveau. | M12: OUI | N12: D. CREDIT | O12: 2 | P12: =H12 -> 5 | Q12: =I12/O12 -> 2 | R12: =P12*Q12 -> 10
E13: Absence d'établissement de lien juridique ou de propriété entre le client et l'activité déclarer par ce dernier | F13: Risque de fraude | G13: Risque de crédit | H13: 4 | I13: 4 | J13: =H13*I13 -> 16 | L13: Checklise de la documentation disponible | R13: =P13*Q13 -> 0
E14: Forte Concentration de secteur d'activités ou type de prêt en matière de crédit | F14: Risque de concentration | G14: Risque de crédit | H14: 4 | I14: 4 | J14: =H14*I14 -> 16 | L14: Seuil plafond de concentration sur un produit ou activité prévu par la politique de crédit | M14: OUI | N14: D. CREDIT | O14: 2 | P14: =H14 -> 4 | Q14: =I14/O14 -> 2 | R14: =P14*Q14 -> 8
E15: Absence de domiciliation irrévoccable sur les crédits causés (Avance sur facture, bon de commande, marché) | F15: Risque de détournement d'objet Risque de fraude | G15: Risque de crédit | H15: 4 | I15: 4 | J15: =H15*I15 -> 16 | L15: Obligation de call back systématique avec confirmation auprés du payeur final | M15: OUI | N15: D. CREDIT | O15: 2 | P15: =H15 -> 4 | Q15: =I15/O15 -> 2 | R15: =P15*Q15 -> 8
E16: Absence d'archivage physique et électronique des dossiers de crédit | F16: Risque opérationnel Pertes de données | G16: Risque opérationnel | H16: 3 | I16: 4 | J16: =H16*I16 -> 12 | L16: Systéme d'archivage electronique gerer par créditflow | M16: OUI | N16: D. CREDIT | O16: 2 | P16: =H16 -> 3 | Q16: =I16/O16 -> 2 | R16: =P16*Q16 -> 6
E17: Absence d'inventaire des dossiers de crédit/ou inventaire non exhaustif | F17: Risque de perte de dossier Dossiers ficitifs | G17: Risque opérationnel | H17: 3 | I17: 4 | J17: =H17*I17 -> 12 | L17: Inventaire exhaustif des dossiers de crédit au niveau central avec documentation. | M17: OUI | N17: D. CREDIT | O17: 2 | P17: =H17 -> 3 | Q17: =I17/O17 -> 2 | R17: =P17*Q17 -> 6
E18: Mise en place d'un produit de crédit non validé par le groupe | F18: risque de non-conformité risque de contrepartie | G18: Risque de crédit | H18: 4 | I18: 3 | J18: =H18*I18 -> 12 | L18: S'assurer que toutes les fiches produits existent et sont validés par le groupe. | N18: D. CREDIT | O18: 2 | P18: =H18 -> 4 | Q18: =I18/O18 -> 1.5 | R18: =P18*Q18 -> 6
E19: Absence d'une procédure normée sur les Call back auprés du payeur final. | F19: risque de contrepartie risque de non-conformité | G19: Risque de crédit | H19: 4 | I19: 3 | J19: =H19*I19 -> 12 | L19: Veiller à mettre en place une procédure ou une politique qui cadre les call-back auprès du payeur final | M19: Non | N19: D. CREDIT | O19: 1 | P19: =H19 -> 4 | Q19: =I19/O19 -> 3 | R19: =P19*Q19 -> 12
E20: Erreur de saisie sur le contrat de prêt | F20: Risque de non-conformité | G20: Risque opérationnel | H20: 4 | I20: 3 | J20: =H20*I20 -> 12 | L20: Existence d'un dispositif de plusieurs niveaux de contrôle | N20: D. CREDIT | O20: 2 | P20: =H20 -> 4 | Q20: =I20/O20 -> 1.5 | R20: =P20*Q20 -> 6
E21: '• Incohérence entre les frais prélevés dans le SI et ceux mentionnés dans le contrat de prêt | F21: Risque de non-conformité | G21: Risque de crédit | H21: 4 | I21: 3 | J21: =H21*I21 -> 12 | L21: Vérification à J+1 par les vérificateurs post déblocage | M21: OUI | N21: D. CREDIT | O21: 2 | P21: =H21 -> 4 | Q21: =I21/O21 -> 1.5 | R21: =P21*Q21 -> 6
E22: '• Erreur de renseignement sur les fiches CAT | F22: Risque de non-conformité | G22: Risque opérationnel | H22: 4 | I22: 3 | J22: =H22*I22 -> 12 | L22: Existence d'un dispositif de plusieurs niveaux de contrôle | M22: OUI | N22: D. CREDIT | O22: 2 | P22: =H22 -> 4 | Q22: =I22/O22 -> 1.5 | R22: =P22*Q22 -> 6
E23: • Absence de signature du PV d'aprobation du comité crédit conseil d'administration pour les dossiers > à la limite filiale | F23: Risque de non-conformité | G23: Risque opérationnel | H23: 4 | I23: 3 | J23: =H23*I23 -> 12 | L23: Les PV sont signés et classés dans le dossier de prêt via créditflow | M23: OUI | N23: D. CREDIT | O23: 2 | P23: =H23 -> 4 | Q23: =I23/O23 -> 1.5 | R23: =P23*Q23 -> 6
E24: Absence de formalisation des garanties | F24: Risque de crédit Risque de non-conformité | G24: Risque de crédit | H24: 4 | I24: 3 | J24: =H24*I24 -> 12 | L24: Formalisation systématique des garanties avant mise en place Vérifacation effectuée par les vérificateurs post déblocage | M24: OUI | N24: D. CREDIT | O24: 2 | P24: =H24 -> 4 | Q24: =I24/O24 -> 1.5 | R24: =P24*Q24 -> 6
E25: Non | F25: Risque de perte de données confidentielles en cas d'incendie Risque de vol | G25: Risque opérationnel | H25: 4 | I25: 3 | J25: =H25*I25 -> 12 | L25: Garanties gérées par le juridique | M25: OUI (Les armoires ignifuges qui sont en place sont pleines, il convient d'en rajouter une autre ) | N25: D. CREDIT | O25: 2 | P25: =H25 -> 4 | Q25: =I25/O25 -> 1.5 | R25: =P25*Q25 -> 6
D26: Octroi de credit & Monitoring / Gestion du Portefeuille | E26: • Erreur d'analyse dans l'étude des dossiers des crédits | F26: Risque d'impayés Risque de pertes financières | G26: Risque de crédit | H26: 5 | I26: 3 | J26: =H26*I26 -> 15 | L26: Contre vérification obligatoire pour tout dossiers jusqu'à 7M Contre évaluation obligatoire des dossiers comités par les analystes crédit | M26: OUI | N26: D. CREDIT | O26: 2 | P26: =H26 -> 5 | Q26: =I26/O26 -> 1.5 | R26: =P26*Q26 -> 7.5
E27: • Financement de plusieurs prêts pour un seul client disposant de plusieurs comptes | F27: Risque de fraude Risque de pertes financières | G27: Risque de Fraude | H27: 5 | I27: 3 | J27: =H27*I27 -> 15 | L27: L'outil de gestion et d'instruction des dossiers de crédit créditflow prend en compte le nombre de comptes dont dispose un client | M27: OUI | N27: D. CREDIT | O27: 1 | P27: =H27 -> 5 | Q27: =I27/O27 -> 3 | R27: =P27*Q27 -> 15
E28: • Non-respect des niveaux de PAR (30, 90, 180) | F28: Risque réglementaire Risque de fraude | G28: Risque réglementaire | H28: 5 | I28: 5 | J28: =H28*I28 -> 25 | L28: Monitoring de suivi strict conformément à la politique de recouvrement et suivi des impayés | M28: OUI | N28: D. CREDIT | O28: 2 | P28: =H28 -> 5 | Q28: =I28/O28 -> 2.5 | R28: =P28*Q28 -> 12.5
E29: • Non réalisation systématique des visites et contre-visite terrain permettant de localiser l'activité ou le domicile du client, de constater visuellement l'existence des biens présentés en garantie et d'évaluer la capacité de remboursement du client | F29: Risque de détournement d'objet Risque de fraude | G29: Risque de crédit | H29: 3 | I29: 5 | J29: =H29*I29 -> 15 | L29: Contre vérification obligatoire pour tout dossiers jusqu'à 7M Contre évaluation obligatoire des dossiers comités par les analystes crédit | M29: OUI | N29: D. CREDIT | O29: 2 | P29: =H29 -> 3 | Q29: =I29/O29 -> 2.5 | R29: =P29*Q29 -> 7.5
D30: Gestion des prêts restructurés, impayés & Pré-Contentieux | E30: • Absence de suivi des prêts restructurés ou décalés | F30: Risque réglementaire Risque de pertes financières | G30: Risque de crédit | H30: 5 | I30: 3 | J30: =H30*I30 -> 15 | L30: Suivi assurer par le risque | M30: OUI | N30: D. CREDIT | O30: 2 | P30: =H30 -> 5 | Q30: =I30/O30 -> 1.5 | R30: =P30*Q30 -> 7.5
E31: Restructuration de prêt sans matérialisation du consentement du client | F31: Risque opérationnel Risque de fraude Risque de non-conformité | G31: Risque de Fraude | H31: 5 | I31: 4 | J31: =H31*I31 -> 20 | L31: Obligation de signature des clients avant restructuration Vérification et suivi assurer au niveau du risque | M31: OUI | N31: D. CREDIT | O31: 2 | P31: =H31 -> 5 | Q31: =I31/O31 -> 2 | R31: =P31*Q31 -> 10
E32: Décalage échéance sans matérialisation de la demande du client | F32: Risque opérationnel Risque de fraude Risque de non-conformité | G32: Risque de Fraude | H32: 4 | I32: 4 | J32: =H32*I32 -> 16 | L32: Obligation de signature des clients avant décalage Vérification et suivi assurer au niveau du risque | M32: OUI | N32: D. CREDIT | O32: 2 | P32: =H32 -> 4 | Q32: =I32/O32 -> 2 | R32: =P32*Q32 -> 8
D33: Gestion des garanties | E33: Inventaire des garanties non exhaustives | F33: Risque opérationnel Risque de non-conformité | G33: Risque de crédit | H33: 4 | I33: 4 | J33: =H33*I33 -> 16 | L33: Existence d'un planning (6mois) de verification et de suivi des garanties pour s'assurer de leurs exhaustivitées | M33: OUI | N33: D. CREDIT | O33: 1 | P33: =H33 -> 4 | Q33: =I33/O33 -> 4 | R33: =P33*Q33 -> 16
E34: Mise en place d'un crédit avec de fausses garanties données par le client (Fausses cartes grises, Faux titres…) | F34: Risque de fraude Risque de pertes financières | G34: Risque de crédit | H34: 5 | I34: 3 | J34: =H34*I34 -> 15 | L34: Vérification de la disponibilité et de l'authenticité des garanties par les vérificateur post déblocage | M34: OUI | N34: D. CREDIT | O34: 2 | P34: =H34 -> 5 | Q34: =I34/O34 -> 1.5 | R34: =P34*Q34 -> 7.5
E35: Procéder à l'adjudication des garanties pour solder une créance sans disposer des Etats de droits réels | F35: Risque opérationnel Risque de fraude Risque de non-conformité | G35: Risque de Fraude | H35: 5 | I35: 3 | J35: =H35*I35 -> 15 | L35: Obligation de la complétude de la documentation (PV de justice ...) avant de passer les écritures | M35: OUI | N35: D. CREDIT | O35: 2 | P35: =H35 -> 5 | Q35: =I35/O35 -> 1.5 | R35: =P35*Q35 -> 7.5
D36: Gestion des dossiers d'engagement Hors bilan | E36: • Incomplétude des dossiers d'engagement par signature | F36: Risque de conformité | G36: Risque de crédit | H36: 4 | I36: 3 | J36: =H36*I36 -> 12 | L36: Digitalisation en cours | M36: NON | N36: D. CREDIT | O36: 1 | P36: =H36 -> 4 | Q36: =I36/O36 -> 3 | R36: =P36*Q36 -> 12
E37: • Appel à la caution des traites tombées en impayés | F37: Risque de perte financière | G37: Risque de crédit | H37: 5 | I37: 2 | J37: =H37*I37 -> 10 | L37: Constitution d'un dossier avec garantie a l'appui | M37: OUI | N37: D. CREDIT | O37: 2 | P37: =H37 -> 5 | Q37: =I37/O37 -> 1 | R37: =P37*Q37 -> 5
A38: CREDIT & RISQUES | E38: EVALUATION INTRINSEQUE | H38: =+ROUND(IFERROR(AVERAGE(H5:H37),0),0) -> 4 | I38: =+ROUND(IFERROR(AVERAGE(I5:I37),0),0) -> 3 | J38: =I38*H38 -> 12 | L38: EVALUATION RESIDUELLE | O38: =+ROUND(IFERROR(AVERAGE(O5:O36),0),0) -> 2 | P38: =+ROUND(IFERROR(AVERAGE(P5:P36),0),0) -> 4 | Q38: =+ROUND(IFERROR(AVERAGE(Q5:Q36),0),0) -> 2 | R38: =+ROUND(IFERROR(AVERAGE(R5:R36),0),0) -> 8
F41: Risque de Fraude | G41: =COUNTIF(G5:G37,F41) -> 7
F42: Risque opérationnel | G42: =COUNTIF(G5:G37,F42) -> 6
F43: Risque stratégique | G43: =COUNTIF(G5:G37,F43) -> 0
F44: Risque de crédit | G44: =COUNTIF(G5:G37,F44) -> 16
F45: Risque réglementaire | G45: =COUNTIF(G5:G37,F45) -> 1
F46: Risque de liquidité | G46: =COUNTIF(G5:G37,F46) -> 0
F47: Risque exogéne | G47: =COUNTIF(G5:G37,F47) -> 0

Sheet FINANCES & REPORTING
A1: ANALYSE DES RISQUES OPERATIONNELS - FINANCE & COMPTABILITE
A2: N° | B2: PROCESSUS | C2: RATIO | D2: SOUS PROCESSUS | E2: EXCEPTIONS MAJEURES CONSTATEES | F2: RISQUES CORRELES | G2: FAMILLE DE RISQUE | H2: Gravité | I2: Probabilité | J2: Risque brut (Rb) | K2: Justification de l'évaluation en cas de risque jugé critique | L2: DISPOSITIF DE PREVENTION ET DE CONTRÔLE | P2: Gravité résiduelle | Q2: Probabilité résiduelle | R2: Risque résiduel (Rb)
H4: G | I4: P | J4: est égal à GxP | L4: Description du dispositif | M4: Dispositif existant ou Non | N4: Owner du Contrôle | O4: Efficacité du dispositif | P4: G | Q4: Pr | R4: est égal à GxP
E5: Absence de ventillation des immobilisations par site | F5: Risque financier | G5: Risque financier | H5: 4 | I5: 4 | J5: =H5*I5 -> 16 | L5: Mis a du fichier immobilisation | M5: NON | N5: DFC | O5: 1 | P5: 4 | Q5: =I5/O5 -> 4 | R5: =Q5*P5 -> 16
E6: existence d'écarts entre le fichier extra comptable des immobilisations et la comptabilité | F6: Risque Financier | G6: Risque financier | H6: 4 | I6: 4 | J6: =H6*I6 -> 16 | L6: Correction des écarts | M6: NON | N6: DFC | O6: 1 | Q6: =I6/O6 -> 4 | R6: =Q6*P6 -> 0
E7: Non respect des inventaires annuels | F7: Risque opérationnels | G7: Risque opérationnels | H7: 3 | I7: 2 | J7: =H7*I7 -> 6 | L7: Procedure de ges gestion des inventaires existant | M7: OUI | N7: DFC | O7: 3 | P7: 3 | Q7: =I7/O7 -> 0.66666667 | R7: =Q7*P7 -> 2
A8: 5 | B8: FINANCE & REPORTING | C8: 0.1 | D8: Arrêté & clôture périodique comptable | E8: Absence d'analyse (Proof) des comptes internes et rapprochements bancaires et/ou de suivi des suspens identifiés | F8: Risque de pertes financières Risque de fraude | G8: Risque de Fraude | H8: 5 | I8: 4 | J8: =H8*I8 -> 20 | L8: Analyse des comptes effectué chaque mois | M8: OUI | N8: DFC | O8: 2 | P8: =H8 -> 5 | Q8: =I8/O8 -> 2 | R8: =Q8*P8 -> 10
E9: • Non justification des opérations comptabilisées dans le système par des pièces probantes | F9: Risque de fraude | G9: Risque de Fraude | H9: 5 | I9: 4 | J9: =H9*I9 -> 20 | L9: Contrôle de 2e niveau à J pour toutes les opérations passées dans le SI | M9: Le contrôle existe mais n'est pas réalisé à J | N9: CONTRÔLE INTERNE | O9: 2 | P9: =H9 -> 5 | Q9: =I9/O9 -> 2 | R9: =Q9*P9 -> 10
E10: • Gap de provisionnement selon les exigences de la banque centrale | F10: Risque de fraude Risque de non-conformité des informations comptables | G10: Risque de Fraude | H10: 5 | I10: 4 | J10: =H10*I10 -> 20 | L10: Contrôle de second mis en place mensuellement | M10: OUI | N10: CONTRÔLE INTERNE | O10: 2 | P10: =H10 -> 5 | Q10: =I10/O10 -> 2 | R10: =Q10*P10 -> 10
E11: • Prélévement automatique de la TAF non exhaustif | F11: Risque de redressement fiscal Risque de pertes financières, pénalités | G11: Risque réglementaire | H11: 5 | I11: 2 | J11: =H11*I11 -> 10 | L11: Assurer un suivi du paramétrage efficace sur tous les prélévements de TAF | M11: OUI | N11: HEAD IT | O11: 1 | P11: =H11 -> 5 | Q11: =I11/O11 -> 2 | R11: =P11*Q11 -> 10
E12: • Prélévement automatique de l'IRCD non exhaustif | F12: Risque de redressement fiscal Risque de pertes financières, pénalités | G12: Risque réglementaire | H12: 5 | I12: 2 | J12: =H12*I12 -> 10 | L12: Assurer un suivi du paramétrage efficace sur tous les prélévements IRCD | M12: OUI | N12: HEAD IT | O12: 1 | P12: =H12 -> 5 | Q12: =I12/O12 -> 2 | R12: =P12*Q12 -> 10
E13: • Défaut de provisionnement des congés | F13: Risque de fraude Risque de non-conformité des informations comptables | G13: Risque de Fraude | H13: 4 | I13: 4 | J13: =H13*I13 -> 16 | L13: Note de service existant limtant le plaffond des solde de congés à 72 jours | M13: OUI | N13: CONTRÔLE INTERNE | O13: 2 | P13: =H13 -> 4 | Q13: =I13/O13 -> 2 | R13: =Q13*P13 -> 8
E14: • Charges constatées sur des comptes non appropriés (Enregistrement des opérations de charge dans les comptes d'attente) | F14: Risque de fraude Risque de non-conformité des informations comptables | G14: Risque de Fraude | H14: 5 | I14: 4 | J14: =H14*I14 -> 20 | L14: Analyse des comptes d'attente effectué chaque mois Contrôle de second mesuel instauré | M14: OUI | N14: CONTRÔLE INTERNE | O14: 2 | P14: =H14 -> 5 | Q14: =I14/O14 -> 2 | R14: =Q14*P14 -> 10
E15: • Précompte d'intérêts ou commissions sur crédits non échus | F15: Risque de fraude Risque de non-conformité des informations comptables | G15: Risque de Fraude | H15: 5 | I15: 3 | J15: =H15*I15 -> 15 | L15: Veiller au respect du manuel de procédures comptables | M15: OUI | N15: CONTRÔLE INTERNE | O15: 2 | P15: =H15 -> 5 | Q15: =I15/O15 -> 1.5 | R15: =Q15*P15 -> 7.5
E16: • Radiation de créances non effectuée sur les comptes de charge appropriés | F16: Risque de fraude Risque de non-conformité des informations comptables | G16: Risque de Fraude | H16: 5 | I16: 3 | J16: =H16*I16 -> 15 | L16: Veiller à ce que les comptabilisations soient faites conformément au référentiel SFD | M16: OUI | N16: DFC | O16: 2 | P16: =H16 -> 5 | Q16: =I16/O16 -> 1.5 | R16: =Q16*P16 -> 7.5
E17: Absence d'une procédure d'encadrement des clôtures | H17: 4 | I17: 4 | J17: =H17*I17 -> 16 | M17: NON | N17: DFC | O17: 1 | P17: 4 | Q17: =I17/O17 -> 4 | R17: =Q17*P17 -> 16
E18: • Déséquilibre de la balance à une date d'arrêté donnée | F18: Risque opérationnel Risque de fraude | G18: Risque de Fraude | H18: 4 | I18: 4 | J18: =H18*I18 -> 16 | L18: Effectuer une analyse efficiente et un suivi particulier de la balance de façon Hebdomadaire | M18: OUI | N18: DFC | O18: 2 | P18: =H18 -> 4 | Q18: =I18/O18 -> 2 | R18: =Q18*P18 -> 8
D19: Dossiers comptables | E19: '• Dossiers comptables incomplets (Absence de facture proformat ou Bon de commande) | F19: Risque opérationnel Risque de fraude | G19: Risque de Fraude | H19: 4 | I19: 3 | J19: =H19*I19 -> 12 | L19: Contrôle de 2e niveau pour toutes journées comptables à J. | M19: Le contrôle existe mais n'est pas réalisé à J | N19: CONTRÔLE INTERNE | O19: 2 | P19: =H19 -> 4 | Q19: =I19/O19 -> 1.5 | R19: =Q19*P19 -> 6
E20: Non-Conformité des factures | F20: Risque financier Risque de fraude | G20: Risque de Fraude | H20: 4 | I20: 3 | J20: =H20*I20 -> 12 | L20: Validation de Responsable achat logistique avec matérialisation avant ransmission à la DFC | M20: OUI | N20: DFC | O20: 2 | P20: =H20 -> 4 | Q20: =I20/O20 -> 1.5 | R20: =Q20*P20 -> 6
D21: Reporting financier (groupe - bailleurs) / Règlementaire (Tutelle-DRS-BCEAO-COBAC-BCRG) | E21: • Sanctions règlementaires du fait du non-respect systématique des normes de gestion (limitation des risques, couverture des emplois, limitation des prêts aux dirigeants, limitation des risques par signature, coefficient de liquidité, constitution de la réserve générale, capitalisation,....) du dispositif prudentiel instaurées par l'Institution | F21: Sanctions légales Sanctions pécunaires | G21: Risque réglementaire | H21: 5 | I21: 2 | J21: =H21*I21 -> 10 | L21: Recruter un contrôleur de gestion et assurer un suivi efficace et rigoureux du dispositif prudentiel | M21: OUI | N21: DFC | O21: 2 | P21: =H21 -> 5 | Q21: =I21/O21 -> 1 | R21: =Q21*P21 -> 5
E22: • Non automatisation des reporting règlementaire, financier et métier | F22: Risque de non-conformité des informations issues du SI | G22: Risque réglementaire | H22: 4 | I22: 4 | J22: =H22*I22 -> 16 | L22: Mettre en place dans le SI, une production automatisée de tous les reportings | M22: NON | N22: IT | O22: 1 | P22: =H22 -> 4 | Q22: =I22/O22 -> 4 | R22: =Q22*P22 -> 16
E23: Absence de Contrôle des informations financières et comptables communiquées aux Autorités de tutelle | F23: Non-conformité Litige avec les autorités | G23: Risque réglementaire | H23: 4 | I23: 3 | J23: =H23*I23 -> 12 | L23: Validation du CFO avnat la transmission des informations | M23: OUI | N23: DFC | O23: 2 | P23: =H23 -> 4 | Q23: =I23/O23 -> 1.5 | R23: =Q23*P23 -> 6
E24: Retard de dépôt des reporting règlementaires | F24: Risque de non-conformité | G24: Risque réglementaire | H24: 4 | I24: 4 | J24: =H24*I24 -> 16 | L24: S'assurer du dépôt des reporting obligatoires dans les délais | M24: OUI | N24: DFC | O24: 3 | P24: =H24 -> 4 | Q24: =I24/O24 -> 1.3333333 | R24: =Q24*P24 -> 5.3333333
D25: SUIVI BUDGETAIRE | E25: • Retard de déclaration/paiement des impôts, taxes et redevances et/ou erreur de calcul dans la détermination des impôts, taxes et redevances à payer | F25: Risque de redressement fiscal, ou pénalités | G25: Risque réglementaire | H25: 4 | I25: 4 | J25: =H25*I25 -> 16 | L25: Contrôle de 2e niveau pour toutes les déclarations à M. | M25: Le contrôle existe mais n'est pas réalisé à M | N25: CONTRÔLE INTERNE | O25: 2 | P25: =H25 -> 4 | Q25: =I25/O25 -> 2 | R25: =Q25*P25 -> 8
E26: Absence de déclaration des commissions liées à certaines activités hors épargne et crédit | F26: Risque réglementaire | G26: Risque opérationnelle | H26: 4 | I26: 3 | J26: =H26*I26 -> 12 | L26: Mise en place d'un controele de niveau1 | M26: NON | P26: =H26 -> 4
E27: Absence d'un suivi budgétaire par département | J27: =H27*I27 -> 0 | L27: Mise en place d'un suivi budgetaire par département | M27: NON
E28: Absence de Contrôle de la correcte comptabilisation de l'impôt/taxe | F28: Non-conformité Litige avec les autorités | G28: Risque réglementaire | H28: 4 | I28: 3 | J28: =H28*I28 -> 12 | L28: Il s'agit de s'assurer de la correcte comptabilisation : - de l'impôt / taxe dans les comptes sociaux (bilan : charge à payer ou dette fiscale et résultat) et dans la bonne période, - de l'impôt exigible et de l'impôt différé dans des comptes distincts, - de l'impôt différé en capitaux propres et non en résultat, si il affecte des éléments de capitaux propres - des écritures de centralisation des déclarations , - l'absence de compensation indue des créances et dettes d'impôt. - l'absence de compensation entre actifs et passifs d'impôt exigible sauf justification adhoc. Il s'agit par ailleurs de s'assurer de la justification des traitements comptables et la piste d'audit des retraitements fiscaux. | M28: NON | N28: DFC | O28: 2 | P28: =H28 -> 4 | Q28: =I28/O28 -> 1.5 | R28: =Q28*P28 -> 6
D29: Trésorerie / ALM | E29: • Risque de liquidité, de taux d'intérêt et de taux de change et non respect des ratios règlementaires | F29: Sanctions légales Sanctions pécunaires | G29: Risque de liquidité | H29: 4 | I29: 3 | J29: =H29*I29 -> 12 | L29: Recruter un contrôleur de gestion et assurer un suivi efficace et rigoureux du dispositif prudentiel | M29: OUI | N29: DFC | O29: 2 | P29: =H29 -> 4 | Q29: =I29/O29 -> 1.5 | R29: =Q29*P29 -> 6
E30: Absence de procédure et politique sur la gestion de la trésorerie | F30: Risque de liquidité Risque de pertes financières | G30: Risque de liquidité | H30: 4 | I30: 3 | J30: =H30*I30 -> 12 | L30: S'assurer de l'existence d'une politique de gestion de la trésorerie et veiller au respect de la procédure | M30: NON | N30: DFC | O30: 2 | P30: =H30 -> 4 | Q30: =I30/O30 -> 1.5 | R30: =Q30*P30 -> 6
A31: FINANCES & REPORTING | E31: EVALUATION INTRINSEQUE | H31: =+ROUND(IFERROR(AVERAGE(H8:H29),0),0) -> 4 | I31: =+ROUND(IFERROR(AVERAGE(I8:I29),0),0) -> 3 | J31: =H31*I31 -> 12 | L31: EVALUATION RESIDUELLE | O31: =+ROUND(IFERROR(AVERAGE(O8:O29),0),0) -> 2 | P31: =+ROUND(IFERROR(AVERAGE(P8:P29),0),0) -> 4 | Q31: =+ROUND(IFERROR(AVERAGE(Q8:Q29),0),0) -> 2 | R31: =Q31*P31 -> 8
F34: Risque de Fraude | G34: =COUNTIF(G2:G30,F34) -> 10
F35: Risque opérationnelle | G35: =COUNTIF(G5:G30,F35) -> 1
F36: Risque stratégique | G36: =COUNTIF(G4:G32,F36) -> 0
F37: Risque de crédit | G37: =COUNTIF(G5:G33,F37) -> 0
F38: Risque réglementaire | G38: =COUNTIF(G6:G34,F38) -> 8
F39: Risque de liquidité | G39: =COUNTIF(G7:G35,F39) -> 2
F40: Risque exogéne | G40: =COUNTIF(G8:G36,F40) -> 0

Sheet IT 
A1: ANALYSE DES RISQUES OPERATIONNELS - SYSTÈME D'INFORMATION
A2: N° | B2: PROCESSUS | C2: RATIO | D2: SOUS PROCESSUS | E2: EXCEPTIONS MAJEURES CONSTATEES | F2: RISQUES CORRELES | G2: FAMILLE DE RISQUE | H2: Gravité | I2: Probabilité | J2: Risque bruts (Rb) | K2: Justification de l'évaluation en cas de risque jugé critique | L2: DISPOSITIF DE PREVENTION ET DE CONTRÔLE | P2: Gravité résiduelle | Q2: Probabilité résiduelle | R2: Risque résiduel (Rr)
H4: G | I4: P | J4: est égal à GxP | L4: Description du dispositif | M4: Dispositif existant ou non | N4: Owner du Contrôle | O4: Efficacité du dispositif | P4: G | Q4: Pr | R4: est égal à GxPr
A5: 3 | B5: IT | C5: 0.05 | D5: Gestion du SI FLEXCUBE | E5: • Indisponibilité du SIG (FLEXCUBE) | F5: Risque de pertes financères Risque opérationnel | G5: Risque opérationnel | H5: 4 | I5: 3 | J5: =H5*I5 -> 12 | L5: Contrôle permanent du serveur Elaboration et mise en place d'un PCA propre à la filiale | M5: OUI | N5: HEAD IT | O5: 2 | P5: =H5 -> 4 | Q5: =I5/O5 -> 1.5 | R5: =P5*Q5 -> 6
E6: • Défaillances du CBS (dysfonctionnement) identifiées non corrigées | F6: Risque de pertes financères Risque opérationnel | G6: Risque opérationnel | H6: 5 | I6: 2 | J6: =H6*I6 -> 10 | L6: Correction systématique de toutes les défaillances | M6: OUI | N6: HEAD IT | O6: 1 | P6: =H6 -> 5 | Q6: =I6/O6 -> 2 | R6: =P6*Q6 -> 10
D7: Gestion des changements Système et Réseau | E7: • Non-respect de la procédure des changements, des configurations et des mises en production (Un changement consiste à modifier, créer ou supprimer un des composants de l'infrastructure du système d'information) | F7: Risque opérationnel Risque de fraude | G7: Risque de Fraude | H7: 4 | I7: 4 | J7: =H7*I7 -> 16 | L7: Veiller au strict respect de la procédure | M7: OUI | N7: HEAD IT / CONTRÔLE INTERNE | O7: 2 | P7: =H7 -> 4 | Q7: =I7/O7 -> 2 | R7: =P7*Q7 -> 8
D8: Gestion des comptes et habilitations | E8: • Accès non autorisé et inadéquation des accès à la fonction ou poste occupé | F8: Risque de fraude | G8: Risque de Fraude | H8: 5 | I8: 2 | J8: =H8*I8 -> 10 | L8: Veiller au strict respect de la procédure des habilitations | M8: OUI | N8: HEAD IT / CONTRÔLE INTERNE | O8: 2 | P8: =H8 -> 5 | Q8: =I8/O8 -> 1 | R8: =P8*Q8 -> 5
E9: • Absence de fiabilité de la matrice des habilitations mise en place par le groupe | F9: Risque de fraude | G9: Risque de Fraude | H9: 4 | I9: 3 | J9: =H9*I9 -> 12 | M9: OUI | O9: 2 | P9: =H9 -> 4 | Q9: =I9/O9 -> 1.5 | R9: =P9*Q9 -> 6
E10: • Manque de communication en interne, entrainant une faiblesse dans la désactivation des profils sortants. | F10: Risque de fraude | G10: Risque de Fraude | H10: 4 | I10: 4 | J10: =H10*I10 -> 16 | L10: Mettre en place une matrice des habilitations complexe et fiable (Communication automatique aux Its pour tout mouvement ou départ du staff) | M10: OUI | N10: HEAD IT / CONTRÔLE INTERNE | O10: 2 | P10: =H10 -> 4 | Q10: =I10/O10 -> 2 | R10: =P10*Q10 -> 8
D11: Gestion de la sécurité physique et Réseau | E11: • Systéme d'Alarme non fonctionnelle | F11: Risque de vol, braquage, d'insécurité | G11: Risque de Fraude | H11: 4 | I11: 3 | J11: =H11*I11 -> 12 | L11: Suivi hebdomadaire et régulier de la fonctionnalité des alarmes | M11: OUI | N11: HEAD IT | O11: 2 | P11: =H11 -> 4 | Q11: =I11/O11 -> 1.5 | R11: =P11*Q11 -> 6
E12: • Manque d'espace de stockage des images de la vidéo-surveillance | F12: Non identification des images en cas de vol | G12: Risque de Fraude | H12: 4 | I12: 4 | J12: =H12*I12 -> 16 | L12: Mettre en place des disques de haute capacité pour le stockage de toutes les images d'au minimum 6 mois | M12: OUI | N12: HEAD IT | O12: 2 | P12: =H12 -> 4 | Q12: =I12/O12 -> 2 | R12: =P12*Q12 -> 8
E13: • Défaillance des détecteurs de mouvement ou de fumée | F13: Risque de sécurité | G13: Risque opérationnel | H13: 3 | I13: 4 | J13: =H13*I13 -> 12 | L13: Suivi mensuel et régulier de tous les détecteurs de mouvement et fumée | M13: OUI | N13: HEAD IT | O13: 2 | P13: =H13 -> 3 | Q13: =I13/O13 -> 2 | R13: =P13*Q13 -> 6
E14: • Absence d'un PCA (Plan de Continuité d'activité) | F14: Risque de non continuité des activités | G14: Risque opérationnel | H14: 3 | I14: 4 | J14: =H14*I14 -> 12 | L14: Mettre en place un PCA efficace | M14: OUI | N14: HEAD IT | O14: 2 | P14: =H14 -> 3 | Q14: =I14/O14 -> 2 | R14: =P14*Q14 -> 6
E15: • Absence d'un régulateur de tension ou Onduleur dans le local technique | F15: Risque de non continuité des activités | G15: Risque opérationnel | H15: 4 | I15: 3 | J15: =H15*I15 -> 12 | L15: Mettre en place un régulateur de tension et onduleur de qualité et d'en assurer une maintenance régulière. | M15: OUI | N15: HEAD IT | O15: 2 | P15: =H15 -> 4 | Q15: =I15/O15 -> 1.5 | R15: =P15*Q15 -> 6
E16: • Faiblesse de la sécurité par rapport à l'accès de la salle serveur. | F16: Risque de sécurité | G16: Risque de Fraude | H16: 4 | I16: 3 | J16: =H16*I16 -> 12 | L16: Renforcer la sécurité par rapport à l'accès de la salle serveur. | M16: OUI | N16: HEAD IT | O16: 1 | P16: =H16 -> 4 | Q16: =I16/O16 -> 3 | R16: =P16*Q16 -> 12
D17: Administration des bases de données | E17: • Corruption de la base de données (Possibilité de créer, modifier et supprimer des informations) | F17: Risque de fraude | G17: Risque de Fraude | H17: 5 | I17: 3 | J17: =H17*I17 -> 15 | L17: Rendre inaccessible la base de données aux IT locaux et veiller à un suivi de haute sécurité à distance | M17: OUI | N17: MANAGEMENT | O17: 2 | P17: =H17 -> 5 | Q17: =I17/O17 -> 1.5 | R17: =P17*Q17 -> 7.5
E18: • Non sauvegarde des données et pas de site de secours | F18: Risque de perte de données | G18: Risque opérationnel | H18: 4 | I18: 4 | J18: =H18*I18 -> 16 | L18: Mettre en place un site de secours de la sauvegarde journalière de toutes les données | M18: OUI | N18: HEAD IT | O18: 1 | P18: =H18 -> 4 | Q18: =I18/O18 -> 4 | R18: =P18*Q18 -> 16
D19: Gestion des postes de travail | E19: Indisponibilité d'un poste de travail sur une fonction stratégique | F19: Risque opérationnel | G19: Risque stratégique | H19: 3 | I19: 3 | J19: =H19*I19 -> 9 | L19: Identifier les postes de travail critiques. Prévoir des machines de réserve déjà configurées. | M19: OUI | N19: HEAD IT | O19: 1 | P19: =H19 -> 3 | Q19: =I19/O19 -> 3 | R19: =P19*Q19 -> 9
D20: Gestion des incidents | E20: • Absence de documentation du suivi des incidents qui ne permet pas au management d’apprécier à date leur récurrence et les actions entreprises pour leur résolution. | F20: Risque opérationnel | G20: Risque opérationnel | H20: 3 | I20: 3 | J20: =H20*I20 -> 9 | L20: Suivi des rapports d'incidents et effectuer les remontées vers le top management en fonction du niveau de criticité | M20: OUI | N20: HEAD IT | O20: 2 | P20: =H20 -> 3 | Q20: =I20/O20 -> 1.5 | R20: =P20*Q20 -> 4.5
D21: Gestion de la sécurité SI | E21: Absence de scan(recherche) des vulnérabilités (afilles de sécurité) internes | F21: Risque opérationnel | G21: Risque opérationnel | H21: 4 | I21: 3 | J21: =H21*I21 -> 12 | L21: Mettre en place et suivre les rapports de scans de vulnérabilités internes | M21: OUI | N21: HEAD IT ET RSSI | O21: 2 | P21: =H21 -> 4 | Q21: =I21/O21 -> 1.5 | R21: =P21*Q21 -> 6
E22: Absence de formation présentielle des utilisateurs sur les bonnes pratiques | F22: Risque humain | G22: Risque stratégique | H22: 4 | I22: 3 | J22: =H22*I22 -> 12 | L22: Suivi du planning de formation des utilisateurs | M22: OUI | N22: HEAD IT ET RSSI | O22: 2 | P22: =H22 -> 4 | Q22: =I22/O22 -> 1.5 | R22: =P22*Q22 -> 6
D23: Gestion de la messagerie | E23: Absence de procédure de classification de l'information (caractère secret, confidentiel, interne et public) | F23: Risque humain | G23: Risque stratégique | H23: 4 | I23: 3 | J23: =H23*I23 -> 12 | L23: Identifier pour chaque processus le niveau de classification de l'information | M23: OUI | N23: HEAD IT ET RSSI | O23: 2 | P23: =H23 -> 4 | Q23: =I23/O23 -> 1.5 | R23: =P23*Q23 -> 6
D24: Gestion des ressources IT | E24: Absence de backup à certains postes critiques | F24: Risque humain | G24: Risque stratégique | H24: 4 | I24: 3 | J24: =H24*I24 -> 12 | L24: S'assurer que chaque fonction critique dispose d'un backup | M24: OUI | N24: HEAD IT ET DRH | O24: 2 | P24: =H24 -> 4 | Q24: =I24/O24 -> 1.5 | R24: =P24*Q24 -> 6
E25: Absence de formation ou de mise à niveau des ressources | F25: Risque humain | G25: Risque stratégique | H25: 4 | I25: 3 | J25: =H25*I25 -> 12 | L25: Identifier les formations qui sont en adéquation avec l'évolution de la fonction exercée | M25: OUI | N25: HEAD IT ET DRH | O25: 2 | P25: =H25 -> 4 | Q25: =I25/O25 -> 1.5 | R25: =P25*Q25 -> 6
D26: Gestion de la maintenance du SI | E26: Absence de contrat de maintenance sur les actifs critiques du local informatique | F26: Risque opérationnel | G26: Risque opérationnel | H26: 5 | I26: 4 | J26: =H26*I26 -> 20 | L26: S'assurer de l'existence d'un contrat de maintenance pour les actifs critiques du local technique Effectuer des tests periodiques (avec le contrôle permament) sur l'état de fonctionnement des actifs critiques (onduleur, groupe éléectrogène, climatisation, détecteur d'humidité, extincteurs, dispositif extinction automatique incendie...) | M26: OUI | N26: HEAD IT | O26: 2 | P26: =H26 -> 5 | Q26: =I26/O26 -> 2 | R26: =P26*Q26 -> 10
D27: Gestion de la cybersécurité | E27: Fraud par comprimission d'un mail professionnel par | F27: Risque de fraude | G27: Risque de Fraude | H27: 5 | I27: 4 | J27: =H27*I27 -> 20 | L27: activation de la MFA, Geolocalisation de adresse mail, activation du DMARC sur le domaine, campagne de sensibilisation | M27: NON | N27: RSSI | O27: 2 | P27: =H27 -> 5 | Q27: =I27/O27 -> 2 | R27: =P27*Q27 -> 10
E28: Fraud par intrusion externe dans le SI | F28: Risque de fraude | G28: Risque de Fraude | H28: 5 | I28: 5 | J28: =H28*I28 -> 25 | L28: Scan de vulnérabilité externe effectuée chaque mois, mise en place de règles strictes avant exposition d'une application sur internet, surveillance reseaux 24/7 *365, revue des paramètres | M28: NON | N28: RSSI | O28: 2 | P28: =H28 -> 5 | Q28: =I28/O28 -> 2.5 | R28: =P28*Q28 -> 12.5
E29: Exflitration de données par ronçongiciel | F29: Risque de fraude | G29: Risque de Fraude | H29: 5 | I29: 4 | J29: =H29*I29 -> 20 | L29: renforcement Anti-virus, sensibilisation, surveillance des flux réseau, | M29: NON | N29: RSSI | O29: 2 | P29: =H29 -> 5 | Q29: =I29/O29 -> 2 | R29: =P29*Q29 -> 10
E30: Compromission d'un poste de travail via mail phishing | F30: Risque de fraude | G30: Risque de Fraude | H30: 4 | I30: 4 | J30: =H30*I30 -> 16 | L30: Sensibilisation, renfoncement anti virus, application du moindre privilège sur les machines utilisateurs, surveillance des mouvement lateraux par le soc | M30: NON | N30: RSSI | O30: 2 | P30: =H30 -> 4 | Q30: =I30/O30 -> 2 | R30: =P30*Q30 -> 8
A31: IT | E31: EVALUATION INTRINSEQUE | H31: =+ROUND(IFERROR(AVERAGE(H5:H30),0),0) -> 4 | I31: =+ROUND(IFERROR(AVERAGE(I5:I30),0),0) -> 3 | J31: =I31*H31 -> 12 | L31: EVALUATION RESIDUELLE | O31: =+ROUND(IFERROR(AVERAGE(O5:O30),0),0) -> 2 | P31: =+ROUND(IFERROR(AVERAGE(P5:P30),0),0) -> 4 | Q31: =+ROUND(IFERROR(AVERAGE(Q5:Q30),0),0) -> 2 | R31: =P31*Q31 -> 8
F34: Risque de Fraude | G34: =COUNTIF(G5:G30,F34) -> 12
F35: Risque opérationnel | G35: =COUNTIF(G5:G30,F35) -> 9
F36: Risque stratégique | G36: =COUNTIF(G5:G30,F36) -> 5
F37: Risque de crédit | G37: =COUNTIF(G5:G30,F37) -> 0
F38: Risque réglementaire | G38: =COUNTIF(G5:G30,F38) -> 0
F39: Risque de liquidité | G39: =COUNTIF(G5:G30,F39) -> 0
F40: Risque exogéne | G40: =COUNTIF(G5:G30,F40) -> 0

Sheet RECOUVREMENT

Sheet PRODUITS DIGITAUX
A1: ANALYSE DES RISQUES OPERATIONNELS - MARKETING & PRODUITS
A2: N° | B2: PROCESSUS | C2: RATIO | D2: SOUS PROCESSUS | E2: EXCEPTIONS MAJEURES CONSTATEES | F2: RISQUES CORRELES | G2: FAMILLE DE RISQUE | H2: Gravité | I2: Probabilité | J2: Risque brut (Rb) | K2: Justification de l'évaluation en cas de risque jugé critique | L2: DISPOSITIF DE PREVENTION ET DE CONTRÔLE | P2: Gravité résiduelle | Q2: Probabilité résiduelle | R2: Risque résiduel (Rr)
H4: G | I4: P | J4: est égal à GxP | L4: Description du dispositif à mettre en œuvre | M4: Dispositif existant ou Non | N4: Owner du Contrôle | O4: Efficacité du dispositif | P4: G | Q4: Pr | R4: est égal à GxP
A5: 1 | B5: PRODUITS DIGITAUX & CHANGE | C5: 0.025 | D5: MONETIQUE | E5: Absence de réconciliation des transactions liées aux CARTES GIM UEMOA | F5: Risque opérationnel Risque de fraude | G5: Risque de Fraude | H5: 5 | I5: 3 | J5: =H5*I5 -> 15 | L5: S'assurer que les réconciliations sont réaliséees quotidiennement | M5: OUI | N5: Resp OPS | O5: 3 | P5: =H5 -> 5 | Q5: =I5/O5 -> 1 | R5: =P5*Q5 -> 5
E6: Non-respect des procedures d'approvisionnement de cartes et de rechargement | F6: Risque opérationnel | G6: Risque opérationnel | H6: 4 | I6: 4 | J6: =H6*I6 -> 16 | L6: Veiller au stricte respect de la procedure d'approvisonnement de carte prepayée | M6: NON(absence de procédure d'approvisionnement) | N6: OPS/FINANCE | O6: 2 | P6: 3 | Q6: =I6/O6 -> 2 | R6: =P6*Q6 -> 6
E7: Absence d'inventaire et de fichier de suivi de stocks de cartes | F7: Risque opérationnel | G7: Risque opérationnel | H7: 4 | I7: 2 | J7: =H7*I7 -> 8 | L7: S'assurer de la realisation d'un inventaire permanent et la tenue d'un fichier de suivi de la variation des cartes | M7: OUI | N7: RESP MONETIQUE | O7: 2 | P7: =H7 -> 4 | Q7: =I7/O7 -> 1 | R7: =P7*Q7 -> 4
E8: Verifier que les cartes prepayées sont conservées dans un endroit securisé, fermé à clef et l'accés reglementé | F8: Risque de vol | G8: Risque de Fraude | H8: 4 | I8: 1 | J8: =H8*I8 -> 4 | L8: Veiller à la bonne conservation des cartes et à la securisation de l'accés au stockage des cartes | M8: OUI | N8: RESP MONETIQUE | O8: 2 | P8: =H8 -> 4 | Q8: =I8/O8 -> 0.5 | R8: =P8*Q8 -> 2
E9: Vice de forme sur les contrats d'abonnements | F9: Risque opérationnel | G9: Risque opérationnel | H9: 5 | I9: 2 | J9: =H9*I9 -> 10 | L9: S'assurer de l'exhaustivité et de la completitude des informations sur les contrats d'abonnement de carte prepayée | M9: OUI | N9: RESP MONETIQUE /CC | O9: 2 | P9: =H9 -> 5 | Q9: =I9/O9 -> 1 | R9: =P9*Q9 -> 5
E10: Defaut de prise en charge des suspens sur l'application OMB | F10: Risque de fraude | G10: Risque de Fraude | H10: 3 | I10: 4 | J10: =H10*I10 -> 12 | L10: Veiller à l'appurement de tous les suspens sur l'application OMB | O10: 3 | P10: =H10 -> 3 | Q10: =I10/O10 -> 1.3333333 | R10: =P10*Q10 -> 4
E11: Absence de suivi de l'encours des cartes expirés | F11: Risque opérationnel | G11: Risque opérationnel | H11: 5 | I11: 2 | J11: =H11*I11 -> 10 | L11: Demander un onglet sur la plateforme pour avoir une vue sur l'encours total des cartes distribuées aux clients | M11: NON(absence d'onglet sur la plateforme) | N11: RESP monetique/IT | O11: 2 | P11: =H11 -> 5 | Q11: =I11/O11 -> 1 | R11: =P11*Q11 -> 5
E12: Absence de prise en charge des reclamations clients | F12: Risque d'image | G12: Risque stratégique | H12: 4 | I12: 1 | J12: =H12*I12 -> 4 | L12: S'assurer de la prise en charge de toutes les reclamations clients en monnaie éléctronique | M12: OUI | N12: RESP MONETIQUE | O12: 2 | P12: =H12 -> 4 | Q12: =I12/O12 -> 0.5 | R12: =P12*Q12 -> 2
E13: Vente de carte COFICARTE à des clients ne disposant pas de documents d'identification valide | F13: risque de non-conformité | G13: Risque de Fraude | H13: 4 | I13: 2 | J13: =H13*I13 -> 8 | L13: s'assurer de recueillir les pièces d'identification valide lors de la souscription | M13: OUI | N13: CC/RESP MONETIQUE | O13: 2 | P13: =H13 -> 4 | Q13: =I13/O13 -> 1 | R13: =P13*Q13 -> 4
E14: Non compensation en cas de fraude sur la carte COFICARTE | F14: Risque de reputation | G14: Risque de Fraude | H14: 5 | I14: 2 | J14: =H14*I14 -> 10 | L14: sensibiliser les clients sur les mesures de sécurité à adopter avec la carte lors de l'achat. | M14: OUI | N14: CC | O14: 2 | P14: =H14 -> 5 | Q14: =I14/O14 -> 1 | R14: =P14*Q14 -> 5
D15: B2W / W2B | E15: Défaut ou non-identification de la clientèle de l'Institution à l'ouverture du compte (usurpation d'identité, blanchiment des capitaux, financement du terrorisme, …) | F15: Risque de fraude Risque d'image Risque de pertes fiancières | G15: Risque de Fraude | H15: 4 | I15: 2 | J15: =H15*I15 -> 8 | L15: Mettre à disposition de la fonction "Conformité" des moyens humains et matériels adéquats et suffisant afin de mener à bien et efficacement sa mission. | M15: OUI | N15: CC/CONFORMITE | O15: 1 | P15: =H15 -> 4 | Q15: =I15/O15 -> 2 | R15: =P15*Q15 -> 8
E16: Dépassement du seuil réglementaire fixé à 2.000.000 francs CFA lors de la réalisation d'une ou plusieurs opérations. | F16: Risque de non-conformité Risque réglementaire Risque d'image Risque de pertes financières | G16: Risque réglementaire | H16: 4 | I16: 4 | J16: =H16*I16 -> 16 | L16: Paramétrer le système d'information de sorte à bloquer toutes opérations cumulées ou unique à 2.000.000 francs CFA lors de la réalisation des opérations par la clientèle. | M16: OUI | N16: Resp Digital & Partenariat Resp IT Conformité | O16: 3 | P16: =H16 -> 4 | Q16: =I16/O16 -> 1.3333333 | R16: =P16*Q16 -> 5.3333333
E17: Non justification des opérations (dépôt sur compte mobile money/dépôt sur comptes COFINA) | F17: Risque de fraude Risque d'image Risque de pertes fiancières | G17: Risque de Fraude | H17: 4 | I17: 4 | J17: =H17*I17 -> 16 | L17: Paramétrer le système d'information de sorte à rendre obligatoire la justification des opérations d'un seuil prédéfinis (à minima 500.000 francs CFA) Mettre à disposition de la fonction "Conformité" des moyens humains et matériels adéquats et suffisant afin de mener à bien et efficacement sa mission | M17: NON | N17: CC/Partenariat/Conformité | O17: 1 | P17: =H17 -> 4 | Q17: =I17/O17 -> 4 | R17: =P17*Q17 -> 16
E18: Absence de débit ou crédit lors des opérations B2W et/ou W2B | F18: Risque de pertes financières Risque opérationnel | G18: Risque opérationnel | H18: 5 | I18: 4 | J18: =H18*I18 -> 20 | L18: Paramétrer le système de sorte que les opèrations B2W W2B soient comptabiliser normalement dans le système | M18: NON | N18: IT/OPS | P18: =H18 -> 5 | Q18: 4 | R18: =P18*Q18 -> 20
E19: Rupture d'activité suite à un dysfonctionnement du système d'information (bugg) | F19: Risque de fraude Risque d'image Risque de pertes fiancières | G19: Risque de Fraude | H19: 4 | I19: 3 | J19: =H19*I19 -> 12 | L19: - Informer la clientèle pour éviter tout mécontentement - participer à la résolution du dysfonctionnement - faire le suivi du traitement réalisé | M19: OUI | N19: IT/DMCC | O19: 1 | P19: =H19 -> 4 | Q19: =I19/O19 -> 3 | R19: =P19*Q19 -> 12
E20: Réalisation des opérations de dépôts sur les comptes mobile money suite à une Intrusion malveillante dans le système d'information | F20: Risque de fraude Risque d'image Risque de pertes fiancières | G20: Risque de Fraude | H20: 4 | I20: 2 | J20: =H20*I20 -> 8 | L20: Paramétrer le système d'information de sorte à limiter les opérations de dépôt à un seuil prédéfinis (2.000.000 francs CFA) Paramétrer le système d'information de sorte à communiquer un code de validation de la transaction au titulaire du compte sur un numéro ou mail autre que le principal Renforcer la sensibilisation du personnel sur les bonnes pratiques d'utilisation de l'ordinateur, des mails et système d'information Sensibiliser la clientèle sur le processus d'utilisation de l'application | M20: OUI | N20: OPS/IT | O20: 2 | P20: =H20 -> 4 | Q20: =I20/O20 -> 1 | R20: =P20*Q20 -> 4
E21: Détention du mot de passe utilisateur du titulaire du compte par une personne malveillante | F21: Risque de fraude Risque d'image Risque de pertes fiancières | G21: Risque de Fraude | H21: 4 | I21: 1 | J21: =H21*I21 -> 4 | L21: Paramétrer le système d'information de sorte à communiquer un code de validation au titulaire du compte sur un numéro ou mail autre que le principal lors de la réalisation d'une opération ou lors de la connexion à la session Sensibiliser régulièrement la clientèle sur l'utilisation du mot de passe | M21: OUI | N21: CC/IT | O21: 2 | P21: =H21 -> 4 | Q21: =I21/O21 -> 0.5 | R21: =P21*Q21 -> 2
E22: Traitement inapproprié des données à caractère personnel de la clientèle dans sa généralité (collecte de données sensibles ou à caractère personnel non autorisé, diffusion non appropriée, mauvaise conservation) | F22: Risque de fraude Risque d'image Risque de pertes fiancières | G22: Risque de Fraude | H22: 4 | I22: 3 | J22: =H22*I22 -> 12 | L22: Insérer la clause de protection des données personnelles dans les Conditions Générales d'Utilisation (CGU) de l'application "COFINA Mobile" et "USSD" | M22: OUI | N22: CC/IT | O22: 1 | P22: =H22 -> 4 | Q22: =I22/O22 -> 3 | R22: =P22*Q22 -> 12
E23: Erreur de saisie du numéro du compte mobile money lors de la réalisation de l'opération de dépôt à partir du compte du client domicilié dans les livres de COFINA SN | F23: Risque de fraude Risque d'image Risque de pertes fiancières | G23: Risque de Fraude | H23: 5 | I23: 3 | J23: =H23*I23 -> 15 | L23: Paramétrer le système d'information de sorte à communiquer un code de validation au titulaire du compte sur un numéro ou mail autre que le principal lors de la réalisation d'une opération ou lors de la connexion à la session Sensibiliser la clientèle sur la conduite à tenir lors de la réalisation de l'opération sur les applicatifs | M23: OUI | N23: CC/IT/OPS | O23: 2 | P23: =H23 -> 5 | Q23: =I23/O23 -> 1.5 | R23: =P23*Q23 -> 7.5
E24: - Non identification de l'émetteur de l'opération de dépôt vers le compte du client domicilié dans les livres de l'Institution - non identification du client titulaire du compte domicilié dans les livres de l'Institution et bénéficiaire des fonds | F24: Risque de fraude Risque d'image Risque de pertes fiancières | G24: Risque de Fraude | H24: 4 | I24: 3 | J24: =H24*I24 -> 12 | L24: Renforcer l'équipe du service Conformité pour assurer une efficacité dans le contrôle | M24: OUI | N24: CC/OPS | O24: 1 | P24: =H24 -> 4 | Q24: =I24/O24 -> 3 | R24: =P24*Q24 -> 12
E25: Erreur sur le numero de compte du bénéficiaire des fonds de l'opération de dépôt réalisée via un compte mobile money | F25: Risque de fraude Risque d'image Risque de pertes fiancières | G25: Risque de Fraude | H25: 4 | I25: 2 | J25: =H25*I25 -> 8 | L25: Paramétrer le système d'information de sorte à rendre obligatoire la justification des opérations d'un seuil prédéfinis (à minima 500.000 francs CFA) Mettre à disposition de la fonction "Conformité" des moyens humains et matériels adéquats et suffisant afin de mener à bien et efficacement sa mission Vérification des opérations de plus de 2.000.000 francs CFA (unique ou fractionnées) réalisées sur le compte d'un client à partir d'un ou plusieurs comptes mobile money | M25: OUI | N25: CC/DMCC/OPS | O25: 1 | P25: =H25 -> 4 | Q25: =I25/O25 -> 2 | R25: =P25*Q25 -> 8
A26: PRODUITS DIGITAUX & CHANGE | E26: EVALUATION INTRINSEQUE | H26: =+ROUND(IFERROR(AVERAGE(H5:H25),0),0) -> 4 | I26: =+ROUND(IFERROR(AVERAGE(I5:I25),0),0) -> 3 | J26: =H26*I26 -> 12 | L26: EVALUATION RESIDUELLE | O26: =+ROUND(IFERROR(AVERAGE(O5:O25),0),0) -> 2 | P26: =+ROUND(IFERROR(AVERAGE(P5:P25),0),0) -> 4 | Q26: =+ROUND(IFERROR(AVERAGE(Q5:Q25),0),0) -> 2 | R26: =+ROUND(IFERROR(AVERAGE(R5:R25),0),0) -> 7
F29: Risque de Fraude | G29: =COUNTIF(G5:G25,F29) -> 14
F30: Risque opérationnel | G30: =COUNTIF(G5:G25,F30) -> 5
F31: Risque stratégique | G31: =COUNTIF(G5:G25,F31) -> 1
F32: Risque de crédit | G32: =COUNTIF(G5:G25,F32) -> 0
F33: Risque réglementaire | G33: =COUNTIF(G5:G25,F33) -> 1
F34: Risque de liquidité | G34: =COUNTIF(G5:G25,F34) -> 0
F35: Risque exogéne | G35: =COUNTIF(G5:G25,F35) -> 0

Sheet GOUV & CONTRÔLE INTERNE
A1: ANALYSE DES RISQUES OPERATIONNELS - GOUVERNANCE & CONTRÔLE INTERNE
A2: N° | B2: PROCESSUS | C2: RATIO | D2: SOUS PROCESSUS | E2: EXCEPTIONS MAJEURES CONSTATEES | F2: RISQUES CORRELES | G2: FAMILLE DE RISQUE | H2: Gravité | I2: Probabilité | J2: Risque brut (Rb) | K2: Justification de l'évaluation en cas de risque jugé critique | L2: DISPOSITIF DE PREVENTION ET DE CONTRÔLE | P2: Gravité résiduelle | Q2: Probabilité résiduelle | R2: Risque résiduel (Rr)
H4: G | I4: P | J4: est égal à GxP | L4: Description du dispositif | M4: Dispositif existant ou Non | N4: Owner du Contrôle | O4: Efficacité du dispositif | P4: G | Q4: Pr | R4: est égal à GxP
A5: 6 | B5: GOUVERNANCE & CI | C5: 0.025 | D5: Gouvernance | E5: • Absence de suivi systématique relatif au respect des dispositions légales et Réglementaires relatives à la gouvernance (Respect de la loi sur les microfinances, des instructions, des statuts) | F5: Sanctions légales Sanctions pécuniaires | G5: Risque réglementaire | H5: 4 | I5: 4 | J5: =H5*I5 -> 16 | L5: Mettre en place un service juridique qui va s'assurer de faire un suivi strict et rigoureux des dispositions légales et réglementaires | M5: OUI | N5: MANAGEMENT / CONTRÔLE INTERNE | O5: 1 | P5: =H5 -> 4 | Q5: =I5/O5 -> 4 | R5: =P5*Q5 -> 16
E6: • Conformité des statuts avec la législation | F6: Sanctions légales Sanctions pécuniaires | G6: Risque réglementaire | H6: 4 | I6: 2 | J6: =H6*I6 -> 8 | L6: Mettre en place un service juridique qui va s'assurer de faire un suivi strict et rigoureux des dispositions légales et réglementaires | M6: OUI | N6: MANAGEMENT / CONTRÔLE INTERNE | O6: 1 | P6: =H6 -> 4 | Q6: =I6/O6 -> 2 | R6: =P6*Q6 -> 8
E7: • Absence de suivi des recos issues du régulateur | F7: Sanctions légales Sanctions pécuniaires | G7: Risque réglementaire | H7: 4 | I7: 3 | J7: =H7*I7 -> 12 | L7: Nstauration d'un point de suivi recos 2 fois par mois | M7: OUI | N7: MANAGEMENT / CONTRÔLE INTERNE | O7: 2 | P7: =H7 -> 4 | Q7: =I7/O7 -> 1.5 | R7: =P7*Q7 -> 6
E8: Non complétude de certaines procédures sur certaines activités | F8: Risque opérationnel | G8: Risque opérationnel | H8: 4 | I8: 3 | J8: =H8*I8 -> 12 | L8: Revue des procedure annuelle | M8: OUI | N8: MANAGEMENT / CONTRÔLE INTERNE | O8: 2 | P8: =H8 -> 4 | Q8: =I8/O8 -> 1.5 | R8: =P8*Q8 -> 6
E9: Procédures non adaptées à la pratique de l'institution | F9: Risque opérationnel | G9: Risque opérationnel | H9: 4 | I9: 2 | J9: =H9*I9 -> 8 | L9: Revue des procedure annuelle | M9: OUI | N9: MANAGEMENT / CONTRÔLE INTERNE | O9: 2 | P9: =H9 -> 4 | Q9: =I9/O9 -> 1 | R9: =P9*Q9 -> 4
E10: Sécurité des dirigeants | F10: Pertes des moyens d'exploitation | G10: Risque stratégique | H10: 4 | I10: 2 | J10: =H10*I10 -> 8 | L10: S'assurer que les dirigeants ne sont pas exposés de façon simultanée à des situations à risques (déplacements, etc.) | M10: OUI | N10: MANAGEMENT / CONTRÔLE INTERNE | O10: 2 | P10: =H10 -> 4 | Q10: =I10/O10 -> 1 | R10: =P10*Q10 -> 4
E11: Suivi de l'ensemble des comités de Direction et de leurs décisions (Direction Générale) | F11: Litiges avec les autorités | G11: Risque stratégique | H11: 3 | I11: 3 | J11: =H11*I11 -> 9 | L11: S'assurer que l'ensemble des comités décisionnels de Direction sont mis en place, se tiennent et que les décisions prises font l'objet d'un suivi (Direction Générale) | M11: OUI | N11: MANAGEMENT / CONTRÔLE INTERNE | O11: 2 | P11: =H11 -> 3 | Q11: =I11/O11 -> 1.5 | R11: =P11*Q11 -> 4.5
E12: • Bon fonctionnement des organes d'administration et de direction et de contrôle | F12: Sanctions légales Sanctions pécuniaires | G12: Risque réglementaire | H12: 4 | I12: 2 | J12: =H12*I12 -> 8 | L12: Mettre en place un service juridique qui va s'assurer de faire un suivi strict | M12: OUI | N12: MANAGEMENT / CONTRÔLE INTERNE | O12: 2 | P12: =H12 -> 4 | Q12: =I12/O12 -> 1 | R12: =P12*Q12 -> 4
D13: Contrôle interne | E13: • Faiblesse dans l'accessibilité et Connaissance des politiques réglementaires en vigueur | F13: Sanctions légales Sanctions pécuniaires | G13: Risque réglementaire | H13: 4 | I13: 3 | J13: =H13*I13 -> 12 | L13: Plan de Formation sur les exigences réglementaires à mettre en place pour les auditeurs et contrôleurs | M13: NON | N13: MANAGEMENT / CONTRÔLE INTERNE | O13: 2 | P13: =H13 -> 4 | Q13: =I13/O13 -> 1.5 | R13: =P13*Q13 -> 6
E14: • Absence de Réalisation systématique des contrôles de 2e niveau pour toutes les opérations liées à l'acitivté | F14: Risques de fraude Risque de pertes financières Risque opérationnel | G14: Risque opérationnel | H14: 4 | I14: 3 | J14: =H14*I14 -> 12 | L14: Etoffer le département Contrôle interne avec un recrutement d'au minimum 2 staffs et redéfinir une MSP efficiente | M14: OUI | N14: MANAGEMENT / CONTRÔLE INTERNE | O14: 2 | P14: =H14 -> 4 | Q14: =I14/O14 -> 1.5 | R14: =P14*Q14 -> 6
E15: Absence de contrôle de certaines activités | F15: Risque opérationnel | G15: Risque opérationnel | H15: 4 | I15: 3 | J15: =H15*I15 -> 12 | L15: Veiller au suivi de la MSP | M15: OUI | N15: MANAGEMENT / CONTRÔLE INTERNE | O15: 2 | P15: =H15 -> 4 | Q15: =I15/O15 -> 1.5 | R15: =P15*Q15 -> 6
E16: Absence de Mise à jour de la cartographie des risques | F16: Risque de non-conformité | G16: Risque opérationnel | H16: 4 | I16: 2 | J16: =H16*I16 -> 8 | L16: S'assurer de la mise à jour de la cartographie des risques au moins 2 fois par an | M16: OUI | N16: MANAGEMENT / CONTRÔLE INTERNE | O16: 2 | P16: =H16 -> 4 | Q16: =I16/O16 -> 1 | R16: =P16*Q16 -> 4
E17: Formation en matière de contrôle interne | F17: Risque de non-conformité | G17: Risque stratégique | H17: 4 | I17: 3 | J17: =H17*I17 -> 12 | L17: S'assurer que les collaborateurs ont suivi les formations sur le contrôle interne adaptées à leur poste et/ou leurs missions | M17: OUI | N17: MANAGEMENT / CONTRÔLE INTERNE | O17: 2 | P17: =H17 -> 4 | Q17: =I17/O17 -> 1.5 | R17: =P17*Q17 -> 6
E18: Absence de mise en place et monitoring du contrôle de niveau 1 | F18: Risque de non-conformité | G18: Risque réglementaire | H18: 4 | I18: 3 | J18: 12 | L18: Mettre en place le contrôle de niveau 1 | M18: OUI | N18: CONTRÔLE INTERNE | O18: 3 | P18: 4 | Q18: =I18/O18 -> 1 | R18: =P18*Q18 -> 4
E19: Inexistence d'un plan annuel de contrôle et d'audit | F19: Risque de non-conformité | G19: Risque réglementaire | H19: 4 | I19: 2 | J19: 8 | L19: Elaborer et faire approuver les plans de contrôle chaque début d'année | M19: OUI | N19: CONTRÔLE INTERNE | O19: 2 | P19: 4 | Q19: =I19/O19 -> 1 | R19: =P19*Q19 -> 4
E20: Couverture du périmètre de déploiement du dispositif de contrôle permanent | F20: Risque de non-conformité | G20: Risque opérationnel | H20: 4 | I20: 3 | J20: =H20*I20 -> 12 | L20: S'assurer de l'exhaustivité et de la mise à jour du périmètre de déploiement du dispositif de contrôle permanent, de sa conformité aux obligations réglementaires, et suivre le déploiement effectif du dispositif sur ce périmètre | M20: OUI | N20: MANAGEMENT / CONTRÔLE INTERNE | O20: 2 | P20: =H20 -> 4 | Q20: =I20/O20 -> 1.5 | R20: =P20*Q20 -> 6
E21: Élaborer le rapport sur le Contrôle Interne et le faire valider | F21: Risque de non-conformité | G21: Risque réglementaire | H21: 4 | I21: 3 | J21: =H21*I21 -> 12 | L21: S'assurer que le rapport sur le Contrôle Interne est réalisé et validé | M21: OUI | N21: MANAGEMENT / CONTRÔLE INTERNE | O21: 2 | P21: =H21 -> 4 | Q21: =I21/O21 -> 1.5 | R21: =P21*Q21 -> 6
E22: • Absence de suivi efficace sur la politique de lutte anti blanchiment ou non détection des opérations suspectes | F22: Risque de non-conformité réglementaire | G22: Risque réglementaire | H22: 4 | I22: 3 | J22: =H22*I22 -> 12 | L22: Formation sur la lutte contre le Blanchiment à mettre en place pour les auditeurs et contrôleurs. A voir avec la CENTIF Mise en place d'un système de filtrage et d'identification automatique des opérations suspectes | M22: OUI pour la formation NON pour le système automatique car le système actuel ne le permet pas | N22: MANAGEMENT / CONTRÔLE INTERNE | O22: 2 | P22: =H22 -> 4 | Q22: =I22/O22 -> 1.5 | R22: =P22*Q22 -> 6
E23: • Mise en place et fonctionnement d'un comité d'audit | F23: Risque de non-conformité | G23: Risque réglementaire | H23: 4 | I23: 2 | J23: =H23*I23 -> 8 | L23: S'assurer d'un bon fonctionnement efficace du Comité Audit | M23: OUI | N23: MANAGEMENT / CONTRÔLE INTERNE | O23: 2 | P23: =H23 -> 4 | Q23: =I23/O23 -> 1 | R23: =P23*Q23 -> 4
E24: Retard de dépôt des rapports règlementaires | F24: Risque rélgementaire | G24: Risque réglementaire | H24: 4 | I24: 2 | J24: =H24*I24 -> 8 | L24: S'assurer de l'élaboration et du dépôt dans les délais des rapports règlementaires | M24: OUI | N24: MANAGEMENT / CONTRÔLE INTERNE | O24: 2 | P24: =H24 -> 4 | Q24: =I24/O24 -> 1 | R24: =P24*Q24 -> 4
A25: GOUVERNANCE & CI | E25: EVALUATION INTRINSEQUE | H25: =+ROUND(IFERROR(AVERAGE(H5:H23),0),0) -> 4 | I25: =+ROUND(IFERROR(AVERAGE(I5:I23),0),0) -> 3 | J25: =H25*I25 -> 12 | L25: EVALUATION RESIDUELLE | O25: =+ROUND(IFERROR(AVERAGE(O5:O23),0),0) -> 2 | P25: =+ROUND(IFERROR(AVERAGE(P5:P23),0),0) -> 4 | Q25: =+ROUND(IFERROR(AVERAGE(Q5:Q23),0),0) -> 1 | R25: =Q25*P25 -> 4
F28: Risque de Fraude | G28: =COUNTIF(G5:G24,F28) -> 0
F29: Risque opérationnel | G29: =COUNTIF(G5:G24,F29) -> 6
F30: Risque stratégique | G30: =COUNTIF(G5:G24,F30) -> 3
F31: Risque de crédit | G31: =COUNTIF(G5:G24,F31) -> 0
F32: Risque réglementaire | G32: =COUNTIF(G5:G24,F32) -> 11
F33: Risque de liquidité | G33: =COUNTIF(G5:G24,F33) -> 0
F34: Risque exogéne | G34: =COUNTIF(G5:G24,F34) -> 0

Sheet JURIDIQUE & CONTENTIEUX
A1: ANALYSE DES RISQUES OPERATIONNELS - SERVICE JURIDIQUE & CONTENTIEUX
A2: N° | B2: PROCESSUS | C2: RATIO | D2: SOUS PROCESSUS | E2: EXCEPTIONS MAJEURES CONSTATEES | F2: RISQUES CORRELES | G2: FAMILLE DE RISQUE | H2: Gravité | I2: Probabilité | J2: Risque brut (Rb) | K2: Justification de l'évaluation en cas de risque jugé critique | L2: DISPOSITIF DE PREVENTION ET DE CONTRÔLE | P2: Gravité résiduelle | Q2: Probabilité résiduelle | R2: Risque résiduel (Rr)
H4: G | I4: P | J4: est égal à GxP | L4: Description du dispositif | M4: Dispositif existant ou Non | N4: Owner du Contrôle | O4: Efficacité du dispositif | P4: G | Q4: Pr | R4: est égal à GxP
A5: 7 | B5: JURIDIQUE & CONTENTIEUX | C5: 0.025 | D5: Gestion du Contentieux | E5: • Risque lié aux difficultés de localisation des clients (changement d'adresse, de coordonnées) pouvant entrainer des difficultés de recouvrement et des pertes financières pour COFINA SN | F5: Risques d'impayés, pertes financières | G5: Risque de crédit | H5: 4 | I5: 4 | J5: =H5*I5 -> 16 | L5: Veiller à ce que tous dossiers disposent obligatoirement d'un plan de géolocalisation activité et domicile du client | M5: OUI | N5: JURIDIQUE | O5: 1 | P5: =H5 -> 4 | Q5: =I5/O5 -> 4 | R5: =P5*Q5 -> 16
E6: Non formalisation de l'aval du client lors de certaines restructurations | F6: Risque de fraude | G6: Risque de Fraude | H6: 4 | I6: 4 | J6: =H6*I6 -> 16 | L6: Formalisation du protocole d'accord | M6: NON | N6: JURIDIQUE | O6: 2 | P6: =H6 -> 4 | Q6: =I6/O6 -> 2 | R6: =P6*Q6 -> 8
D7: Gestion des contrats et Etudes juridiques | E7: • Modification abusive ou non autorisée des contrats de crédit par les entités opérationnelles et/ou contrat non établi ou vérifié par le juridique | F7: Risque de poursuite judiciaire | G7: Risque de Fraude | H7: 4 | I7: 1 | J7: =H7*I7 -> 4 | L7: Mettre en place un service juridique qui va s'assurer de faire un suivi strict et rigoureux sur tous les dossiers de prêts financés | M7: OUI | N7: MANAGEMENT | O7: 2 | P7: =H7 -> 4 | Q7: =I7/O7 -> 0.5 | R7: =P7*Q7 -> 2
E8: Absence de suivi de tous les contrats liant COFINA à des tiers qu'il s'agisse des banques, fournisseurs, interco... (termes, durée…) | F8: Risque juridique Risque de fraude | G8: Risque de Fraude | H8: 3 | I8: 3 | J8: =H8*I8 -> 9 | L8: Base de donnée des contrats liant COFINA aux tiers mis en place avec une revue semestrielle | M8: OUI | N8: MANAGEMENT | O8: 1 | P8: 4 | Q8: =I8/O8 -> 3 | R8: =P8*Q8 -> 12
D9: Gestion des garanties | E9: • Impossibilité de réaliser une garantie foncière en raison d'une détérioration normale et/ou de sinistre impactant de manière significative la valeur de l'actif (incendie, dégât des eaux, etc.) | F9: Risques d'impayés, pertes financières | G9: Risque de crédit | H9: 4 | I9: 4 | J9: =H9*I9 -> 16 | L9: Mettre en place un service juridique qui va s'assurer de faire un suivi strict et rigoureux sur toutes de Garantie | M9: OUI | N9: MANAGEMENT | O9: 2 | P9: =H9 -> 4 | Q9: =I9/O9 -> 2 | R9: =P9*Q9 -> 8
E10: Mauvaise localisation du bien garanti, immeubles construits sur des titres précaires, perte d'emploi pour des particuliers salariés, garantie pris sur des actifs non éligibles par la règlementation | F10: Risques d'impayés, pertes financières | G10: Risque de crédit | H10: 4 | I10: 3 | J10: =H10*I10 -> 12 | L10: Mettre en place un service juridique qui va s'assurer de faire un suivi strict et rigoureux sur toutes les Garanties | M10: OUI | N10: MANAGEMENT | O10: 2 | P10: =H10 -> 4 | Q10: =I10/O10 -> 1.5 | R10: =P10*Q10 -> 6
E11: Garanties sur évaluées lors d'une expertise | F11: Risque de pertes financières Risque de fraude | G11: Risque de crédit | H11: 4 | I11: 4 | J11: =H11*I11 -> 16 | L11: Contracter avec des expert agrée | M11: NON | N11: JURIDIQUE | O11: 2 | P11: =H11 -> 4 | Q11: =I11/O11 -> 2 | R11: =P11*Q11 -> 8
E12: Non respect des procédures de saisies garanties | F12: Risque de contrepartie | G12: Risque de crédit | H12: 4 | I12: 3 | J12: =H12*I12 -> 12 | L12: Materialiser les revue de portefeuille avec l'huissier et l'avocat | M12: OUI | N12: JURIDIQUE | O12: 2 | P12: =H12 -> 4 | Q12: =I12/O12 -> 1.5 | R12: =P12*Q12 -> 6
E13: Adjudication des garanties afin d'éteindre la créance sans disposition des états de droits réels ou certificat d'inscription hypothécaire | F13: Risque de fraude Risque de crédit | G13: Risque de crédit | H13: 4 | I13: 4 | J13: =H13*I13 -> 16 | L13: S'assurer que toutes les garanties qui ont fait objet d'appel à adjudication pour solder la créance du client, l'institution a reçu les EDR et certificat dinscription hypothécaire en son nom avant de procéder à l'opération | M13: OUI | N13: JURIDIQUE | O13: 2 | P13: =H13 -> 4 | Q13: =I13/O13 -> 2 | R13: =P13*Q13 -> 8
D14: Gestion des Avis à Tiers Détenteur ou ATD, des saisies attributions et saisies conservatoires | E14: • Traitement inapproprié ou hors délai des Avis à Tiers Détenteur ou ATD, des saisies attributions et saisies conservatoires | F14: Risque de poursuite judiciaire | G14: Risque de crédit | H14: 4 | I14: 2 | J14: =H14*I14 -> 8 | L14: Contrôle de 1er niveau sur les traitement effectués par l'assistant juridique | M14: OUI | N14: MANAGEMENT | O14: 2 | P14: =H14 -> 4 | Q14: =I14/O14 -> 1 | R14: =P14*Q14 -> 4
D15: Passages en pertes | E15: Absence de suivi Passage en perte (write-off) | F15: Risque financier, risque opérationnel, fraude | G15: Risque opérationnel | H15: 4 | I15: 4 | J15: =H15*I15 -> 16 | L15: S'assurer que les écritures de passage en pertes sont correctement traitées et approuvées par les personnes autorisées. Acccompagné d'un PV de carence | M15: NON | N15: JURIDIQUE | O15: 2 | P15: =H15 -> 4 | Q15: =I15/O15 -> 2 | R15: =P15*Q15 -> 8
E16: Non reversement ou reversement tardive de collecte effectué par les avocats | F16: Risque de perte financière | G16: Risque oérationnel | H16: 4 | I16: 2 | J16: =H16*I16 -> 8 | L16: Faire un suivi régulier sur le recouvrement effectué | M16: OUI | N16: JURIDIQUE | O16: 2 | P16: =H16 -> 4 | Q16: =I16/O16 -> 1 | R16: =P16*Q16 -> 4
E17: Non respect des délais de tenue des sessions des organces délibérants (AG, CA d'arreté des comptes | F17: Risque réglementaire | G17: Risque opérationnel | H17: 3 | I17: 2 | J17: =H17*I17 -> 6 | L17: Calendrier prévisionnel mis en place et monitoré | M17: OUI | N17: JURIDIQUE | O17: 2 | P17: =H17 -> 3 | Q17: =I17/O17 -> 1 | R17: =P17*Q17 -> 3
E18: Absence de formalisation des décisions (Nomination, changement de statut, augmentation de capital) | F18: Risque réglementaire | G18: risque opérationnel | H18: 2 | I18: 2 | J18: =H18*I18 -> 4 | L18: Mettre en place un tableau de bord de sur la gouvernance | M18: NON | N18: JURIDIQUE | O18: 2 | P18: =H18 -> 2 | Q18: =I18/O18 -> 1 | R18: =P18*Q18 -> 2
A20: JURIDIQUE & CONTENTIEUX | D20: EVALUATION INTRINSEQUE | H20: =+ROUND(IFERROR(AVERAGE(H5:H14),0),0) -> 4 | I20: =+ROUND(IFERROR(AVERAGE(I5:I14),0),0) -> 3 | J20: =H20*I20 -> 12 | L20: EVALUATION RESIDUELLE | O20: =+ROUND(IFERROR(AVERAGE(O5:O14),0),0) -> 2 | P20: =+ROUND(IFERROR(AVERAGE(P5:P14),0),0) -> 4 | Q20: =+ROUND(IFERROR(AVERAGE(Q5:Q14),0),0) -> 2 | R20: =P20*Q20 -> 8
F23: Risque de Fraude | G23: =COUNTIF(G5:G15,F23) -> 3
F24: Risque opérationnel | G24: =COUNTIF(G5:G20,F24) -> 3
F25: Risque stratégique | G25: =COUNTIF(G5:G15,F25) -> 0
F26: Risque de crédit | G26: =COUNTIF(G5:G15,F26) -> 7
F27: Risque réglementaire | G27: =COUNTIF(G5:G15,F27) -> 0
F28: Risque de liquidité | G28: =COUNTIF(G5:G15,F28) -> 0
F29: Risque exogéne | G29: =COUNTIF(G5:G15,F29) -> 0

Sheet ACHATS & LOGISTIQUE
A1: ANALYSE DES RISQUES OPERATIONNELS - ACHATS & LOGISTIQUE
A2: N° | B2: PROCESSUS | C2: RATIO | D2: SOUS PROCESSUS | E2: EXCEPTIONS MAJEURES CONSTATEES | F2: RISQUES CORRELES | G2: FAMILLE DE RISQUE | H2: Gravité | I2: Probabilité | J2: Risque brut (Rb) | K2: Justification de l'évaluation en cas de risque jugé critique | L2: DISPOSITIF DE PREVENTION ET DE CONTRÔLE | P2: Gravité résiduelle | Q2: Probabilité résiduelle | R2: Risque résiduel (Rr)
H4: G | I4: P | J4: est égal à GxP | L4: Description du dispositif | M4: Dispositif existant ou Non | N4: Owner du Contrôle | O4: Efficacité du dispositif | P4: G | Q4: Pr | R4: est égal à GxP
A5: 9 | B5: ACHATS & LOGISTIQUE | C5: 0.05 | D5: Planification & Administration des achats | E5: • Non-respect de la politique d'achat | F5: Risque de vol Risque de fraude liée à la surfacturation | G5: Risque de Fraude | H5: 4 | I5: 2 | J5: =H5*I5 -> 8 | L5: Veiller au strict respect de la procédure | M5: OUI | N5: ACHAT & LOGISTIQUE | O5: 2 | P5: =H5 -> 4 | Q5: =I5/O5 -> 1 | R5: =P5*Q5 -> 4
E6: Absence de fournisseur ou d'évaluation de fournisseur agréer | F6: risque fraude/Vol | G6: Risque de Fraude | H6: 3 | I6: 3 | J6: =H6*I6 -> 9 | L6: Etablissement d'une liste de prstataire agrée +évaluation annuel | M6: OUI | N6: ACHAT & LOGISTIQUE | O6: 3 | P6: 3 | Q6: =I6/O6 -> 1 | R6: =P6*Q6 -> 3
E7: Absence de Nettoyage des locaux et non-acheminement des ordures dans les zones appropriées | F7: Risque d'image Démotivation du personnel liée à la mauvaise hygiène impactant les conditions de travail | G7: Risque stratégique | H7: 4 | I7: 1 | J7: =H7*I7 -> 4 | L7: Contrat d'entretien signée avec des prestataire pour le nétoyage | M7: OUI | N7: ACHAT & LOGISTIQUE | O7: 2 | P7: =+H7 -> 4 | Q7: =I7/O7 -> 0.5 | R7: =P7*Q7 -> 2
E8: Absence de suivi sur la gestion du stock de fournitures | F8: Risque de vol | G8: Risque de Fraude | H8: 4 | I8: 3 | J8: =H8*I8 -> 12 | L8: Acquisition d'outils qui gere le stock de facon automatique | M8: OUI | N8: ACHAT & LOGISTIQUE | O8: 2 | P8: =H8 -> 4 | Q8: =I8/O8 -> 1.5 | R8: =P8*Q8 -> 6
E9: • Réalisation de dépenses non-autorisées | F9: Risque de vol Risque de fraude liée à la surfacturation | G9: Risque de Fraude | H9: 4 | I9: 2 | J9: =H9*I9 -> 8 | L9: Politique d'achat encadrant la gestion des dépense disponible | M9: OUI | N9: ACHAT & LOGISTIQUE | O9: 3 | P9: =H9 -> 4 | Q9: =I9/O9 -> 0.66666667 | R9: =P9*Q9 -> 2.6666667
E10: • Absence ou Pertes de pièces justificatives des achats (Non justification des achats) | F10: Dépense fictive ou détournement d'objet | G10: Risque de Fraude | H10: 4 | I10: 3 | J10: =H10*I10 -> 12 | L10: Veiller au strict respect de la procédure | M10: OUI | N10: ACHAT & LOGISTIQUE | O10: 3 | P10: =H10 -> 4 | Q10: =I10/O10 -> 1 | R10: =P10*Q10 -> 4
E11: Inexistence ou non mise à jour d'un fichier des immobilisations | F11: Risque opérationnel | G11: Risque opérationnel | H11: 4 | I11: 3 | J11: =H11*I11 -> 12 | L11: Mettre à jour systématiquement le fichier des immobilisations/Procdure d'inventaire rédigée | M11: OUI | N11: ACHAT & LOGISTIQUE | O11: 2 | P11: 4 | Q11: =I11/O11 -> 1.5 | R11: =P11*Q11 -> 6 | S11: difficulté de faire le suivi
E12: Non-respect de la procédure de gestion des sorties et cessions d'immobilisations | F12: Vol | G12: Risque de Fraude | H12: 4 | I12: 4 | J12: =H12*I12 -> 16 | L12: S'assurer du respect de la procédure | N12: RAF | O12: 2 | P12: 4 | Q12: =I12/O12 -> 2 | R12: =P12*Q12 -> 8
E13: • Prise en charge des dépenses liées à la flotte téléphonie mobile à des staffs inexistants ou démissionnaires | F13: Dépense fictive ou détournement d'objet | G13: Risque de Fraude | H13: 4 | I13: 3 | J13: =H13*I13 -> 12 | L13: Contrôle de niveau trimestriel liste staff vs facture flotte | M13: OUI | N13: ACHAT & LOGISTIQUE/RH | O13: 3 | P13: =H13 -> 4 | Q13: =I13/O13 -> 1 | R13: =P13*Q13 -> 4
E14: • Faiblesse dans l'archivage des dossiers d'appel d'offres ou bon de commande/facture | F14: Risque de perte de document | G14: Risque opérationnel | H14: 3 | I14: 2 | J14: =H14*I14 -> 6 | L14: Politique d'archivage disponible S | M14: OUI | N14: ACHAT & LOGISTIQUE | O14: 2 | P14: =H14 -> 3 | Q14: =I14/O14 -> 1 | R14: =P14*Q14 -> 3
D15: Logistique & moyens généraux | E15: '• Perte / vol / et dégradation du patrimoine immobilier, mobilier et consommables | F15: Risque de perte financière | G15: Risque de Fraude | H15: 4 | I15: 2 | J15: =H15*I15 -> 8 | L15: Inventaire mensuel ou bimensuel (semestriel ou annuel) de toutes les immobilisations. Suivi & Manitenance journalier des matériels. | M15: OUI | N15: ACHAT & LOGISTIQUE | O15: 2 | P15: =H15 -> 4 | Q15: =I15/O15 -> 1 | R15: =P15*Q15 -> 4
E16: Faiblesse dans la Gestion du parc automobile | F16: Risque d'utilisation frauduleuse des engins | G16: Risque de Fraude | H16: 4 | I16: 1 | J16: =H16*I16 -> 4 | L16: Mise en place d'un tableaud de bord lié à la gestion du parc automobile | M16: OUI | N16: ACHAT & LOGISTIQUE | O16: 2 | P16: =H16 -> 4 | Q16: =I16/O16 -> 0.5 | R16: =P16*Q16 -> 2
E17: • Inadéquation des systèmes de sécurité incendie et absence de plan d'évacuation des locaux | F17: Risque de perte financière Rique lié à l'insécurité | G17: Risque opérationnel | H17: 4 | I17: 3 | J17: =H17*I17 -> 12 | L17: Suvi & Maintenance mensuel de tous les sytémes de sécurité Mettre en œuvre un plan d'évacuation des locaux | M17: OUI | N17: ACHAT & LOGISTIQUE | O17: 1 | P17: =H17 -> 4 | Q17: =I17/O17 -> 3 | R17: =P17*Q17 -> 12
D18: Gestion administrative | E18: • Perte de valeurs et de courriers due à une conservation ou un mode d'acheminement ou un traitement inapproprié | F18: Risque de non respect des documents confidentiels | G18: Risque opérationnel | H18: 4 | I18: 2 | J18: =H18*I18 -> 8 | L18: Transmission effectué par un prestataire experrt en la matière | M18: OUI | N18: ACHAT & LOGISTIQUE | O18: 2 | P18: =H18 -> 4 | Q18: =I18/O18 -> 1 | R18: =P18*Q18 -> 4
D19: Gestion des droits d'accès physiques | E19: Accès aux locaux sensibles | F19: Intrusion dans les locaux, vol de biens matériels, d'informations sensibles, vandalisme | G19: Risque de Fraude | H19: 4 | I19: 3 | J19: =H19*I19 -> 12 | L19: Système de badge installé avec restiction des accés | M19: OUI | N19: ACHAT & LOGISTIQUE/IT | O19: 2 | P19: =H19 -> 4 | Q19: =I19/O19 -> 1.5 | R19: =P19*Q19 -> 6
D20: Assurance dommage aux biens | E20: Absence Assurance dommage aux biens immeubles (globale de banque) ou Absence Assurance multirisque-professionnel | F20: Risque de déterioration d'actif Risque de pertes financières ou d'exploitation | G20: Risque opérationnel | H20: 4 | I20: 3 | J20: =H20*I20 -> 12 | L20: Assurance global dommage, RC souscrit | M20: NON | N20: ACHAT & LOGISTIQUE | O20: 2 | P20: =H20 -> 4 | Q20: =I20/O20 -> 1.5 | R20: =P20*Q20 -> 6
D21: Suivi des contrats d'assurance | E21: Non-conformité des déclarations de sinistres dans les délais | F21: Déchéance des droits à remboursement Perte de patrimoine | G21: Risque opérationnel | H21: 4 | I21: 2 | J21: =H21*I21 -> 8 | L21: S'assurer que les sinistres sont déclarés dans les délais, en conformité avec les clauses contractuelles et en lien avec le service assurance. | M21: OUI | N21: ACHAT & LOGISTIQUE | O21: 2 | P21: =H21 -> 4 | Q21: =I21/O21 -> 1 | R21: =P21*Q21 -> 4
A22: ACHATS & LOGISTIQUE | E22: EVALUATION INTRINSEQUE | H22: =+ROUND(IFERROR(AVERAGE(H5:H18),0),0) -> 4 | I22: =+ROUND(IFERROR(AVERAGE(I5:I18),0),0) -> 2 | J22: =H22*I22 -> 8 | L22: EVALUATION RESIDUELLE | O22: =+ROUND(IFERROR(AVERAGE(O5:O18),0),0) -> 2 | P22: =+ROUND(IFERROR(AVERAGE(P5:P18),0),0) -> 4 | Q22: =I22/O22 -> 1 | R22: =P22*Q22 -> 4
F25: Risque de Fraude | G25: =COUNTIF(G5:G21,F25) -> 10
F26: Risque opérationnel | G26: =COUNTIF(G5:G22,F26) -> 6
F27: Risque stratégique | G27: =COUNTIF(G5:G21,F27) -> 1
F28: Risque de crédit | G28: =COUNTIF(G5:G21,F28) -> 0
F29: Risque réglementaire | G29: =COUNTIF(G5:G21,F29) -> 0
F30: Risque de liquidité | G30: =COUNTIF(G5:G21,F30) -> 0
F31: Risque exogéne | G31: =COUNTIF(G5:G21,F31) -> 0

Sheet CONFORMITE
A1: ANALYSE DES RISQUES OPERATIONNELS - ACHATS & LOGISTIQUE
A2: N° | B2: PROCESSUS | C2: RATIO | D2: SOUS PROCESSUS | E2: EXCEPTIONS MAJEURES CONSTATEES | F2: RISQUES CORRELES | G2: FAMILLE DE RISQUE | H2: Gravité | I2: Probabilité | J2: Risque brut (Rb) | K2: Justification de l'évaluation en cas de risque jugé critique | L2: DISPOSITIF DE PREVENTION ET DE CONTRÔLE | P2: Gravité résiduelle | Q2: Probabilité résiduelle | R2: Risque résiduel (Rr)
H4: G | I4: P | J4: est égal à GxP | L4: Description du dispositif | M4: Dispositif existant ou Non | N4: Owner du Contrôle | O4: Efficacité du dispositif | P4: G | Q4: Pr | R4: est égal à GxP
A5: 9 | B5: CONFORMITE | C5: 0.05 | D5: LAB/FT | E5: Identification du client (comptes sans Photo & comptes sans signature dans le système Flexcube) | F5: Risque opérationnel Risque de non-conformité | G5: Risque opérationnel | H5: 4 | I5: 3 | J5: =H5*I5 -> 12 | L5: Ne pas procéder à l'ouverture du compte dans le SI en cas d'absence de photo ou signature | M5: OUI | N5: Responsable Conformité | O5: 2 | P5: =H5 -> 4 | Q5: =I5/O5 -> 1.5 | R5: =P5*Q5 -> 6
E6: Non enrôlement des clients dans COFINALAB | F6: Risque réglementaire | G6: Risque réglementaire | H6: 3 | I6: 3 | J6: =H6*I6 -> 9 | L6: Contrôle de second de la conformité lors de la revue docuentaire | M6: oui | N6: Responsable Conformité | O6: 2 | P6: 3 | Q6: =I6/O6 -> 1.5 | R6: =P6*Q6 -> 4.5
E7: Défaillance danst la conservation des dossiers et des documents relatifs à l'identification des clients | F7: Risque réglementaire | G7: Risque réglementaire | H7: 3 | I7: 3 | J7: =H7*I7 -> 9 | L7: Disponibilité d'une politique d'archivage et numérisation en cours | M7: OUI | N7: Responsable Conformité | O7: 2 | P7: 3 | Q7: =I7/O7 -> 1.5 | R7: =P7*Q7 -> 4.5
E8: Entrée en relation avec un client évoluant dans un secteur à risque ( Finance digitale et les actifs virtuels; financement participattif; les jeux de hasard; l'immobilier; les professions juridiques indépendantes ; le sport professionnel et le commerce : location de véhicules | F8: Risque réglementaire | G8: Risque réglementaire | H8: 3 | I8: 3 | J8: =H8*I8 -> 9 | L8: Mise en place d'un outilsde profilage REIS KYC | M8: OUI | N8: Responsable Conformité | O8: 2 | P8: 3 | Q8: =I8/O8 -> 1.5 | R8: =P8*Q8 -> 4.5
E9: Défaut de mise à jour des procédures LBC/FT/ FP | F9: Risque réglementaire | G9: Risque réglementaire | H9: 5 | I9: 2 | J9: =H9*I9 -> 10 | L9: Procédure mis en place conformément à la règlementation et récement mis à jour et validé par le CA le 11-07-2025 | M9: OUI | N9: CONFORMITE | O9: 2 | P9: 5 | Q9: =I9/O9 -> 1 | R9: =P9*Q9 -> 5
E10: Dysfonctionnement de l'outil d'alerte et de profilage des clients | F10: Risque de non-conformité | G10: Risque réglementaire | H10: 4 | I10: 3 | J10: =H10*I10 -> 12 | L10: Outils fonctionnel | M10: OUI | N10: MANAGEMENT | O10: 1 | P10: 4 | Q10: =I10/O10 -> 3 | R10: =P10*Q10 -> 12
E11: Non mise en oeuvre du programme annuel de formation sur les thématiques du BC/FT/FP, l'éthique et la déontologie, la fraude… | F11: Risque de non-conformité | G11: Risque réglementaire | H11: 4 | I11: 3 | J11: =H11*I11 -> 12 | L11: Planning disponible et exécuté avec feulle de présence a l'appui | M11: OUI | N11: CONTRÔLE PERMANENT ET CONFORMITE | O11: 2 | P11: 4 | Q11: =I11/O11 -> 1.5 | R11: =P11*Q11 -> 6
E12: Non-élaboration et transmission du rapport annuel de mise en oeuvre du sur le dispositif de LBC/FT/FP. | F12: Risque de non-conformité | G12: Risque réglementaire | H12: 4 | I12: 3 | J12: =H12*I12 -> 12 | L12: Tableau de bord des reporting réglementaire établi | M12: OUI | N12: Responsable Conformité | O12: 2 | P12: 4 | Q12: =I12/O12 -> 1.5 | R12: =P12*Q12 -> 6
E13: Non-conformité des piéces d'identité (Présence de clients ayant plusieurs pièces différentes) | F13: Risque de non-conformité Risque de fraude | G13: Risque de Fraude | H13: 5 | I13: 2 | J13: =H13*I13 -> 10 | L13: Outils de profilage REIS KYC | M13: OUI | N13: Responsable Conformité | O13: 2 | P13: =H13 -> 5 | Q13: =I13/O13 -> 1 | R13: =P13*Q13 -> 5
E14: Méconnaissance et défaut de suivi de la liste des PPE | F14: Risque de non-conformité Risque de fraude | G14: Risque de Fraude | H14: 4 | I14: 4 | J14: =H14*I14 -> 16 | L14: Mettre en place le suivi des PPE au sein de la filiale | M14: NON | N14: Responsable Conformité | O14: 2 | P14: =H14 -> 4 | Q14: =I14/O14 -> 2 | R14: =P14*Q14 -> 8
E15: Absence de suivi sur les opérations remarquables | F15: Risque de non-conformité Risque de fraude | G15: Risque de Fraude | H15: 4 | I15: 3 | J15: =H15*I15 -> 12 | L15: Miise en place de seuil d'alerte et suivi assuré par un outils de surveillance | M15: OUI | N15: Responsable Conformité | O15: 2 | P15: =H15 -> 4 | Q15: =I15/O15 -> 1.5 | R15: =P15*Q15 -> 6
E16: Absence de l'évaluation des risques de blanchiment de capitaux et de financement du terrorisme sur les nouveaux produits | F16: Risque réglementaire | G16: Risque réglementaire | H16: 4 | I16: 2 | J16: =H16*I16 -> 8 | L16: Validation systèmatique des produit par la conformité avant lancement encadré par la polititque des gestion des nouveau produit | M16: OUI | N16: Responsable Conformité | O16: 2 | P16: 4 | Q16: =I16/O16 -> 1
E17: Déclaration des opérations suspectes non effectuées au niveau de la CENTIF | F17: Risque de non-conformité Risque de fraude | G17: Risque de Fraude | H17: 4 | I17: 4 | J17: =H17*I17 -> 16 | L17: Faire les DOS conformément aux exigences de la réglementation | M17: OUI | N17: Responsable Conformité | O17: 2 | P17: =H17 -> 4 | Q17: =I17/O17 -> 2 | R17: =P17*Q17 -> 8
D18: COMMUNICATION | E18: Défaut d'affichage du règlement intérieur dans les locaux contrairement aux dispositions de l'Art.L 100 du code du travail. | F18: Risque d'image de l'institution | G18: Risque stratégique | H18: 4 | I18: 2 | J18: =H18*I18 -> 8 | L18: Afficher le règlement intérieur au siège et dans les Agences | M18: Non | N18: Responsable Conformité | O18: 1 | P18: =H18 -> 4 | Q18: =I18/O18 -> 2 | R18: =P18*Q18 -> 8
E19: Défaut d'affichage des conditions générales en Agence | F19: Risque réglementaire | G19: Risque réglementaire | H19: 4 | I19: 2 | J19: =H19*I19 -> 8 | L19: Afficher les conditions générales de banque et s'assurer de la publication au niveau de la banque centrale | M19: OUI | N19: Responsable Conformité | O19: 2 | P19: =H19 -> 4 | Q19: =I19/O19 -> 1 | R19: =P19*Q19 -> 4
D20: ETHIQUE & DEONTOLOGIE | E20: Non respect de la confidentialité | F20: Risque d'image de l'institution | G20: Risque stratégique | H20: 4 | I20: 3 | J20: =H20*I20 -> 12 | L20: Respect de la charte de l'éthique et de la déontologie | M20: Oui | N20: Responsable Conformité | O20: 2 | P20: =H20 -> 4 | Q20: =I20/O20 -> 1.5 | R20: =P20*Q20 -> 6
E21: Non respect des lois et reglement intérieur | F21: Risque d'image de l'institution | G21: Risque stratégique | H21: 4 | I21: 3 | J21: =H21*I21 -> 12 | L21: Respect de la charte de l'éthique et de la déontologie | M21: Oui | N21: Responsable Conformité | O21: 2 | P21: =H21 -> 4 | Q21: =I21/O21 -> 1.5 | R21: =P21*Q21 -> 6
E22: Manque d'intégrité | F22: Risque perte financière, Risque d'image de l'institution | G22: Risque stratégique | H22: 5 | I22: 3 | J22: =H22*I22 -> 15 | L22: Respect de la charte de l'éthique et de la déontologie | M22: Oui | N22: Responsable Conformité | O22: 2 | P22: =H22 -> 5 | Q22: =I22/O22 -> 1.5 | R22: =P22*Q22 -> 7.5
D23: VEILLE REGLEMENTAIRE | E23: Absence de veille réglementaire au sein de l'entité | F23: Risque réglementaire | G23: Risque réglementaire | H23: 4 | I23: 3 | J23: =H23*I23 -> 12 | L23: Procédure sur la veille réglementaire | M23: Oui | N23: Responsable Conformité | O23: 2 | P23: =H23 -> 4 | Q23: =I23/O23 -> 1.5 | R23: =P23*Q23 -> 6
E25: EVALUATION INTRINSEQUE | H25: =+ROUND(IFERROR(AVERAGE(H5:H23),0),0) -> 4 | I25: =+ROUND(IFERROR(AVERAGE(I5:I23),0),0) -> 3 | J25: =H25*I25 -> 12 | L25: EVALUATION RESIDUELLE | O25: =+ROUND(IFERROR(AVERAGE(O5:O23),0),0) -> 2 | P25: =+ROUND(IFERROR(AVERAGE(P5:P23),0),0) -> 4 | Q25: =I25/O25 -> 1.5 | R25: =P25*Q25 -> 6
F28: Risque de Fraude | G28: =COUNTIF(G5:G23,F28) -> 4
F29: Risque opérationnel | G29: =COUNTIF(G5:G25,F29) -> 1
F30: Risque stratégique | G30: =COUNTIF(G5:G23,F30) -> 4
F31: Risque de crédit | G31: =COUNTIF(G5:G23,F31) -> 0
F32: Risque réglementaire | G32: =COUNTIF(G5:G23,F32) -> 10
F33: Risque de liquidité | G33: =COUNTIF(G5:G23,F33) -> 0
F34: Risque exogéne | G34: =COUNTIF(G5:G23,F34) -> 0

Sheet PLUS GROS RISQUES
A1: RISQUES OPERATIONNELS A FORT IMPACT BUSINESS
A2: PROCESSUS | B2: SOUS PROCESSUS | C2: EXCEPTIONS MAJEURES CONSTATEES | D2: FAMILLE DE RISQUE | E2: Gravité | F2: Probabilité | G2: Risque brut (Rb)
E4: G | F4: P | G4: est égal à GxP
A5: RESSOURCE HUMAINE | B5: Mauvaise gestion des prêts octroyés au personnel (non respect de la quotité cessible, échéance non prélevée…) | C5: Risque opérationnel | D5: Risque opérationnel | E5: 5 | F5: 3 | G5: =E5*F5 -> 15
B6: Exixtance de solde de congés supérieurs à la norme | C6: Perturbation/baisse de rendement | D6: Risque opérationnel | E6: 5 | F6: 3 | G6: =E6*F6 -> 15
B7: Non évaluation annuelle et suivi des besoins de formation du personnel | C7: Non renforcement des compétences Démotivation du personnel | D7: Risque stratégique | E7: 4 | F7: 4 | G7: =E7*F7 -> 16
B8: Absence d'une politique de conservation ou rétention du personnel | C8: Risque d'image , Risque réputationnel | D8: Risque stratégique | E8: 4 | F8: 4 | G8: =E8*F8 -> 16
B9: Qualité du mobilier | C9: Risque de dégradation de la santé physique des collaborateurs | D9: Risque stratégique | E9: 4 | F9: 4 | G9: =E9*F9 -> 16
B10: Manque d'hygiène | C10: Risque de maladie | D10: Risque opérationnel | E10: 4 | F10: 4 | G10: =E10*F10 -> 16
A11: OPERATION | B11: • Rejet tardif de la banque partenaire sur le sort d'un cheque apres comptabilisation dans nos livres | C11: Risques d'impayés Risque de fraude Risque de pertes financières | D11: Risque de Fraude | E11: 4 | F11: 4 | G11: =E11*F11 -> 16
B12: • Absence de prélévements des frais de remises cheques | C12: Risques de pertes financieres | D12: Risques de pertes financieres | E12: 4 | F12: 4 | G12: =E12*F12 -> 16
B13: '• Longs suspens de plus de 90 jours sur les comptes internes et les rapprochements bancaires | C13: Risque de pertes financières Risque de fraude | D13: Risque de Fraude | E13: 5 | F13: 3 | G13: =E13*F13 -> 15
B14: Absence d'analyse des comptes internes | C14: Risque de fraude Risque de pertes financières | D14: Risque de Fraude | E14: 5 | F14: 3 | G14: =E14*F14 -> 15
B15: • Dossiers de crédit incomplets (Absence de la convention, contrat cautionnement, certificat de résidence, géolocalisation, Fiche CAT...) | C15: Risque de crédit Risque de non-conformité | D15: Risque de crédit | E15: 4 | F15: 4 | G15: =E15*F15 -> 16
A16: CREDIT | B16: • Non respect du seuil de validation crédit par SCO | C16: Risque de non-conformité | D16: Risque de crédit | E16: 4 | F16: 4 | G16: =E16*F16 -> 16
B17: Prêts débloqués non décaissés sur une balance agée de plus de 3 mois | C17: Risque opérationnel Risque de fraude Risque de non-conformité | D17: Risque de Fraude | E17: 5 | F17: 4 | G17: =E17*F17 -> 20
B18: Absence de communication et de validation préalable avec le client sur les condtions du crédit avant la mise en place | C18: Risque de crédit Risque de conformité | D18: risque de crédit Risque de conformité | E18: 5 | F18: 3 | G18: =E18*F18 -> 15
B19: Absence de visibilité de la Direction crédit sur les dossiers niveau agence et RZ | C19: Risque de crédit Risque de conformité | D19: risque de crédit Risque de conformité | E19: 4 | F19: 4 | G19: =E19*F19 -> 16
B20: Mise en place de COFI-EXPRESS ou SPOT dans le but de solder une partie d'impayés d'un crédit classique | C20: Risque opérationnel Risque de fraude Risque de non-conformité | D20: Risque de Fraude | E20: 5 | F20: 4 | G20: =E20*F20 -> 20
B21: Mise en place de crédit fictif (Activité inexistante, Escompte de facture déjà payée avec complicité du payeur final…) | C21: Risque opérationnel Risque de fraude Risque de non-conformité | D21: Risque de Fraude | E21: 5 | F21: 4 | G21: =E21*F21 -> 20
B22: Absence d'établissement de lien juridique ou de propriété entre le client et l'activité déclarer par ce dernier | C22: Risque de fraude | D22: Risque de crédit | E22: 4 | F22: 4 | G22: =E22*F22 -> 16
B23: Forte Concentration de secteur d'activités ou type de prêt en matière de crédit | C23: Risque de concentration | D23: Risque de crédit | E23: 4 | F23: 4 | G23: =E23*F23 -> 16
B24: Absence de domiciliation irrévoccable sur les crédits causés (Avance sur facture, bon de commande, marché) | C24: Risque de détournement d'objet Risque de fraude | D24: Risque de crédit | E24: 4 | F24: 4 | G24: =E24*F24 -> 16
B25: • Erreur d'analyse dans l'étude des dossiers des crédits | C25: Risque d'impayés Risque de pertes financières | D25: Risque de crédit | E25: 5 | F25: 3 | G25: =E25*F25 -> 15
B26: • Financement de plusieurs prêts pour un seul client disposant de plusieurs comptes | C26: Risque de fraude Risque de pertes financières | D26: Risque de Fraude | E26: 5 | F26: 3 | G26: =E26*F26 -> 15
B27: • Non réalisation systématique des visites et contre-visite terrain permettant de localiser l'activité ou le domicile du client, de constater visuellement l'existence des biens présentés en garantie et d'évaluer la capacité de remboursement du client | C27: Risque de détournement d'objet Risque de fraude | D27: Risque de crédit | E27: 3 | F27: 5 | G27: =E27*F27 -> 15
B28: • Absence de suivi des prêts restructurés ou décalés | C28: Risque réglementaire Risque de pertes financières | D28: Risque de crédit | E28: 5 | F28: 3 | G28: =E28*F28 -> 15
... B33: Procéder à l'adjudication des garanties pour solder une créance sans disposer des Etats de droits réels | C33: Risque opérationnel Risque de fraude Risque de non-conformité | D33: Risque de Fraude | E33: 5 | F33: 3 | G33: =E33*F33 -> 15
A34: FINANCE | B34: • Non automatisation des reporting règlementaire, financier et métier | C34: Risque de non-conformité des informations issues du SI | D34: Risque réglementaire | E34: 4 | F34: 4 | G34: =E34*F34 -> 16
B35: Retard de dépôt des reporting règlementaires | C35: Risque de non-conformité | D35: Risque réglementaire | E35: 4 | F35: 4 | G35: =E35*F35 -> 16
B36: • Retard de déclaration/paiement des impôts, taxes et redevances et/ou erreur de calcul dans la détermination des impôts, taxes et redevances à payer | C36: Risque de redressement fiscal, ou pénalités | D36: Risque réglementaire | E36: 4 | F36: 4 | G36: =E36*F36 -> 16
A37: IT | B37: • Non-respect de la procédure des changements, des configurations et des mises en production (Un changement consiste à modifier, créer ou supprimer un des composants de l'infrastructure du système d'information) | C37: Risque opérationnel Risque de fraude | D37: Risque de Fraude | E37: 4 | F37: 4 | G37: =E37*F37 -> 16
B38: • Manque de communication en interne, entrainant une faiblesse dans la désactivation des profils sortants. | C38: Risque de fraude | D38: Risque de Fraude | E38: 4 | F38: 4 | G38: =E38*F38 -> 16
B39: • Manque d'espace de stockage des images de la vidéo-surveillance | C39: Non identification des images en cas de vol | D39: Risque de Fraude | E39: 4 | F39: 4 | G39: =E39*F39 -> 16
B40: • Corruption de la base de données (Possibilité de créer, modifier et supprimer des informations) | C40: Risque de fraude | D40: Risque de Fraude | E40: 5 | F40: 3 | G40: =E40*F40 -> 15
B41: • Non sauvegarde des données et pas de site de secours | C41: Risque de perte de données | D41: Risque opérationnel | E41: 4 | F41: 4 | G41: =E41*F41 -> 16
B42: Compromission d'un poste de travail via mail phishing | C42: Risque de fraude | D42: Risque de Fraude | E42: 4 | F42: 4 | G42: =E42*F42 -> 16
A43: PRODUIT DIGITAUX | B43: Absence de réconciliation des transactions liées aux CARTES GIM UEMOA | C43: Risque opérationnel Risque de fraude | D43: Risque de Fraude | E43: 5 | F43: 3 | G43: =E43*F43 -> 15
B44: Non-respect des procedures d'approvisionnement de cartes et de rechargement | C44: Risque opérationnel | D44: Risque opérationnel | E44: 4 | F44: 4 | G44: =E44*F44 -> 16
B45: Dépassement du seuil réglementaire fixé à 2.000.000 francs CFA lors de la réalisation d'une ou plusieurs opérations. | C45: Risque de non-conformité Risque réglementaire Risque d'image Risque de pertes financières | D45: Risque réglementaire | E45: 4 | F45: 4 | G45: =E45*F45 -> 16
B46: Non justification des opérations (dépôt sur compte mobile money/dépôt sur comptes COFINA) | C46: Risque de fraude Risque d'image Risque de pertes fiancières | D46: Risque de Fraude | E46: 4 | F46: 4 | G46: =E46*F46 -> 16
B47: Erreur de saisie du numéro du compte mobile money lors de la réalisation de l'opération de dépôt à partir du compte du client domicilié dans les livres de COFINA SN | C47: Risque de fraude Risque d'image Risque de pertes fiancières | D47: Risque de Fraude | E47: 5 | F47: 3 | G47: =E47*F47 -> 15
A48: GOUV ET CONTRÔLE INTERNE | B48: • Absence de suivi systématique relatif au respect des dispositions légales et Réglementaires relatives à la gouvernance (Respect de la loi sur les microfinances, des instructions, des statuts) | C48: Sanctions légales Sanctions pécuniaires | D48: Risque réglementaire | E48: 4 | F48: 4 | G48: =E48*F48 -> 16
A49: JURIDIQUE ET CONTENTIEUX | B49: • Risque lié aux difficultés de localisation des clients (changement d'adresse, de coordonnées) pouvant entrainer des difficultés de recouvrement et des pertes financières pour COFINA SN | C49: Risques d'impayés, pertes financières | D49: Risque de crédit | E49: 4 | F49: 4 | G49: =E49*F49 -> 16
B50: Non formalisation de l'aval du client lors de certaines restructurations | C50: Risque de fraude | D50: Risque de Fraude | E50: 4 | F50: 4 | G50: =E50*F50 -> 16
B51: • Impossibilité de réaliser une garantie foncière en raison d'une détérioration normale et/ou de sinistre impactant de manière significative la valeur de l'actif (incendie, dégât des eaux, etc.) | C51: Risques d'impayés, pertes financières | D51: Risque de crédit | E51: 4 | F51: 4 | G51: =E51*F51 -> 16
B52: Garanties sur évaluées lors d'une expertise | C52: Risque de pertes financières Risque de fraude | D52: Risque de crédit | E52: 4 | F52: 4 | G52: =E52*F52 -> 16
B53: Adjudication des garanties afin d'éteindre la créance sans disposition des états de droits réels ou certificat d'inscription hypothécaire | C53: Risque de fraude Risque de crédit | D53: Risque de crédit | E53: 4 | F53: 4 | G53: =E53*F53 -> 16
B54: Absence de suivi Passage en perte (write-off) | C54: Risque financier, risque opérationnel, fraude | D54: Risque opérationnel | E54: 4 | F54: 4 | G54: =E54*F54 -> 16
A55: ACHAT LOGISTIQUE | B55: Non-respect de la procédure de gestion des sorties et cessions d'immobilisations | C55: Vol | D55: Risque de Fraude | E55: 4 | F55: 4 | G55: =E55*F55 -> 16
A56: CONFORMITE | B56: Méconnaissance et défaut de suivi de la liste des PPE | C56: Risque de non-conformité Risque de fraude | D56: Risque de Fraude | E56: 4 | F56: 4 | G56: =E56*F56 -> 16
B57: Déclaration des opérations suspectes non effectuées au niveau de la CENTIF | C57: Risque de non-conformité Risque de fraude | D57: Risque de Fraude | E57: 4 | F57: 4 | G57: =E57*F57 -> 16
B58: Manque d'intégrité | C58: Risque perte financière, Risque d'image de l'institution | D58: Risque stratégique | E58: 5 | F58: 3 | G58: =E58*F58 -> 15
A59: GRAND COMPTE | B59: Absence de suivi des clients décédés | C59: Risque opérationnel Risque de non-conformité | D59: Risque opérationnel | E59: 4 | F59: 4 | G59: 16
B60: • Mauvais archivage des dossiers d'ouverture de compte | C60: Risque de pertes de document | D60: Risque opérationnel | E60: 4 | F60: 4 | G60: =E60*F60 -> 16
B61: • Manque de suivi des fermetures de compte Client | C61: Risque opérationnel Risque de conformité | D61: Risque opérationnel | E61: 4 | F61: 4 | G61: =E61*F61 -> 16

Sheet INNOVATION ET PARTENARIAT
A1: ANALYSE DES RISQUES OPERATIONNELS - INNOVATION & PARTENARIAT
A2: N° | B2: PROCESSUS | C2: RATIO | D2: SOUS PROCESSUS | E2: EXCEPTIONS MAJEURES CONSTATEES | F2: RISQUES CORRELES | G2: FAMILLE DE RISQUE | H2: Gravité | I2: Probabilité | J2: Risque brut (Rb) | K2: Justification de l'évaluation en cas de risque jugé critique | L2: DISPOSITIF DE PREVENTION ET DE CONTRÔLE | P2: Gravité résiduelle | Q2: Probabilité résiduelle | R2: Risque résiduel (Rr)
H4: G | I4: P | J4: est égal à GxP | L4: Description du dispositif à mettre en œuvre | M4: Dispositif existant ou Non | N4: Owner du Contrôle | O4: Efficacité du dispositif | P4: G | Q4: Pr | R4: est égal à GxP
A5: 1 | B5: INNOVATION ET PARTENARIAT | D5: Identification partenaires | E5: Sélection d’un partenaire non fiable | F5: Risque financier et réputationnel | G5: Risque stratégique | H5: 4 | I5: 2 | J5: =H5*I5 -> 8 | L5: Charte partenariale : Document de référence d'ethique et de valeurs Politique de partenariat: Document de référence à la fois stratégique et opérationnel qui permet de s'assurer d'un alignement sur des objectifs communs Politique de crédit: Document de réference en matiere d'octroi de crédit | M5: Existant En cours Existant | N5: Responsable département | O5: 2 | P5: 4 | Q5: =I5/O5 -> 1 | R5: =P5*Q5 -> 4
A6: 2 | E6: Partenaire impliqué dans des activités illicites | F6: Sanctions réglementaires | G6: Risque de non confirmité | H6: 4 | I6: 2 | J6: =H6*I6 -> 8 | L6: Charte partenariale Textes réglementaires en vigueur | M6: Existant Existant | N6: Responsable département | O6: 2 | P6: 4 | Q6: =I6/O6 -> 1 | R6: =P6*Q6 -> 4
A7: 3 | D7: Analyse partenaires | E7: Mauvaise évaluation financière du partenaire (Défaillance du partenariat) | F7: Financier | G7: Risque Financier | H7: 3 | I7: 3 | J7: =H7*I7 -> 9 | L7: Business Case à valider avec la finance | M7: Elaboré selon le projet | N7: Cheffe pole partenariat | O7: 2 | P7: 3 | Q7: =I7/O7 -> 1.5 | R7: =P7*Q7 -> 4.5
A8: 4 | D8: Sélection partenaires | E8: Partenaire non aligné avec la stratégie (Critères stratégiques absents, Partenariat inefficace) | F8: Stratégique | G8: Risque stratégique | H8: 4 | I8: 2 | J8: =H8*I8 -> 8 | L8: Charte partenariale Politique de partenariat Document de stratégie innovation & partenariat | M8: Existant Existant Existant | N8: Cheffe pole partenariat | O8: 2 | P8: 2 | Q8: =I8/O8 -> 1 | R8: =P8*Q8 -> 2
A9: 5 | D9: Négociation | E9: Clauses contractuelles défavorables (Faible implication du juridique) | F9: Litiges ou pertes financières Risque Juridique | G9: Risque juridique | H9: 3 | I9: 2 | J9: =H9*I9 -> 6 | L9: Conventions et contrats soumis systématiquement au juridique Document de stratégie innovation & partenariat | M9: Existant | N9: Cheffe pole partenariat | O9: 2 | P9: 3 | Q9: =I9/O9 -> 1 | R9: =P9*Q9 -> 3
A10: 6 | E10: Absence de contrat formel (Partenariat informel) | F10: Risque juridique | G10: Risque juridique | H10: 4 | I10: 2 | J10: =H10*I10 -> 8 | L10: Conventions et contrats soumis systématiquement au juridique Document de stratégie innovation & partenariat | M10: Existant | N10: Cheffe pole partenariat | O10: 2 | P10: 4 | Q10: =I10/O10 -> 1 | R10: =P10*Q10 -> 4
A11: 7 | D11: Signature partenariat | E11: Engagement financier mal estimé (Analyse budgétaire insuffisante) | F11: Dépassement budgétaire | G11: Risque opérationnel | H11: 3 | I11: 2 | J11: =H11*I11 -> 6 | L11: Business Case à valider avec la finance Document de stratégie innovation & partenariat Projet de budget validé | M11: Elaboré selon le projet Existant Existant | N11: Responsable département | O11: 2 | P11: 3 | Q11: =I11/O11 -> 1 | R11: =P11*Q11 -> 3
A12: 8 | D12: Gestion partenariat | E12: Non-respect des engagements du partenaire (Suivi contractuel insuffisant) | F12: Retard des projets | G12: Risque opérationnel | H12: 3 | I12: 2 | J12: =H12*I12 -> 6 | L12: Comité de suivi et d'évaluation des partenariats Proposition d'un avenant Dénonciation et résiliation | M12: Existant Selon le partenariat Selon le partenariat | N12: Responsable département | O12: 2 | P12: 3 | Q12: =I12/O12 -> 1 | R12: =P12*Q12 -> 3
A13: 9 | E13: Conflit d’intérêt dans la sélection (Manque de transparence) | F13: Atteinte à la réputation | G13: Risque de Fraude | H13: 4 | I13: 2 | J13: =H13*I13 -> 8 | L13: Charte partenariale Politique de partenariat | M13: Existant Existant | N13: Responsable département | O13: 2 | P13: 4 | Q13: =I13/O13 -> 1 | R13: =P13*Q13 -> 4
A14: 10 | E14: Dépendance excessive à un partenaire (Manque de diversification) | F14: Vulnérabilité stratégique | G14: Risque stratégique | H14: 3 | I14: 2 | J14: =H14*I14 -> 6 | L14: Politique de partenariat Document de stratégie innovation & partenariat | M14: Existant Existant | N14: Responsable département | O14: 2 | P14: 3 | Q14: =I14/O14 -> 1 | R14: =P14*Q14 -> 3
A15: 11 | D15: Pilotage et Suivi projets | E15: Retard dans la mise en œuvre (Planification insuffisante) | F15: Perte d’opportunités | G15: Risque opérationnel | H15: 3 | I15: 2 | J15: =H15*I15 -> 6 | L15: Note de cadrage: définition du périmetre du projet Document de planification opérationnelle: suivi et exécution du projet | M15: Selon le projet Selon le projet | N15: Responsable département | O15: 2 | P15: 3 | Q15: =I15/O15 -> 1 | R15: =P15*Q15 -> 3
A16: 12 | E16: Dépassement du budget (Suivi financier faible) | F16: Impact sur la rentabilité | G16: Risque Financier | H16: 2 | I16: 2 | J16: =H16*I16 -> 4 | L16: Projet de budget validé Arbitrage et validation du dépassement par la direction financiére et | M16: Existant Selon le projet | N16: Responsable département | O16: 2 | P16: 2 | Q16: =I16/O16 -> 1 | R16: =P16*Q16 -> 2
A17: 13 | E17: Mauvaise coordination des projets (Gouvernance insuffisante) | F17: Echec des projets | G17: Risque opérationnel | H17: 2 | I17: 2 | J17: =H17*I17 -> 4 | L17: Note de cadrage Document de stratégie innovation & partenariat | M17: Selon le projet Existant | N17: Responsable département | O17: 2 | P17: 2 | Q17: =I17/O17 -> 1 | R17: =P17*Q17 -> 2
A18: 14 | E18: Absence d’indicateurs de performance (Outils de suivi inexistants) | F18: Difficulté d’évaluation | G18: Risque opérationnel | H18: 2 | I18: 2 | J18: =H18*I18 -> 4 | L18: Document de planification opérationnelle | M18: Selon le projet | N18: Responsable département | O18: 2 | P18: 2 | Q18: =I18/O18 -> 1 | R18: =P18*Q18 -> 2
A19: 18 | D19: Innovation digitale | E19: Défaillance technologique (Infrastructure IT insuffisante) | F19: Interruption des services | G19: Risque technologique | H19: 4 | I19: 3 | J19: =H19*I19 -> 12 | L19: Note de cadrage Document de planification opérationnelle Document de stratégie innovation & partenariat Coordination inter-métiers | M19: Selon le projet Selon le projet Selon le projet Selon le projet | N19: chef pole innovation | O19: 2 | P19: 4 | Q19: =I19/O19 -> 1.5 | R19: =P19*Q19 -> 6
A20: 19 | E20: Cyberattaque (Sécurité informatique faible) | F20: Perte de données | G20: Risque technologique | H20: 4 | I20: 3 | J20: =H20*I20 -> 12 | L20: Note de cadrage Document de planification opérationnelle Document de stratégie innovation & partenariat Coordination inter-métiers | M20: Selon le projet Selon le projet Selon le projet Selon le projet | N20: chef pole innovation | O20: 2 | P20: 4 | Q20: =I20/O20 -> 1.5 | R20: =P20*Q20 -> 6
A21: 20 | D21: Gestion données | E21: Fuite de données (Protection insuffisante) | F21: Risque réputationnel | G21: Risque technologique | H21: 4 | I21: 2 | J21: =H21*I21 -> 8 | L21: Note de cadrage Document de planification opérationnelle Document de stratégie innovation & partenariat Coordination inter-métiers | M21: Selon le projet Selon le projet Selon le projet Selon le projet | N21: chef pole innovation | O21: 2 | P21: 4 | Q21: =I21/O21 -> 1 | R21: =P21*Q21 -> 4
A22: 21 | E22: Données de mauvaise qualité (Base de données non fiable) | F22: Décisions erronées | G22: Risque opérationnel | H22: 4 | I22: 2 | J22: =H22*I22 -> 8 | L22: Note de cadrage Document de planification opérationnelle Document de stratégie innovation & partenariat Coordination inter-métiers | M22: Selon le projet Selon le projet Selon le projet Selon le projet | N22: chef pole innovation | O22: 2 | P22: 4 | Q22: =I22/O22 -> 1 | R22: =P22*Q22 -> 4
A23: 22 | D23: Financement projets | E23: Mauvaise utilisation des fonds | F23: Risque de fraude | G23: Risque de Fraude | H23: 4 | I23: 3 | J23: =H23*I23 -> 12 | L23: Document de planification financiere Coordination inter-métiers finance et trésorier | M23: Selon le projet Selon le projet | N23: Responsable département | O23: 2 | P23: 4 | Q23: =I23/O23 -> 1.5 | R23: =P23*Q23 -> 6
A24: 23 | E24: Non-respect des exigences bailleurs (Gestion inadéquate) | F24: Suspension financement | G24: Risque de non confirmité | H24: 4 | I24: 2 | J24: =H24*I24 -> 8 | L24: Comité de suivi des partenariats Coordination inter-métiers | M24: Selon le projet Selon le projet | N24: Responsable département | O24: 2 | P24: 4 | Q24: =I24/O24 -> 1 | R24: =P24*Q24 -> 4
A25: 24 | D25: Communication | E25: Mauvaise communication des partenariats (Coordination insuffisante) | F25: Atteinte à l’image Risque réputationnel | G25: Risque opérationnel | H25: 3 | I25: 2 | J25: =H25*I25 -> 6 | L25: Accord de confidentialité Contractualisation des initiatives de communication | M25: Selon le projet Selon le projet | N25: Responsable département | O25: 2 | P25: 3 | Q25: =I25/O25 -> 1 | R25: =P25*Q25 -> 3
A26: 25 | D26: Gouvernance innovation | E26: Absence de stratégie d’innovation (Manque de vision) | F26: Projets inefficaces | G26: Risque stratégique | H26: 3 | I26: 2 | J26: =H26*I26 -> 6 | L26: Document de stratégie innovation & partenariat | M26: Existant | N26: chef pole innovation | O26: 2 | P26: 3 | Q26: =I26/O26 -> 1 | R26: =P26*Q26 -> 3
A27: 26 | E27: Mauvaise priorisation des projets (Gouvernance faible) | F27: Perte de ressources | G27: Risque stratégique | H27: 2 | I27: 2 | J27: =H27*I27 -> 4 | L27: Document de stratégie innovation & partenariat | M27: Existant | N27: chef pole innovation | O27: 2 | P27: 2 | Q27: =I27/O27 -> 1 | R27: =P27*Q27 -> 2
A28: INNOVATION ET PARTENARIATS | E28: EVALUATION INTRINSEQUE | H28: =+ROUND(IFERROR(AVERAGE(H5:H27),0),0) -> 3 | I28: =+ROUND(IFERROR(AVERAGE(I5:I27),0),0) -> 2 | J28: =H28*I28 -> 6 | L28: EVALUATION RESIDUELLE | O28: =+ROUND(IFERROR(AVERAGE(O5:O27),0),0) -> 2 | P28: =+ROUND(IFERROR(AVERAGE(P5:P27),0),0) -> 3 | Q28: =+ROUND(IFERROR(AVERAGE(Q5:Q27),0),0) -> 1 | R28: =P28*Q28 -> 3
F31: Risque de Fraude | G31: =COUNTIF($G$5:$G$27,F31) -> 2
F32: Risque opérationnel | G32: =COUNTIF($G$5:$G$27,F32) -> 7
F33: Risque stratégique | G33: =COUNTIF($G$5:$G$27,F33) -> 5
F34: Risque de crédit | G34: =COUNTIF($G$5:$G$27,F34) -> 0
F35: Risque réglementaire | G35: =COUNTIF($G$5:$G$27,F35) -> 0
F36: Risque de liquidité | G36: =COUNTIF($G$5:$G$27,F36) -> 0
F37: Risque exogéne | G37: =COUNTIF($G$5:$G$27,F37) -> 0
F38: Risque juridique | G38: =COUNTIF($G$5:$G$27,F38) -> 2
F39: Risque Financier | G39: =COUNTIF($G$5:$G$27,F39) -> 2
F40: Risque de non confirmité | G40: =COUNTIF($G$5:$G$27,F40) -> 2
F41: Risque technologique | G41: =COUNTIF($G$5:$G$27,F41) -> 3

Sheet CARTOGRAPHIE RISQUES RESIDUELS
A1: CARTOGRAPHIE DES RISQUES RESIDUELS
A3: PROBABILITE | B3: 6 | C3: 6 ○→ CONFORMITE | D3: 12 | E3: 18 | F3: 24 | G3: 30 | H3: 36
B4: 5 | C4: 5 ○→ MARKETING & PRODUITS ○→ AGENCES ○→ GRAND COMPTE | D4: 10 | E4: 15 | F4: 20 | G4: 25 | H4: 30
B5: 4 | C5: 4 ○→ ACHAT LOGIST | D5: 8 ○→ CREDIT & RISQUES ○→ IT ○→ JURIDIQUE & CONTENTIEUX | E5: 12 | F5: 16 | G5: 20 | H5: 24
B6: 3 | C6: 3 ○→ RESS HUM ○→INNOVATION ET PARTENARIAT | D6: 6 | E6: 9 | F6: 12 | G6: 15 | H6: 18
B7: 2 | C7: 2 | D7: 4 ○→ GOUV & CI | E7: 6 | F7: 8 ○→ RECOUVREMENT ○→ PRODUITS DIGITAUX & CHANGE ○→ FINANCE | G7: 10 ○→ OPERATIONS | H7: 12
B8: 1 | C8: 1 | D8: 2 | E8: 3 | F8: 4 | G8: 5 | H8: 6
B9: 0 | C9: 1 | D9: 2 | E9: 3 | F9: 4 | G9: 5 | H9: 6
H10: GRAVITE
C12: BAREME RISQUE | F12: =LEGENDE!C2 -> PROCESSUS | G12: =LEGENDE!D2 -> GRAVITE | H12: =LEGENDE!E2 -> PROBABILITE | I12: =LEGENDE!F2 -> RISQUE BRUT
D13: CRITIQUE | F13: =LEGENDE!C3 -> #REF! | G13: =DMCC!#REF! -> #REF! | H13: =DMCC!#REF! -> #REF! | I13: =G13*H13 -> #REF!
D14: TRES ELEVE | F14: =LEGENDE!C4 -> #REF! | G14: =AGENCES!#REF! -> #REF! | H14: =AGENCES!#REF! -> #REF! | I14: =G14*H14 -> #REF!
D15: ELEVE | F15: =LEGENDE!C5 -> #REF! | G15: =CREDIT!#REF! -> #REF! | H15: =CREDIT!#REF! -> #REF! | I15: =G15*H15 -> #REF!
D16: MODERE | F16: =LEGENDE!C6 -> #REF! | G16: =RECOUVREMENT!#REF! -> #REF! | H16: =RECOUVREMENT!#REF! -> #REF! | I16: =G16*H16 -> #REF!
D17: FAIBLE | F17: =LEGENDE!C7 -> #REF! | G17: =OPERATIONS!#REF! -> #REF! | H17: =OPERATIONS!#REF! -> #REF! | I17: =G17*H17 -> #REF!
D18: NON SIGNIFICATIF | F18: =LEGENDE!C8 -> #REF! | G18: ='PRODUITS DIGITAUX'!#REF! -> #REF! | H18: ='PRODUITS DIGITAUX'!#REF! -> #REF! | I18: =G18*H18 -> #REF!
F19: =LEGENDE!C9 -> #REF! | G19: ='FINANCES & REPORTING'!#REF! -> #REF! | H19: ='FINANCES & REPORTING'!#REF! -> #REF! | I19: =G19*H19 -> #REF!
F20: ='IT '!#REF! -> #REF! | G20: ='IT '!#REF! -> #REF! | H20: ='IT '!#REF! -> #REF! | I20: =G20*H20 -> #REF!
F21: =LEGENDE!C11 -> GOUVERNANCE & CI | G21: ='GOUV & CONTRÔLE INTERNE'!P25 -> 4 | H21: ='GOUV & CONTRÔLE INTERNE'!Q25 -> 1 | I21: =G21*H21 -> 4
F22: =LEGENDE!C12 -> #REF! | G22: ='JURIDIQUE & CONTENTIEUX'!#REF! -> #REF! | H22: ='JURIDIQUE & CONTENTIEUX'!#REF! -> #REF! | I22: =G22*H22 -> #REF!
F23: =LEGENDE!C13 -> #REF! | G23: ='RESSOURCES HUMAINES'!#REF! -> #REF! | H23: ='RESSOURCES HUMAINES'!#REF! -> #REF! | I23: =G23*H23 -> #REF!
F24: =LEGENDE!C14 -> #REF! | G24: ='ACHATS & LOGISTIQUE'!#REF! -> #REF! | H24: ='ACHATS & LOGISTIQUE'!#REF! -> #REF! | I24: =G24*H24 -> #REF!
F25: =CONFORMITE!#REF! -> #REF! | G25: =CONFORMITE!#REF! -> #REF! | H25: =CONFORMITE!#REF! -> #REF! | I25: =G25*H25 -> #REF!
F26: FILIALE | G26: =+ROUND(IFERROR(AVERAGE(G13:G24),0),0) -> 0 | H26: =+ROUND(IFERROR(AVERAGE(H13:H24),0),0) -> 0 | I26: =G26*H26 -> 0

Sheet CARTOGRAPHIE RISQUES BRUTS
A1: CARTOGRAPHIE DES RISQUES BRUTS
A3: PROBABILITE | B3: 6 | C3: 6 | D3: 12 | E3: 18 | F3: 24 | G3: 30 | H3: 36
B4: 5 | C4: 5 | D4: 10 | E4: 15 | F4: 20 | G4: 25 | H4: 30
B5: 4 | C5: 4 | D5: 8 | E5: 12 | F5: 16 ○→ CREDIT & RISQUES ○→ RECOUVREMENT | G5: 20 | H5: 24
B6: 3 | C6: 3 | D6: 6 | E6: 9 ○→ MARKETING & PRODUITS | F6: 12 ○→ PRODUITS DIGITAUX & CHANGE ○→ FINANCES & REPORTING ○→ OPERATIONS & TRANSFERT ○→ JURIDIQUE & CONTENTIEUX ○→ AGENCES ○→ IT ○→ GOUV & CI ○→ RESSOURCES HUMAINES ○→ ACHAT LOGIST ○→ CONFORMITE | G6: 15 | H6: 18
B7: 2 | C7: 2 | D7: 4 | E7: 6 | F7: 8 | G7: 10 | H7: 12
B8: 1 | C8: 1 | D8: 2 | E8: 3 | F8: 4 | G8: 5 | H8: 6
B9: 0 | C9: 1 | D9: 2 | E9: 3 | F9: 4 | G9: 5 | H9: 6
H10: GRAVITE
C12: BAREME RISQUE | F12: =LEGENDE!C2 -> PROCESSUS | G12: =LEGENDE!D2 -> GRAVITE | H12: =LEGENDE!E2 -> PROBABILITE | I12: =LEGENDE!F2 -> RISQUE BRUT
D13: CRITIQUE | F13: =DMCC!B5 -> MARKETING PRODUITS | G13: =DMCC!H23 -> 4 | H13: =DMCC!I23 -> 2 | I13: =G13*H13 -> 8
D14: TRES ELEVE | F14: AGENCES | G14: =AGENCES!H40 -> 4 | H14: =AGENCES!I40 -> 2 | I14: =AGENCES!J40 -> 8
D15: ELEVE | F15: RESSOURCES HUMAINES | G15: ='RESSOURCES HUMAINES'!H37 -> 3 | H15: ='RESSOURCES HUMAINES'!I37 -> 2 | I15: ='RESSOURCES HUMAINES'!J37 -> 6
D16: MODERE | F16: OPERATIONS | G16: =OPERATIONS!H32 -> 4 | H16: =OPERATIONS!I32 -> 2 | I16: =OPERATIONS!J32 -> 8
D17: FAIBLE | F17: CREDIT | G17: =CREDIT!H38 -> 4 | H17: =OPERATIONS!I32 -> 2 | I17: =G17*H17 -> 8
D18: NON SIGNIFICATIF | F18: FINANCES § REPORTING | G18: ='FINANCES & REPORTING'!H31 -> 4 | H18: ='FINANCES & REPORTING'!I31 -> 3 | I18: =G18*H18 -> 12
F19: IT | G19: ='IT '!H31 -> 4 | H19: ='IT '!I31 -> 3 | I19: =G19*H19 -> 12
F20: =LEGENDE!C11 -> GOUVERNANCE & CI | G20: ='GOUV & CONTRÔLE INTERNE'!H25 -> 4 | H20: =LEGENDE!E11 -> 3 | I20: =G20*H20 -> 12
F21: RECOUVREMENT | H21: =LEGENDE!E12 -> #REF! | I21: =G21*H21 -> #REF!
F22: PRODUITS DIGITAUX | G22: ='PRODUITS DIGITAUX'!H26 -> 4 | H22: ='PRODUITS DIGITAUX'!I26 -> 3 | I22: =G22*H22 -> 12
F23: JURIDIQUE § CONTENTIEUX | G23: ='JURIDIQUE & CONTENTIEUX'!H20 -> 4 | H23: ='JURIDIQUE & CONTENTIEUX'!I20 -> 3 | I23: =G23*H23 -> 12
F24: ACHATS § LOGISTIQUE | G24: ='ACHATS & LOGISTIQUE'!H22 -> 4 | H24: ='ACHATS & LOGISTIQUE'!I22 -> 2 | I24: =G24*H24 -> 8
F25: CONFORMITE | G25: =CONFORMITE!H25 -> 4 | H25: =CONFORMITE!I25 -> 3 | I25: =G25*H25 -> 12
F26: INNOVATION ET PARTENARIAT | G26: =+ROUND(IFERROR(AVERAGE(G13:G25),0),0) -> 4 | H26: ='INNOVATION ET PARTENARIAT'!I28 -> 2 | I26: =G26*H26 -> 8
F27: GRAND COMPTE | G27: ='GRAND COMPTE'!H32 -> 4 | H27: ='GRAND COMPTE'!I32 -> 2 | I27: ='GRAND COMPTE'!J32 -> 8

Sheet GRAND COMPTE
A1: ANALYSE DES RISQUES OPERATIONNELS - DIRECTION EXPLOITATION
A2: N° | B2: PROCESSUS | C2: RATIO | D2: SOUS PROCESSUS | E2: EXCEPTIONS MAJEURES CONSTATEES | F2: RISQUES CORRELES | G2: FAMILLE DE RISQUE | H2: Gravité | I2: Probabilité | J2: Risque brut (Rb) | K2: Justification de l'évaluation en cas de risque jugé critique | L2: DISPOSITIF DE PREVENTION ET DE CONTRÔLE | P2: Gravité résiduelle | Q2: Probabilité résiduelle | R2: Risque résiduel (Rr)
H4: G | I4: P | J4: est égal à GxP | L4: Description du dispositif | M4: Dispositif existant ou Non | N4: Owner du Contrôle | O4: Efficacité du dispositif | P4: G | Q4: Pr | R4: est égal à GxP
B5: AGENCES | C5: 0.1 | D5: Gestion clientèle (ouverture de compte, Gestion opérationnelle des produits) | E5: '• Identification du client (comptes sans Photo & comptes sans signature dans le système NAFA) | F5: Risque opérationnel Risque de non-conformité | G5: Risque opérationnel | H5: 4 | I5: 3 | J5: =H5*I5 -> 12 | L5: Ne pas procéder à l'ouverture du compte dans le SI en cas d'absence de photo ou signature | M5: OUI | N5: RGC | O5: 2 | P5: =H5 -> 4 | Q5: =I5/O5 -> 1.5 | R5: =P5*Q5 -> 6
E6: • Défaut dans la conformité des piéces d'identité (Présence de clients ayant plusieurs pièces différentes) | F6: Risque de non-conformité Risque de fraude | G6: Risque de Fraude | H6: 5 | I6: 1 | J6: =H6*I6 -> 5 | L6: Vérifier l'authenticité des pièces d'identité et s'assurer qu'elles ne sont pas expirées | M6: OUI | N6: RGC | O6: 2 | P6: =H6 -> 5 | Q6: =I6/O6 -> 0.5 | R6: =P6*Q6 -> 2.5
E7: • Absence de prélévement des frais de tenue de compte pour défaut de provision (Manque de suivi sur la gestion de la clientèle), Perte de revenus | F7: Risque de pertes financières Risque opérationnel | G7: Risque opérationnel | H7: 4 | I7: 1 | J7: =H7*I7 -> 4 | L7: Veuiller au versement des frais apres ouverture compte . | M7: OUI | N7: RGC | O7: 2 | P7: =H7 -> 4 | Q7: =I7/O7 -> 0.5 | R7: =P7*Q7 -> 2
E8: Vérification des originaux des statuts et pv nomination du gérant ou du Directeur Général pour les SA ; SARL ; SUARL | F8: Risque de non-conformité Risque de fraude | G8: Risque de Fraude | H8: 3 | I8: 3 | J8: =H8*I8 -> 9 | L8: S'assurer que les documents originaux sont conformes et authentiques et apposer le cachet "copie conforme à l'original" sur la copie. | M8: OUI | N8: CC/RGC | O8: 2 | P8: =H8 -> 3 | Q8: =I8/O8 -> 1.5 | R8: =P8*Q8 -> 4.5
E9: Incomplétude des dossiers d'ouverture de compte | F9: Risque opérationnel Risque de non-conformité | G9: Risque opérationnel | H9: 4 | I9: 1 | J9: 8 | L9: S'assurer dès l'entrée en relation de la complétude des dossiers d'ouverture de compte | M9: OUI | N9: CC/RGC | O9: 3 | P9: 4 | Q9: =I9/O9 -> 0.33333333 | R9: =P9*Q9 -> 1.3333333
E10: Absence de suivi des clients décédés | F10: Risque opérationnel Risque de non-conformité | G10: Risque opérationnel | H10: 4 | I10: 4 | J10: 16 | L10: Mettre en place une liste exhaustive des clients décédés.S'assurer de la correcte gestion des comptes des clients décédés | M10: NON | N10: RGC | O10: 1 | P10: 4 | Q10: =I10/O10 -> 4 | R10: =P10*Q10 -> 16
E11: Fraude sur l'enrolement des produits digitaux et les cartes prépayées (Exemple : Création de profil, Modification des informations personnelles…) | F11: Risque opérationnel Risque de fraude | G11: Risque de Fraude | H11: 4 | I11: 3 | J11: =H11*I11 -> 12 | L11: S'assurer qu'il existe deux personnes dans le process opérationnel : Celle qui initie et celle qui valide toute création ou modification de données | N11: CC/RGC | O11: 2 | P11: =H11 -> 4 | Q11: =I11/O11 -> 1.5 | R11: =P11*Q11 -> 6
E12: '• Modification de type de compte dans le SI (Compte courant en compte épargne) | F12: Risque de conformité Risque de fraude | G12: Risque de Fraude | H12: 4 | I12: 1 | J12: =H12*I12 -> 4 | L12: Rendre impossible dans le SI, la modification du type de compte. | M12: OUI | N12: CC/RGC | O12: 2 | P12: =H12 -> 4 | Q12: =I12/O12 -> 0.5 | R12: =P12*Q12 -> 2
E13: Défaut dans la modification des packs (fiche non signée, frais non prélevés, code catégorie non modifié…) | F13: Risque opérationnel Perte financière | G13: Risque opérationnel | H13: 4 | I13: 2 | J13: =H13*I13 -> 8 | L13: Respecter vigoureusement la procédure de modification de pack | M13: OUI | N13: CC/RGC | O13: 2 | P13: =H13 -> 4 | Q13: =I13/O13 -> 1 | R13: =P13*Q13 -> 4
E14: Défaut dans l'établissement des procurations liées aux comptes mandataires | F14: Risque opérationnel Risque de fraude | G14: Risque de Fraude | H14: 4 | I14: 3 | J14: =H14*I14 -> 12 | L14: Vérifier l'exactitude des procurations reçues | M14: OUI | N14: RGC | O14: 2 | P14: =H14 -> 4 | Q14: =I14/O14 -> 1.5 | R14: =P14*Q14 -> 6
E15: • Ouverture ou fermeture incomplète des comptes dans le SI (comptes en instance d'ouverture, comptes à valider, demande clôture, à clôturer) | F15: Risque de conformité | G15: Risque opérationnel | H15: 4 | I15: 2 | J15: =H15*I15 -> 8 | L15: Ne pas valider à l'ouverture du compte dans le SI en cas de dossier incomplet | M15: OUI | N15: CC/RGC | O15: 2 | P15: =H15 -> 4 | Q15: =I15/O15 -> 1 | R15: =P15*Q15 -> 4
E16: • Mauvais archivage des dossiers d'ouverture de compte | F16: Risque de pertes de document | G16: Risque opérationnel | H16: 4 | I16: 4 | J16: =H16*I16 -> 16 | L16: Proceder a l'évacuation des dossiers aux archives et s'assurer d'un systéme d'archivage efficace pour tous les dossiers sans exception | M16: OUI | N16: CC | O16: 2 | P16: =H16 -> 4 | Q16: =I16/O16 -> 2 | R16: =P16*Q16 -> 8
E17: • Manque de suivi des fermetures de compte Client | F17: Risque opérationnel Risque de conformité | G17: Risque opérationnel | H17: 4 | I17: 4 | J17: =H17*I17 -> 16 | L17: Veiller à respecter rigoureusement la procédure | M17: OUI | N17: CC/RGC | O17: 2 | P17: =H17 -> 4 | Q17: =I17/O17 -> 2 | R17: =P17*Q17 -> 8
E18: Insuffisance dans les mesures de modification de signature et de numéro de téléphone | F18: Risque de fraude | G18: Risque de Fraude | H18: 4 | I18: 2 | J18: =H18*I18 -> 8 | L18: Veiller à une confirmation supplémentaire des modifications (présence du client obligatoire en agence) avant validation dans le SI | M18: OUI | N18: CC / RR / CA | O18: 2 | P18: =H18 -> 4 | Q18: =I18/O18 -> 1 | R18: =P18*Q18 -> 4
E19: • Non prise en charge des demandes de prêt en agence | F19: Mauvaise qualité de service Risque lié à la mission commerciale | G19: Risque stratégique | H19: 4 | I19: 1 | J19: =H19*I19 -> 4 | L19: Assurer un suivi ou monitoring via crédit flow de toutes les demandes de prêt | M19: NON | N19: CC/RGC | O19: 1 | P19: =H19 -> 4 | Q19: =I19/O19 -> 1 | R19: =P19*Q19 -> 4
