Workbook

Sheet Accueil
D1: Entité: | E1: COFINA Togo | I1: Page d'accueil | N1: =AVERAGE(B8:B27,D3,I3,COUNTA(Contracts!B3:R4)/34,COUNTA('✅ Projets 2026'!#REF!)/60) -> 0.94999342
D3: =QG!B2 -> 1 | I3: =Secu!B2 -> 1
B6: Services IT
B7: Taux de remplissage | C7: Application | D7: Existant | E7: Nom de la solution | F7: Editeur | G7: Importance | H7: Version | I7: Dernière version | J7: SLA existant | K7: SaaS ou sur site | L7: # users | M7: # licences | N7: Type de licences | O7: Niveau de personnalisation | P7: Sauvegardes | Q7: ETP Support | R7: ETP Changes | S7: Archi HD
B8: =SUM(CBS!$E$7:$E$63)/COUNT(CBS!$E$7:$E$63) -> 1 | D8: oui | E8: =CBS!$C$9 -> Oracle FLEXCUBE Universal Banking | F8: =CBS!$C$8 -> Oracle | G8: =CBS!$C$14 -> Primoridal | H8: =CBS!$C$10 -> Version 14.7 | I8: =CBS!$C$11 -> Version 14.8 | J8: =LEFT(CBS!$C$38,3) -> Oui | K8: =CBS!$C$45 -> On-site | L8: =CBS!$C$28 -> 1000 pour tout le groupe | M8: =CBS!$C$32 -> VOIR IT GROUPE | N8: =CBS!$C$33 -> Nominatives | O8: =CBS!$C$23 -> Moyen | P8: =CBS!$C$59 -> Oui | Q8: =CBS!$C$39 -> 1. Niveau 1 : o Nombre d'ETP : 4 o Répartition des Activités : Résolution des tickets de premier niveau, support de base aux utilisateurs, gestion des demandes simples et Analyse des incidents 2. Niveau 2 : o Nombre d'ETP : 5 o Entité : Holding o Répartition des Activités : Analyse des incidents plus complexes, gestion des escalades du niveau 1, résolution de problèmes techniques avancés. o Compétences : Expertise technique, capacité à résoudre des problèmes complexes. o Rôles : Technicien Support Niveau 2 3. Niveau 3 : o Nombre d'ETP : DEFINIR o Entité : PROVIDER o Répartition des Activités : Gestion des problèmes critiques, développement de solutions, coordination avec les équipes de développement. o Compétences : Expertise approfondie, compétences en développement et en gestion des incidents majeurs. o Rôles : Ingénieur Support Niveau 3 | R8: =CBS!$C$40 -> Holding : ETP dédiés : 5 Filiale : ETP dédiés : 1 | S8: =CBS!$C$52 -> Non
E9: NAFA
B10: =SUM(LOS!$E$7:$E$61)/COUNT(LOS!$E$7:$E$61) -> 1 | D10: oui | E10: =LOS!$C$9 -> CREDITFLOW | F10: =IF(LOS!$C$7="Développement interne","COFINA",LOS!$C$8) -> EDAN | G10: =LOS!$C$14 -> Moyen | H10: =LOS!$C$10 -> 1.0 | I10: =LOS!$C$11 -> 1.0 | J10: =LEFT(LOS!$C$36,3) -> Non | K10: =LOS!$C$43 -> Cloud | L10: =LOS!$C$26 -> environ 50 | M10: =LOS!$C$30 -> VOIR IT GROUPE | N10: =LOS!$C$31 -> VOIR IT GROUPE | O10: =LOS!$C$21 -> Moyen | P10: =LOS!$C$57 -> Non | Q10: =LOS!$C$37 -> 1. Niveau 1 : o Nombre d'ETP : 3 o Répartition des Activités : Résolution des tickets de premier niveau, support de base aux utilisateurs, gestion des demandes simples et Analyse des incidents 2. Niveau 2 : o Nombre d'ETP : A DEFINIR o Entité : Holding o Répartition des Activités : Analyse des incidents plus complexes, gestion des escalades du niveau 1, résolution de problèmes techniques avancés. o Compétences : Expertise technique, capacité à résoudre des problèmes complexes. o Rôles : Technicien Support Niveau 2 3. Niveau 3 : o Nombre d'ETP : DEFINIR par IT GROUPE o Entité : PROVIDER o Répartition des Activités : Gestion des problèmes critiques, développement de solutions, coordination avec les équipes de développement. o Compétences : Expertise approfondie, compétences en développement et en gestion des incidents majeurs. o Rôles : Ingénieur Support Niveau 3 | R10: =LOS!$C$38 -> Holding : ETP dédiés : 0 Filiale : ETP dédiés : 0 | S10: =LOS!$C$50 -> Non
B11: =SUM(AB!$E$7:$E$61)/COUNT(AB!$E$7:$E$61) -> 1 | D11: OUI | E11: =AB!$C$9 -> KIWI | F11: =IF(AB!$C$7="Développement interne","COFINA",AB!$C$8) -> SMARTS SOLUTIONS | G11: =AB!$C$14 -> Moyen | H11: =AB!$C$10 -> 1.7 | I11: =AB!$C$11 -> 1.7.5 | J11: =LEFT(AB!$C$36,3) -> Non | K11: =AB!$C$43 -> Cloud | L11: =AB!$C$26 -> VOIR IT GROUPE | M11: =AB!$C$30 -> VOIR IT GROUPE | N11: =AB!$C$31 -> Nominatives | O11: =AB!$C$21 -> Haut | P11: =AB!$C$57 -> Oui | Q11: =AB!$C$37 -> 1. Niveau 1 : o Nombre d'ETP : 3 o Répartition des Activités : Résolution des tickets de premier niveau, support de base aux utilisateurs, gestion des demandes simples et Analyse des incidents 2. Niveau 2 : o Nombre d'ETP : 5 o Entité : Holding o Répartition des Activités : Analyse des incidents plus complexes, gestion des escalades du niveau 1, résolution de problèmes techniques avancés. o Compétences : Expertise technique, capacité à résoudre des problèmes complexes. o Rôles : Technicien Support Niveau 2 3. Niveau 3 : o Nombre d'ETP : DEFINIR o Entité : PROVIDER o Répartition des Activités : Gestion des problèmes critiques, développement de solutions, coordination avec les équipes de développement. o Compétences : Expertise approfondie, compétences en développement et en gestion des incidents majeurs. o Rôles : Ingénieur Support Niveau 3 | R11: =AB!$C$38 -> Holding : ETP dédiés : 5 Filiale : ETP dédiés : 1 | S11: =AB!$C$50 -> Non
B12: =SUM(MB!$E$7:$E$60)/COUNT(MB!$E$7:$E$60) -> 1 | D12: oui | E12: =IF(MB!$C$7="Non prévu",MB!$C$7,MB!$C$9) -> COFINA MOBILE + | F12: =IF(MB!$C$7="Développement interne","COFINA",MB!$C$8) -> SMARTS SOLUTIONS | G12: =MB!$C$14 -> Primoridal | H12: =MB!$C$10 -> 1.7 | I12: =MB!$C$11 -> 1.7.5 | J12: =LEFT(MB!$C$35,3) -> Non | K12: =MB!$C$42 -> Cloud | L12: =MB!$C$25 -> 8600 | M12: =MB!$C$29 -> VOIR IT GROUPE | N12: =MB!$C$30 -> Nominatives | O12: =MB!$C$21 -> Très haut | P12: =MB!$C$56 -> Oui | Q12: =MB!$C$36 -> 1. Niveau 1 : o Nombre d'ETP : 4 o Répartition des Activités : Résolution des tickets de premier niveau, support de base aux utilisateurs, gestion des demandes simples et Analyse des incidents 2. Niveau 2 : o Nombre d'ETP : 5 o Entité : Holding o Répartition des Activités : Analyse des incidents plus complexes, gestion des escalades du niveau 1, résolution de problèmes techniques avancés. o Compétences : Expertise technique, capacité à résoudre des problèmes complexes. o Rôles : Technicien Support Niveau 2 3. Niveau 3 : o Nombre d'ETP : DEFINIR o Entité : PROVIDER o Répartition des Activités : Gestion des problèmes critiques, développement de solutions, coordination avec les équipes de développement. o Compétences : Expertise approfondie, compétences en développement et en gestion des incidents majeurs. o Rôles : Ingénieur Support Niveau 3 | R12: =MB!$C$37 -> Holding : ETP dédiés : 5 Filiale : ETP dédiés : 1 | S12: =MB!$C$49 -> Oui
B13: =SUM(IB!$E$7:$E$61)/COUNT(IB!$E$7:$E$61) -> 1 | D13: non | E13: =IF(IB!$C$7="Non prévu",IB!$C$7,IB!$C$9) -> Non prévu | F13: =IF(IB!$C$7="Développement interne","COFINA",IB!$C$8) -> 0 | G13: =IB!$C$14 -> Moyen | H13: =IB!$C$10 -> 0 | I13: =IB!$C$11 -> 0 | J13: =LEFT(IB!$C$36,3) | K13: =IB!$C$43 -> 0 | L13: =IB!$C$26 -> 0 | M13: =IB!$C$30 -> 0 | N13: =IB!$C$31 -> 0 | O13: =IB!$C$21 -> 0 | P13: =IB!$C$57 -> 0 | Q13: =IB!$C$37 -> 0 | R13: =IB!$C$38 -> 0 | S13: =IB!$C$50 -> 0
B14: =SUM(AML!$E$7:$E$62)/COUNT(AML!$E$7:$E$62) -> 0.98113208 | D14: OUI | E14: =IF(AML!$C$7="Non prévu",AML!$C$7,AML!$C$9) -> REIS | F14: =IF(AML!$C$7="Développement interne","COFINA",AML!$C$8) -> Vneuron | G14: =AML!$C$14 -> Critique | H14: =AML!$C$10 -> Vneuron © Reis™ RCS 4.1 | I14: =AML!$C$11 -> 4.1 | J14: =LEFT(AML!$C$36,3) -> Oui | K14: =AML!$C$43 -> Cloud | L14: =AML!$C$26 -> une vingtaine | M14: =AML!$C$30 -> une licence par filiale | N14: =AML!$C$31 -> Partagées | O14: =AML!$C$21 -> Très haut | P14: =AML!$C$57 -> Oui | Q14: =AML!$C$37 -> 1. Niveau 1 : o Nombre d'ETP : 4 o Répartition des Activités : Résolution des tickets de premier niveau, support de base aux utilisateurs, gestion des demandes simples et Analyse des incidents 2. Niveau 2 : o Nombre d'ETP : 5 o Entité : Holding o Répartition des Activités : Analyse des incidents plus complexes, gestion des escalades du niveau 1, résolution de problèmes techniques avancés. o Compétences : Expertise technique, capacité à résoudre des problèmes complexes. o Rôles : Technicien Support Niveau 2 3. Niveau 3 : o Nombre d'ETP : DEFINIR o Entité : PROVIDER o Répartition des Activités : Gestion des problèmes critiques, développement de solutions, coordination avec les équipes de développement. o Compétences : Expertise approfondie, compétences en développement et en gestion des incidents majeurs. o Rôles : Ingénieur Support Niveau 3 | R14: =AML!$C$38 -> Holding : ETP dédiés : 5 Filiale : ETP dédiés : 1 | S14: =AML!$C$50 -> Non
B15: =SUM(Collect!$E$7:$E$61)/COUNT(Collect!$E$7:$E$61) -> 1 | D15: non | E15: =IF(Collect!$C$7="Non prévu",Collect!$C$7,Collect!$C$9) -> Module : Collection | F15: =IF(Collect!$C$7="Développement interne","COFINA",Collect!$C$8) -> 0 | G15: =Collect!$C$14 -> Critique | H15: =Collect!$C$10 -> Version 14.7 | I15: =Collect!$C$11 -> Version 14.9 | J15: =LEFT(Collect!$C$36,3) -> VOI | K15: =Collect!$C$43 -> On-site | L15: =Collect!$C$26 -> 1000 pour tout le groupe | M15: =Collect!$C$30 -> VOIR IT GROUPE | N15: =Collect!$C$31 -> VOIR IT GROUPE | O15: =Collect!$C$21 -> Très haut | P15: =Collect!$C$57 -> Non | Q15: =Collect!$C$37 -> Niveau 1: Holding : ETP dédiés : 5 Niveau 2 : Filiale : ETP dédiés : 3 Niveau 3 : Nombre d'ETP : DEFINIR par IT GROUPE | R15: =Collect!$C$38 -> Holding : ETP dédiés : 5 Filiale : ETP dédiés : 1 | S15: =Collect!$C$50 -> Non
B16: =SUM(CRM!$E$7:$E$61)/COUNT(CRM!$E$7:$E$61) -> 1 | D16: non | E16: =IF(CRM!$C$7="Non prévu",CRM!$C$7,CRM!$C$9) -> Non prévu | F16: =IF(CRM!$C$7="Développement interne","COFINA",CRM!$C$8) -> 0 | G16: =CRM!$C$14 -> Moyen | H16: =CRM!$C$10 -> 0 | I16: =CRM!$C$11 -> 0 | J16: =LEFT(CRM!$C$36,3) | K16: =CRM!$C$43 -> 0 | L16: =CRM!$C$26 -> 0 | M16: =CRM!$C$30 -> 0 | N16: =CRM!$C$31 -> 0 | O16: =CRM!$C$21 -> 0 | P16: =CRM!$C$57 -> 0 | Q16: =CRM!$C$37 -> 0 | R16: =CRM!$C$38 -> 0 | S16: =CRM!$C$50 -> 0
B17: =IF(COUNT(CC!$E$7:$E$61)=0,1,SUM(CC!$E$7:$E$61)/COUNT(CC!$E$7:$E$61)) -> 1 | D17: non | E17: =IF(CC!$C$7="Non prévu",CC!$C$7,CC!$C$9) -> Non prévu | F17: =IF(CC!$C$7="Développement interne","COFINA",CC!$C$8) -> 0 | G17: =CC!$C$14 -> Moyen | H17: =CC!$C$10 -> 0 | I17: =CC!$C$11 -> 0 | J17: =LEFT(CC!$C$36,3) | K17: =CC!$C$43 -> 0 | L17: =CC!$C$26 -> 0 | M17: =CC!$C$30 -> 0 | N17: =CC!$C$31 -> 0 | O17: =CC!$C$21 -> 0 | P17: =CC!$C$57 -> 0 | Q17: =CC!$C$37 -> 0 | R17: =CC!$C$38 -> 0 | S17: =CC!$C$50 -> 0
B18: =SUM(DocM!$E$7:$E$61)/COUNT(DocM!$E$7:$E$61) -> 1 | D18: non | E18: =IF(DocM!$C$7="Non prévu",DocM!$C$7,DocM!$C$9) -> Non prévu | F18: =IF(DocM!$C$7="Développement interne","COFINA",DocM!$C$8) -> 0 | G18: =DocM!$C$14 -> Faible | H18: =DocM!$C$10 -> 0 | I18: =DocM!$C$11 -> 0 | J18: =LEFT(DocM!$C$36,3) | K18: =DocM!$C$43 -> 0 | L18: =DocM!$C$26 -> 0 | M18: =DocM!$C$30 -> 0 | N18: =DocM!$C$31 -> 0 | O18: =DocM!$C$21 -> 0 | P18: =DocM!$C$57 -> 0 | Q18: =DocM!$C$37 -> 0 | R18: =DocM!$C$38 -> 0 | S18: =DocM!$C$50 -> 0
B19: =SUM(BI!$E$7:$E$59)/COUNT(BI!$E$7:$E$59) -> 1 | D19: non | E19: =IF(BI!$C$7="Non prévu",BI!$C$7,BI!$C$9) -> Non prévu | F19: =IF(BI!$C$7="Développement interne","COFINA",BI!$C$8) -> 0 | G19: =BI!$C$14 -> Moyen | H19: =BI!$C$51 -> 0 | I19: =BI!$C$11 -> 0 | J19: =LEFT(BI!$C$34,3) | K19: =BI!$C$41 -> 0 | L19: =BI!$C$24 -> 0 | M19: =BI!$C$28 -> 0 | N19: =BI!$C$29 -> 0 | O19: =BI!$C$19 -> 0 | P19: =BI!$C$55 -> 0 | Q19: =BI!$C$35 -> 0 | R19: =BI!$C$36 -> 0 | S19: =BI!$C$47 -> 0
B20: =SUM(SOA!$E$7:$E$52)/COUNT(SOA!$E$7:$E$52) -> 1 | D20: non | E20: =IF(BI!$C$7="Non prévu",BI!$C$7,BI!$C$9) -> Non prévu | F20: =IF(BI!$C$7="Développement interne","COFINA",BI!$C$8) -> 0 | G20: =BI!$C$14 -> Moyen | H20: =BI!$C$51 -> 0 | I20: =BI!$C$11 -> 0 | J20: =LEFT(BI!$C$34,3) | K20: =BI!$C$41 -> 0 | L20: =BI!$C$24 -> 0 | M20: =BI!$C$28 -> 0 | N20: =BI!$C$29 -> 0 | O20: =BI!$C$19 -> 0 | P20: =BI!$C$55 -> 0 | Q20: =BI!$C$35 -> 0 | R20: =BI!$C$36 -> 0 | S20: =BI!$C$47 -> 0
B21: =SUM('ERP1'!$E$7:$E$61)/COUNT('ERP1'!$E$7:$E$61) -> 1 | D21: oui | E21: =IF('ERP1'!$C$7="Non prévu",'ERP1'!$C$7,'ERP1'!$C$9) -> Non | F21: =IF('ERP1'!$C$7="Développement interne","COFINA",'ERP1'!$C$8) -> Oui | G21: ='ERP1'!$C$14 -> 2024 | H21: ='ERP1'!$C$16 -> Très haut | I21: ='ERP1'!$C$11 -> Non | J21: =LEFT('ERP1'!$C$36,3) | K21: ='ERP1'!$C$43 -> 0 | L21: ='ERP1'!$C$26 -> Non | M21: ='ERP1'!$C$30 -> journaliere | N21: ='ERP1'!$C$31 -> Oui | O21: ='ERP1'!$C$21 -> Non | P21: ='ERP1'!$C$57 -> 0 | Q21: ='ERP1'!$C$37 -> 0 | R21: ='ERP1'!$C$38 -> 0 | S21: ='ERP1'!$C$50 -> 0
B22: =SUM('ERP2'!$E$7:$E$59)/COUNT('ERP2'!$E$7:$E$59) -> 1 | D22: oui | E22: =IF('ERP2'!$C$7="Non prévu",'ERP2'!$C$7,'ERP2'!$C$9) -> digitalisée d'évaluation des performances de COFINA | F22: =IF('ERP2'!$C$7="Développement interne","COFINA",'ERP2'!$C$8) -> COFINA | G22: ='ERP2'!$C$14 -> Moyen | H22: ='ERP2'!$C$10 -> Voir IT GROUPE | I22: ='ERP2'!$C$11 -> Voir IT GROUPE | J22: =LEFT('ERP2'!$C$34,3) -> NON | K22: ='ERP2'!$C$41 -> On-site | L22: ='ERP2'!$C$24 -> Voir IT GROUPE | M22: ='ERP2'!$C$28 -> Voir IT GROUPE | N22: ='ERP2'!$C$29 -> Voir IT GROUPE | O22: ='ERP2'!$C$19 -> Haut | P22: ='ERP2'!$C$55 -> Non | Q22: ='ERP2'!$C$35 -> 1. Niveau 1 : o Nombre d'ETP : 4 o Répartition des Activités : Résolution des tickets de premier niveau, support de base aux utilisateurs, gestion des demandes simples et Analyse des incidents 2. Niveau 2 : o Nombre d'ETP : 5 o Entité : Holding o Répartition des Activités : Analyse des incidents plus complexes, gestion des escalades du niveau 1, résolution de problèmes techniques avancés. o Compétences : Expertise technique, capacité à résoudre des problèmes complexes. o Rôles : Technicien Support Niveau 2 | R22: ='ERP2'!$C$36 -> Holding : ETP dédiés : 3 Filiale : ETP dédiés : 1 | S22: ='ERP2'!$C$48 -> Oui
B23: =SUM(Achats!$E$7:$E$59)/COUNT(Achats!$E$7:$E$59) -> 1 | D23: oui | E23: =IF(Achats!$C$7="Non prévu",Achats!$C$7,Achats!$C$9) -> COFIFED | F23: =IF(Achats!$C$7="Développement interne","COFINA",Achats!$C$8) -> COFINA | G23: =Achats!$C$14 -> Moyen | H23: =Achats!$C$10 -> 1.1 | I23: =Achats!$C$11 -> 1.2 | J23: =LEFT(Achats!$C$34,3) -> NON | K23: =Achats!$C$41 -> On-site | L23: =Achats!$C$24 -> Illimité | M23: =Achats!$C$28 -> NON | N23: =Achats!$C$29 -> NON | O23: =Achats!$C$19 -> Moyen | P23: =Achats!$C$55 -> Oui | Q23: =Achats!$C$35 -> Niveau 1: Filiale : ETP dédiés : 3 Niveau 2 : Filiale : ETP dédiés : 3 Niveau 3 : Filiale d'ETP : 3 | R23: =Achats!$C$36 -> Filiale : ETP dédiés : 3 | S23: =Achats!$C$48 -> Non
B24: =SUM(GC!$E$7:$E$59)/COUNT(GC!$E$7:$E$59) -> 1 | D24: oui | E24: =IF(GC!$C$7="Non prévu",GC!$C$7,GC!$C$9) -> application de recrutement RH & gestion des contrats | F24: =IF(GC!$C$7="Développement interne","COFINA",GC!$C$8) -> COFINA | G24: =GC!$C$14 -> Moyen | H24: =GC!$C$10 -> 1.0 | I24: =GC!$C$11 -> 1.0 | J24: =LEFT(GC!$C$34,3) -> Non | K24: =GC!$C$41 -> On-site | L24: =GC!$C$24 -> Illimité | M24: =GC!$C$28 -> NON | N24: =GC!$C$29 -> NON | O24: =GC!$C$19 -> Très haut | P24: =GC!$C$55 -> Non | Q24: =GC!$C$35 -> Niveau 1: Holding : ETP dédiés : 3 Niveau 2 : Filiale : ETP dédiés : 3 GROUPE | R24: =GC!$C$36 -> Holding : ETP dédiés : 3 Filiale : ETP dédiés : 1 | S24: =GC!$C$48 -> Non
B25: =SUM(Mail!$E$7:$E$42)/COUNT(Mail!$E$7:$E$42) -> 1 | D25: oui | E25: =IF(Mail!$C$7="Non prévu",Mail!$C$7,Mail!$C$9) -> OFFICE 365 | F25: =IF(Mail!$C$7="Développement interne","COFINA",Mail!$C$8) -> Microsoft | G25: =Mail!$C$17 -> Primoridal | H25: =Mail!$C$10 -> NA | I25: =Mail!$C$11 -> NA | J25: =LEFT(Mail!$C$28,3) -> Non | K25: =Mail!$C$12 -> Cloud | M25: =Mail!$C$25 -> NA | P25: =Mail!$C$38 -> Non | Q25: =Mail!$C$29 -> N1 & 2 | S25: =Mail!$C$33 -> Oui
B26: =Others!E177 -> 0.96969697 | D26: =Others!F177 -> 1
B27: =IT!E93 -> 1 | D27: oui

Sheet QG
A1: Retour à la page d'accueil
A2: Questions génériques IT | B2: =C136 -> 1 | D2: Complément
A3: Global | B3: Réponse, détail et/ou fichier fourni | C3: Eval | D3: Document à fournir | F3: NB Pour les questions concernant l’audit de l’existant IT, veuillez prendre en compte les réponses écrites en orange
A4: est-ce que vous avez mis en place la stratégie IT ? Découle-t-elle de la stratégie de l'entreprise ? Si oui, pouvez-vous les partager? | B4: Stratégie d'Entreprise : Notre vision : Etre le modèle panafricain de la finance inclusive. Notre mission : Créer de la valeur ajoutée pour nos partenaires et participer durablement au développement du continent africain. Stratégie IT Vision IT : Votre rêve devient notre mission Stratégie IT La vision de COFINA TOGO s’inscrit dans la stratégie IT du groupe COFINA. En effet le groupe a pour ambition à l’horizon 2025 d’avoir : • Un SI centralisé et sécurité • Une automatisation des 80% de des taches de la filiale • Une démocratisation de l’information à travers un BI (Business Intelligence) self-service • Un IT « As à profit Center » : l’IT serait un centre de profit et non un centre de cout | C4: =IF(TRIM(B4)="",0,1) -> 1 | D4: voir le schéma directeur
A5: Pouvez-vous présenter l'organisation IT ? Pouvez-vous fournir un organigramme détaillé (départements, sections, groupes, équipes, etc.) des divisions informatiques comprenant des informations sur les effectifs et les responsabilités (en spécifiant: interne, prestataire, temporaire, stagiaire, vacant) | B5: Organisation IT 1. Responsable du département Informatique Responsable informatique Filiale  Effectif : 1 (interne)  Responsabilités : Supervision générale de toutes les opérations informatiques, définition de la stratégie IT, gestion des budgets, collaboration avec la direction générale.  Définition et mise en œuvre des politiques de sécurité, gestion des risques, surveillance des systèmes pour détecter les intrusions.  Analyse des vulnérabilités, réponse aux incidents de sécurité, audits de sécurité réguliers.  Garantir la Confidentialité, l’Intégrité, la Disponibilité et la Sécurité du système  d’information de l’institution et assurer les évolutions technologiques afin de satisfaire la clientèle interne et externe.  Faciliter l’utilisation du matériel informatique, des outils bureautiques et des logiciels mis à la disposition des utilisateurs  Veiller à leur bon fonctionnement et à leur meilleure exploitation, dans les délais requis afin de réduire au maximum les interruptions de services et contribuer ainsi à la  réalisation de la production de l’Entreprise.  Assurer le bon fonctionnement de la base de données et la disponibilité des informations 2. Administrateur des Systèmes et Réseaux Effectif : vacant  Responsabilités : Supervision de l'infrastructure réseau et des systèmes, gestion des projets de mise à jour et de maintenance.  Configuration et maintenance des serveurs, des réseaux, résolution des problèmes techniques, sécurité des systèmes.  Support technique de niveau 1, assistance aux administrateurs, maintenance de base des équipements. 3. Assistant Systèmes et Réseaux :  Effectif : 1 (interne) - Dépanner et configurer le matériel informatique dans les délais requis, afin que les utilisateurs disposent de leur équipement en bon état tout en respectant les SLA définis ; - Aider et former les utilisateurs à une bonne exploitation du matériel informatique et des outils bureautiques afin d’augmenter la production de l’entreprise ; - Organiser et fournir des statistiques sur la gestion du matériel informatique en panne afin de prévenir les éventuelles interruptions de service des utilisateurs. 4. Administrateur des Bases de Données et Développement Applicatif Effectif : vacant  Responsabilités : Gestion des bases de données, supervision des projets de développement, coordination avec les autres départements.  Installation, configuration et maintenance des bases de données, optimisation des performances, sauvegarde et récupération.  Développement et maintenance des applications internes, développement de nouvelles fonctionnalités, correction de bugs.  Support aux administrateurs et aux développeurs, tâches de développement de base, gestion des données.  Supervision de l'équipe de support, gestion des incidents et des demandes des utilisateurs.  Assistance technique aux utilisateurs, résolution des incidents, formation des utilisateurs. 5. Assistant base de données :  Effectif : 2 (interne) Responsabilités : Assurer l’administration des bases de données Oracle afin de garantir une disponibilité maximale des applications aux utilisateurs. - Encadrer et superviser les activités du service Exploitation afin de garantir aux utilisateurs le taux de disponibilité prévu. - Superviser les activités de paramétrage afin garantir un fonctionnement optimal de l’applicatif bancaire conforme aux exigences du métier | C5: =IF(TRIM(B5)="",0,1) -> 1 | D5: Oui
A6: Pouvez-vous me partager les fiches de postes (pour chaque poste figurant sur l'organigramme IT) ? | B6: oui | C6: =IF(TRIM(B6)="",0,1) -> 1 | D6: Oui
A7: Est-ce qu'il y a des fonctions ou activités qui sont entièrement ou partiellement externalisées à des sous-traitants ou des partenaires (par exemple, gestion des installations pour les centres de données, service d'assistance informatique, opérations de certaines applications ou infrastructures, ADM dans certains domaines d'application), ...? | B7: oui | C7: =IF(TRIM(B7)="",0,1) -> 1 | D7: installation des nouveaux systèmes de sécurité électronique (contrôle d'accès, système incendie, anti-intrusion) et de vidéo surveillance
A8: Quel était le Turnover en 2023 ? | B8: nous n'avons enregistré aucun départ de collaborateurs durant cette période | C8: =IF(TRIM(B8)="",0,1) -> 1 | D8: Oui
A9: Avez-vous mis en place un schéma directeur IT? Si oui, pouvez-vous le partager? | B9: oui | C9: =IF(TRIM(B9)="",0,1) -> 1 | D9: Oui
A10: Quelles sont les principales améliorations informatiques attendues de la part de la communauté des utilisateurs métiers ? Exemples: · TTM plus court · Performances des services alignées sur les performances de l'entreprise · Amélioration mesurable du service basée sur des KPI convenus · Compétences améliorées en informatique pour mieux comprendre les exigences de l'entreprise et les traduire en solutions informatiques · Gestion de la demande simplifiée et efficace | B10: Automatisation des processus / Analytique avancée et reporting / Intégration et interopérabilité/ Simplicité d'utilisation:voici l’approche détaillée : Automatisation des Processus : • Plan : Développer des applications pour automatiser les processus clés tels que la gestion des stocks, la gestion des ventes, la gestion des conventions de crédit, et les processus de recrutement, etc. • Timing : Courant de l'année 2024. • Budget : Développement local. Analytique Avancée et Reporting : • Plan : Mise en place d'une plateforme analytique centralisée utilisant des outils comme Power BI ou Tableau pour visualiser et analyser les données opérationnelles et financières. • Timing : 2025. • Budget : À définir. Intégration et Interopérabilité : • Plan : Intégration entre les systèmes Oracle Flexcube et les plateformes de nos différents partenaires tels que Togocom (projet bank to wallet), GTP (pour les cartes VISA), l’application mobile, etc. • Timing : Déploiements itératifs sur les 2 prochains mois | C10: =IF(TRIM(B10)="",0,1) -> 1 | D10: Pouvez-vous détailler comment avez-vous prévu de le faire et quand? Quel est le budget validé pour ces initiatives?
A11: Quelles sont les principales améliorations IT identifiées par la communauté IT? Exemples: · Harmonisation de l'architecture · Gestion simplifiée des fournisseurs · Harmonisation du contrat de support · Rareté des ressources qualifiées · Gestion des incidents · Demandes de service standardisées · Mesures visant à améliorer la disponibilité des services, telles que - Améliorer la gestion des pannes et des performances - Introduire des outils de gestion des services IT - Standardiser les processus - Mettre à jour la documentation - Restructurer lorganisation IT - Consolider les centres de données et les centres d'opérations | B11: Automatisation et IA: L'automatisation des processus IT et l'intégration de l'intelligence artificielle pour améliorer l'efficacité opérationnelle. Sécurité renforcée: Des technologies avancées pour protéger les données et les infrastructures contre les cybermenaces croissantes. Cloud computing: L'adoption accrue des services cloud pour la flexibilité, l'évolutivité et la réduction des coûts. IoT (Internet des Objets): L'utilisation croissante des appareils connectés pour collecter des données et optimiser les processus. Blockchain: L'exploration des applications de la technologie blockchain pour la sécurisation des transactions et des contrats. Analyse des données avancée: Utilisation de l'analyse prédictive et du big data pour prendre des décisions plus éclairées. Expérience utilisateur améliorée | C11: =IF(TRIM(B11)="",0,1) -> 1 | D11: Pouvez-vous détailler comment avez-vous prévu de le faire et quand? Quel est le budget validé pour ces initiatives?
A12: Applications | B12: Réponse, détail et/ou fichier fourni | D12: Document à fournir
A13: Pouvez-vous montrer l'architecture informatique actuelle prenant en charge l'ensemble de l'activité (interne et externe) ？ | B13: oui | C13: =IF(TRIM(B13)="",0,1) -> 1 | D13: Non
A14: Est-ce que les applications sont centralisées pour toutes les filiales ou chaque filiale à son propre SI ou s'agit-il d'une combinaison des 2? | B14: NON | C14: =IF(TRIM(B14)="",0,1) -> 1 | D14: Non
A15: Est-ce que vous disposez d'une cartographie des applications existantes? Par filiale? | B15: oui | C15: =IF(TRIM(B15)="",0,1) -> 1 | D15: Non
A16: Existe-t-il une stratégie d’architecture d’application commune interfiliale mise en œuvre/prévu ? si oui: - quels composants d'application font partie des plans - à quel niveau l'harmonisation des composants est-elle atteinte o fournisseur et logiciel uniquement o version du système o configuration et customisation du système o système centralisé avec configuration multi-tenant | B16: NON | C16: =IF(TRIM(B16)="",0,1) -> 1 | D16: Non
A17: Si oui, est-ce qu'elle spécifie bien ce qui est fournis par des prestataires externes de ce qui est développé en interne? | B17: NA | C17: =IF(TRIM(B17)="",0,1) -> 1 | D17: Non
A18: Pour les les solutions qui ont été développées en interne, quelle language a été utilisé ? et pourquoi? | B18: Les langages utilisés pour le développement de nos applications internes sont PHP avec le framework Laravel combiné avec du Vue JS.Nous avons préféré utiliser PHP avec le framework Laravel parceque ce dernier est un framework backend qui se distingue par sa documentation exhaustive, sa communauté active, ses migrations de base de données robustes, son ORM Eloquent, ses fonctionnalités de sécurité intégrées, ses outils de tests automatisés, sa facilité d'intégration de services tiers, son outil en ligne de commande Artisan, sa gestion efficace des dépendances, son système de routage flexible et son moteur de template Blade, en faisant un choix idéal pour le développement d'applications web de toute envergure. | C18: =IF(TRIM(B18)="",0,1) -> 1 | D18: Pourquoi?
A19: Avez-vous un cadre de développement ? | B19: Choisir Laravel pour le backend et Vue.js pour le frontend permet de bénéficier d'un développement web moderne et efficace, avec une gestion simplifiée de l'authentification et des ORM, à la réactivité des composants réutilisables. En ce qui concerne l'utilisation de Vue.JS en frontend, c'est est un framework JavaScript qui se distingue par sa flexibilité, son intégration facile avec d'autres projets ou bibliothèques, sa réactivité grâce à son système de liaison de données bidirectionnelle, sa capacité à créer des composants réutilisables, son écosystème riche avec des outils comme Vue CLI et Vuex, et sa forte communauté de développeurs, en faisant un choix idéal pour le développement d'interfaces utilisateur dynamiques et modernes. | C19: =IF(TRIM(B19)="",0,1) -> 1 | D19: Pourquoi?
A20: Quelle est la taille de l’équipe de développement ? | B20: L'équipe de developpement est composée de 3 personnes (les deux assistants et moi-même ) | C20: =IF(TRIM(B20)="",0,1) -> 1 | D20: Ce n'est pas ce qui apparait sur l'organigramme
A21: Est-ce que vous avez une documentation? Si oui, est-elle à jour? | B21: OUI | C21: =IF(TRIM(B21)="",0,1) -> 1 | D21: Pouvez-vous partager un exemple ou 2?
A22: Qui assure le support des outils internes ? | B22: Le support des outils internes est assuré par IT LOCAL | C22: =IF(TRIM(B22)="",0,1) -> 1 | D22: Oui
A23: Comment gérez-vous le versioning ? Avez-vous une feuille de route ? | B23: Le versionning est géré par Git et Github | C23: =IF(TRIM(B23)="",0,1) -> 1 | D23: Oui
A24: Contractualisation | B24: Réponse, détail et/ou fichier fourni | D24: Document à fournir
A25: Est-ce que vous avez des contrats de support avec tous les prestataires IT? | B25: NON Pour certains systèmes, nous avons préféré gérer le support et la maintenance préventive et curative en local afin d'économiser au niveau de la filiale, car nous venions de débuter l'activité. Cependant, nous prévoyons de signer un contrat de maintenance avec des prestataires d'ici décembre 2024 | C25: =IF(TRIM(B25)="",0,1) -> 1 | D25: Pourquoi?
A26: Est-ce que les contrats existants incluent des SLA? Pourvez-vous me les partager? | B26: NON | C26: =IF(TRIM(B26)="",0,1) -> 1 | D26: Pouvez-vous les partager ?
A27: Infrastructure | B27: Réponse, détail et/ou fichier fourni | D27: Document à fournir
A28: Pouvez-vous partager l'architecture du réseau ? | B28: oui | C28: =IF(TRIM(B28)="",0,1) -> 1 | D28: Non
A29: Est-ce que vous utilisez exclusivement des infrastructures sur le Cloud ou sur site ou un mix des 2 ? | B29: MIX DES DEUX | D29: Non
A30: Si vous utilisez des infrastructures sur le Cloud, s'agit-il de Cloud public, lequel ? ou privé ? | B30: Voir IT GROUPE | D30: Non
A31: Si vous utilisez des infrastructures sur site, l'IT est propriétaire de son (ou ses) centre de données ou utilisez-vous un datacenter partagé ? Précisez lesquels et les infra installés | B31: Pour les datacenters à Abidjan ou Dakar, le local est partagées mais en filiale Nous utilisons des infrastructures sur site pour notre IT. Nous ne possédons pas de centre de données dédié, mais nous gérons nos propres serveurs dans notre environnement local. Cela inclut un serveur physique Cisco UCS C220 M5SX qui héberge plusieurs machines virtuelles Windows Server et Linux, ainsi que d'autres infrastructures réseau comme notre firewall Fortinet et notre réseau VLAN segmenté. | D31: Non
A32: Envisagez-vous de grands changements dans le Datacenter ? Si oui, quoi et quand ? | B32: Voir IT GROUPE | C32: =IF(TRIM(B32)="",0,1) -> 1 | D32: Non
A33: Quels sont les liens existants et leurs bandes passantes ? | B33: notre siège dispose d'une liaison principale de 50 Mo avec une liaison de backup de 10 Mo via un autre FAI. Pour les agences, nous avons une liaison principale de 10 Mo en fibre optique, avec des modems 4G+ d'un autre opérateur assurant le backup en cas d'interruption de la liaison principale | C33: =IF(TRIM(B33)="",0,1) -> 1 | D33: Peux-tu décrie les lien du siège et des agences, principaux et secondaires?
A34: Existe-t-il des stratégies d’architecture matérielle commune interfiliale mis en œuvre/prévu ? si oui - quels composants font partie des plans - jusqu'où niveau l'harmonisation des composants est-elle atteinte o fournisseur et type de matériel uniquement o Version du système d'exploitation/base de données o configuration du système telle que la configuration de la virtualisation o système centralisé hébergeant plusieurs applications utilisées par les pays | B34: oui type de matériel uniquement o Version du système d'exploitation/base de données o configuration du système telle que la configuration de la virtualisation o système centralisé hébergeant plusieurs applications utilisées par les pays | C34: =IF(TRIM(B34)="",0,1) -> 1 | D34: malheureusement ça n'a pas été formalisé.
A35: Veuillez fournir une liste de serveurs existants, de systèmes d'exploitation et de fournisseurs ? | B35: ESXI CISCO/HYPERVISEUR VMWARE 7.0 Update 1/ SYROAD/EN LOCALE | C35: =IF(TRIM(B35)="",0,1) -> 1 | D35: Non
A36: Veuillez fournir des informations sur les éléments de stockage et leur configuration opérationnelle, par ex. NAS, SAN? | B36: oui Nous effectuons des sauvegardes journalières sur un ordinateur avec un disque dur de 24 To. Le premier jour de chaque mois, nous copions les données du mois précédent pour les externaliser dans un autre site au sein de nos agences. Cela nous permet de récupérer les données en cas de défaillance du serveur de sauvegarde. | C36: =IF(TRIM(B36)="",0,1) -> 1 | D36: Non
A37: Veuillez fournir une liste des équipements réseaux dans l'environnement LAN/WAN, par ex. routeurs, pare-feu | B37: ROUTEUR CISCO/ Cisco IOS/ SYROAD/EN LOCALE FIREWALL FORTINET/FortiOS/ SYROAD/EN LOCALE APFORTINET/FortiOS/ SYROAD/EN LOCALE SWITCH CISCO/Cisco IOS / SYROAD/ EN LOCALE | C37: =IF(TRIM(B37)="",0,1) -> 1 | D37: Non
A38: Veuillez mentionner l'emplacement physique des équipements IT ci-dessus dans les centres de données? | B38: La majorité de nos équipements, réseaux et systèmes se trouvent dans un local IT au siège. Ce local respecte tous les normes ISO 27001 à l'exception de la protection contre les incendies, un point que nous prévoyons de corriger d'ici le 31 janvier 2025. | C38: =IF(TRIM(B38)="",0,1) -> 1 | D38: Non
A39: Est-ce que tous ces équipements sont supervisés à distance? | B39: NON | C39: =IF(TRIM(B39)="",0,1) -> 1 | D39: Non
A40: Est-ce que vous faites des maintenances préventive? Sur quel système et à quelle fréquence? | B40: oui tous les trois mois | C40: =IF(TRIM(B40)="",0,1) -> 1 | D40: Non
A41: Si oui, pouvons-nous voir des exemples de communicaton en amont et de rapports après une maintenance régulière, avec les principales conclusions et corrections ? | B41: oui | C41: =IF(TRIM(B41)="",0,1) -> 1 | D41: Peux-tu partager une communication?
A42: Gouvernance et services IT | B42: Réponse, détail et/ou fichier fourni | D42: Document à fournir
A43: Comment s’articule la Gouvernance entre le Métier et l’IT ? Quels forums sont en place avec la fréquence des réunions et les participants | B43: Nous organisons notre réunion hebdomadaire des responsables IT des filiales, avec la présence de l'équipe IT groupe et du DSI. notre dernière réunion a eu lieu le 29/12/2022. Depuis, nous avons mis ce projet en standby en raison de la migration de Flexcube au niveau des filiales. Malheureusement, ces réunions n'ont pas été sanctionnées par un PV. (EMC) | C43: =IF(TRIM(B43)="",0,1) -> 1 | D43: Pouvez-vous partager 2 ou 3 exemples d'agendas et comptes rendus?
A44: Existe-t-il un processus établi entre les départements métiers et l'informatique concernant les KPI, par ex. faire correspondre les KPI pertinents pour l’entreprise aux indicateurs technologiques ? | B44: non Manque de processus formel pour coordonner la définition, la mise en œuvre et la mesure des KPI entre les départements métiers et l'informatique. | C44: =IF(TRIM(B44)="",0,1) -> 1 | D44: Pourquoi?
A45: Quel département est le plus demandeur de services informatiques ? | B45: exploitration | C45: =IF(TRIM(B45)="",0,1) -> 1 | D45: Non
A46: Dans quelle mesure les normes industrielles comme ITIL sont-elles mises en œuvre ? ou envisagez-vous de le faire ? Si oui, quand et quels processus ? | B46: envisagez-vous de le faire : enours Phases de mise en œuvre : • Formation : sensibilisé l’équipe IT local aux meilleures pratiques ITIL Processus à prioriser : Démarrez par les processus ITIL les plus critiques : Gestion des incidents : Pour gérer et résoudre les incidents rapidement et efficacement. • Gestion des problèmes : Pour identifier et résoudre les causes profondes des incidents. • Gestion des changements : Pour gérer les changements de manière structurée afin de minimiser les risques. • Gestion des configurations : Pour maintenir des enregistrements précis de tous les actifs IT. | C46: =IF(TRIM(B46)="",0,1) -> 1 | D46: Détails
A47: Si oui, veuillez détailler et fournir ceux qui existent déjà? | B47: gestion des incidents, gestion des problèmes, gestion des changements | C47: =IF(TRIM(B47)="",0,1) -> 1 | D47: Oui
A48: Si c'est le cas, est-ce qu'il y a une stratégie de standardisation pour toutes les filiales? | B48: non Oui, mais Cofihelp gère partiellement le problème. Il nous permet juste de gérer les tickets entre les IT filiales et l'IT groupe. Cependant, les requêtes des métiers ne sont pas tracées aujourd'hui. | C48: =IF(TRIM(B48)="",0,1) -> 1 | D48: Et Cofihelp n'est pas un outil de ticketing?
A49: Avez-vous un outil pour les gérer ? | B49: NON ce projet n'était pas priorisé pour cette année | C49: =IF(TRIM(B49)="",0,1) -> 1 | D49: Pourquoi?
A50: Si oui, quels sont le numéro unique et l'adresse e-mail ? | B50: helpdesk.ittogo@cofinacorp.com | C50: =IF(TRIM(B50)="",0,1) -> 1 | D50: Non
A51: Est-ce qu'il existe un Service Desk ou helpdesk, comme point d'entrée unique à la DSI pour la gestion des services IT et tout ce qui est incidents/requêtes/problèmes? | B51: oui | C51: =IF(TRIM(B51)="",0,1) -> 1 | D51: Non
A52: Pouvez-vous fournir la liste des applications informatiques utilisées pour les activités d'exploitation et de maintenance : Y compris Service Desk, gestion des incidents/problèmes, gestion des performances, gestion des stocks et des actifs, gestion des ordres de travail, gestion des changements, gestion de la configuration, gestion des capacités… etc. | B52: cofihelp | C52: =IF(TRIM(B52)="",0,1) -> 1 | D52: Détails
A53: Avez-vous établi un catalogue de services IT où les utilisateurs finaux peuvent se référer ? | B53: NON | C53: =IF(TRIM(B53)="",0,1) -> 1 | D53: Non
A54: Si oui, alors - Pouvez-vous fournir ce catalogue de services avec une description des éléments de service ? - Pouvez-vous fournir des enregistrements sur les demandes de services liées à ce catalogue faites et ce par types d'utilisateurs finaux/départements ? | B54: NON | C54: =IF(TRIM(B54)="",0,1) -> 1 | D54: Non
... A60: Envisagez-vous de vous lancer dans une certification ISO 20000 ? | B60: NON | C60: =IF(TRIM(B60)="",0,1) -> 1 | D60: Non
A61: Questions au Service Desk / support niveau 1 | B61: Réponse, détail et/ou fichier fourni | D61: Document à fournir
A62: Est-ce que lorsque un utilisateur rencontre un incident, il passe systématiquement par le Service Desk / helpdesk? | B62: oui | C62: =IF(TRIM(B62)="",0,1) -> 1 | D62: Pourquoi?
A63: Quels sont les canaux d'ouverture d'incidents? | B63: MAIL Oui, Cofihelp permet aux IT des filiales de remonter certaines requêtes vers le groupe IT. En ce qui concerne les utilisateurs, les incidents sont remontés par mail à leur IT de filiale pour traitement. Si pendant le traitement il y a des points nécessitant le support du groupe, l'incident est alors remonté via Cofihelp par IT filiale | C63: =IF(TRIM(B63)="",0,1) -> 1 | D63: Et Cofihelp n'est pas un outil de ticketing?
A64: Est-ce que vous traitez les incidents à votre niveau? | B64: oui | C64: =IF(TRIM(B64)="",0,1) -> 1 | D64: Non
A65: Si oui, lequels? Et est-ce que que cela est formalisé dans un processus? Lequel? | B65: Dépanner / configurer le matériel informatique/ système d’information: 1. Dépanner le matériel informatique : o Diagnostiquer et résoudre les problèmes matériels sur les ordinateurs, les serveurs, et autres périphériques. o Remplacer ou réparer les composants défectueux. o Assurer la maintenance préventive pour éviter les pannes. 2. Configurer le matériel informatique : o Installer et configurer de nouveaux ordinateurs, serveurs, imprimantes, switchs , des équipements de sécurité électronique etc. o Mettre à jour les pilotes et le firmware pour optimiser les performances et la sécurité. o Assurer la compatibilité et l'intégration avec le réseau et les autres systèmes. 3. Dépanner le système d'information : o Identifier et résoudre les problèmes logiciels et systèmes. o Gérer les mises à jour logicielles et les correctifs de sécurité. o Assurer la disponibilité et la fiabilité des applications critiques comme Oracle Flexcube et les systèmes de reporting ect 4. Configurer le système d'information : o Installer et configurer de nouvelles applications et modules. o Paramétrer les permissions d'accès et les configurations de sécurité. o Assurer la sauvegarde et la restauration des données pour la continuité des opérations. | C65: =IF(TRIM(B65)="",0,1) -> 1 | D65: Détails
A66: Est-ce qu'il y a une tentative de résolution des incidents par l'équipe Service Desk? | B66: oui , il relève de notre responsabilité d'assurer le support de premier niveau | C66: =IF(TRIM(B66)="",0,1) -> 1 | D66: Pourquoi?
A67: Est-ce que le Service Desk a été formé pour gérer les incidents de niveau 1? | B67: oui | C67: =IF(TRIM(B67)="",0,1) -> 1 | D67: Pourquoi?
A68: Comment percevez-vous votre rôle et responsabilités dans la gestion des incidents/problèmes ? | B68: Le responsable du département informatique joue un rôle stratégique dans la gestion des incidents et des problèmes. Il doit non seulement réagir rapidement aux incidents mais aussi anticiper et prévenir les problèmes potentiels. En assurant une communication efficace, en documentant rigoureusement et en cherchant constamment à améliorer les processus, il contribue à la continuité des opérations et à la satisfaction des utilisateurs finaux | C68: =IF(TRIM(B68)="",0,1) -> 1 | D68: Non
A69: Est-ce qu'il y a un objectif de trouver une solution temporaire rapidement pour remettre le service en marche en attendant de trouver une solution définitive ou pas? | B69: oui | C69: =IF(TRIM(B69)="",0,1) -> 1 | D69: Non
A70: Si les incidents ne sont pas résolus par le Service Desk, est-ce qu'on est sûr qu'ils sont escaladés à la bonne équipe? | B70: oui , j'aurais besoin de plus d'explications sur le sujet | C70: =IF(TRIM(B70)="",0,1) -> 1 | D70: comment?
A71: Y'a-t-il une procédure d'escalade formalisée? | B71: non | C71: =IF(TRIM(B71)="",0,1) -> 1 | D71: Non
A72: Comment s'assure-t-on que l'équipe à qui on a escaladé a pris en charge l'incident? | B72: non | C72: =IF(TRIM(B72)="",0,1) -> 1 | D72: Non
A73: Quels sont les clients majeurs de la DSI ? | B73: départements internes de la filiale & Les utilisateurs finaux | C73: =IF(TRIM(B73)="",0,1) -> 1 | D73: Non
... A109: Pouvez-vous me partager la liste des incidents ouverts des 3 derniers mois (ou depuis le 01/01) avec toutes les infos: - n° incident - statut de l'incident - date/heure d'ouverture - criticité (ou sévérité/priorité) - application concernée - intitulé de l'incident - description de l'incident - demandeur (et son dept) - qui a pris en charge - date/heure d'escalade (si escalade) - date/heure de résolution - qui a résolu - solution appliquée - autres infos utiles | B109: incident impacte actuellement l'accès à notre système d'information (SI) 01/07/24 / Non accès internet à l'Agence d'Agoe 05/05/24: n souci de coupure de fibre optique sur le tronçon menant chez l'agence | C109: =IF(TRIM(B109)="",0,1) -> 1 | D109: Pourquoi?
A110: Demandes de changements | B110: Réponse, détail et/ou fichier fourni | D110: Document à fournir
A111: Veuillez fournir des informations sur les volumes et la fréquence des demandes de changement (CR) émanant des utilisateurs finaux et celles émanant par l'IT. Veuillez inclure des données historiques ainsi que des prévisions. | B111: Les demandes de changement ne sont actuellement pas formalisées, ce qui rend difficile de quantifier précisément leur volume et leur fréquence | C111: =IF(TRIM(B111)="",0,1) -> 1 | D111: Pourquoi?
A112: Combien de ces demandes surviennent en moyenne par an ? | B112: Les demandes de changement ne sont actuellement pas formalisées, ce qui rend difficile de quantifier précisément leur volume et leur fréquence | C112: =IF(TRIM(B112)="",0,1) -> 1 | D112: Pourquoi?
A113: Veuillez fournir des informations sur le volume et la fréquence des versions mineures et majeures. | B113: Les demandes de changement ne sont actuellement pas formalisées, ce qui rend difficile de quantifier précisément leur volume et leur fréquence | C113: =IF(TRIM(B113)="",0,1) -> 1 | D113: Pourquoi?
A114: Veuillez fournir des informations sur les KPI et mesures de performances des CR et développement d'applications, ci-dessous quelques exemples: - Catégorisation des CR en termes d'effort, par ex. petit < 15 JH, moyen < 25 JH, etc. - Catégorisation des CR en termes d'impact sur le Business - Nombre de CR par département - Nombre de CR demandés vs approuvés - Nombre de CR mis en Live par mois - Pourcentage de CR mis en Live dans les délais convenus - Pourcentage de CR mis en Live dans le budget prévu - ... | B114: Nous tenons à vous informer que nous ne disposons pas actuellement des indicateurs nécessaires. Nous aurons besoin de votre support pour formaliser et suivre cela, car nous n'avons pas encore effectué ce genre d'exercice. | C114: =IF(TRIM(B114)="",0,1) -> 1 | D114: Pourquoi?
A115: Veuillez fournir ces informations si possible par domaine d'application | B115: Nous tenons à vous informer que nous ne disposons pas actuellement des indicateurs nécessaires. Nous aurons besoin de votre support pour formaliser et suivre cela, car nous n'avons pas encore effectué ce genre d'exercice. | C115: =IF(TRIM(B115)="",0,1) -> 1 | D115: Pourquoi?
A116: Combien de FTE des opérations (1er et 2eme niveau) sont utilisés pour les CR (en dehors du cadre de l'exploitation « normale ») ? | B116: Nous tenons à vous informer que nous ne disposons pas actuellement des indicateurs nécessaires. Nous aurons besoin de votre support pour formaliser et suivre cela, car nous n'avons pas encore effectué ce genre d'exercice. | C116: =IF(TRIM(B116)="",0,1) -> 1 | D116: Pourquoi?
A117: Projets | B117: Réponse, détail et/ou fichier fourni | D117: Document à fournir
A118: Quels sont les critères utilisés pour qualifier les demandes utilisateurs en CR ou projet? | B118: voici quelques critères généraux qui sont souvent utilisés pour prendre cette décision : Portée du changement : La taille et l'impact de la demande peuvent déterminer si elle nécessite un traitement comme un projet ou peut être gérée comme un simple changement requis. Complexité : Les demandes plus complexes qui nécessitent des ressources significatives en termes de temps, d'argent ou de compétences techniques sont souvent traitées comme des projets. Ressources nécessaires : La disponibilité et l'allocation de ressources telles que le personnel, le financement et le matériel peuvent influencer si la demande est gérée comme un projet ou non. Impact sur les autres systèmes ou processus : Les demandes qui affectent d'autres systèmes, processus ou parties prenantes peuvent nécessiter une gestion plus structurée comme un projet pour assurer une coordination appropriée et minimiser les risques. Objectifs et bénéfices attendus : Les objectifs stratégiques ou les bénéfices attendus peuvent être pris en compte pour décider du niveau de gestion et de suivi requis pour la demande. Risques associés : Les risques potentiels liés à la mise en œuvre de la demande peuvent influencer la décision de la gérer comme un projet pour permettre une gestion proactive des risques . 1. Portée du changement :  Pourquoi : Déterminer l'impact du changement aide à comprendre si la demande est mineure ou majeure. 2. Complexité :  Pourquoi :. Gérer ces demandes comme des projets permet d'assurer une coordination efficace, une allocation appropriée des compétences et une surveillance continue pour éviter les échecs. 3. Ressources nécessaires :  Pourquoi : Les projets nécessitent souvent une planification budgétaire, une gestion des ressources humaines et matérielles, ce qui justifie un traitement plus structuré. 4. Impact sur les autres systèmes ou processus :  Pourquoi : permet de planifier et de gérer les interdépendances, de minimiser les risques de perturbations et d'assurer une communication adéquate entre les parties prenantes. 5. Objectifs et bénéfices attendus :  Pourquoi : permet de garantir que les objectifs sont atteints de manière efficace. | C118: =IF(TRIM(B118)="",0,1) -> 1 | D118: Pourquoi?
A119: Quels sont les principaux projets IT (métiers) en cours et prévus, par ex. implémentations du CBS, Mobile Banking, upgrade de la messagerie, …? Et projets IT (internes) en cours et prévus, par ex. mises à niveau du système, modifications architecturales logicielles et matérielles ? | D119: Non
A120: Quelle est la performance sur les délais de livraison des projets ? | B120: Acceptable, On n'avait pas défini d'indicateurs pour les mesures, mais on se base sur le retour des utilisateurs de façon informelle et sur l'appropriation des outils par les utilisateurs. | C120: =IF(TRIM(B120)="",0,1) -> 1 | D120: Comment cela a été mesuré?
A121: Quel est le processus pour l’introduction de nouvelles technologies (HW et SW) ? | B121: Identification des besoins / Évaluation des technologies disponibles / Analyse de faisabilité./ Planification et budgétisation Identification des besoins : • Pourquoi ? : Elle permet de définir clairement les problèmes à résoudre ou les opportunités à exploiter. Évaluation des technologies disponibles : • Pourquoi ? : pour choisir la technologie qui correspond le mieux aux besoins identifiés. Analyse de faisabilité : • Pourquoi ? : permet de s'assurer que la technologie est faisable dans le contexte spécifique et répond aux attente Planification et budgétisation : • Pourquoi ? : permet de planifier le déploiement de manière détaillée et de s'assurer que les ressources financières nécessaires sont disponibles. Cela inclut l'estimation des coûts d'acquisition, de mise en œuvre, de formation et de maintenance. | C121: =IF(TRIM(B121)="",0,1) -> 1 | D121: Pourquoi? | H121: NB Pour les questions concernant l’audit de l’existant IT, veuillez prendre en compte les réponses écrites en orange
A122: Quel est le processus pour la conception de nouveaux services aux utilisateurs finaux ? Quels sont les délais de réalisation de ce processus et à quoi ressemble le résultat (modèles de documents) ? | B122: Identification des besoins/ Définition des spécification/ Conception 1. Identification des besoins Cela permet de bien comprendre ce que les utilisateurs finaux attendent du système ou du logiciel. 2. Définition des spécifications Fournit une description détaillée des fonctionnalités et des contraintes du système ou du logiciel. 3. Conception Permet de créer une architecture et un plan de développement structurés pour le projet | C122: =IF(TRIM(B122)="",0,1) -> 1 | D122: Pourquoi?
A123: Combien de ces demandes surviennent en moyenne par an ? | B123: 3 | C123: =IF(TRIM(B123)="",0,1) -> 1 | D123: Pouvez-vous partager les dernières?
A124: Combien de FTE des opérations (1er et 2eme niveau) sont utilisés pour des projets (en dehors du cadre de l'exploitation « normale ») ? | B124: J'ai jamais fait cet exercice avant. | C124: =IF(TRIM(B124)="",0,1) -> 1 | D124: Pourquoi?
A125: Comment est organisé le processus d’approbation financière (budgétaire) des projets ? | B125: Identification du besoin : Analyse approfondie des besoins du marché et des parties prenantes pour définir le problème à résoudre ou l'opportunité à exploiter. • Élaboration du projet : Conception du projet incluant les objectifs, la portée, les livrables, et la stratégie de mise en œuvre. • Préparation de la proposition : Rédaction d'une proposition détaillée présentant le projet, ses objectifs, ses méthodes et les ressources nécessaires. • Projections financières : Estimations financières incluant les coûts prévus, les sources de financement potentielles, et les revenus attendus. • Justification des coûts et bénéfices : Explication claire et documentée des coûts impliqués et des bénéfices attendus, démontrant la viabilité et la rentabilité du projet. | C125: =IF(TRIM(B125)="",0,1) -> 1 | D125: Pourquoi?
A126: Environnement informatique de l'utilisateur final | B126: Réponse, détail et/ou fichier fourni | D126: Document à fournir
A127: Veuillez décrire l'environnement de travail des utilisateurs finaux: ordinateurs, ordinateurs portables, imprimantes, appareils mobiles, VoIP, vidéoconférence, etc. | B127: Les utilisateurs finaux disposent d'ordinateurs et d'ordinateurs portables équipés du système d'exploitation Windows. Ils sont connectés à Internet via un réseau interne câblé ou WiFi. Pour l'impression, ils utilisent des imprimantes multifonctions centralisées, chaque utilisateur ayant un code de sécurité spécifique pour accéder à ces appareils. Enfin, tout le réseau est protégé par un équipement de pare-feu Fortinet, assurant une sécurité renforcée. | C127: =IF(TRIM(B127)="",0,1) -> 1 | D127: Non
A128: Qui est responsable du support sur l'environnement utilisateur? | B128: TEAM IT | C128: =IF(TRIM(B128)="",0,1) -> 1 | D128: Non
A129: Veuillez fournir des informations sur les systèmes de support pour l'environnement de l'utilisateur final, par ex. gestion des actifs et des licences, configuration des logiciels, déploiement des configurations, archivage des images, sécurité, etc. | B129: Sécurité : o Mise en œuvre de politiques de sécurité robustes incluant la gestion des correctifs, l'authentification multifactorielle, et la surveillance des menaces. o Utilisation de pare-feu, de logiciels antivirus et de solutions de chiffrement pour protéger les données et les systèmes contre les menaces internes et externes. Firewall (Fortinet) : Configurez et maintenez un pare-feu robuste pour contrôler le trafic réseau entrant et sortant. o Logiciels antivirus (Kaspersky) : Utilisez des solutions de protection contre les logiciels malveillants pour détecter et éliminer les menace Gestion des incidents et support utilisateur : o Utilisation de systèmes de gestion des incidents pour suivre, résoudre et documenter les problèmes rencontrés par les utilisateurs. o Fourniture d'un support utilisateur efficace à travers des portails d'assistance, des centres d'appels ou des équipes dédiées. Supervision soc Assurez-vous de mettre en place une surveillance continue des événements de sécurité et des incidents à travers un SOC pour une réponse proactive aux menaces. | C129: =IF(TRIM(B129)="",0,1) -> 1 | D129: Pour le support, cela est en paradox avec les réponses plus haut
A130: Veuillez lister les applications poste de travail actuellement utilisées pour les différentes catégories de personnel? | B130: 1. Suite bureautique : Microsoft Office (Word, Excel, PowerPoint) 2. Logiciel de messagerie : Outlook, 3. Logiciel de gestion documentaire : SharePoint, Dropbox, Google Drive 4. Navigateurs web : Google Chrome, Mozilla Firefox, Microsoft Edge 5. Communication d'équipe : Microsoft Teams, Slack, Zoom 6. Outils de virtualisation : VMware, VirtualBox 7. Outils de gestion de bases de données : MySQL Workbench, Microsoft SQL Server Management Studio 8. Logiciel de gestion des tickets : ServiceNow, JIRA Service Desk, Zendesk 9. Outils de support à distance : TeamViewer, AnyDesk, Remote Desktop Services (RDS) 10. Logiciels de surveillance et de gestion réseau : SOC Nous utilisons actuellement Google Drive et Zoom pour échanger avec nos partenaires externes. ServiceNow et Jira SD sont en phase d’expérimentation pour améliorer nos processus internes. Pour le support technique à distance, nous utilisons souvent AnyDesk et Teamviewer. Nous n'avons pas actuellement de licence authentique pour ces outils en dehors ZOOM | C130: =IF(TRIM(B130)="",0,1) -> 1 | D130: Pourquoi Google Drive, Zoom alors que vous avez le pack Microsoft? Pourquoi ServiceNow et Jira SD et Zendesk, alors que outil ITSM est non? Pourquoi AnyDesk et Teamviewer? Y'a-t-il des licences?
A131: Vendeurs | B131: Réponse, détail et/ou fichier fourni | D131: Document à fournir
A132: Existe-t-il une approche à l’échelle du groupe concernant les fournisseurs privilégiés ? Si oui, pouvez-vous s'il vous plaît fournir la liste des fournisseurs, leurs classements et domaines de livraison ? Veuillez également indiquer les changements prévus et les fournisseurs envisagés dans un avenir proche. | B132: NON | C132: =IF(TRIM(B132)="",0,1) -> 1 | D132: Non
A133: Décrire les contrats de support matériel et logiciel actuels avec les fournisseurs de systèmes concernés. | B133: NON | C133: =IF(TRIM(B133)="",0,1) -> 1 | D133: Non
A134: Utilisez-vous un outil de mesure de la performance des fournisseurs ? Si tel est le cas, veuillez nous informer sur l'outil et répertorier les scores par fournisseur. | B134: NON | C134: =IF(TRIM(B134)="",0,1) -> 1 | D134: Non
A135: Tous les matériels et logiciels concernés sont-ils toujours entièrement pris en charge ? Ou avez-vous certains hors support? | B135: OUI | C135: =IF(TRIM(B135)="",0,1) -> 1 | D135: Détails
C136: =SUM(C4:C135)/COUNT(C4:C135) -> 1

Sheet Secu
A1: Retour à la page d'accueil
A2: Questions Sécurité | B2: =C51 -> 1 | D2: Complément
A3: Sécurité de l’information - Information et documentation à fournir | B3: Réponse, détail et/ou fichier fourni | C3: Eval | D3: Questions complémentaires
A4: Quels systèmes, procédures ou pratiques de sécurité sont en place pour protéger les systèmes d’information ? | B4: Kaspersky Advanced, EDR Kaspersky, SIEM Qradar, Qualys, SOC, Fortinet,IPS et IDS | C4: =IF(TRIM(A4)="","",IF(TRIM(B4)="",0,1)) -> 1 | D4: Qu'en est-il des procédures et politiques?
A5: Existe-t-il des restrictions légales concernant le traitement des données par d'autres parties que le client ? Toute limitation pour l'accès à distance aux systèmes, les opérations à distance des systèmes | B5: oui | C5: =IF(TRIM(A5)="","",IF(TRIM(B5)="",0,1)) -> 1 | D5: Détailler
A6: Existe-t-il des plans de reprise après sinistre et de continuité des activités ? | B6: oui | C6: =IF(TRIM(A6)="","",IF(TRIM(B6)="",0,1)) -> 1 | D6: Pouvez-vous les partager?
A7: Existe-t-il une solution de reprise après sinistre (DR) ? | B7: oui Sauvegarde et restauration | C7: =IF(TRIM(A7)="","",IF(TRIM(B7)="",0,1)) -> 1 | D7: Détailler
A8: Sinon, avez-vous au moins des procédures de récupération ? Pour quels services? | B8: oui | C8: =IF(TRIM(A8)="","",IF(TRIM(B8)="",0,1)) -> 1 | D8: Pouvez-vous les partager?
A9: Y a-t-il des politiques de sécurité informatique en place ? | B9: oui | C9: =IF(TRIM(A9)="","",IF(TRIM(B9)="",0,1)) -> 1 | D9: Pouvez-vous les partager?
A10: o Gestion des utilisateurs : | B10: OUI | C10: =IF(TRIM(A10)="","",IF(TRIM(B10)="",0,1)) -> 1 | D10: Questions complémentaires
A11: § La procédure technique concernant la mise à jour des utilisateurs (création / modification / suppression) ; | B11: oui | C11: =IF(TRIM(A11)="","",IF(TRIM(B11)="",0,1)) -> 1 | D11: Pouvez-vous la partager?
A12: § La procédure technique concernant la désactivation / activation utilisateur; | B12: oui | C12: =IF(TRIM(A12)="","",IF(TRIM(B12)="",0,1)) -> 1 | D12: Pouvez-vous la partager?
A13: o Gestion des habilitations : | B13: OUI | C13: =IF(TRIM(A13)="","",IF(TRIM(B13)="",0,1)) -> 1 | D13: Questions complémentaires
A14: § La liste des administrateurs système (y compris comptes administrateurs de domaines). | B14: oui | C14: =IF(TRIM(A14)="","",IF(TRIM(B14)="",0,1)) -> 1 | D14: Pouvez-vous la partager?
A15: § La liste des profils disponibles dans chaque application | B15: oui | C15: =IF(TRIM(A15)="","",IF(TRIM(B15)="",0,1)) -> 1 | D15: Pouvez-vous la partager?
... A22: · Règles d’attribution | B22: oui | C22: =IF(TRIM(A22)="","",IF(TRIM(B22)="",0,1)) -> 1 | D22: Pouvez-vous les partager?
A23: · Durée de vie. | B23: 45 jours | C23: =IF(TRIM(A23)="","",IF(TRIM(B23)="",0,1)) -> 1
A24: · Longueur minimale. | B24: 14 | C24: =IF(TRIM(A24)="","",IF(TRIM(B24)="",0,1)) -> 1
A25: · Complexité. | B25: oui | C25: =IF(TRIM(A25)="","",IF(TRIM(B25)="",0,1)) -> 1
A26: · Blocage après X tentatives de connexions infructueuses. | B26: oui | C26: =IF(TRIM(A26)="","",IF(TRIM(B26)="",0,1)) -> 1
A27: · Historique. | B27: oui | C27: =IF(TRIM(A27)="","",IF(TRIM(B27)="",0,1)) -> 1
A28: · Changement obligatoire du mot de passe d’initialisation. | B28: oui | C28: =IF(TRIM(A28)="","",IF(TRIM(B28)="",0,1)) -> 1
A29: · Durée d’inactivité avant verrouillage de la session. | B29: oui | C29: =IF(TRIM(A29)="","",IF(TRIM(B29)="",0,1)) -> 1
A30: o Antivirus/antimaleware : | B30: OUI | C30: =IF(TRIM(A30)="","",IF(TRIM(B30)="",0,1)) -> 1 | D30: Questions complémentaires
A31: § Les copies d’écrans des versions d’antivirus/antimaleware installées sur les serveurs | B31: oui | C31: =IF(TRIM(A31)="","",IF(TRIM(B31)="",0,1)) -> 1 | D31: Pouvez-vous les partager?
A32: § Une copie d’écran de la version d’antivirus/antimaleware installée sur un poste de travail. | B32: oui | C32: =IF(TRIM(A32)="","",IF(TRIM(B32)="",0,1)) -> 1 | D32: Pouvez-vous les partager?
A33: o Sauvegardes : | B33: OUI | C33: =IF(TRIM(A33)="","",IF(TRIM(B33)="",0,1)) -> 1 | D33: Questions complémentaires
A34: § La politique de sauvegarde des données informatiques, incluant les procédures de restauration et d’archivage ; | B34: oui | C34: =IF(TRIM(A34)="","",IF(TRIM(B34)="",0,1)) -> 1 | D34: Pouvez-vous la partager?
A35: § Le planning des sauvegardes ; | B35: oui | C35: =IF(TRIM(A35)="","",IF(TRIM(B35)="",0,1)) -> 1 | D35: Pourquoi?
A36: Sécurité physique et accès au(x) site(s) | B36: Réponse, détail et/ou fichier fourni | D36: Questions complémentaires
A37: Décrire la manière dont l'accès aux bureaux est organisé (badges nominatifs, empreintes digitales, photos, …) | B37: badges | C37: =IF(TRIM(A37)="","",IF(TRIM(B37)="",0,1)) -> 1 | D37: Non
A38: Décrire les installations qui hébergent actuellement l'organisation des opérations : Emplacement(s), taille(s), Type (centre de données, centre d'opérations central, centre d'opérations local, etc.), Propriété (loué-en leasing-propriétaire), … | B38: centre d'opérations local | C38: =IF(TRIM(A38)="","",IF(TRIM(B38)="",0,1)) -> 1 | D38: Non
A39: Fournir des informations sur la manière dont l'accès aux sites des centres de données est organisé | B39: badges | C39: =IF(TRIM(A39)="","",IF(TRIM(B39)="",0,1)) -> 1 | D39: Non
A40: Existe-t-il des restrictions d'accès (24h/24 et 7j/7) aux sites des centres de données | B40: oui l'accès aux centres de données est restreint et soumis à des politiques strictes de sécurité et d'accès. Contrôle d'accès physique / Horaires d'accès / Autorisations préalables : L'accès peut nécessiter une autorisation préalable et être strictement réservé au personnel autorisé ou aux techniciens en cas d'intervention d'urgence / Surveillance continue | C40: =IF(TRIM(A40)="","",IF(TRIM(B40)="",0,1)) -> 1 | D40: Lesquels?
A41: Existe-t-il un Data Center de secours? Si oui, suit-il des restrictions? Lesquels? | B41: oui | C41: =IF(TRIM(A41)="","",IF(TRIM(B41)="",0,1)) -> 1 | D41: Détails
A42: Outils de sécurité | B42: Réponse, détail et/ou fichier fourni | D42: Questions complémentaires
A43: Pouvez-vous lister de sécurité mis en place et décrires brièvement leurs fonctionnalités dans la colonne détails (gestion des mdp, gestion des logs, IAM, DLP, antimaleware, SASE, …) ? | B43: en dehors de la gestion des mots de passe et de l'Antivirus (Kaspersky Advanced, EDR Kaspersky), les autres dispositifs de sécurité sont gérés au niveau de l'IT groupe : Firewall : Fortinet avec IDS/IPS activé. SOC : Supervision 24/7 des actifs du groupe COFINA pour prévenir toute cyberattaque. SIEM : Qradar, Qualys. | C43: =IF(TRIM(A43)="","",IF(TRIM(B43)="",0,1)) -> 1 | D43: Pourquoi?
A44: Veuillez préciser pour chaque outil s'il est installé sur site ou utilisé à partir du Cloud (SaaS) ? | B44: SITE | C44: =IF(TRIM(A44)="","",IF(TRIM(B44)="",0,1)) -> 1 | D44: Pourquoi?
A45: Quelle est la criticité de chaque outil ? | B45: Firewall Fortinet avec IDS/IPS activé : Criticité : Très élevée Raison : Le firewall Fortinet avec IDS/IPS joue un rôle crucial en sécurisant le périmètre réseau, en détectant et en prévenant les intrusions potentielles. Il est essentiel pour protéger vos systèmes contre les attaques externes et internes. SOC (Security Operations Center) : Criticité : Élevée Raison : Le SOC est responsable de la surveillance continue de vos actifs informatiques, détectant les menaces et répondant aux incidents de sécurité en temps réel. Il contribue à minimiser les risques de cyberattaques et à assurer la résilience de votre infrastructure. SIEM (Security Information and Event Management) - Qradar, Qualys : Criticité : Élevée Raison : Le SIEM est crucial pour la collecte, la corrélation et l'analyse des événements de sécurité à travers votre réseau. Qradar et Qualys fournissent des capacités avancées de gestion des informations de sécurité, aidant à identifier les menaces potentielles et à répondre aux incidents de manière proactive. | C45: =IF(TRIM(A45)="","",IF(TRIM(B45)="",0,1)) -> 1 | D45: Pourquoi?
A46: Quel est le nombre actuel de licences détenues par la filiale pour chaque outil ? | B46: voir IT groupe | C46: =IF(TRIM(A46)="","",IF(TRIM(B46)="",0,1)) -> 1 | D46: Pourquoi?
A47: Quel est le coût du support éditeur/partenaire pour chaque outil ? | B47: voir IT groupe | C47: =IF(TRIM(A47)="","",IF(TRIM(B47)="",0,1)) -> 1 | D47: Pourquoi?
A48: Quel type de contrat pour chaque outil: global couvrant plusieurs filiales ou dédié à la filiale ? | B48: voir IT groupe | C48: =IF(TRIM(A48)="","",IF(TRIM(B48)="",0,1)) -> 1 | D48: Pourquoi?
A49: Lancez-vous régulièrement des campagnes (internes ou externes) de sensibilisation antiphishing ? | B49: oui | C49: =IF(TRIM(A49)="","",IF(TRIM(B49)="",0,1)) -> 1 | D49: Pouvez-vous partager un exemple de communication?
A50: Lancez-vous régulièrement des pentest ? Si oui, pouvez-vous partager le dernier rapport et les actions entreprises par la suite | B50: NON | C50: =IF(TRIM(A50)="","",IF(TRIM(B50)="",0,1)) -> 1 | D50: Non
C51: =SUM(C4:C50)/COUNT(C4:C50) -> 1
A123: Combien de ces demandes surviennent en moyenne par an ?

Sheet Contracts
A1: Retour à la page d'accueil
A2: # | B2: Nom du fichier | C2: Lien du fichier | D2: Prestataire | E2: Bénéficiaire | F2: Scope (périmètre, solution, modules/ services inclus, etc.) | G2: [L]icences [S]ouscription [I]mplémentation [M]aintenance/Support | H2: Volume (# licences, # souscriptions, …) | I2: Coût | J2: Mécanisme de coût | K2: Importance (haute / moyenne / faible) | L2: Date de début | M2: Durée du contrat | N2: SLA (dispo ou pas) et lien | O2: Notification de résiliation | P2: Contrat signé par les 2 parties (oui/non) | Q2: Remise appliquée | R2: Responsable Achat | S2: Commentaires / Information complémentaire / Questions à poser
A3: 1 | B3: INFOGERANCE | C3: NA | D3: CANOPUS | E3: COFINA TOGO | F3: LOCATION D'IMPRIMANTE | G3: NA | H3: NA | I3: 7380000 | K3: moyenne | L3: 2022 | N3: NA | O3: 2 mois | P3: OUI | Q3: N/A | R3: Amadou Mar DIOP
A4: 2 | B4: FAI | C4: NA | D4: GVA | E4: COFINA TOGO | F4: INTERNET | G4: M | H4: NA | I4: 13200000 | K4: haute | L4: 2021 | N4: NA | O4: 2 mois | P4: OUI | Q4: N/A | R4: Amadou Mar DIOP
A5: 3 | B5: FAI | C5: NA | D5: TOGOCOM | E5: COFINA TOGO | F5: INTERNET | G5: M | H5: NA | I5: 5436000 | K5: haute | L5: 2021 | N5: NA | O5: 2 mois | P5: OUI | Q5: N/A | R5: Amadou Mar DIOP
A6: 4 | B6: GOMISE | C6: NA | D6: CAGECFI | E6: COFINA TOGO | F6: PAIE | G6: M | H6: NA | I6: 593000 | K6: haute | L6: 2021 | N6: NA | O6: 2 mois | P6: OUI | Q6: N/A | R6: IT GROUPE
A7: 5 | B7: MOBILE | C7: NA | D7: Smarts Solutions Managers | E7: COFINA TOGO | F7: COFINA MOBILE + | G7: M | H7: NA | I7: VOIR IT GROUPE | K7: haute | L7: 2024 | M7: NA | N7: NA | O7: 2 mois | P7: OUI | Q7: N/A | R7: IT GROUPE
A8: 6 | B8: IMMO | C8: NA | D8: MEDIASOFT | E8: COFINA TOGO | F8: IMMOBILISATION DES BIEN ET ACTIFS | G8: L | H8: NA | I8: 4200000 | K8: haute | L8: 2023 | N8: NA | O8: 2 mois | P8: OUI | Q8: N/A | R8: DIRECTION
A9: 7 | B9: FLEXCUBE | C9: NA | D9: JMR Infotech | E9: COFINA TOGO | F9: SYSTÈME D'INFORMATION | G9: M | H9: NA | I9: VOIR IT GROUPE | K9: haute | L9: 2024 | M9: NA | N9: NA | O9: 2 mois | P9: OUI | Q9: N/A | R9: IT GROUPE
A10: 8
A11: 9
A12: 10
A13: 11
A14: 12
A15: 13
A16: 14
A17: 15
A18: 16
A19: 17
A20: 18
A21: 19
... A72: 70
A123: Combien de ces demandes surviennent en moyenne par an ?

Sheet ✅ Projets 2026
A1: Retour à la page d'accueil
B2: Projet | C2: Objectif | D2: État Actuel | E2: Progrès Réalisé (%) | F2: Résultats et Avantages | G2: Commentaire
B3: Présentation Projets Informatiques Accomplis 2025
A4: 1 | B4: Digitalisation des processus arrêt de caisse | C4: Automatiser et simplifier les processus de clôture de caisse | D4: Processus automatisés, réduction du temps | E4: 1 | F4: - Gain de temps.
F5: - Minimisation des erreurs humaines.
A6: 3 | B6: Application de rappel des échéances (15j, 7j, J) | C6: Optimiser la gestion des échéances pour éviter les retards | D6: Application fonctionnelle, rappels envoyés | E6: 1 | F6: - Réduction des retards de paiement.
F7: - Amélioration de la trésorerie.
A8: 5 | B8: Logiciel de Gestion du Parc Informatique & Helpdesk COFIHELP | C8: Améliorer la gestion du parc & le support technique | D8: Système opérationnel | E8: 1 | F8: - Réduction des pannes.
F9: - Productivité accrue.
A10: 6 | D10: Correctifs appliqués | E10: 1 | F10: - Stabilité et sécurité renforcées.
A11: 7 | D11: Transactions opérationnelles | E11: 0.9 | F11: - Fluidité des paiements.
F12: - Plus de choix pour les clients.
A13: 8 | B13: Digitalisation des conventions de crédit | C13: Accélérer le traitement des contrats de crédit | D13: Projet terminé | E13: 1 | F13: - Réduction des délais de traitement.
F14: - Meilleure traçabilité , Minimisation des erreurs humaines
A15: 9 | B15: Automatisation des extractions opérationnelles Flexcube REPORT | C15: Gagner du temps sur la génération de rapports | D15: Extractions automatisées | E15: 1 | F15: - Moins de charge manuelle.
F16: - Rapports disponibles rapidement.
A17: 11 | B17: Application de gestion des COFICARTES | C17: Suivre les ventes et le stock de cartes VISA | D17: Application opérationnelle | E17: 1 | F17: - Suivi en temps réel.
F18: - Traçabilité améliorée.
A19: 12 | B19: Application Recrutement RH | C19: Améliorer le processus de recrutement | D19: Application fonctionnelle | E19: 0.8 | F19: - Processus fluidifié.
A20: 14 | B20: IMMO – Gestion des immobilisations | C20: Suivre les immobilisations de l'entreprise | D20: Application fonctionnelle | E20: 1 | F20: - Meilleure visibilité patrimoniale.
A21: 15 | B21: COFIGED – Archivage numérique | C21: Digitaliser l’archivage des documents | D21: Application déployée | E21: 1 | F21: - Réduction du papier.
F22: - Accès rapide aux documents.
A23: 16 | B23: GESTION DE STOCK (Parc IT, consommables…) | C23: Optimiser le suivi des stocks | D23: Application en production | E23: 1 | F23: - Traçabilité complète.
A24: 18 | B24: Implémentation Carthago (réglementaire) | C24: Assurer la conformité réglementaire | D24: Système en production | E24: 1 | F24: - Conformité assurée.
F25: - Risques réglementaires réduits.
A26: 19 | B26: Application d’Intégration Automatique des OD | C26: Simplifier les opérations comptables | D26: Application en service | E26: 1 | F26: - Rapidité et fiabilité des OD.
A27: 20 | B27: COFINA MOBILE+ | C27: Cofina Mobile+ est une application web et mobile , permettant aux clients d'accéder à des services bancaires à distance 24h/24 et 7j/7 depuis un ordinateur, une tablette ou un smartphone. | D27: Déployé et opérationnel | E27: 1 | F27: - Disponibilité permanente des services
F28: - Réduction de l'affluence en agence
F29: - Amélioration de l’expérience utilisateur
F30: - Extension de la portée des services bancaires
A31: 21 | B31: SMS Banking | C31: Le service SMS Banking permet aux clients de recevoir des notifications par SMS en temps réel pour chaque mouvement effectué sur leur compte bancaire. Ce service vise à renforcer la transparence et la sécurité des transactions tout en offrant aux clients un suivi instantané de leurs opérations financières. | D31: Déployé et opérationnel | E31: 1 | F31: - Transparence accrue
F32: - Suivi en temps réel des opérations
F33: - Renforcement de la sécurité des comptes
A35: 22 | B35: B2W/W2B | C35: Le projet B2W (Bank to Wallet) / W2B (Wallet to Bank) vise à mettre en place un service permettant aux clients de transférer des fonds entre leurs comptes bancaires et leurs portefeuilles mobiles via un canal USSD. | D35: En phase finale de tests et intégrations | E35: 0.9 | F35: - Accessibilité pour les utilisateurs sans smartphone
F36: - Inclusion financière renforcée
F37: - Réduction des délais de transfert
A39: 23 | B39: Outil de suivi des commissions et digitalisation des workflows | C39: L'Outil de suivi des commissions et digitalisation des workflows vise à améliorer la gestion et le suivi des commissions prelevées en agence et par les équipes back-office. Il intègre une automatisation des processus de validation et de traitement afin d'optimiser l'efficacité opérationnelle et la transparence dans le calcul et le paiement des commissions | D39: Déployé et en production | E39: 1 | F39: - Meilleure visibilité sur les commissions
F40: - Automatisation des validations
F41: - Fiabilité accrue des calculs
F42: - Gains de temps significatifs
A43: 24 | B43: Digitalisation des conventions de crédit V2 | C43: Accélérer le traitement des contrats de crédit | D43: Projet terminé | E43: 1 | F43: - Meilleure traçabilité
F44: - Réduction des erreurs humaines
F45: - Délai de traitement réduit
A48: 25 | B48: Automatisation de l'envoi mensuel des relevés de compte clients | C48: Automatiser la génération, la mise en forme et l’envoi des relevés de compte clients à la fin de chaque mois | D48: Fonctionnalité déployée et testée | E48: 1 | F48: - Moins d’intervention manuelle
F49: - Amélioration de la ponctualité
F50: - Meilleure conformité réglementaire
F51: - Expérience client renforcée
A52: 26 | B52: Automatisation de l’ouverture et de la fermeture du Système d’Information | C52: Automatiser les routines quotidiennes du système d'information. | D52: Finalisé | E52: 1 | F52: - Gain de temps opérationnel
F53: - Réduction des risques d’oubli ou d’erreur humaine
A54: 4 | B54: Déploiement TPE (pour collecte) | C54: Déployer les terminaux de paiement (TPE) pour faciliter la collecte. | D54: STANDBY | E54: 0.9 | F54: - Modernisation des moyens de collecte | G54: Le déploiement est presque finalisé. Reste la formation continue des agents terrain et quelques derniers tests de validation.
F55: - Réduction de la manipulation de liquidités
F56: - Suivi en temps réel des transactions

Sheet CofiDesk
A2: Priorité | B2: Projet | C2: Objectif | E2: Progrès réalisé | F2: Résultats & Avantages | G2: Owner | H2: Start Date | I2: End Date | J2: Date de livraison
A3: 5 | B3: Digitalisation des processus d’arrêt de caisse (ecart de caisse) | C3: Automatiser et simplifier les processus de clôture de caisse | D3: Not Star | F3: - Gain de temps significatif | G3: BABACAR | H3: À définir | I3: À définir | J3: À définir
F4: - Minimisation des erreurs humaines
A5: 7 | B5: ERB – État de Rapprochement Bancaire | C5: Automatiser le rapprochement bancaire | D5: Not Star | F5: - Meilleure traçabilité | G5: À définir | H5: À définir | I5: À définir | J5: À définir
F6: - Réduction des écarts et erreurs humaines
A7: 4 | B7: Application de gestion des COFICARTES | C7: Assurer le suivi des ventes et du stock de cartes VISA | D7: In Progress | F7: - Suivi en temps réel | G7: MAR | H7: — | I7: —
F8: - Traçabilité améliorée
F9: - Réduction des risques réglementaires
A10: 6 | B10: Gestion des pièces comptables – Intégration automatique des OD | C10: Simplifier et fiabiliser les opérations comptables | D10: Not Star | F10: - Rapidité de traitement | G10: MODOU | H10: — | I10: —
F11: Réduire significativement l’impression massive de pièces comptables
F12: archivage
F13: - Fiabilité des écritures comptables
A14: 2 | B14: Digitalisation des conventions de crédit | C14: Accélérer le traitement des contrats de crédit | D14: In Progress | F14: - Meilleure traçabilité | G14: MAR | H14: — | I14: —
F15: - Réduction des erreurs humaines
F16: - Délai de traitement réduit
A17: 1 | B17: Gestion PIP | C17: Optimiser la gestion et le suivi des PIP | D17: In Progress | F17: - Amélioration du suivi opérationnel | G17: MAR | H17: À définir | I17: À définir | J17: À définir
F18: - Données centralisées
A19: 3 | B19: Gestion Fiche Dépense (FED), Petite Caisse & Budget | C19: Digitaliser et contrôler les dépenses internes | D19: In Progress | F19: - Meilleur contrôle budgétaire | G19: MANSOUR | H19: À définir | I19: À définir
F20: - Traçabilité des dépenses
F21: - Réduction des fraudes
B22: Engagements

Sheet PROJETS EN COURS
B1: Priorité | C1: Projet | D1: Objectif | E1: État Actuel | F1: Progrès Réalisé (%) | G1: Résultats et Avantages | H1: Owner | I1: Commentaire
C2: Présentation des Projets Informatiques ENCOURS 2026
A3: 1 | C3: outils de gestion de parc informatique | D3: Centraliser et automatiser le suivi des équipements informatiques (postes, imprimantes, serveurs, etc.) | E3: DONE | F3: 1 | G3: Amélioration du suivi du parc
G4: Réduction des pertes et pannes | H4: BABACAR
A7: 2 | C7: CofiRH | D7: Application RH couvrant : gestion des entretiens d’embauche, gestion des contrats, intranet, communication interne, fiches d’habilitation | E7: DONE | F7: 1 | G7: Centralisation des données RH
G8: - Gestion efficace des habilitations | H8: MODOU/BABACAR
G9: Avance sur salaire
A11: 3 | B11: Priorité 1 | C11: Projet DATA & BI (COFIdash) | D11: Suivi des commissions et pilotage de la performance : PNB & PBT, suivi des objectifs et réalisations | E11: EN COURS | F11: 0.65 | G11: - Décisions basées sur données fiables
G12: - Suivi des performances en temps réel | H12: MODOU/NDICK
A15: 4 | B15: Priorité 2 | C15: Vue Client 360° | D15: Centraliser toutes les informations client issues des différents systèmes (Core Banking, Mobile, Agence, Produits digitaux) dans une interface unique | E15: EN COURS | F15: 0.25 | G15: Vision complète du client
G16: Amélioration de l’expérience client | H16: NDICK/MODOU
A18: 5 | C18: Interopérabilité BCEAO PIP | D18: Assurer une compatibilité avec les systèmes BCEAO pour les transactions. | E18: ENCOURS | F18: 0.98 | G18: - Meilleure conformité réglementaire
G19: - Intégration dans l’écosystème bancaire régional | H19: MAR
G20: - Automatisation des échanges
A21: 6 | B21: Priorité 5 | C21: Cofilcolatte: gestion des garanties | D21: Suivi et gestion des garanties des produits et clients | E21: EN COURS | F21: 0.95 | G21: - Meilleur contrôle des garanties
G22: - Réduction des risques | H22: MANSSOUR
A24: 7 | B24: Priorité 3 | C24: Digitalisation des conventions de crédit | D24: Accélérer le traitement des contrats de crédit | E24: ENCOURS | F24: 0.8 | G24: - Meilleure traçabilité
G25: - Réduction des erreurs humaines | H25: MAR
G26: - Délai de traitement réduit
A27: 8 | B27: Priorité 2 | C27: Gestion Fiche Dépense (FED), Petite Caisse & Budget | D27: Digitaliser et contrôler les dépenses internes | E27: ENCOURS | F27: 0.7 | G27: - Meilleur contrôle budgétaire
G28: - Traçabilité des dépenses | H28: MANSSOUR
G29: - Réduction des fraudes
A30: 9 | C30: Application de gestion des COFICARTES V1 | D30: Assurer le suivi des ventes et du stock de cartes VISA | E30: ENCOURS | F30: 0.9 | G30: - Suivi en temps réel
G31: - Traçabilité améliorée | H31: MAR
G32: - Réduction des risques réglementaires
A33: 10 | C33: Mise en service des équipements de sécurité électronique au niveau des agences.
A36: 10 | C36: Stabilisation de la connexion internet dans les différentes agences
C43: EN COURS+31:48+B43

Sheet CBS
A1: Retour à la page d'accueil | C1: Réponse corrigé à partir du fichier CTI
B2: Core Banking System - Système de Gestion Bancaire
B3: Veuillez répondre à toutes les questions et donner plus de détails (colonne D) lorsque nécessaire, un taux de remplissage est calculé dans le sommaire et devrait être à 100%
B4: Certaines questions peuvent en faire apparaitre de nouvelles auxquelles il faudra répondre, cela entre également dans le calcul du taux de remplissage
B6: Questions | C6: Réponses | D6: Détails | E6: Eval | F6: Complément
B7: COTS ou Développement interne? (Commercial Off-The-Shelf solution) | C7: COTS | E7: =IF(TRIM(B7)="","",IF(TRIM(C7)="",0,1)) -> 1 | F7: Non
B8: =IF(C7="COTS","Nom de l'éditeur","") -> Nom de l'éditeur | C8: Oracle | D8: le produit est directement développé et édité par Oracle Corporation . JMR Infotech, comme partenaire et intégrateur de solutions Oracle. | E8: =IF(TRIM(B8)="","",IF(TRIM(C8)="",0,1)) -> 1 | F8: Non
B9: Nom de la solution | C9: Oracle FLEXCUBE Universal Banking | E9: =IF(TRIM(B9)="","",IF(TRIM(C9)="",0,1)) -> 1 | F9: Non
B10: Quelle est la version/release de l'application ? | C10: Version 14.7 | D10: Version 14.7 | E10: =IF(TRIM(B10)="","",IF(TRIM(C10)="",0,1)) -> 1 | F10: Non
B11: Quelle est la dernière version de l'application ? | C11: Version 14.8 | D11: Version 14.8 | E11: =IF(TRIM(B11)="","",IF(TRIM(C11)="",0,1)) -> 1 | F11: Non
B12: Etes-vous au courant d’une évolution majeure en cours sur cette Application ? | C12: Oui | D12: La version 14.7.0.0.0 d’Oracle FLEXCUBE Universal Banking propose plusieurs améliorations significatives. Voici un aperçu des principales mises à jour : Améliorations : Fonctionnalités Avancées : Intégration de nouvelles fonctionnalités pour améliorer l’efficacité opérationnelle des institutions financières. Amélioration des modules de gestion des comptes, des prêts et des transactions. ==> Interface Utilisateur :Interface utilisateur améliorée pour une meilleure expérience utilisateur. Simplification des processus de navigation et d’utilisation des différentes fonctionnalités du logiciel. ==>Sécurité :Renforcement des mesures de sécurité pour protéger les données sensibles. Mise en conformité avec les dernières réglementations en matière de sécurité bancaire. =>Détails sur les Composants Logiciels : ==>Composants Noyau :Mise à jour des composants noyau pour une performance optimisée. Améliorations dans les processus de traitement des transactions pour une rapidité accrue. ==>Modules Spécifiques :Améliorations dans les modules spécifiques tels que la gestion des risques, les services bancaires numériques et le traitement des paiements. Environnement et Logiciels Tiers : Compatibilité : Compatibilité étendue avec les derniers systèmes d'exploitation et infrastructures matérielles. Intégration facilitée avec les logiciels tiers couramment utilisés dans l’industrie bancaire. Outils de Développement : Inclusion de nouveaux outils de développement pour faciliter la personnalisation et l’extension des fonctionnalités du logiciel. Documentation enrichie pour aider les développeurs et les administrateurs à mieux comprendre et utiliser les nouvelles capacités. | E12: =IF(TRIM(B12)="","",IF(TRIM(C12)="",0,1)) -> 1 | F12: Non
B13: Qui contrôle les évolutions sur cette Application ? | C13: Oracle | D13: les évolutions de l'application Oracle FLEXCUBE Universal Banking sont le fruit d'un effort coordonné entre les équipes internes d'Oracle, les clients, et les partenaires externes, sous la direction et le contrôle principal de l'éditeur Oracle Corporation. | E13: =IF(TRIM(B13)="","",IF(TRIM(C13)="",0,1)) -> 1 | F13: Non
B14: Quelle est la criticité de cette application ? combien de temps peut-on supporter son indisponibilité (colonne détail) ? | C14: Primoridal | D14: Oracle FLEXCUBE Universal Banking a une criticité élevée, et la durée acceptable de son indisponibilité doit être très courte, idéalement limitée à quelques heures au maximum pour éviter des impacts significatifs sur les opérations bancaires et la satisfaction des clients | E14: =IF(TRIM(B14)="","",IF(TRIM(C14)="",0,1)) -> 1 | F14: Non
B15: Quels sont les modules utlisés? | C15: RB/CB/ PY /CL/ LN/ DE | D15: Voici quelques-uns des modules utilisés dans FCUBS : 1. Retail Banking (RB) : Gestion des opérations bancaires de détail, y compris les comptes d'épargne, les prêts personnels, etc. 2. Core Banking (CB) : Gère les fonctions bancaires de base telles que les comptes, les prêts, les dépôts, etc. 3. Payments (PY) : Gestion des opérations de paiement, y compris les virements, les paiements en temps réel, etc. 4. Collections (CL) : Gestion des opérations de recouvrement et de gestion des créances. 5. Lending (LN) : Gestion des opérations de prêt, y compris l'octroi de prêts, la gestion des garanties, etc. 6. Deposits (DE) : Gère les produits de dépôt. | E15: =IF(TRIM(B15)="","",IF(TRIM(C15)="",0,1)) -> 1 | F15: Non
B16: Est-ce que la solution dispose d'un module integré de gestion des documents (mise en page, formatage, impression, …) ? | C16: Non il fait l'objet d'une solution séparée | D16: Oracle FLEXCUBE Universal Banking (FCUBS) est un système de gestion bancaire complet, mais il n'inclut pas nativement de module intégré spécifique pour la gestion des documents tels que la mise en page, le formatage et l'impression. Cependant, FCUBS offre des capacités d'intégration avec d'autres systèmes et peut être personnalisé pour intégrer des solutions tierces qui fournissent ces fonctionnalités. Pour des besoins spécifiques , notre partenaire JMR Infotech a développer une solutions tierces spécialisées OAS. | E16: =IF(TRIM(B16)="","",IF(TRIM(C16)="",0,1)) -> 1 | F16: Non
B17: Est-ce que la solution dispose d'un module de gestion de catalogue de produits ? | C17: Oui | D17: Oui, Oracle FLEXCUBE Universal Banking inclut un module de gestion de catalogue de produits. Ce module permet aux banques de gérer et de proposer une large gamme de produits bancaires, tels que des comptes, des prêts, des cartes, et d'autres services financiers. Il est conçu pour être flexible afin de s'adapter aux besoins spécifiques des institutions financières et de leurs clients. | E17: =IF(TRIM(B17)="","",IF(TRIM(C17)="",0,1)) -> 1 | F17: Non
B18: Est-ce que la solution dispose d'un module de gestion de campagnes ? | C18: Non nous n'en avons pas | D18: Non, Oracle FLEXCUBE Universal Banking 14.4.0.0.0 ne dispose pas d'un module de gestion de campagnes intégré dans sa solution de base. Oracle FLEXCUBE est principalement conçu pour la gestion des opérations bancaires de base telles que les dépôts, les prêts, les paiements et autres services bancaires traditionnels. | E18: =IF(TRIM(B18)="","",IF(TRIM(C18)="",0,1)) -> 1 | F18: Non
B19: Est-ce que la solution dispose d'un module de gestion des notifications (sms, mail, …) ? | C19: Non il fait l'objet d'une solution séparée | D19: Oracle FLEXCUBE Universal Banking ne dispose pas nativement d'un module de gestion des notifications telles que les SMS ou les e-mails. Cependant, il est souvent possible d'intégrer des solutions tierces pour gérer ces fonctionnalités de notification dans le cadre d'une configuration personnalisée ou d'une intégration spécifique avec d'autres systèmes. | E19: =IF(TRIM(B19)="","",IF(TRIM(C19)="",0,1)) -> 1 | F19: j'ai cru comprendre qu'il faisait partie du package Oui, effectivement, je fais allusion au canal que nous utilisons pour envoyer les SMS.
B20: Quand l’application a-t-elle été implémentée ? | C20: 2024 | D20: 45387 | E20: =IF(TRIM(B20)="","",IF(TRIM(C20)="",0,1)) -> 1 | F20: Non
B21: Qui l'a implémenté? | C21: JMR Infotech | E21: =IF(TRIM(B21)="","",IF(TRIM(C21)="",0,1)) -> 1 | F21: Non
B22: Quels sont les processus fonctionnels couverts ? | C22: Caisse, Compte, Client, Credit, virement, Dat,Comptabilité | E22: =IF(TRIM(B22)="","",IF(TRIM(C22)="",0,1)) -> 1 | F22: Non
B23: Quel est le niveau de personnalisation de l’Application ? | C23: Moyen | E23: =IF(TRIM(B23)="","",IF(TRIM(C23)="",0,1)) -> 1 | F23: Détails
B24: Quelle(s) technologie(s) sous-jacente(s) ? | C24: VOIR IT GROUPE | E24: =IF(TRIM(B24)="","",IF(TRIM(C24)="",0,1)) -> 1 | F24: Non
B25: Est-ce que cette solution dispose d'une interface Mobile? | C25: Oui | D25: Mais il ne répond pas à nos besoins spécifiques. C'est pourquoi nous avons décidé d'opter pour une autre solution, qui consiste à interfacer Flexcube Developer avec un éditeur différent. | E25: =IF(TRIM(B25)="","",IF(TRIM(C25)="",0,1)) -> 1 | F25: Non
B26: =IF(C25="Oui","Si oui, dispose-t-elle d'une version smartphone ou tablette ou les 2 ?","") -> Si oui, dispose-t-elle d'une version smartphone ou tablette ou les 2 ? | C26: Les 2 | E26: =IF(TRIM(B26)="","",IF(TRIM(C26)="",0,1)) -> 1
B27: Est-ce qu'il est prévu de remplacer cette solution par une autre? Si oui, veuillez mettre le nom de la nouvelle solution et la période prévue dans la colonne détails | C27: Non | E27: =IF(TRIM(B27)="","",IF(TRIM(C27)="",0,1)) -> 1 | F27: Non
B28: Quel est le nombre d’utilisateurs finaux de cette application ? | C28: 1000 pour tout le groupe | E28: =IF(TRIM(B28)="","",IF(TRIM(C28)="",0,1)) -> 1 | F28: Non
B29: Y a-t-il des utilisateurs du Groupe sur les activités de la filiale ? | C29: Oui | D29: oui, le Groupe inclut plusieurs utilisateurs impliqués dans les activités de la filiale. Nous avons des contrôleurs et des auditeurs du Groupe qui interviennent dans le système pour effectuer un contrôle de deuxième niveau sur les activités de la filiale. De plus, le Responsable Crédit du Groupe est chargé de la validation de certains crédits dépassant des montants spécifiques. | E29: =IF(TRIM(B29)="","",IF(TRIM(C29)="",0,1)) -> 1 | F29: Quelles sont les activités qu'ils font?
B30: =IF(C29="Oui","Quel est le ratio ?","") -> Quel est le ratio ? | C30: VOIR IT GROUPE | E30: =IF(TRIM(B30)="","",IF(TRIM(C30)="",0,1)) -> 1 | F30: Non
B31: Quels ont été les acquisitions de licences détaillées (nombre, date, coût) ? | C31: VOIR IT GROUPE | E31: =IF(TRIM(B31)="","",IF(TRIM(C31)="",0,1)) -> 1 | F31: Non
B32: Quel est le nombre actuel de licences détenues par la filiale? | C32: VOIR IT GROUPE | E32: =IF(TRIM(B32)="","",IF(TRIM(C32)="",0,1)) -> 1 | F32: Non
B33: Quel type de licences (nominatives/partagées) ? | C33: Nominatives | E33: =IF(TRIM(B33)="","",IF(TRIM(C33)="",0,1)) -> 1 | F33: Non
B34: Des licences supplémentaires sont-elles nécessaires pour l'utilisation de l'application (outil supplémentaire, interfaces, modules complémentaires, …) ? Par module / par utilisateur ? | C34: VOIR IT GROUPE | E34: =IF(TRIM(B34)="","",IF(TRIM(C34)="",0,1)) -> 1 | F34: Non
B35: Quel est le coût du support éditeur ? | C35: VOIR IT GROUPE | E35: =IF(TRIM(B35)="","",IF(TRIM(C35)="",0,1)) -> 1 | F35: Non
B36: Existe-t-il un contrat de support avec un fournisseur ou un partenaire ? Pouvez-vous le partager? | C36: Oui | E36: =IF(TRIM(B36)="","",IF(TRIM(C36)="",0,1)) -> 1 | F36: Non
B37: Le contrat est-il global couvrant plusieurs filiales ou dédié à la filiale ? | C37: Dédié | D37: Global | E37: =IF(TRIM(B37)="","",IF(TRIM(C37)="",0,1)) -> 1 | F37: Non
B38: Le contrat comprend-il un SLA formel ? Cela inclut-il un engagement de performance ? | C38: Oui et non | D38: Non pour les 2 | E38: =IF(TRIM(B38)="","",IF(TRIM(C38)="",0,1)) -> 1 | F38: Non
B39: Combien de ETP internes sont dédiés aux support (Niveaux 1, 2 et 3) de cette solution? Veuillez décrire dans la colonne détail de quelle entité sont-ils (Holding ou pays), la répartition des principales activités, les compétences et les rôles | C39: 1. Niveau 1 : o Nombre d'ETP : 4 o Répartition des Activités : Résolution des tickets de premier niveau, support de base aux utilisateurs, gestion des demandes simples et Analyse des incidents 2. Niveau 2 : o Nombre d'ETP : 5 o Entité : Holding o Répartition des Activités : Analyse des incidents plus complexes, gestion des escalades du niveau 1, résolution de problèmes techniques avancés. o Compétences : Expertise technique, capacité à résoudre des problèmes complexes. o Rôles : Technicien Support Niveau 2 3. Niveau 3 : o Nombre d'ETP : DEFINIR o Entité : PROVIDER o Répartition des Activités : Gestion des problèmes critiques, développement de solutions, coordination avec les équipes de développement. o Compétences : Expertise approfondie, compétences en développement et en gestion des incidents majeurs. o Rôles : Ingénieur Support Niveau 3 | D39: Niveau 1: Holding : ETP dédiés : 5 Niveau 2 : Filiale : ETP dédiés : 4 Niveau 3 : Nombre d'ETP : DEFINIR par IT GROUPE | E39: =IF(TRIM(B39)="","",IF(TRIM(C39)="",0,1)) -> 1 | F39: Combien d'ETP?
B40: Combien de ETP internes sont dédiés aux changements opérés sur cette solution (incluant Dev, Config, Mise en prod)? Veuillez décrire dans la colonne détail de quelle entité sont-ils (Holding ou pays), la répartition des principales activités, les compétences et les rôles | C40: Holding : ETP dédiés : 5 Filiale : ETP dédiés : 1 | D40: Holding : ETP dédiés : 5 Filiale : ETP dédiés : 1 | E40: =IF(TRIM(B40)="","",IF(TRIM(C40)="",0,1)) -> 1 | F40: Combien d'ETP?
B41: Qui administre cette solution et apporte le support aux utilisateurs l'IT Groupe, l'IT local ou les 2 ? | C41: Les 2 | D41: équipe IT locale se concentre principalement sur les aspects applicatifs et les opérations quotidiennes liées aux applications, tandis que l'équipe ITgroupe est responsable de la gestion et de l'administration des bases de données. | E41: =IF(TRIM(B41)="","",IF(TRIM(C41)="",0,1)) -> 1 | F41: Qui fait quoi?
B42: =IF(C41="Les 2","A quelle proportion chacun ? et existe-t-il un SLA interne entre Group IT et la filiale ? S'il existe, pouvez-vous le partager vous pouvez décrire dans la partie détails les responsabilités de chaque partie","") -> A quelle proportion chacun ? et existe-t-il un SLA interne entre Group IT et la filiale ? S'il existe, pouvez-vous le partager vous pouvez décrire dans la partie détails les responsabilités de chaque partie | C42: Non | E42: =IF(TRIM(B42)="","",IF(TRIM(C42)="",0,1)) -> 1 | F42: Non
B43: Avez-vous un historique des KPI pour la disponibilité et le support de cette application ? Si oui, pouvez-vous les partager | C43: Non | E43: =IF(TRIM(B43)="","",IF(TRIM(C43)="",0,1)) -> 1 | F43: Non
B44: Existe-t-il un processus de suivi des contrats groupe et tiers ? | C44: Non | E44: =IF(TRIM(B44)="","",IF(TRIM(C44)="",0,1)) -> 1 | F44: Non
B45: L'application est-elle installée sur site ou utilisée sur le Cloud (SaaS) ? | C45: On-site | D45: les serveurs de Cofina TOGO sont hébergés au niveau des datacenters de MTN Côte d'Ivoire et Free Sénégal | E45: =IF(TRIM(B45)="","",IF(TRIM(C45)="",0,1)) -> 1 | F45: Non
B46: =IF(C45="Cloud","Si c'est sur le Cloud, est-ce entièrement SaaS ou Infra gérée par l'équipe locale ?","") | E46: =IF(TRIM(B46)="","",IF(TRIM(C46)="",0,1)) | F46: Non
B47: S'agit-il d'une architecture Client/Serveur à 3 niveaux ? Décrivez s'il vous plait | C47: Non | E47: =IF(TRIM(B47)="","",IF(TRIM(C47)="",0,1)) -> 1 | F47: Est-ce que le middleware est utilisé pour les intégrations? Si oui, au CBS uniquement ou de façon plus globale?
B48: =IF(C45="On-site","Comment sont acquis les serveurs (achat/location/sous-traitance) ?","") -> Comment sont acquis les serveurs (achat/location/sous-traitance) ? | C48: Achat | E48: =IF(TRIM(B48)="","",IF(TRIM(C48)="",0,1)) -> 1
B49: Où sont installés les serveurs ? | C49: MTN CIV | E49: =IF(TRIM(B49)="","",IF(TRIM(C49)="",0,1)) -> 1 | F49: Non
B50: Sur quels systèmes (versions) cette application s'exécute-t-elle ? | C50: Oracle Lunix 8.9 | E50: =IF(TRIM(B50)="","",IF(TRIM(C50)="",0,1)) -> 1 | F50: Non
B51: Sur quelle base de données cette application tourne-t-elle ? | C51: ORACLE 19C | E51: =IF(TRIM(B51)="","",IF(TRIM(C51)="",0,1)) -> 1 | F51: Non
B52: Existe-t-il une architecture haute disponibilité (réplication) ? | C52: Non | E52: =IF(TRIM(B52)="","",IF(TRIM(C52)="",0,1)) -> 1 | F52: Est-on sûr?
B53: =IF(C52="Oui","Entièrement ou partiellement ? Actif-Actif ou Actif-Passif ?","") | C53: ACTIF-PASSIF | E53: =IF(TRIM(B53)="","",IF(TRIM(C53)="",0,1)) | F53: Non
B54: Existe-t-il un plan de récupération pour cette application ? | C54: Oui | E54: =IF(TRIM(B54)="","",IF(TRIM(C54)="",0,1)) -> 1 | F54: Pouvez-vous le partager?
B55: Qui gère les données de la base de données ? | C55: IT GROUPE/ LOCAL | E55: =IF(TRIM(B55)="","",IF(TRIM(C55)="",0,1)) -> 1 | F55: Non
B56: Quelles sont les interfaces existantes de cette application ? Veuillez décrire et partager tout document d'architecture | C56: VOIR IT GROUPE | D56: COFINA MOBILE +, KIWI, REIS, CARTAGO | E56: =IF(TRIM(B56)="","",IF(TRIM(C56)="",0,1)) -> 1 | F56: Avec quel SI?
B57: L'application est-elle complètement en temps réel ou y'a-t-il des batchs la nuit ? Décrivez s'il vous plait | C57: Temps réel | E57: =IF(TRIM(B57)="","",IF(TRIM(C57)="",0,1)) -> 1 | F57: Non
B58: Avez-vous connaissance d'un quelconque problème potentiel lié à la continuité de cette application (par exemple départ ou indisponibilité des ressources clés, fin de support, bug critique, ...), si oui lequel dans détails? | C58: Non | E58: =IF(TRIM(B58)="","",IF(TRIM(C58)="",0,1)) -> 1 | F58: Non
B59: Est-ce que des sauvegardes sont réalisées régulièrement? | C59: Oui | D59: NON | E59: =IF(TRIM(B59)="","",IF(TRIM(C59)="",0,1)) -> 1 | F59: Non
B60: =IF(C59="Oui","A quelle fréquence sont-elles exécutées?","") -> A quelle fréquence sont-elles exécutées? | C60: journaliere | E60: =IF(TRIM(B60)="","",IF(TRIM(C60)="",0,1)) -> 1 | F60: S'il y a un crash en fin de journée, on perd toutes les transactions de la journée? oui
B61: =IF(C59="Oui","Avez-vous une politique de rétention en place ? Si oui, pouvez-vous me la partager?","") -> Avez-vous une politique de rétention en place ? Si oui, pouvez-vous me la partager? | C61: Oui | D61: NON | E61: =IF(TRIM(B61)="","",IF(TRIM(C61)="",0,1)) -> 1
B62: =IF(C59="Oui","Quelle est la solution de sauvegarde/récupération utilisée ?","") -> Quelle est la solution de sauvegarde/récupération utilisée ? | C62: RMAN | E62: =IF(TRIM(B62)="","",IF(TRIM(C62)="",0,1)) -> 1
B63: =IF(C59="Oui","Quelle est la taille totale estimée des sauvegardes ?","") -> Quelle est la taille totale estimée des sauvegardes ? | C63: 300 Gigas | D63: actuellement, nous ne réalisons pas de sauvegardes avant et après les traitements du batcht pour la filiale du Togo. | E63: =IF(TRIM(B63)="","",IF(TRIM(C63)="",0,1)) -> 1
A123: Combien de ces demandes surviennent en moyenne par an ?

Sheet LOS
A1: Retour à la page d'accueil
B2: Loan Origination System - Système de Gestion des Credits | C2: Oui existant
B3: Veuillez répondre à toutes les questions et donner plus de détails (colonne D) lorsque nécessaire, un taux de remplissage est calculé dans le sommaire et devrait être à 100%
B4: Certaines questions peuvent en faire apparaitre de nouvelles auxquelles il faudra répondre, cela entre également dans le calcul du taux de remplissage
B6: Questions | C6: Réponses | D6: Détails | E6: Eval | F6: Complément
B7: =IF(C2="Oui existant","COTS ou Développement interne? (Commercial Off-The-Shelf solution)","Vous prévoyez quel type de solution?: COTS ou Développement interne? (Commercial Off-The-Shelf solution)") -> COTS ou Développement interne? (Commercial Off-The-Shelf solution) | C7: Développement externalisé | E7: =IF(TRIM(B7)="","",IF(TRIM(C7)="",0,1)) -> 1 | F7: Non
B8: =IF(C7="COTS","Nom de l'éditeur","") | C8: EDAN | E8: =IF(TRIM(B8)="","",IF(TRIM(C8)="",0,1)) | F8: Non
B9: =IF(C2="Oui existant","Nom de la solution",IF(AND(C7<>"Non prévu",C7<>""),"Nom de la solution (si déjà identifiée)","")) -> Nom de la solution | C9: CREDITFLOW | D9: Fonctionnalités principales : Gestion des demandes de crédit, Évaluation du crédit et Décision de crédit | E9: =IF(TRIM(B9)="","",IF(TRIM(C9)="",0,1)) -> 1 | F9: Non
B10: =IF(C2="Oui existant","Quelle est la version/release de l'application ?",IF(C7="COTS","Quelle est la version/release qui sera implémentée ?","")) -> Quelle est la version/release de l'application ? | C10: 1.0 | E10: =IF(TRIM(B10)="","",IF(TRIM(C10)="",0,1)) -> 1 | F10: Non
B11: =IF(C2="Oui existant","Quelle est la dernière version de l'application ?",IF(C7="COTS","Quelle est la dernière version de cette nouvelle solution ?","")) -> Quelle est la dernière version de l'application ? | C11: 1.0 | E11: =IF(TRIM(B11)="","",IF(TRIM(C11)="",0,1)) -> 1 | F11: Non
B12: =IF(C2="Oui existant","Etes-vous au courant d’une évolution majeure en cours sur cette application","") -> Etes-vous au courant d’une évolution majeure en cours sur cette application | C12: Non | E12: =IF(TRIM(B12)="","",IF(TRIM(C12)="",0,1)) -> 1 | F12: Non
B13: =IF(C2="Oui existant","Qui contrôle les évolutions sur cette Application ?","") -> Qui contrôle les évolutions sur cette Application ? | C13: COFINA | E13: =IF(TRIM(B13)="","",IF(TRIM(C13)="",0,1)) -> 1 | F13: Non
B14: =IF(C2="Oui existant","Quelle est la criticité de cette application ? combien de temps peut-on supporter son indisponibilité (colonne détail) ?","Quelle est la criticité de ce besoin ?") -> Quelle est la criticité de cette application ? combien de temps peut-on supporter son indisponibilité (colonne détail) ? | C14: Moyen | E14: =IF(TRIM(B14)="","",IF(TRIM(C14)="",0,1)) -> 1 | F14: Non
B15: =IF(C7="COTS","Est-ce un module du CBS ou une solution séparée?","") | E15: =IF(TRIM(B15)="","",IF(TRIM(C15)="",0,1)) | F15: Non
B16: =IF(C2="Oui existant","Quand l’application a-t-elle été implémentée ?",IF(AND(C7<>"Non prévu",C7<>""),"Quand l’application sera-t-elle implémentée ?","")) -> Quand l’application a-t-elle été implémentée ? | C16: 2024 | D16: PLUS DE 4 MOIS | E16: =IF(TRIM(B16)="","",IF(TRIM(C16)="",0,1)) -> 1 | F16: Non
B17: =IF(C2="Oui existant","Qui l'a implémenté ?",IF(AND(C7<>"Non prévu",C7<>""),"Qui doit l'implémenter ?","")) -> Qui l'a implémenté ? | C17: EDAN | E17: =IF(TRIM(B17)="","",IF(TRIM(C17)="",0,1)) -> 1 | F17: Non
B18: =IF(C2="Oui existant","Quels sont les processus fonctionnels couverts ?",IF(AND(C7<>"Non prévu",C7<>""),"Quels sont les processus fonctionnels qui doivent être couverts ?","")) -> Quels sont les processus fonctionnels couverts ? | C18: Fonctionnalités principales : Gestion des demandes de crédit, Évaluation du crédit et Décision de crédit | E18: =IF(TRIM(B18)="","",IF(TRIM(C18)="",0,1)) -> 1 | F18: Non
B19: =IF(C2="Oui existant","Est-ce que la solution est integrée au CBS ?",IF(AND(C7<>"Non prévu",C7<>""),"Est-ce que la solution sera integrée au CBS ?","")) -> Est-ce que la solution est integrée au CBS ? | C19: Non | E19: =IF(TRIM(B19)="","",IF(TRIM(C19)="",0,1)) -> 1 | F19: Non
B20: =IF(C19="Oui",IF(C2="Oui existant","Comment et quels sont les processus et données qui transitent ?",IF(AND(C7<>"Non prévu",C7<>""),"Comment et quels seront les processus et données qui vont transiter ?","")),"") | E20: =IF(TRIM(B20)="","",IF(TRIM(C20)="",0,1)) | F20: Non
B21: =IF(C2="Oui existant","Quel est le niveau de personnalisation de l’Application ?",IF(C7="COTS","Quel est le niveau de personnalisation prévu de l’Application ?","")) -> Quel est le niveau de personnalisation de l’Application ? | C21: Moyen | E21: =IF(TRIM(B21)="","",IF(TRIM(C21)="",0,1)) -> 1 | F21: Non
B22: =IF(C2="Oui existant","Quelle(s) technologie(s) sous-jacente(s) ?","") -> Quelle(s) technologie(s) sous-jacente(s) ? | C22: NA | E22: =IF(TRIM(B22)="","",IF(TRIM(C22)="",0,1)) -> 1 | F22: Non
B23: =IF(C2="Oui existant","Est-ce que cette solution dispose d'une interface Mobile?",IF(AND(C7<>"Non prévu",C7<>""),"Est-ce qu'il est prévu une version Mobile ?","")) -> Est-ce que cette solution dispose d'une interface Mobile? | C23: Non | E23: =IF(TRIM(B23)="","",IF(TRIM(C23)="",0,1)) -> 1 | F23: Non
B24: =IF(AND(C7<>"Non prévu",C7<>""),IF(C23="Oui","Dispose-t-elle d'une version smartphone ou tablette ou les 2 ?",""),"") | E24: =IF(TRIM(B24)="","",IF(TRIM(C24)="",0,1)) | F24: Non
B25: =IF(C2="Oui existant","Est-ce qu'il est prévu de remplacer cette solution par une autre ? Si oui, veuillez mettre le nom de la nouvelle solution et la période prévue dans la colonne détails","") -> Est-ce qu'il est prévu de remplacer cette solution par une autre ? Si oui, veuillez mettre le nom de la nouvelle solution et la période prévue dans la colonne détails | C25: Non | D25: faire la refonte de celle-ci | E25: =IF(TRIM(B25)="","",IF(TRIM(C25)="",0,1)) -> 1 | F25: Si, la reflexion est là, remplacer ou faire la refonte de celle-ci
B26: =IF(C2="Oui existant","Quel est le nombre d’utilisateurs finaux de cette application ?",IF(AND(C7<>"Non prévu",C7<>""),"Quel est le nombre d’utilisateurs finaux prévus pour cette application ?","")) -> Quel est le nombre d’utilisateurs finaux de cette application ? | C26: environ 50 | E26: =IF(TRIM(B26)="","",IF(TRIM(C26)="",0,1)) -> 1 | F26: On peut le savoir au nombre d'utilisateurs
B27: =IF(C2="Oui existant","Y a-t-il des utilisateurs du Groupe sur les activités de la filiale ?","") -> Y a-t-il des utilisateurs du Groupe sur les activités de la filiale ? | C27: Oui | E27: =IF(TRIM(B27)="","",IF(TRIM(C27)="",0,1)) -> 1 | F27: Non
B28: =IF(C27="Oui","Quel est le ratio ?","") -> Quel est le ratio ? | C28: non | E28: =IF(TRIM(B28)="","",IF(TRIM(C28)="",0,1)) -> 1 | F28: Non
B29: =IF(C2="Oui existant","Quels ont été les acquisitions de licences détaillées (nombre, date, coût) ?","") -> Quels ont été les acquisitions de licences détaillées (nombre, date, coût) ? | C29: VOIR IT GROUPE | E29: =IF(TRIM(B29)="","",IF(TRIM(C29)="",0,1)) -> 1 | F29: Non
B30: =IF(C2="Oui existant","Quel est le nombre actuel de licences détenues par la filiale?",IF(C7="COTS","Combien de licences projettez-vous d'acquérir ?","")) -> Quel est le nombre actuel de licences détenues par la filiale? | C30: VOIR IT GROUPE | E30: =IF(TRIM(B30)="","",IF(TRIM(C30)="",0,1)) -> 1 | F30: Non
B31: =IF(C2="Oui existant","Quel type de licences (nominatives/partagées) ?",IF(C7="COTS","Est-ce que ce sera des licences nominatives ou partagées ?","")) -> Quel type de licences (nominatives/partagées) ? | C31: VOIR IT GROUPE | E31: =IF(TRIM(B31)="","",IF(TRIM(C31)="",0,1)) -> 1 | F31: Non
B32: =IF(C2="Oui existant","Des licences supplémentaires sont-elles nécessaires pour l'utilisation de l'application (outil supplémentaire, interfaces, modules complémentaires, …) ? Par module / par utilisateur ?",IF(C7="COTS","Est-ce que vous projettez d'acquérir d'autres licences dans un second temps ? combien et quand ?","")) -> Des licences supplémentaires sont-elles nécessaires pour l'utilisation de l'application (outil supplémentaire, interfaces, modules complémentaires, …) ? Par module / par utilisateur ? | C32: VOIR IT GROUPE | D32: VOIR IT GROUPE | E32: =IF(TRIM(B32)="","",IF(TRIM(C32)="",0,1)) -> 1 | F32: Non
B33: =IF(C2="Oui existant","Quel est le coût du support éditeur ?",IF(C7="COTS","Quel sera le coût du support éditeur ?","")) -> Quel est le coût du support éditeur ? | C33: VOIR IT GROUPE | E33: =IF(TRIM(B33)="","",IF(TRIM(C33)="",0,1)) -> 1 | F33: Non
B34: =IF(C2="Oui existant","Existe-t-il un contrat de support avec un fournisseur ou un partenaire ? Pouvez-vous le partager ?","") -> Existe-t-il un contrat de support avec un fournisseur ou un partenaire ? Pouvez-vous le partager ? | C34: Non | E34: =IF(TRIM(B34)="","",IF(TRIM(C34)="",0,1)) -> 1 | F34: Détails
B35: =IF(C2="Oui existant","Le contrat est-il global couvrant plusieurs filiales ou dédié à la filiale ?",IF(C7="COTS","Projettez-vous une acquisition individuelle ou groupe ?","")) -> Le contrat est-il global couvrant plusieurs filiales ou dédié à la filiale ? | C35: Global | E35: =IF(TRIM(B35)="","",IF(TRIM(C35)="",0,1)) -> 1 | F35: Non
B36: =IF(C2="Oui existant","Le contrat comprend-il un SLA formel ? Cela inclut-il un engagement de performance ?","") -> Le contrat comprend-il un SLA formel ? Cela inclut-il un engagement de performance ? | C36: Non pour les 2 | E36: =IF(TRIM(B36)="","",IF(TRIM(C36)="",0,1)) -> 1 | F36: Pourquoi?
B37: =IF(C2="Oui existant","Combien de ETP internes sont dédiés aux support (Niveaux 1, 2 et 3) de cette solution ? Veuillez décrire dans la colonne détail de quelle entité sont-ils (Holding ou pays), la répartition des principales activités, les compétences et les rôles",IF(AND(C7<>"Non prévu",C7<>""),"Combien de ETP internes projettez-vous de dédier aux support (Niveaux 1, 2 et 3) de cette solution ?","")) -> Combien de ETP internes sont dédiés aux support (Niveaux 1, 2 et 3) de cette solution ? Veuillez décrire dans la colonne détail de quelle entité sont-ils (Holding ou pays), la répartition des principales activités, les compétences et les rôles | C37: 1. Niveau 1 : o Nombre d'ETP : 3 o Répartition des Activités : Résolution des tickets de premier niveau, support de base aux utilisateurs, gestion des demandes simples et Analyse des incidents 2. Niveau 2 : o Nombre d'ETP : A DEFINIR o Entité : Holding o Répartition des Activités : Analyse des incidents plus complexes, gestion des escalades du niveau 1, résolution de problèmes techniques avancés. o Compétences : Expertise technique, capacité à résoudre des problèmes complexes. o Rôles : Technicien Support Niveau 2 3. Niveau 3 : o Nombre d'ETP : DEFINIR par IT GROUPE o Entité : PROVIDER o Répartition des Activités : Gestion des problèmes critiques, développement de solutions, coordination avec les équipes de développement. o Compétences : Expertise approfondie, compétences en développement et en gestion des incidents majeurs. o Rôles : Ingénieur Support Niveau 3 | D37: Niveau 1: Holding : ETP dédiés : 0 Niveau 2 : Filiale : ETP dédiés : 3 Niveau 2- 3 : Nombre d'ETP : A DEFINIR Par EDAN | E37: =IF(TRIM(B37)="","",IF(TRIM(C37)="",0,1)) -> 1 | F37: Vous n'intervenez pas dans le support?
B38: =IF(C2="Oui existant","Combien de ETP internes sont dédiés aux changes opérés sur cette solution (incluant Dev, Config, Mise en prod) ? Veuillez décrire dans la col. détail de quelle entité sont-ils (Holding ou pays), la répartition des activités, les compétences et les rôles",IF(AND(C7<>"Non prévu",C7<>""),"Combien de ETP internes projettez-vous de dédier aux futurs changes sur cette solution (incluant Dev, Config, Mise en prod) ?","")) -> Combien de ETP internes sont dédiés aux changes opérés sur cette solution (incluant Dev, Config, Mise en prod) ? Veuillez décrire dans la col. détail de quelle entité sont-ils (Holding ou pays), la répartition des activités, les compétences et les rôles | C38: Holding : ETP dédiés : 0 Filiale : ETP dédiés : 0 | D38: Holding : ETP dédiés : 0 Filiale : ETP dédiés : 0 | E38: =IF(TRIM(B38)="","",IF(TRIM(C38)="",0,1)) -> 1 | F38: Vous n'intervenez pas dans les changements?
B39: =IF(C2="Oui existant","Qui administre cette solution et apporte le support aux utilisateurs l'IT Groupe, l'IT local ou les 2 ?",IF(AND(C7<>"Non prévu",C7<>""),"Qui va administrer cette solution et apporter le support aux utilisateurs: l'IT Groupe, l'IT local ou les 2 ?","")) -> Qui administre cette solution et apporte le support aux utilisateurs l'IT Groupe, l'IT local ou les 2 ? | C39: IT Groupe | D39: NON | E39: =IF(TRIM(B39)="","",IF(TRIM(C39)="",0,1)) -> 1 | F39: Vous n'intervenez pas dans le support?
B40: =IF(C39="Les 2","A quelle proportion chacun ? et existe-t-il un SLA interne entre Group IT et la filiale ? S'il existe, pouvez-vous le partager vous pouvez décrire dans la partie détails les responsabilités de chaque partie","") | E40: =IF(TRIM(B40)="","",IF(TRIM(C40)="",0,1))
B41: =IF(C2="Oui existant","Avez-vous un historique des KPI pour la disponibilité et le support de cette application ? Si oui, pouvez-vous les partager","") -> Avez-vous un historique des KPI pour la disponibilité et le support de cette application ? Si oui, pouvez-vous les partager | C41: Non | E41: =IF(TRIM(B41)="","",IF(TRIM(C41)="",0,1)) -> 1 | F41: Vous devez l'exiger à EDAN
B42: =IF(C2="Oui existant","Existe-t-il un processus de suivi des contrats groupe et tiers ?","") -> Existe-t-il un processus de suivi des contrats groupe et tiers ? | C42: Non | E42: =IF(TRIM(B42)="","",IF(TRIM(C42)="",0,1)) -> 1 | F42: Non
B43: =IF(C2="Oui existant","L'application est-elle installée sur site ou utilisée sur le Cloud (SaaS) ?",IF(AND(C7<>"Non prévu",C7<>""),"La nouvelle solution sera-t-elle installée sur site ou utilisée sur le Cloud (SaaS) ?","")) -> L'application est-elle installée sur site ou utilisée sur le Cloud (SaaS) ? | C43: Cloud | D43: nous n'avons pas suffisamment d'informations pour répondre à votre question | E43: =IF(TRIM(B43)="","",IF(TRIM(C43)="",0,1)) -> 1 | F43: Lequel?
B44: =IF(AND(C43="Cloud",C7="COTS"),"Est-ce entièrement SaaS ou Infra gérée par l'équipe locale ?","") | C44: SaaS | E44: =IF(TRIM(B44)="","",IF(TRIM(C44)="",0,1))
B45: =IF(C2="Oui existant","S'agit-il d'une architecture Client/Serveur à 3 niveaux ? Décrivez s'il vous plait","") -> S'agit-il d'une architecture Client/Serveur à 3 niveaux ? Décrivez s'il vous plait | C45: Non | D45: nous n'avons pas suffisamment d'informations pour répondre à votre question | E45: =IF(TRIM(B45)="","",IF(TRIM(C45)="",0,1)) -> 1 | F45: Non
B46: =IF(C43="On-site","Comment sont acquis les serveurs (achat/location/sous-traitance) ?","") | E46: =IF(TRIM(B46)="","",IF(TRIM(C46)="",0,1))
B47: =IF(C2="Oui existant","Où sont installés les serveurs ?","") -> Où sont installés les serveurs ? | C47: nous n'avons pas suffisamment d'informations pour répondre à votre question | E47: =IF(TRIM(B47)="","",IF(TRIM(C47)="",0,1)) -> 1 | F47: Vous devez le savoir
B48: =IF(C2="Oui existant","Sur quels systèmes (versions) cette application s'exécute-t-elle ?",IF(AND(C7<>"Non prévu",C7<>""),"Sur quels systèmes (versions) cette application sera-t-elle implémentée ?","")) -> Sur quels systèmes (versions) cette application s'exécute-t-elle ? | C48: nous n'avons pas suffisamment d'informations pour répondre à votre question | E48: =IF(TRIM(B48)="","",IF(TRIM(C48)="",0,1)) -> 1 | F48: Vous devez le savoir
B49: =IF(C2="Oui existant","Sur quelle base de données cette application tourne-t-elle ?",IF(AND(C7<>"Non prévu",C7<>""),"Sur quelle base de données cette application tournera-t-elle ?","")) -> Sur quelle base de données cette application tourne-t-elle ? | C49: nous n'avons pas suffisamment d'informations pour répondre à votre question | E49: =IF(TRIM(B49)="","",IF(TRIM(C49)="",0,1)) -> 1 | F49: Vous devez le savoir
B50: =IF(C2="Oui existant","Existe-t-il une architecture haute disponibilité (réplication) ?",IF(AND(C7<>"Non prévu",C7<>""),"Est-ce qu'il est prévu une architecture haute disponibilité (réplication) ?","")) -> Existe-t-il une architecture haute disponibilité (réplication) ? | C50: Non | D50: nous n'avons pas suffisamment d'informations pour répondre à votre question | E50: =IF(TRIM(B50)="","",IF(TRIM(C50)="",0,1)) -> 1 | F50: Non
B51: =IF(C50="Oui","Entièrement ou partiellement ? Actif-Actif ou Actif-Passif ?","") | E51: =IF(TRIM(B51)="","",IF(TRIM(C51)="",0,1))
B52: =IF(C2="Oui existant","Existe-t-il un plan de récupération pour cette application ?","") -> Existe-t-il un plan de récupération pour cette application ? | C52: Non | D52: nous n'avons pas suffisamment d'informations pour répondre à votre question | E52: =IF(TRIM(B52)="","",IF(TRIM(C52)="",0,1)) -> 1 | F52: Vous devez l'exiger à EDAN
B53: =IF(C2="Oui existant","Qui gère les données de la base de données ?",IF(AND(C7<>"Non prévu",C7<>""),"Qui va gèrer les données de la base de données ?","")) -> Qui gère les données de la base de données ? | C53: EDAN | D53: nous n'avons pas suffisamment d'informations pour répondre à votre question | E53: =IF(TRIM(B53)="","",IF(TRIM(C53)="",0,1)) -> 1 | F53: Non
B54: =IF(C2="Oui existant","Quelles sont les interfaces existantes de cette application ? Veuillez décrire et partager tout document d'architecture",IF(AND(C7<>"Non prévu",C7<>""),"Quelles sont les interfaces prévues ? Veuillez décrire et partager tout document d'architecture cible","")) -> Quelles sont les interfaces existantes de cette application ? Veuillez décrire et partager tout document d'architecture | C54: nous n'avons pas suffisamment d'informations pour répondre à votre question | D54: nous n'avons pas suffisamment d'informations pour répondre à votre question | E54: =IF(TRIM(B54)="","",IF(TRIM(C54)="",0,1)) -> 1 | F54: Non
B55: =IF(C2="Oui existant","L'application est-elle complètement en temps réel ou y'a-t-il des batchs la nuit ? Décrivez s'il vous plait",IF(AND(C7<>"Non prévu",C7<>""),"L'application sera-t-elle complètement en temps réel ou y'aura-t-il des batchs la nuit ? Décrivez s'il vous plait","")) -> L'application est-elle complètement en temps réel ou y'a-t-il des batchs la nuit ? Décrivez s'il vous plait | C55: nous n'avons pas suffisamment d'informations pour répondre à votre question | D55: nous n'avons pas suffisamment d'informations pour répondre à votre question | E55: =IF(TRIM(B55)="","",IF(TRIM(C55)="",0,1)) -> 1 | F55: Non
B56: =IF(C2="Oui existant","Avez-vous connaissance d'un quelconque problème potentiel lié à la continuité de cette application (par exemple départ ou indisponibilité des ressources clés, fin de support, bug critique, ...), si oui lequel dans détails ?","") -> Avez-vous connaissance d'un quelconque problème potentiel lié à la continuité de cette application (par exemple départ ou indisponibilité des ressources clés, fin de support, bug critique, ...), si oui lequel dans détails ? | C56: Oui | D56: Lenteur dans l'exploitation essentiellement, exigence élévée en utilisation de la bande passante | E56: =IF(TRIM(B56)="","",IF(TRIM(C56)="",0,1)) -> 1 | F56: Non
B57: =IF(C2="Oui existant","Est-ce que des sauvegardes sont réalisées régulièrement ?",IF(AND(C7<>"Non prévu",C7<>""),"Est-ce que des sauvegardes sont prévus dès l'implémentation ?","")) -> Est-ce que des sauvegardes sont réalisées régulièrement ? | C57: Non | E57: =IF(TRIM(B57)="","",IF(TRIM(C57)="",0,1)) -> 1 | F57: Vous devez l'exiger à EDAN
B58: =IF(C57="Oui","A quelle fréquence sont-elles exécutées?","") | E58: =IF(TRIM(B58)="","",IF(TRIM(C58)="",0,1))
B59: =IF(C57="Oui","Avez-vous une politique de rétention en place ? Si oui, pouvez-vous me la partager?","") | E59: =IF(TRIM(B59)="","",IF(TRIM(C59)="",0,1))
B60: =IF(C57="Oui","Quelle est la solution de sauvegarde/récupération utilisée ?","") | E60: =IF(TRIM(B60)="","",IF(TRIM(C60)="",0,1))
B61: =IF(C57="Oui","Quelle est la taille totale estimée des sauvegardes ?","") | E61: =IF(TRIM(B61)="","",IF(TRIM(C61)="",0,1))
A123: Combien de ces demandes surviennent en moyenne par an ?

Sheet AB
A1: Retour à la page d'accueil | C1: Réponse corrigé à partir du fichier CTI
B2: Agency Banking - Système de Gestion des Agences | C2: Oui existant
B3: Veuillez répondre à toutes les questions et donner plus de détails (colonne D) lorsque nécessaire, un taux de remplissage est calculé dans le sommaire et devrait être à 100%
B4: Certaines questions peuvent en faire apparaitre de nouvelles auxquelles il faudra répondre, cela entre également dans le calcul du taux de remplissage
B6: Questions | C6: Réponses | D6: Détails | E6: Eval | F6: Complément
B7: =IF(C2="Oui existant","COTS ou Développement interne? (Commercial Off-The-Shelf solution)","Vous prévoyez quel type de solution?: COTS ou Développement interne? (Commercial Off-The-Shelf solution)") -> COTS ou Développement interne? (Commercial Off-The-Shelf solution) | C7: Développement externalisé | E7: =IF(TRIM(B7)="","",IF(TRIM(C7)="",0,1)) -> 1 | F7: Non
B8: =IF(C7="COTS","Nom de l'éditeur","") | C8: SMARTS SOLUTIONS | E8: =IF(TRIM(B8)="","",IF(TRIM(C8)="",0,1)) | F8: Non
B9: =IF(C2="Oui existant","Nom de la solution",IF(AND(C7<>"Non prévu",C7<>""),"Nom de la solution (si déjà identifiée)","")) -> Nom de la solution | C9: KIWI | D9: COFINA MOBILE + | E9: =IF(TRIM(B9)="","",IF(TRIM(C9)="",0,1)) -> 1 | F9: Non
B10: =IF(C2="Oui existant","Quelle est la version/release de l'application ?",IF(C7="COTS","Quelle est la version/release qui sera implémentée ?","")) -> Quelle est la version/release de l'application ? | C10: 1.7 | E10: =IF(TRIM(B10)="","",IF(TRIM(C10)="",0,1)) -> 1 | F10: Non
B11: =IF(C2="Oui existant","Quelle est la dernière version de l'application ?",IF(C7="COTS","Quelle est la dernière version de cette nouvelle solution ?","")) -> Quelle est la dernière version de l'application ? | C11: 1.7.5 | E11: =IF(TRIM(B11)="","",IF(TRIM(C11)="",0,1)) -> 1 | F11: Non
B12: =IF(C2="Oui existant","Etes-vous au courant d’une évolution majeure en cours sur cette application","") -> Etes-vous au courant d’une évolution majeure en cours sur cette application | C12: Non | E12: =IF(TRIM(B12)="","",IF(TRIM(C12)="",0,1)) -> 1
B13: =IF(C2="Oui existant","Qui contrôle les évolutions sur cette Application ?","") -> Qui contrôle les évolutions sur cette Application ? | C13: editeur | E13: =IF(TRIM(B13)="","",IF(TRIM(C13)="",0,1)) -> 1
B14: =IF(C2="Oui existant","Quelle est la criticité de cette application ? combien de temps peut-on supporter son indisponibilité (colonne détail) ?","Quelle est la criticité de ce besoin ?") -> Quelle est la criticité de cette application ? combien de temps peut-on supporter son indisponibilité (colonne détail) ? | C14: Moyen | D14: Critique | E14: =IF(TRIM(B14)="","",IF(TRIM(C14)="",0,1)) -> 1 | F14: Non
B15: =IF(C7="COTS","Est-ce un module du CBS ou une solution séparée?","") | C15: Solution séparée | E15: =IF(TRIM(B15)="","",IF(TRIM(C15)="",0,1)) | F15: Non
B16: =IF(C2="Oui existant","Quand l’application a-t-elle été implémentée ?",IF(AND(C7<>"Non prévu",C7<>""),"Quand l’application sera-t-elle implémentée ?","")) -> Quand l’application a-t-elle été implémentée ? | C16: A DEFINIR | D16: phase de deploiement | E16: =IF(TRIM(B16)="","",IF(TRIM(C16)="",0,1)) -> 1 | F16: Quel est le statut?
B17: =IF(C2="Oui existant","Qui l'a implémenté ?",IF(AND(C7<>"Non prévu",C7<>""),"Qui doit l'implémenter ?","")) -> Qui l'a implémenté ? | C17: SMARTS SOLUTIONS | D17: PROVIDER | E17: =IF(TRIM(B17)="","",IF(TRIM(C17)="",0,1)) -> 1 | F17: Est-ce le même prestataire?
B18: =IF(C2="Oui existant","Quels sont les processus fonctionnels couverts ?",IF(AND(C7<>"Non prévu",C7<>""),"Quels sont les processus fonctionnels qui doivent être couverts ?","")) -> Quels sont les processus fonctionnels couverts ? | C18: CASH IN / CASH OUT | D18: oui | E18: =IF(TRIM(B18)="","",IF(TRIM(C18)="",0,1)) -> 1 | F18: Ce sera bien utilisé par des agents externes à Cofina?
B19: =IF(C2="Oui existant","Est-ce que la solution est integrée au CBS ?",IF(AND(C7<>"Non prévu",C7<>""),"Est-ce que la solution sera integrée au CBS ?","")) -> Est-ce que la solution est integrée au CBS ? | C19: Non | E19: =IF(TRIM(B19)="","",IF(TRIM(C19)="",0,1)) -> 1 | F19: Non
B20: =IF(C19="Oui",IF(C2="Oui existant","Comment et quels sont les processus et données qui transitent ?",IF(AND(C7<>"Non prévu",C7<>""),"Comment et quels seront les processus et données qui vont transiter ?","")),"") | E20: =IF(TRIM(B20)="","",IF(TRIM(C20)="",0,1))
B21: =IF(C2="Oui existant","Quel est le niveau de personnalisation de l’Application ?",IF(C7="COTS","Quel est le niveau de personnalisation prévu de l’Application ?","")) -> Quel est le niveau de personnalisation de l’Application ? | C21: Haut | D21: Moyen | E21: =IF(TRIM(B21)="","",IF(TRIM(C21)="",0,1)) -> 1 | F21: Détails
B22: =IF(C2="Oui existant","Quelle(s) technologie(s) sous-jacente(s) ?","") -> Quelle(s) technologie(s) sous-jacente(s) ? | C22: non | E22: =IF(TRIM(B22)="","",IF(TRIM(C22)="",0,1)) -> 1
B23: =IF(C2="Oui existant","Est-ce que cette solution dispose d'une interface Mobile?",IF(AND(C7<>"Non prévu",C7<>""),"Est-ce qu'il est prévu une version Mobile ?","")) -> Est-ce que cette solution dispose d'une interface Mobile? | C23: Oui | E23: =IF(TRIM(B23)="","",IF(TRIM(C23)="",0,1)) -> 1 | F23: Non
B24: =IF(AND(C7<>"Non prévu",C7<>""),IF(C23="Oui","Dispose-t-elle d'une version smartphone ou tablette ou les 2 ?",""),"") -> Dispose-t-elle d'une version smartphone ou tablette ou les 2 ? | C24: Smartphone | D24: Les 2 | E24: =IF(TRIM(B24)="","",IF(TRIM(C24)="",0,1)) -> 1 | F24: Non
B25: =IF(C2="Oui existant","Est-ce qu'il est prévu de remplacer cette solution par une autre ? Si oui, veuillez mettre le nom de la nouvelle solution et la période prévue dans la colonne détails","") -> Est-ce qu'il est prévu de remplacer cette solution par une autre ? Si oui, veuillez mettre le nom de la nouvelle solution et la période prévue dans la colonne détails | C25: Non | E25: =IF(TRIM(B25)="","",IF(TRIM(C25)="",0,1)) -> 1
B26: =IF(C2="Oui existant","Quel est le nombre d’utilisateurs finaux de cette application ?",IF(AND(C7<>"Non prévu",C7<>""),"Quel est le nombre d’utilisateurs finaux prévus pour cette application ?","")) -> Quel est le nombre d’utilisateurs finaux de cette application ? | C26: VOIR IT GROUPE | E26: =IF(TRIM(B26)="","",IF(TRIM(C26)="",0,1)) -> 1 | F26: Détails
B27: =IF(C2="Oui existant","Y a-t-il des utilisateurs du Groupe sur les activités de la filiale ?","") -> Y a-t-il des utilisateurs du Groupe sur les activités de la filiale ? | C27: Non | E27: =IF(TRIM(B27)="","",IF(TRIM(C27)="",0,1)) -> 1
B28: =IF(C27="Oui","Quel est le ratio ?","") | E28: =IF(TRIM(B28)="","",IF(TRIM(C28)="",0,1))
B29: =IF(C2="Oui existant","Quels ont été les acquisitions de licences détaillées (nombre, date, coût) ?","") -> Quels ont été les acquisitions de licences détaillées (nombre, date, coût) ? | C29: VOIR IT GROUPE | E29: =IF(TRIM(B29)="","",IF(TRIM(C29)="",0,1)) -> 1
B30: =IF(C2="Oui existant","Quel est le nombre actuel de licences détenues par la filiale?",IF(C7="COTS","Combien de licences projettez-vous d'acquérir ?","")) -> Quel est le nombre actuel de licences détenues par la filiale? | C30: VOIR IT GROUPE | E30: =IF(TRIM(B30)="","",IF(TRIM(C30)="",0,1)) -> 1 | F30: Détails
B31: =IF(C2="Oui existant","Quel type de licences (nominatives/partagées) ?",IF(C7="COTS","Est-ce que ce sera des licences nominatives ou partagées ?","")) -> Quel type de licences (nominatives/partagées) ? | C31: Nominatives | E31: =IF(TRIM(B31)="","",IF(TRIM(C31)="",0,1)) -> 1 | F31: Détails
B32: =IF(C2="Oui existant","Des licences supplémentaires sont-elles nécessaires pour l'utilisation de l'application (outil supplémentaire, interfaces, modules complémentaires, …) ? Par module / par utilisateur ?",IF(C7="COTS","Est-ce que vous projettez d'acquérir d'autres licences dans un second temps ? combien et quand ?","")) -> Des licences supplémentaires sont-elles nécessaires pour l'utilisation de l'application (outil supplémentaire, interfaces, modules complémentaires, …) ? Par module / par utilisateur ? | C32: VOIR IT GROUPE | D32: NA | E32: =IF(TRIM(B32)="","",IF(TRIM(C32)="",0,1)) -> 1 | F32: Non
B33: =IF(C2="Oui existant","Quel est le coût du support éditeur ?",IF(C7="COTS","Quel sera le coût du support éditeur ?","")) -> Quel est le coût du support éditeur ? | C33: VOIR IT GROUPE | E33: =IF(TRIM(B33)="","",IF(TRIM(C33)="",0,1)) -> 1 | F33: Non
B34: =IF(C2="Oui existant","Existe-t-il un contrat de support avec un fournisseur ou un partenaire ? Pouvez-vous le partager ?","") -> Existe-t-il un contrat de support avec un fournisseur ou un partenaire ? Pouvez-vous le partager ? | C34: Oui | E34: =IF(TRIM(B34)="","",IF(TRIM(C34)="",0,1)) -> 1
B35: =IF(C2="Oui existant","Le contrat est-il global couvrant plusieurs filiales ou dédié à la filiale ?",IF(C7="COTS","Projettez-vous une acquisition individuelle ou groupe ?","")) -> Le contrat est-il global couvrant plusieurs filiales ou dédié à la filiale ? | C35: Global | D35: nous n'avons l'information proprement dit | E35: =IF(TRIM(B35)="","",IF(TRIM(C35)="",0,1)) -> 1 | F35: Non
B36: =IF(C2="Oui existant","Le contrat comprend-il un SLA formel ? Cela inclut-il un engagement de performance ?","") -> Le contrat comprend-il un SLA formel ? Cela inclut-il un engagement de performance ? | C36: Non pour les 2 | D36: nous n'avons l'information proprement dit | E36: =IF(TRIM(B36)="","",IF(TRIM(C36)="",0,1)) -> 1
B37: =IF(C2="Oui existant","Combien de ETP internes sont dédiés aux support (Niveaux 1, 2 et 3) de cette solution ? Veuillez décrire dans la colonne détail de quelle entité sont-ils (Holding ou pays), la répartition des principales activités, les compétences et les rôles",IF(AND(C7<>"Non prévu",C7<>""),"Combien de ETP internes projettez-vous de dédier aux support (Niveaux 1, 2 et 3) de cette solution ?","")) -> Combien de ETP internes sont dédiés aux support (Niveaux 1, 2 et 3) de cette solution ? Veuillez décrire dans la colonne détail de quelle entité sont-ils (Holding ou pays), la répartition des principales activités, les compétences et les rôles | C37: 1. Niveau 1 : o Nombre d'ETP : 3 o Répartition des Activités : Résolution des tickets de premier niveau, support de base aux utilisateurs, gestion des demandes simples et Analyse des incidents 2. Niveau 2 : o Nombre d'ETP : 5 o Entité : Holding o Répartition des Activités : Analyse des incidents plus complexes, gestion des escalades du niveau 1, résolution de problèmes techniques avancés. o Compétences : Expertise technique, capacité à résoudre des problèmes complexes. o Rôles : Technicien Support Niveau 2 3. Niveau 3 : o Nombre d'ETP : DEFINIR o Entité : PROVIDER o Répartition des Activités : Gestion des problèmes critiques, développement de solutions, coordination avec les équipes de développement. o Compétences : Expertise approfondie, compétences en développement et en gestion des incidents majeurs. o Rôles : Ingénieur Support Niveau 3 | D37: N3 | E37: =IF(TRIM(B37)="","",IF(TRIM(C37)="",0,IF(TRIM(D37)="",0.5,1))) -> 1 | F37: Non
B38: =IF(C2="Oui existant","Combien de ETP internes sont dédiés aux changes opérés sur cette solution (incluant Dev, Config, Mise en prod) ? Veuillez décrire dans la col. détail de quelle entité sont-ils (Holding ou pays), la répartition des activités, les compétences et les rôles",IF(AND(C7<>"Non prévu",C7<>""),"Combien de ETP internes projettez-vous de dédier aux futurs changes sur cette solution (incluant Dev, Config, Mise en prod) ?","")) -> Combien de ETP internes sont dédiés aux changes opérés sur cette solution (incluant Dev, Config, Mise en prod) ? Veuillez décrire dans la col. détail de quelle entité sont-ils (Holding ou pays), la répartition des activités, les compétences et les rôles | C38: Holding : ETP dédiés : 5 Filiale : ETP dédiés : 1 | D38: N3 | E38: =IF(TRIM(B38)="","",IF(TRIM(C38)="",0,IF(TRIM(D38)="",0.5,1))) -> 1 | F38: Non
B39: =IF(C2="Oui existant","Qui administre cette solution et apporte le support aux utilisateurs l'IT Groupe, l'IT local ou les 2 ?",IF(AND(C7<>"Non prévu",C7<>""),"Qui va administrer cette solution et apporter le support aux utilisateurs: l'IT Groupe, l'IT local ou les 2 ?","")) -> Qui administre cette solution et apporte le support aux utilisateurs l'IT Groupe, l'IT local ou les 2 ? | C39: Les 2 | D39: équipe IT locale se concentre principalement sur les aspects applicatifs et les opérations quotidiennes liées aux applications, tandis que l'équipe ITgroupe est responsable de la gestion et de l'administration des bases de données. | E39: =IF(TRIM(B39)="","",IF(TRIM(C39)="",0,1)) -> 1 | F39: Qui fera quoi?
B40: =IF(C39="Les 2","A quelle proportion chacun ? et existe-t-il un SLA interne entre Group IT et la filiale ? S'il existe, pouvez-vous le partager vous pouvez décrire dans la partie détails les responsabilités de chaque partie","") -> A quelle proportion chacun ? et existe-t-il un SLA interne entre Group IT et la filiale ? S'il existe, pouvez-vous le partager vous pouvez décrire dans la partie détails les responsabilités de chaque partie | C40: Pas de SLA | D40: NON | E40: =IF(TRIM(B40)="","",IF(TRIM(C40)="",0,1)) -> 1 | F40: Non
B41: =IF(C2="Oui existant","Avez-vous un historique des KPI pour la disponibilité et le support de cette application ? Si oui, pouvez-vous les partager","") -> Avez-vous un historique des KPI pour la disponibilité et le support de cette application ? Si oui, pouvez-vous les partager | C41: Non | E41: =IF(TRIM(B41)="","",IF(TRIM(C41)="",0,1)) -> 1
B42: =IF(C2="Oui existant","Existe-t-il un processus de suivi des contrats groupe et tiers ?","") -> Existe-t-il un processus de suivi des contrats groupe et tiers ? | C42: Non | E42: =IF(TRIM(B42)="","",IF(TRIM(C42)="",0,1)) -> 1
B43: =IF(C2="Oui existant","L'application est-elle installée sur site ou utilisée sur le Cloud (SaaS) ?",IF(AND(C7<>"Non prévu",C7<>""),"La nouvelle solution sera-t-elle installée sur site ou utilisée sur le Cloud (SaaS) ?","")) -> L'application est-elle installée sur site ou utilisée sur le Cloud (SaaS) ? | C43: Cloud | E43: =IF(TRIM(B43)="","",IF(TRIM(C43)="",0,1)) -> 1 | F43: Non
B44: =IF(AND(C43="Cloud",C7="COTS"),"Est-ce entièrement SaaS ou Infra gérée par l'équipe locale ?","") | E44: =IF(TRIM(B44)="","",IF(TRIM(C44)="",0,1))
B45: =IF(C2="Oui existant","S'agit-il d'une architecture Client/Serveur à 3 niveaux ? Décrivez s'il vous plait","") -> S'agit-il d'une architecture Client/Serveur à 3 niveaux ? Décrivez s'il vous plait | C45: Non | D45: non | E45: =IF(TRIM(B45)="","",IF(TRIM(C45)="",0,IF(TRIM(D45)="",0.5,1))) -> 1
B46: =IF(C43="On-site","Comment sont acquis les serveurs (achat/location/sous-traitance) ?","") | C46: Achat | E46: =IF(TRIM(B46)="","",IF(TRIM(C46)="",0,1)) | F46: Non
B47: =IF(C2="Oui existant","Où sont installés les serveurs ?","") -> Où sont installés les serveurs ? | C47: aucune information | E47: =IF(TRIM(B47)="","",IF(TRIM(C47)="",0,1)) -> 1
B48: =IF(C2="Oui existant","Sur quels systèmes (versions) cette application s'exécute-t-elle ?",IF(AND(C7<>"Non prévu",C7<>""),"Sur quels systèmes (versions) cette application sera-t-elle implémentée ?","")) -> Sur quels systèmes (versions) cette application s'exécute-t-elle ? | C48: Ubuntu | E48: =IF(TRIM(B48)="","",IF(TRIM(C48)="",0,1)) -> 1 | F48: Version?
B49: =IF(C2="Oui existant","Sur quelle base de données cette application tourne-t-elle ?",IF(AND(C7<>"Non prévu",C7<>""),"Sur quelle base de données cette application tournera-t-elle ?","")) -> Sur quelle base de données cette application tourne-t-elle ? | C49: ORACLE 19c | E49: =IF(TRIM(B49)="","",IF(TRIM(C49)="",0,1)) -> 1 | F49: Version?
B50: =IF(C2="Oui existant","Existe-t-il une architecture haute disponibilité (réplication) ?",IF(AND(C7<>"Non prévu",C7<>""),"Est-ce qu'il est prévu une architecture haute disponibilité (réplication) ?","")) -> Existe-t-il une architecture haute disponibilité (réplication) ? | C50: Non | E50: =IF(TRIM(B50)="","",IF(TRIM(C50)="",0,1)) -> 1 | F50: Non
B51: =IF(C50="Oui","Entièrement ou partiellement ? Actif-Actif ou Actif-Passif ?","") | C51: Actif-Passif | E51: =IF(TRIM(B51)="","",IF(TRIM(C51)="",0,1)) | F51: Non
B52: =IF(C2="Oui existant","Existe-t-il un plan de récupération pour cette application ?","") -> Existe-t-il un plan de récupération pour cette application ? | C52: Non | E52: =IF(TRIM(B52)="","",IF(TRIM(C52)="",0,1)) -> 1
B53: =IF(C2="Oui existant","Qui gère les données de la base de données ?",IF(AND(C7<>"Non prévu",C7<>""),"Qui va gèrer les données de la base de données ?","")) -> Qui gère les données de la base de données ? | C53: Smart et DBA Cofina | E53: =IF(TRIM(B53)="","",IF(TRIM(C53)="",0,1)) -> 1 | F53: Non
B54: =IF(C2="Oui existant","Quelles sont les interfaces existantes de cette application ? Veuillez décrire et partager tout document d'architecture",IF(AND(C7<>"Non prévu",C7<>""),"Quelles sont les interfaces prévues ? Veuillez décrire et partager tout document d'architecture cible","")) -> Quelles sont les interfaces existantes de cette application ? Veuillez décrire et partager tout document d'architecture | C54: NA | D54: NA | E54: =IF(TRIM(B54)="","",IF(TRIM(C54)="",0,IF(TRIM(D54)="",0.5,1))) -> 1 | F54: Non
B55: =IF(C2="Oui existant","L'application est-elle complètement en temps réel ou y'a-t-il des batchs la nuit ? Décrivez s'il vous plait",IF(AND(C7<>"Non prévu",C7<>""),"L'application sera-t-elle complètement en temps réel ou y'aura-t-il des batchs la nuit ? Décrivez s'il vous plait","")) -> L'application est-elle complètement en temps réel ou y'a-t-il des batchs la nuit ? Décrivez s'il vous plait | C55: NA | D55: NA | E55: =IF(TRIM(B55)="","",IF(TRIM(C55)="",0,IF(TRIM(D55)="",0.5,1))) -> 1 | F55: Non
B56: =IF(C2="Oui existant","Avez-vous connaissance d'un quelconque problème potentiel lié à la continuité de cette application (par exemple départ ou indisponibilité des ressources clés, fin de support, bug critique, ...), si oui lequel dans détails ?","") -> Avez-vous connaissance d'un quelconque problème potentiel lié à la continuité de cette application (par exemple départ ou indisponibilité des ressources clés, fin de support, bug critique, ...), si oui lequel dans détails ? | C56: Non | E56: =IF(TRIM(B56)="","",IF(TRIM(C56)="",0,1)) -> 1
B57: =IF(C2="Oui existant","Est-ce que des sauvegardes sont réalisées régulièrement ?",IF(AND(C7<>"Non prévu",C7<>""),"Est-ce que des sauvegardes sont prévus dès l'implémentation ?","")) -> Est-ce que des sauvegardes sont réalisées régulièrement ? | C57: Oui | E57: =IF(TRIM(B57)="","",IF(TRIM(C57)="",0,1)) -> 1 | F57: Non
B58: =IF(C57="Oui","A quelle fréquence sont-elles exécutées?","") -> A quelle fréquence sont-elles exécutées? | C58: Journaliere | E58: =IF(TRIM(B58)="","",IF(TRIM(C58)="",0,1)) -> 1
B59: =IF(C57="Oui","Avez-vous une politique de rétention en place ? Si oui, pouvez-vous me la partager?","") -> Avez-vous une politique de rétention en place ? Si oui, pouvez-vous me la partager? | C59: Non | E59: =IF(TRIM(B59)="","",IF(TRIM(C59)="",0,1)) -> 1
B60: =IF(C57="Oui","Quelle est la solution de sauvegarde/récupération utilisée ?","") -> Quelle est la solution de sauvegarde/récupération utilisée ? | C60: DUMP | E60: =IF(TRIM(B60)="","",IF(TRIM(C60)="",0,1)) -> 1
B61: =IF(C57="Oui","Quelle est la taille totale estimée des sauvegardes ?","") -> Quelle est la taille totale estimée des sauvegardes ? | C61: je ne dispose pas encore les informations | E61: =IF(TRIM(B61)="","",IF(TRIM(C61)="",0,1)) -> 1
A123: Combien de ces demandes surviennent en moyenne par an ?

Sheet MB
A1: Retour à la page d'accueil | C1: Réponse corrigé à partir du fichier CTI
B2: Mobile Banking - Application Mobile Client | C2: Oui existant
B3: Veuillez répondre à toutes les questions et donner plus de détails (colonne D) lorsque nécessaire, un taux de remplissage est calculé dans le sommaire et devrait être à 100%
B4: Certaines questions peuvent en faire apparaitre de nouvelles auxquelles il faudra répondre, cela entre également dans le calcul du taux de remplissage
B6: Questions | C6: Réponses | D6: Détails | E6: Eval | F6: Complément
B7: =IF(C2="Oui existant","COTS ou Développement interne? (Commercial Off-The-Shelf solution)","Vous prévoyez quel type de solution?: COTS ou Développement interne? (Commercial Off-The-Shelf solution)") -> COTS ou Développement interne? (Commercial Off-The-Shelf solution) | C7: Développement externalisé | E7: =IF(TRIM(B7)="","",IF(TRIM(C7)="",0,1)) -> 1 | F7: Non
B8: =IF(C7="COTS","Nom de l'éditeur","") | C8: SMARTS SOLUTIONS | E8: =IF(TRIM(B8)="","",IF(TRIM(C8)="",0,1)) | F8: Non
B9: =IF(C2="Oui existant","Nom de la solution",IF(AND(C7<>"Non prévu",C7<>""),"Nom de la solution (si déjà identifiée)","")) -> Nom de la solution | C9: COFINA MOBILE + | E9: =IF(TRIM(B9)="","",IF(TRIM(C9)="",0,1)) -> 1 | F9: Non
B10: =IF(C2="Oui existant","Quelle est la version/release de l'application ?",IF(C7="COTS","Quelle est la version/release qui sera implémentée ?","")) -> Quelle est la version/release de l'application ? | C10: 1.7 | E10: =IF(TRIM(B10)="","",IF(TRIM(C10)="",0,1)) -> 1 | F10: Non
B11: =IF(C2="Oui existant","Quelle est la dernière version de l'application ?",IF(C7="COTS","Quelle est la dernière version de cette nouvelle solution ?","")) -> Quelle est la dernière version de l'application ? | C11: 1.7.5 | E11: =IF(TRIM(B11)="","",IF(TRIM(C11)="",0,1)) -> 1 | F11: Non
B12: =IF(C2="Oui existant","Etes-vous au courant d’une évolution majeure en cours sur cette application","") -> Etes-vous au courant d’une évolution majeure en cours sur cette application | C12: Non | E12: =IF(TRIM(B12)="","",IF(TRIM(C12)="",0,1)) -> 1 | F12: Non
B13: =IF(C2="Oui existant","Qui contrôle les évolutions sur cette Application ?","") -> Qui contrôle les évolutions sur cette Application ? | C13: NA | E13: =IF(TRIM(B13)="","",IF(TRIM(C13)="",0,1)) -> 1 | F13: Non
B14: =IF(C2="Oui existant","Quelle est la criticité de cette application ? combien de temps peut-on supporter son indisponibilité (colonne détail) ?","Quelle est la criticité de ce besoin ?") -> Quelle est la criticité de cette application ? combien de temps peut-on supporter son indisponibilité (colonne détail) ? | C14: Primoridal | E14: =IF(TRIM(B14)="","",IF(TRIM(C14)="",0,1)) -> 1 | F14: Non
B15: =IF(C7="COTS","Est-ce un module du CBS ou une solution séparée?","") | C15: Solution séparée | E15: =IF(TRIM(B15)="","",IF(TRIM(C15)="",0,1)) | F15: Non
B16: =IF(C2="Oui existant","Quand l’application a-t-elle été implémentée ?",IF(AND(C7<>"Non prévu",C7<>""),"Quand l’application sera-t-elle implémentée ?","")) -> Quand l’application a-t-elle été implémentée ? | C16: 2022 | E16: =IF(TRIM(B16)="","",IF(TRIM(C16)="",0,1)) -> 1 | F16: Non
B17: =IF(C2="Oui existant","Qui l'a implémenté ?",IF(AND(C7<>"Non prévu",C7<>""),"Qui doit l'implémenter ?","")) -> Qui l'a implémenté ? | C17: SmartSolution | E17: =IF(TRIM(B17)="","",IF(TRIM(C17)="",0,1)) -> 1 | F17: Non
B18: =IF(C2="Oui existant","Quels sont les processus fonctionnels couverts ?",IF(AND(C7<>"Non prévu",C7<>""),"Quels sont les processus fonctionnels qui doivent être couverts ?","")) -> Quels sont les processus fonctionnels couverts ? | C18: Voici les processus fonctionnels clés : 1. Authentification et Autorisation : 1. Gestion des Utilisateurs : 2. Navigation et Interface Utilisateur : 3. Gestion des Données : 4. Notifications et Alertes : 5. Transactions. 6. Sécurité : 7. Intégration avec d'autres Services : o Connexion avec des API tierces ou des services externes. | E18: =IF(TRIM(B18)="","",IF(TRIM(C18)="",0,1)) -> 1 | F18: Non
B19: =IF(C2="Oui existant","Est-ce que la solution est integrée au CBS ?",IF(AND(C7<>"Non prévu",C7<>""),"Est-ce que la solution sera integrée au CBS ?","")) -> Est-ce que la solution est integrée au CBS ? | C19: Oui | E19: =IF(TRIM(B19)="","",IF(TRIM(C19)="",0,1)) -> 1 | F19: Par quoi passera l'intégration? Middleware ou point à point?
B20: =IF(C19="Oui",IF(C2="Oui existant","Comment et quels sont les processus et données qui transitent ?",IF(AND(C7<>"Non prévu",C7<>""),"Comment et quels seront les processus et données qui vont transiter ?","")),"") -> Comment et quels sont les processus et données qui transitent ? | C20: API | E20: =IF(TRIM(B20)="","",IF(TRIM(C20)="",0,1)) -> 1 | F20: Non
B21: =IF(C2="Oui existant","Quel est le niveau de personnalisation de l’Application ?",IF(C7="COTS","Quel est le niveau de personnalisation prévu de l’Application ?","")) -> Quel est le niveau de personnalisation de l’Application ? | C21: Très haut | E21: =IF(TRIM(B21)="","",IF(TRIM(C21)="",0,1)) -> 1 | F21: Non
B22: =IF(C2="Oui existant","Quelle(s) technologie(s) sous-jacente(s) ?","") -> Quelle(s) technologie(s) sous-jacente(s) ? | C22: NA | E22: =IF(TRIM(B22)="","",IF(TRIM(C22)="",0,1)) -> 1 | F22: Non
B23: =IF(C2="Oui existant","Est-ce que la version existe sur Android, iOS ou les 2 ?",IF(AND(C7<>"Non prévu",C7<>""),"Est-ce qu'il y aura une version Android, iOS ou les 2 ?","")) -> Est-ce que la version existe sur Android, iOS ou les 2 ? | C23: Les 2 | E23: =IF(TRIM(B23)="","",IF(TRIM(C23)="",0,1)) -> 1 | F23: Non
B24: =IF(AND(C7<>"Non prévu",C7<>""),IF(C23 = "Android","Quelle version de Android ?",IF(C23 = "iOS","Quelle version d' iOS ?",IF(C23 = "Les 2","Quelle versions d' iOS et d' Android ?",""))),"") -> Quelle versions d' iOS et d' Android ? | C24: Oui | E24: =IF(TRIM(B24)="","",IF(TRIM(C24)="",0,1)) -> 1 | F24: Quelles versions?
B25: =IF(C2="Oui existant","Quel est le nombre d’utilisateurs finaux de cette application ?",IF(AND(C7<>"Non prévu",C7<>""),"Quel est le nombre d’utilisateurs finaux prévus pour cette application ?","")) -> Quel est le nombre d’utilisateurs finaux de cette application ? | C25: 8600 | E25: =IF(TRIM(B25)="","",IF(TRIM(C25)="",0,1)) -> 1 | F25: Quel est le nombre actuel?
B26: =IF(C2="Oui existant","Y a-t-il des utilisateurs du Groupe sur les activités de la filiale ?","") -> Y a-t-il des utilisateurs du Groupe sur les activités de la filiale ? | C26: Non | E26: =IF(TRIM(B26)="","",IF(TRIM(C26)="",0,1)) -> 1 | F26: Que font-ils?
B27: =IF(C26="Oui","Quel est le ratio ?","") | E27: =IF(TRIM(B27)="","",IF(TRIM(C27)="",0,1))
B28: =IF(C2="Oui existant","Quels ont été les acquisitions de licences détaillées (nombre, date, coût) ?","") -> Quels ont été les acquisitions de licences détaillées (nombre, date, coût) ? | C28: VOIR IT GROUPE | E28: =IF(TRIM(B28)="","",IF(TRIM(C28)="",0,1)) -> 1 | F28: Pourquoi?
B29: =IF(C2="Oui existant","Quel est le nombre actuel de licences détenues par la filiale?",IF(C7="COTS","Combien de licences projettez-vous d'acquérir ?","")) -> Quel est le nombre actuel de licences détenues par la filiale? | C29: VOIR IT GROUPE | E29: =IF(TRIM(B29)="","",IF(TRIM(C29)="",0,1)) -> 1 | F29: Licence par filiale ou par client?
B30: =IF(C2="Oui existant","Quel type de licences (nominatives/partagées) ?",IF(C7="COTS","Est-ce que ce sera des licences nominatives ou partagées ?","")) -> Quel type de licences (nominatives/partagées) ? | C30: Nominatives | E30: =IF(TRIM(B30)="","",IF(TRIM(C30)="",0,1)) -> 1 | F30: Licence par filiale ou par client?
B31: =IF(C2="Oui existant","Des licences supplémentaires sont-elles nécessaires pour l'utilisation de l'application (outil supplémentaire, interfaces, modules complémentaires, …) ? Par module / par utilisateur ?",IF(C7="COTS","Est-ce que vous projettez d'acquérir d'autres licences dans un second temps ? combien et quand ?","")) -> Des licences supplémentaires sont-elles nécessaires pour l'utilisation de l'application (outil supplémentaire, interfaces, modules complémentaires, …) ? Par module / par utilisateur ? | C31: Playstore, Appstore | D31: Playstore, Appstore | E31: =IF(TRIM(B31)="","",IF(TRIM(C31)="",0,1)) -> 1 | F31: Est-ce qu'elles sont actives?
B32: =IF(C2="Oui existant","Quel est le coût du support éditeur ?",IF(C7="COTS","Quel sera le coût du support éditeur ?","")) -> Quel est le coût du support éditeur ? | C32: VOIR IT GROUPE | E32: =IF(TRIM(B32)="","",IF(TRIM(C32)="",0,1)) -> 1 | F32: Non
B33: =IF(C2="Oui existant","Existe-t-il un contrat de support avec un fournisseur ou un partenaire ? Pouvez-vous le partager ?","") -> Existe-t-il un contrat de support avec un fournisseur ou un partenaire ? Pouvez-vous le partager ? | C33: Oui | D33: VOIR IT GROUPE | E33: =IF(TRIM(B33)="","",IF(TRIM(C33)="",0,1)) -> 1 | F33: Non
B34: =IF(C2="Oui existant","Le contrat est-il global couvrant plusieurs filiales ou dédié à la filiale ?",IF(C7="COTS","Projettez-vous une acquisition individuelle ou groupe ?","")) -> Le contrat est-il global couvrant plusieurs filiales ou dédié à la filiale ? | C34: Dédié | E34: =IF(TRIM(B34)="","",IF(TRIM(C34)="",0,1)) -> 1 | F34: Non
B35: =IF(C2="Oui existant","Le contrat comprend-il un SLA formel ? Cela inclut-il un engagement de performance ?","") -> Le contrat comprend-il un SLA formel ? Cela inclut-il un engagement de performance ? | C35: Non pour les 2 | E35: =IF(TRIM(B35)="","",IF(TRIM(C35)="",0,1)) -> 1 | F35: Non
B36: =IF(C2="Oui existant","Combien de ETP internes sont dédiés aux support (Niveaux 1, 2 et 3) de cette solution ? Veuillez décrire dans la colonne détail de quelle entité sont-ils (Holding ou pays), la répartition des principales activités, les compétences et les rôles",IF(AND(C7<>"Non prévu",C7<>""),"Combien de ETP internes projettez-vous de dédier aux support (Niveaux 1, 2 et 3) de cette solution ?","")) -> Combien de ETP internes sont dédiés aux support (Niveaux 1, 2 et 3) de cette solution ? Veuillez décrire dans la colonne détail de quelle entité sont-ils (Holding ou pays), la répartition des principales activités, les compétences et les rôles | C36: 1. Niveau 1 : o Nombre d'ETP : 4 o Répartition des Activités : Résolution des tickets de premier niveau, support de base aux utilisateurs, gestion des demandes simples et Analyse des incidents 2. Niveau 2 : o Nombre d'ETP : 5 o Entité : Holding o Répartition des Activités : Analyse des incidents plus complexes, gestion des escalades du niveau 1, résolution de problèmes techniques avancés. o Compétences : Expertise technique, capacité à résoudre des problèmes complexes. o Rôles : Technicien Support Niveau 2 3. Niveau 3 : o Nombre d'ETP : DEFINIR o Entité : PROVIDER o Répartition des Activités : Gestion des problèmes critiques, développement de solutions, coordination avec les équipes de développement. o Compétences : Expertise approfondie, compétences en développement et en gestion des incidents majeurs. o Rôles : Ingénieur Support Niveau 3 | D36: N2 | E36: =IF(TRIM(B36)="","",IF(TRIM(C36)="",0,IF(TRIM(D36)="",0.5,1))) -> 1 | F36: Nombre d'ETP?
B37: =IF(C2="Oui existant","Combien de ETP internes sont dédiés aux changes opérés sur cette solution (incluant Dev, Config, Mise en prod) ? Veuillez décrire dans la col. détail de quelle entité sont-ils (Holding ou pays), la répartition des activités, les compétences et les rôles",IF(AND(C7<>"Non prévu",C7<>""),"Combien de ETP internes projettez-vous de dédier aux futurs changes sur cette solution (incluant Dev, Config, Mise en prod) ?","")) -> Combien de ETP internes sont dédiés aux changes opérés sur cette solution (incluant Dev, Config, Mise en prod) ? Veuillez décrire dans la col. détail de quelle entité sont-ils (Holding ou pays), la répartition des activités, les compétences et les rôles | C37: Holding : ETP dédiés : 5 Filiale : ETP dédiés : 1 | D37: N2 | E37: =IF(TRIM(B37)="","",IF(TRIM(C37)="",0,IF(TRIM(D37)="",0.5,1))) -> 1 | F37: Nombre d'ETP?
B38: =IF(C2="Oui existant","Qui administre cette solution et apporte le support aux utilisateurs l'IT Groupe, l'IT local ou les 2 ?",IF(AND(C7<>"Non prévu",C7<>""),"Qui va administrer cette solution et apporter le support aux utilisateurs: l'IT Groupe, l'IT local ou les 2 ?","")) -> Qui administre cette solution et apporte le support aux utilisateurs l'IT Groupe, l'IT local ou les 2 ? | C38: Les 2 | D38: équipe IT locale se concentre principalement sur les aspects applicatifs et les opérations quotidiennes liées aux applications, tandis que l'équipe ITgroupe est responsable de la gestion et de l'administration des bases de données. | E38: =IF(TRIM(B38)="","",IF(TRIM(C38)="",0,1)) -> 1 | F38: Qui fait quoi?
B39: =IF(C38="Les 2","A quelle proportion chacun ? et existe-t-il un SLA interne entre Group IT et la filiale ? S'il existe, pouvez-vous le partager vous pouvez décrire dans la partie détails les responsabilités de chaque partie","") -> A quelle proportion chacun ? et existe-t-il un SLA interne entre Group IT et la filiale ? S'il existe, pouvez-vous le partager vous pouvez décrire dans la partie détails les responsabilités de chaque partie | C39: non | D39: non | E39: =IF(TRIM(B39)="","",IF(TRIM(C39)="",0,1)) -> 1 | F39: Non
B40: =IF(C2="Oui existant","Avez-vous un historique des KPI pour la disponibilité et le support de cette application ? Si oui, pouvez-vous les partager","") -> Avez-vous un historique des KPI pour la disponibilité et le support de cette application ? Si oui, pouvez-vous les partager | C40: Non | E40: =IF(TRIM(B40)="","",IF(TRIM(C40)="",0,1)) -> 1 | F40: Incomplet mais existe
B41: =IF(C2="Oui existant","Existe-t-il un processus de suivi des contrats groupe et tiers ?","") -> Existe-t-il un processus de suivi des contrats groupe et tiers ? | C41: Non | E41: =IF(TRIM(B41)="","",IF(TRIM(C41)="",0,1)) -> 1 | F41: Non
B42: =IF(C2="Oui existant","L'application est-elle installée sur site ou utilisée sur le Cloud (SaaS) ?",IF(AND(C7<>"Non prévu",C7<>""),"La nouvelle solution sera-t-elle installée sur site ou utilisée sur le Cloud (SaaS) ?","")) -> L'application est-elle installée sur site ou utilisée sur le Cloud (SaaS) ? | C42: Cloud | E42: =IF(TRIM(B42)="","",IF(TRIM(C42)="",0,1)) -> 1 | F42: Non
B43: =IF(AND(C42="Cloud",C7="COTS"),"Est-ce entièrement SaaS ou Infra gérée par l'équipe locale ?","") | E43: =IF(TRIM(B43)="","",IF(TRIM(C43)="",0,1)) | F43: Non
B44: =IF(C2="Oui existant","S'agit-il d'une architecture Client/Serveur à 3 niveaux ? Décrivez s'il vous plait","") -> S'agit-il d'une architecture Client/Serveur à 3 niveaux ? Décrivez s'il vous plait | C44: Oui | D44: OUI | E44: =IF(TRIM(B44)="","",IF(TRIM(C44)="",0,IF(TRIM(D44)="",0.5,1))) -> 1 | F44: Non
B45: =IF(C42="On-site","Comment sont acquis les serveurs (achat/location/sous-traitance) ?","") | C45: Achat | E45: =IF(TRIM(B45)="","",IF(TRIM(C45)="",0,1)) | F45: Non
B46: =IF(C2="Oui existant","Où sont installés les serveurs ?","") -> Où sont installés les serveurs ? | C46: DATA CENTER CIV | E46: =IF(TRIM(B46)="","",IF(TRIM(C46)="",0,1)) -> 1 | F46: Lequel?
B47: =IF(C2="Oui existant","Sur quels systèmes (versions) cette application s'exécute-t-elle ?",IF(AND(C7<>"Non prévu",C7<>""),"Sur quels systèmes (versions) cette application sera-t-elle implémentée ?","")) -> Sur quels systèmes (versions) cette application s'exécute-t-elle ? | C47: Linux-Ubuntu 22.04.3 | E47: =IF(TRIM(B47)="","",IF(TRIM(C47)="",0,1)) -> 1 | F47: Version?
B48: =IF(C2="Oui existant","Sur quelle base de données cette application tourne-t-elle ?",IF(AND(C7<>"Non prévu",C7<>""),"Sur quelle base de données cette application tournera-t-elle ?","")) -> Sur quelle base de données cette application tourne-t-elle ? | C48: Oracle 19C | E48: =IF(TRIM(B48)="","",IF(TRIM(C48)="",0,1)) -> 1 | F48: Non
B49: =IF(C2="Oui existant","Existe-t-il une architecture haute disponibilité (réplication) ?",IF(AND(C7<>"Non prévu",C7<>""),"Est-ce qu'il est prévu une architecture haute disponibilité (réplication) ?","")) -> Existe-t-il une architecture haute disponibilité (réplication) ? | C49: Oui | E49: =IF(TRIM(B49)="","",IF(TRIM(C49)="",0,1)) -> 1 | F49: Non
B50: =IF(C49="Oui","Entièrement ou partiellement ? Actif-Actif ou Actif-Passif ?","") -> Entièrement ou partiellement ? Actif-Actif ou Actif-Passif ? | C50: Actif-Passif | E50: =IF(TRIM(B50)="","",IF(TRIM(C50)="",0,1)) -> 1 | F50: Non
B51: =IF(C2="Oui existant","Existe-t-il un plan de récupération pour cette application ?","") -> Existe-t-il un plan de récupération pour cette application ? | C51: Non | E51: =IF(TRIM(B51)="","",IF(TRIM(C51)="",0,1)) -> 1 | F51: Non
B52: =IF(C2="Oui existant","Qui gère les données de la base de données ?",IF(AND(C7<>"Non prévu",C7<>""),"Qui va gèrer les données de la base de données ?","")) -> Qui gère les données de la base de données ? | C52: IT Groupe | E52: =IF(TRIM(B52)="","",IF(TRIM(C52)="",0,1)) -> 1 | F52: Non
B53: =IF(C2="Oui existant","Quelles sont les interfaces existantes de cette application ? Veuillez décrire et partager tout document d'architecture",IF(AND(C7<>"Non prévu",C7<>""),"Quelles sont les interfaces prévues ? Veuillez décrire et partager tout document d'architecture cible","")) -> Quelles sont les interfaces existantes de cette application ? Veuillez décrire et partager tout document d'architecture | C53: • Consultation des soldes et historique de transaction • Virements • Ouverture de compte • E-coficash • Situation des crédits • Consultation solde et rechargement de Coficarte • Paiement des factures • Opération Bank to Wallet • Opération Wallet to Bank • Achat de crédit de communication | D53: • Consultation des soldes et historique de transaction • Virements • Ouverture de compte • E-coficash • Situation des crédits • Consultation solde et rechargement de Coficarte • Paiement des factures • Opération Bank to Wallet • Opération Wallet to Bank • Achat de crédit de communication | E53: =IF(TRIM(B53)="","",IF(TRIM(C53)="",0,IF(TRIM(D53)="",0.5,1))) -> 1 | F53: Les integrations?
B54: =IF(C2="Oui existant","L'application est-elle complètement en temps réel ou y'a-t-il des batchs la nuit ? Décrivez s'il vous plait",IF(AND(C7<>"Non prévu",C7<>""),"L'application sera-t-elle complètement en temps réel ou y'aura-t-il des batchs la nuit ? Décrivez s'il vous plait","")) -> L'application est-elle complètement en temps réel ou y'a-t-il des batchs la nuit ? Décrivez s'il vous plait | C54: EN temps réel | D54: EN temps réel | E54: =IF(TRIM(B54)="","",IF(TRIM(C54)="",0,IF(TRIM(D54)="",0.5,1))) -> 1 | F54: Il y a aucune integration avec des partenaires externes qui envoient les données 1xjour? NON
B55: =IF(C2="Oui existant","Avez-vous connaissance d'un quelconque problème potentiel lié à la continuité de cette application (par exemple départ ou indisponibilité des ressources clés, fin de support, bug critique, ...), si oui lequel dans détails ?","") -> Avez-vous connaissance d'un quelconque problème potentiel lié à la continuité de cette application (par exemple départ ou indisponibilité des ressources clés, fin de support, bug critique, ...), si oui lequel dans détails ? | C55: Non | E55: =IF(TRIM(B55)="","",IF(TRIM(C55)="",0,1)) -> 1 | F55: Non
B56: =IF(C2="Oui existant","Est-ce que des sauvegardes sont réalisées régulièrement ?",IF(AND(C7<>"Non prévu",C7<>""),"Est-ce que des sauvegardes sont prévus dès l'implémentation ?","")) -> Est-ce que des sauvegardes sont réalisées régulièrement ? | C56: Oui | E56: =IF(TRIM(B56)="","",IF(TRIM(C56)="",0,1)) -> 1 | F56: Non
B57: =IF(C56="Oui","A quelle fréquence sont-elles exécutées?","") -> A quelle fréquence sont-elles exécutées? | C57: Journaliere | E57: =IF(TRIM(B57)="","",IF(TRIM(C57)="",0,1)) -> 1 | F57: Non
B58: =IF(C56="Oui","Avez-vous une politique de rétention en place ? Si oui, pouvez-vous me la partager?","") -> Avez-vous une politique de rétention en place ? Si oui, pouvez-vous me la partager? | C58: Non | E58: =IF(TRIM(B58)="","",IF(TRIM(C58)="",0,1)) -> 1 | F58: Non
B59: =IF(C56="Oui","Quelle est la solution de sauvegarde/récupération utilisée ?","") -> Quelle est la solution de sauvegarde/récupération utilisée ? | C59: RMAN | E59: =IF(TRIM(B59)="","",IF(TRIM(C59)="",0,1)) -> 1 | F59: Non
B60: =IF(C56="Oui","Quelle est la taille totale estimée des sauvegardes ?","") -> Quelle est la taille totale estimée des sauvegardes ? | C60: A DEFINIR | E60: =IF(TRIM(B60)="","",IF(TRIM(C60)="",0,1)) -> 1 | F60: Non
A123: Combien de ces demandes surviennent en moyenne par an ?

Sheet IB
A1: Retour à la page d'accueil
B2: Internet Banking - Banque en ligne | C2: Non existant
B3: Veuillez répondre à toutes les questions et donner plus de détails (colonne D) lorsque nécessaire, un taux de remplissage est calculé dans le sommaire et devrait être à 100%
B4: Certaines questions peuvent en faire apparaitre de nouvelles auxquelles il faudra répondre, cela entre également dans le calcul du taux de remplissage
B6: Questions | C6: Réponses | D6: Détails | E6: Eval | I6: Editeur | J6: Rate
B7: =IF(C2="Oui existant","COTS ou Développement interne? (Commercial Off-The-Shelf solution)","Vous prévoyez quel type de solution?: COTS ou Développement interne? (Commercial Off-The-Shelf solution)") -> Vous prévoyez quel type de solution?: COTS ou Développement interne? (Commercial Off-The-Shelf solution) | C7: Non prévu | D7: NA | E7: =IF(TRIM(B7)="","",IF(TRIM(C7)="",0,1)) -> 1 | G7: =IF(AND(TRIM(B7)<>"",TRIM(C7)<>""),IF(C7="COTS",5,IF(C7="Développement interne",3,IF(C7="Développement externalisé",1,0))),"") -> 0 | H7: =IF(AND(TRIM(B7)<>"",TRIM(C7)<>""),5,"") -> 5 | I7: Temenos | J7: 8
B8: =IF(C7="COTS","Nom de l'éditeur","") | E8: =IF(TRIM(B8)="","",IF(TRIM(C8)="",0,1)) | G8: =IF(AND(TRIM(B8)<>"",TRIM(C8)<>""),IF(ISNA(VLOOKUP(C8,I7:J17,2,0)),1,VLOOKUP(C8,I7:J17,2,0)),"") | H8: =IF(AND(TRIM(B8)<>"",TRIM(C8)<>""),10,"") | I8: Oracle | J8: 7
B9: =IF(C2="Oui existant","Nom de la solution",IF(AND(C7<>"Non prévu",C7<>""),"Nom de la solution (si déjà identifiée)","")) | E9: =IF(TRIM(B9)="","",IF(TRIM(C9)="",0,1)) | H9: =IF(AND(TRIM(B9)<>"",TRIM(C9)<>""),5,"") | I9: ebankIT | J9: 9
B10: =IF(C2="Oui existant","Quelle est la version/release de l'application ?",IF(C7="COTS","Quelle est la version/release qui sera implémentée ?","")) | E10: =IF(TRIM(B10)="","",IF(TRIM(C10)="",0,1)) | I10: Finshape | J10: 10
B11: =IF(C2="Oui existant","Quelle est la dernière version de l'application ?",IF(C7="COTS","Quelle est la dernière version de cette nouvelle solution ?","")) | E11: =IF(TRIM(B11)="","",IF(TRIM(C11)="",0,1)) | I11: Five Degrees | J11: 8
B12: =IF(C2="Oui existant","Etes-vous au courant d’une évolution majeure en cours sur cette application","") | E12: =IF(TRIM(B12)="","",IF(TRIM(C12)="",0,1)) | I12: Backbase | J12: 8
B13: =IF(C2="Oui existant","Qui contrôle les évolutions sur cette Application ?","") | E13: =IF(TRIM(B13)="","",IF(TRIM(C13)="",0,1)) | I13: NETinfo | J13: 9
B14: =IF(C2="Oui existant","Quelle est la criticité de cette application ? combien de temps peut-on supporter son indisponibilité (colonne détail) ?","Quelle est la criticité de ce besoin ?") -> Quelle est la criticité de ce besoin ? | C14: Moyen | D14: NA | E14: =IF(TRIM(B14)="","",IF(TRIM(C14)="",0,1)) -> 1 | I14: Veritran | J14: 10
B15: =IF(C7="COTS","Est-ce un module du CBS ou une solution séparée?","") | E15: =IF(TRIM(B15)="","",IF(TRIM(C15)="",0,1)) | I15: nCino | J15: 7
B16: =IF(C2="Oui existant","Quand l’application a-t-elle été implémentée ?",IF(AND(C7<>"Non prévu",C7<>""),"Quand l’application sera-t-elle implémentée ?","")) | E16: =IF(TRIM(B16)="","",IF(TRIM(C16)="",0,1)) | G16: =IF(AND(TRIM(B16)<>"",TRIM(C16)<>""),IF((2024-C16)<=5,10,IF((2024-C16)<=10,2,0)),"") | H16: =IF(AND(TRIM(B16)<>"",TRIM(C16)<>""),10,"") | I16: Infosys | J16: 8
B17: =IF(C2="Oui existant","Qui l'a implémenté ?",IF(AND(C7<>"Non prévu",C7<>""),"Qui doit l'implémenter ?","")) | E17: =IF(TRIM(B17)="","",IF(TRIM(C17)="",0,1)) | I17: Intellect | J17: 8
B18: =IF(C2="Oui existant","Quels sont les processus fonctionnels couverts ?",IF(AND(C7<>"Non prévu",C7<>""),"Quels sont les processus fonctionnels qui doivent être couverts ?","")) | E18: =IF(TRIM(B18)="","",IF(TRIM(C18)="",0,1)) | H18: =IF(AND(TRIM(B18)<>"",TRIM(C18)<>""),10,"")
B19: =IF(C2="Oui existant","Est-ce que la solution est integrée au CBS ?",IF(AND(C7<>"Non prévu",C7<>""),"Est-ce que la solution sera integrée au CBS ?","")) | E19: =IF(TRIM(B19)="","",IF(TRIM(C19)="",0,1)) | G19: =IF(AND(TRIM(B19)<>"",TRIM(C19)<>""),IF(C19="Oui",20,0),"") | H19: =IF(AND(TRIM(B19)<>"",TRIM(C19)<>""),20,"")
B20: =IF(C19="Oui",IF(C2="Oui existant","Comment et quels sont les processus et données qui transitent ?",IF(AND(C7<>"Non prévu",C7<>""),"Comment et quels seront les processus et données qui vont transiter ?","")),"") | E20: =IF(TRIM(B20)="","",IF(TRIM(C20)="",0,1)) | I20: Très haut | J20: 0
B21: =IF(C2="Oui existant","Quel est le niveau de personnalisation de l’Application ?",IF(C7="COTS","Quel est le niveau de personnalisation prévu de l’Application ?","")) | E21: =IF(TRIM(B21)="","",IF(TRIM(C21)="",0,1)) | G21: =IF(AND(TRIM(B21)<>"",TRIM(C21)<>""),IF(ISNA(VLOOKUP(C21,I20:J24,2,0)),1,VLOOKUP(C21,I20:J24,2,0)),"") | H21: =IF(AND(TRIM(B21)<>"",TRIM(C21)<>""),10,"") | I21: Haut | J21: 2
B22: =IF(C2="Oui existant","Quelle(s) technologie(s) sous-jacente(s) ?","") | E22: =IF(TRIM(B22)="","",IF(TRIM(C22)="",0,1)) | I22: Moyen | J22: 4
B23: =IF(C2="Oui existant","Est-ce que cette solution dispose d'une interface Mobile?",IF(AND(C7<>"Non prévu",C7<>""),"Est-ce qu'il est prévu une version Mobile ?","")) | E23: =IF(TRIM(B23)="","",IF(TRIM(C23)="",0,1)) | G23: =IF(AND(TRIM(B23)<>"",TRIM(C23)<>""),IF(C23="Oui",5,0),"") | H23: =IF(AND(TRIM(B23)<>"",TRIM(C23)<>""),5,"") | I23: Faible | J23: 6
B24: =IF(AND(C7<>"Non prévu",C7<>""),IF(C23="Oui","Dispose-t-elle d'une version smartphone ou tablette ou les 2 ?",""),"") | E24: =IF(TRIM(B24)="","",IF(TRIM(C24)="",0,1)) | G24: =IF(AND(TRIM(B24)<>"",TRIM(C24)<>""),IF(C24="Les 2",5,4),"") | H24: =IF(AND(TRIM(B24)<>"",TRIM(C24)<>""),5,"") | I24: Inexistant | J24: 10
B25: =IF(C2="Oui existant","Est-ce qu'il est prévu de remplacer cette solution par une autre ? Si oui, veuillez mettre le nom de la nouvelle solution et la période prévue dans la colonne détails","") | E25: =IF(TRIM(B25)="","",IF(TRIM(C25)="",0,1))
B26: =IF(C2="Oui existant","Quel est le nombre d’utilisateurs finaux de cette application ?",IF(AND(C7<>"Non prévu",C7<>""),"Quel est le nombre d’utilisateurs finaux prévus pour cette application ?","")) | E26: =IF(TRIM(B26)="","",IF(TRIM(C26)="",0,1))
B27: =IF(C2="Oui existant","Y a-t-il des utilisateurs du Groupe sur les activités de la filiale ?","") | E27: =IF(TRIM(B27)="","",IF(TRIM(C27)="",0,1))
B28: =IF(C27="Oui","Quel est le ratio ?","") | E28: =IF(TRIM(B28)="","",IF(TRIM(C28)="",0,1))
B29: =IF(C2="Oui existant","Quels ont été les acquisitions de licences détaillées (nombre, date, coût) ?","") | E29: =IF(TRIM(B29)="","",IF(TRIM(C29)="",0,1))
B30: =IF(C2="Oui existant","Quel est le nombre actuel de licences détenues par la filiale?",IF(C7="COTS","Combien de licences projettez-vous d'acquérir ?","")) | E30: =IF(TRIM(B30)="","",IF(TRIM(C30)="",0,1))
B31: =IF(C2="Oui existant","Quel type de licences (nominatives/partagées) ?",IF(C7="COTS","Est-ce que ce sera des licences nominatives ou partagées ?","")) | E31: =IF(TRIM(B31)="","",IF(TRIM(C31)="",0,1))
B32: =IF(C2="Oui existant","Des licences supplémentaires sont-elles nécessaires pour l'utilisation de l'application (outil supplémentaire, interfaces, modules complémentaires, …) ? Par module / par utilisateur ?",IF(C7="COTS","Est-ce que vous projettez d'acquérir d'autres licences dans un second temps ? combien et quand ?","")) | E32: =IF(TRIM(B32)="","",IF(TRIM(C32)="",0,1))
B33: =IF(C2="Oui existant","Quel est le coût du support éditeur ?",IF(C7="COTS","Quel sera le coût du support éditeur ?","")) | E33: =IF(TRIM(B33)="","",IF(TRIM(C33)="",0,1))
B34: =IF(C2="Oui existant","Existe-t-il un contrat de support avec un fournisseur ou un partenaire ? Pouvez-vous le partager ?","") | E34: =IF(TRIM(B34)="","",IF(TRIM(C34)="",0,1)) | G34: =IF(AND(TRIM(B34)<>"",TRIM(C34)<>""),IF(C34="Oui",5,0),"") | H34: =IF(AND(TRIM(B34)<>"",TRIM(C34)<>""),5,"")
B35: =IF(C2="Oui existant","Le contrat est-il global couvrant plusieurs filiales ou dédié à la filiale ?",IF(C7="COTS","Projettez-vous une acquisition individuelle ou groupe ?","")) | E35: =IF(TRIM(B35)="","",IF(TRIM(C35)="",0,1))
B36: =IF(C2="Oui existant","Le contrat comprend-il un SLA formel ? Cela inclut-il un engagement de performance ?","") | E36: =IF(TRIM(B36)="","",IF(TRIM(C36)="",0,1)) | G36: =IF(AND(TRIM(B36)<>"",TRIM(C36)<>""),IF(C36="Oui et oui",5,IF(C36="Oui et non",3,0)),"") | H36: =IF(AND(TRIM(B36)<>"",TRIM(C36)<>""),5,"")
B37: =IF(C2="Oui existant","Combien de ETP internes sont dédiés aux support (Niveaux 1, 2 et 3) de cette solution ? Veuillez décrire dans la colonne détail de quelle entité sont-ils (Holding ou pays), la répartition des principales activités, les compétences et les rôles",IF(AND(C7<>"Non prévu",C7<>""),"Combien de ETP internes projettez-vous de dédier aux support (Niveaux 1, 2 et 3) de cette solution ?","")) | E37: =IF(TRIM(B37)="","",IF(TRIM(C37)="",0,IF(TRIM(D37)="",0.5,1)))
B38: =IF(C2="Oui existant","Combien de ETP internes sont dédiés aux changes opérés sur cette solution (incluant Dev, Config, Mise en prod) ? Veuillez décrire dans la col. détail de quelle entité sont-ils (Holding ou pays), la répartition des activités, les compétences et les rôles",IF(AND(C7<>"Non prévu",C7<>""),"Combien de ETP internes projettez-vous de dédier aux futurs changes sur cette solution (incluant Dev, Config, Mise en prod) ?","")) | E38: =IF(TRIM(B38)="","",IF(TRIM(C38)="",0,IF(TRIM(D38)="",0.5,1)))
B39: =IF(C2="Oui existant","Qui administre cette solution et apporte le support aux utilisateurs l'IT Groupe, l'IT local ou les 2 ?",IF(AND(C7<>"Non prévu",C7<>""),"Qui va administrer cette solution et apporter le support aux utilisateurs: l'IT Groupe, l'IT local ou les 2 ?","")) | E39: =IF(TRIM(B39)="","",IF(TRIM(C39)="",0,1))
B40: =IF(C39="Les 2","A quelle proportion chacun ? et existe-t-il un SLA interne entre Group IT et la filiale ? S'il existe, pouvez-vous le partager vous pouvez décrire dans la partie détails les responsabilités de chaque partie","") | E40: =IF(TRIM(B40)="","",IF(TRIM(C40)="",0,1))
B41: =IF(C2="Oui existant","Avez-vous un historique des KPI pour la disponibilité et le support de cette application ? Si oui, pouvez-vous les partager","") | E41: =IF(TRIM(B41)="","",IF(TRIM(C41)="",0,1)) | G41: =IF(AND(TRIM(B41)<>"",TRIM(C41)<>""),IF(C41="Oui",3,0),"") | H41: =IF(AND(TRIM(B41)<>"",TRIM(C41)<>""),3,"")
B42: =IF(C2="Oui existant","Existe-t-il un processus de suivi des contrats groupe et tiers ?","") | E42: =IF(TRIM(B42)="","",IF(TRIM(C42)="",0,1)) | G42: =IF(AND(TRIM(B42)<>"",TRIM(C42)<>""),IF(C42="Oui",3,0),"") | H42: =IF(AND(TRIM(B42)<>"",TRIM(C42)<>""),3,"")
B43: =IF(C2="Oui existant","L'application est-elle installée sur site ou utilisée sur le Cloud (SaaS) ?",IF(AND(C7<>"Non prévu",C7<>""),"La nouvelle solution sera-t-elle installée sur site ou utilisée sur le Cloud (SaaS) ?","")) | E43: =IF(TRIM(B43)="","",IF(TRIM(C43)="",0,1)) | G43: =IF(AND(TRIM(B43)<>"",TRIM(C43)<>""),IF(C43="Cloud",5,2),"") | H43: =IF(AND(TRIM(B43)<>"",TRIM(C43)<>""),5,"")
B44: =IF(AND(C43="Cloud",C7="COTS"),"Est-ce entièrement SaaS ou Infra gérée par l'équipe locale ?","") | E44: =IF(TRIM(B44)="","",IF(TRIM(C44)="",0,1)) | G44: =IF(AND(TRIM(B44)<>"",TRIM(C44)<>""),IF(C44="SaaS",5,2),"") | H44: =IF(AND(TRIM(B44)<>"",TRIM(C44)<>""),5,"")
B45: =IF(C2="Oui existant","S'agit-il d'une architecture Client/Serveur à 3 niveaux ? Décrivez s'il vous plait","") | E45: =IF(TRIM(B45)="","",IF(TRIM(C45)="",0,IF(TRIM(D45)="",0.5,1)))
B46: =IF(C43="On-site","Comment sont acquis les serveurs (achat/location/sous-traitance) ?","") | E46: =IF(TRIM(B46)="","",IF(TRIM(C46)="",0,1))
B47: =IF(C2="Oui existant","Où sont installés les serveurs ?","") | E47: =IF(TRIM(B47)="","",IF(TRIM(C47)="",0,1))
B48: =IF(C2="Oui existant","Sur quels systèmes (versions) cette application s'exécute-t-elle ?",IF(AND(C7<>"Non prévu",C7<>""),"Sur quels systèmes (versions) cette application sera-t-elle implémentée ?","")) | E48: =IF(TRIM(B48)="","",IF(TRIM(C48)="",0,1))
B49: =IF(C2="Oui existant","Sur quelle base de données cette application tourne-t-elle ?",IF(AND(C7<>"Non prévu",C7<>""),"Sur quelle base de données cette application tournera-t-elle ?","")) | E49: =IF(TRIM(B49)="","",IF(TRIM(C49)="",0,1))
B50: =IF(C2="Oui existant","Existe-t-il une architecture haute disponibilité (réplication) ?",IF(AND(C7<>"Non prévu",C7<>""),"Est-ce qu'il est prévu une architecture haute disponibilité (réplication) ?","")) | E50: =IF(TRIM(B50)="","",IF(TRIM(C50)="",0,1)) | G50: =IF(AND(TRIM(B50)<>"",TRIM(C50)<>""),IF(C50="Oui",5,0),"") | H50: =IF(AND(TRIM(B50)<>"",TRIM(C50)<>""),5,"")
B51: =IF(C50="Oui","Entièrement ou partiellement ? Actif-Actif ou Actif-Passif ?","") | E51: =IF(TRIM(B51)="","",IF(TRIM(C51)="",0,1))
B52: =IF(C2="Oui existant","Existe-t-il un plan de récupération pour cette application ?","") | E52: =IF(TRIM(B52)="","",IF(TRIM(C52)="",0,1)) | G52: =IF(AND(TRIM(B52)<>"",TRIM(C52)<>""),IF(C52="Oui",5,0),"") | H52: =IF(AND(TRIM(B52)<>"",TRIM(C52)<>""),5,"")
B53: =IF(C2="Oui existant","Qui gère les données de la base de données ?",IF(AND(C7<>"Non prévu",C7<>""),"Qui va gèrer les données de la base de données ?","")) | E53: =IF(TRIM(B53)="","",IF(TRIM(C53)="",0,1))
B54: =IF(C2="Oui existant","Quelles sont les interfaces existantes de cette application ? Veuillez décrire et partager tout document d'architecture",IF(AND(C7<>"Non prévu",C7<>""),"Quelles sont les interfaces prévues ? Veuillez décrire et partager tout document d'architecture cible","")) | E54: =IF(TRIM(B54)="","",IF(TRIM(C54)="",0,IF(TRIM(D54)="",0.5,1)))
B55: =IF(C2="Oui existant","L'application est-elle complètement en temps réel ou y'a-t-il des batchs la nuit ? Décrivez s'il vous plait",IF(AND(C7<>"Non prévu",C7<>""),"L'application sera-t-elle complètement en temps réel ou y'aura-t-il des batchs la nuit ? Décrivez s'il vous plait","")) | E55: =IF(TRIM(B55)="","",IF(TRIM(C55)="",0,IF(TRIM(D55)="",0.5,1)))
B56: =IF(C2="Oui existant","Avez-vous connaissance d'un quelconque problème potentiel lié à la continuité de cette application (par exemple départ ou indisponibilité des ressources clés, fin de support, bug critique, ...), si oui lequel dans détails ?","") | E56: =IF(TRIM(B56)="","",IF(TRIM(C56)="",0,1)) | G56: =IF(AND(TRIM(B56)<>"",TRIM(C56)<>""),IF(C56="Oui",0,10),"") | H56: =IF(AND(TRIM(B56)<>"",TRIM(C56)<>""),10,"")
B57: =IF(C2="Oui existant","Est-ce que des sauvegardes sont réalisées régulièrement ?",IF(AND(C7<>"Non prévu",C7<>""),"Est-ce que des sauvegardes sont prévus dès l'implémentation ?","")) | E57: =IF(TRIM(B57)="","",IF(TRIM(C57)="",0,1)) | G57: =IF(AND(TRIM(B57)<>"",TRIM(C57)<>""),IF(C57="Oui",5,0),"") | H57: =IF(AND(TRIM(B57)<>"",TRIM(C57)<>""),5,"")
B58: =IF(C57="Oui","A quelle fréquence sont-elles exécutées?","") | E58: =IF(TRIM(B58)="","",IF(TRIM(C58)="",0,1)) | H58: =IF(AND(TRIM(B58)<>"",TRIM(C58)<>""),3,"")
B59: =IF(C57="Oui","Avez-vous une politique de rétention en place ? Si oui, pouvez-vous me la partager?","") | E59: =IF(TRIM(B59)="","",IF(TRIM(C59)="",0,1)) | G59: =IF(AND(TRIM(B59)<>"",TRIM(C59)<>""),IF(C59="Oui",2,0),"") | H59: =IF(AND(TRIM(B59)<>"",TRIM(C59)<>""),2,"")
B60: =IF(C57="Oui","Quelle est la solution de sauvegarde/récupération utilisée ?","") | E60: =IF(TRIM(B60)="","",IF(TRIM(C60)="",0,1)) | H60: =IF(AND(TRIM(B60)<>"",TRIM(C60)<>""),3,"")
B61: =IF(C57="Oui","Quelle est la taille totale estimée des sauvegardes ?","") | E61: =IF(TRIM(B61)="","",IF(TRIM(C61)="",0,1))
G62: =SUM(G5:G61) -> 0 | H62: =SUM(H5:H61) -> 5
A123: Combien de ces demandes surviennent en moyenne par an ?

Sheet AML
A1: Retour à la page d'accueil | C1: Réponse corrigé à partir du fichier CTI
B2: Anti Money Laundering - Anti blanchiment | C2: Oui existant
B3: Veuillez répondre à toutes les questions et donner plus de détails (colonne D) lorsque nécessaire, un taux de remplissage est calculé dans le sommaire et devrait être à 100%
B4: Certaines questions peuvent en faire apparaitre de nouvelles auxquelles il faudra répondre, cela entre également dans le calcul du taux de remplissage
B6: Questions | C6: Réponses | D6: Détails | E6: Eval | F6: Complément
B7: =IF(C2="Oui existant","COTS ou Développement interne? (Commercial Off-The-Shelf solution)","Vous prévoyez quel type de solution?: COTS ou Développement interne? (Commercial Off-The-Shelf solution)") -> COTS ou Développement interne? (Commercial Off-The-Shelf solution) | C7: COTS | E7: =IF(TRIM(B7)="","",IF(TRIM(C7)="",0,1)) -> 1 | F7: Non
B8: =IF(C7="COTS","Nom de l'éditeur","") -> Nom de l'éditeur | C8: Vneuron | E8: =IF(TRIM(B8)="","",IF(TRIM(C8)="",0,1)) -> 1 | F8: Non
B9: =IF(C2="Oui existant","Nom de la solution",IF(AND(C7<>"Non prévu",C7<>""),"Nom de la solution (si déjà identifiée)","")) -> Nom de la solution | C9: REIS | E9: =IF(TRIM(B9)="","",IF(TRIM(C9)="",0,1)) -> 1 | F9: Non
B10: =IF(C2="Oui existant","Quelle est la version/release de l'application ?",IF(C7="COTS","Quelle est la version/release qui sera implémentée ?","")) -> Quelle est la version/release de l'application ? | C10: Vneuron © Reis™ RCS 4.1 | E10: =IF(TRIM(B10)="","",IF(TRIM(C10)="",0,1)) -> 1 | F10: Non
B11: =IF(C2="Oui existant","Quelle est la dernière version de l'application ?",IF(C7="COTS","Quelle est la dernière version de cette nouvelle solution ?","")) -> Quelle est la dernière version de l'application ? | C11: 4.1 | E11: =IF(TRIM(B11)="","",IF(TRIM(C11)="",0,1)) -> 1 | F11: Non
B12: =IF(C2="Oui existant","Etes-vous au courant d’une évolution majeure en cours sur cette application","") -> Etes-vous au courant d’une évolution majeure en cours sur cette application | C12: Non | E12: =IF(TRIM(B12)="","",IF(TRIM(C12)="",0,1)) -> 1 | F12: Non
B13: =IF(C2="Oui existant","Qui contrôle les évolutions sur cette Application ?","") -> Qui contrôle les évolutions sur cette Application ? | C13: Le partenaire Vneuron | E13: =IF(TRIM(B13)="","",IF(TRIM(C13)="",0,1)) -> 1 | F13: Non
B14: =IF(C2="Oui existant","Quelle est la criticité de cette application ? combien de temps peut-on supporter son indisponibilité (colonne détail) ?","Quelle est la criticité de ce besoin ?") -> Quelle est la criticité de cette application ? combien de temps peut-on supporter son indisponibilité (colonne détail) ? | C14: Critique | E14: =IF(TRIM(B14)="","",IF(TRIM(C14)="",0,1)) -> 1 | F14: Non
B15: =IF(C7="COTS","Est-ce un module du CBS ou une solution séparée?","") -> Est-ce un module du CBS ou une solution séparée? | C15: Solution séparée | E15: =IF(TRIM(B15)="","",IF(TRIM(C15)="",0,1)) -> 1 | F15: Non
B16: =IF(C2="Oui existant","Quand l’application a-t-elle été implémentée ?",IF(AND(C7<>"Non prévu",C7<>""),"Quand l’application sera-t-elle implémentée ?","")) -> Quand l’application a-t-elle été implémentée ? | C16: 2024 | E16: =IF(TRIM(B16)="","",IF(TRIM(C16)="",0,1)) -> 1 | F16: Non
B17: =IF(C2="Oui existant","Qui l'a implémenté ?",IF(AND(C7<>"Non prévu",C7<>""),"Qui doit l'implémenter ?","")) -> Qui l'a implémenté ? | C17: Vneuron avec le support de IT groupe | E17: =IF(TRIM(B17)="","",IF(TRIM(C17)="",0,1)) -> 1 | F17: Non
B18: =IF(C2="Oui existant","Quels sont les processus fonctionnels couverts ?",IF(AND(C7<>"Non prévu",C7<>""),"Quels sont les processus fonctionnels qui doivent être couverts ?","")) -> Quels sont les processus fonctionnels couverts ? | C18: évaluation du risque pour tout nouveau client qui souhaite ouvrir un compte ; le filtrage et le profilage s’effectue lors de la demande d’ouverture de compte | E18: =IF(TRIM(B18)="","",IF(TRIM(C18)="",0,1)) -> 1 | F18: Non
B19: =IF(C2="Oui existant","Est-ce que la solution est integrée au CBS ?",IF(AND(C7<>"Non prévu",C7<>""),"Est-ce que la solution sera integrée au CBS ?","")) -> Est-ce que la solution est integrée au CBS ? | C19: Oui | D19: L'application récupère de facon automatique la liste des clients existant dans le Core Banking et mets à jour sa base de données | E19: =IF(TRIM(B19)="","",IF(TRIM(C19)="",0,1)) -> 1 | F19: Si le client est présent sur les listes, l'utilisateur peut continuer? L'utilisateur confirme la correspondance trouvée et ne poursuit plus l'enroulement du client dans le Core Banking
B20: =IF(C19="Oui",IF(C2="Oui existant","Comment et quels sont les processus et données qui transitent ?",IF(AND(C7<>"Non prévu",C7<>""),"Comment et quels seront les processus et données qui vont transiter ?","")),"") -> Comment et quels sont les processus et données qui transitent ? | C20: NA | E20: =IF(TRIM(B20)="","",IF(TRIM(C20)="",0,1)) -> 1
B21: =IF(C2="Oui existant","Quel est le niveau de personnalisation de l’Application ?",IF(C7="COTS","Quel est le niveau de personnalisation prévu de l’Application ?","")) -> Quel est le niveau de personnalisation de l’Application ? | C21: Très haut | D21: Haut | E21: =IF(TRIM(B21)="","",IF(TRIM(C21)="",0,1)) -> 1 | F21: Détails
B22: =IF(C2="Oui existant","Quelle(s) technologie(s) sous-jacente(s) ?","") -> Quelle(s) technologie(s) sous-jacente(s) ? | C22: NA | E22: =IF(TRIM(B22)="","",IF(TRIM(C22)="",0,1)) -> 1 | F22: Détails
B23: =IF(C2="Oui existant","Est-ce que cette solution dispose d'une interface Mobile?",IF(AND(C7<>"Non prévu",C7<>""),"Est-ce qu'il est prévu une version Mobile ?","")) -> Est-ce que cette solution dispose d'une interface Mobile? | C23: Non | E23: =IF(TRIM(B23)="","",IF(TRIM(C23)="",0,1)) -> 1 | F23: Non
B24: =IF(AND(C7<>"Non prévu",C7<>""),IF(C23="Oui","Dispose-t-elle d'une version smartphone ou tablette ou les 2 ?",""),"") | E24: =IF(TRIM(B24)="","",IF(TRIM(C24)="",0,1))
B25: =IF(C2="Oui existant","Est-ce qu'il est prévu de remplacer cette solution par une autre ? Si oui, veuillez mettre le nom de la nouvelle solution et la période prévue dans la colonne détails","") -> Est-ce qu'il est prévu de remplacer cette solution par une autre ? Si oui, veuillez mettre le nom de la nouvelle solution et la période prévue dans la colonne détails | C25: Non | E25: =IF(TRIM(B25)="","",IF(TRIM(C25)="",0,1)) -> 1 | F25: Non
B26: =IF(C2="Oui existant","Quel est le nombre d’utilisateurs finaux de cette application ?",IF(AND(C7<>"Non prévu",C7<>""),"Quel est le nombre d’utilisateurs finaux prévus pour cette application ?","")) -> Quel est le nombre d’utilisateurs finaux de cette application ? | C26: une vingtaine | E26: =IF(TRIM(B26)="","",IF(TRIM(C26)="",0,1)) -> 1 | F26: Non
B27: =IF(C2="Oui existant","Y a-t-il des utilisateurs du Groupe sur les activités de la filiale ?","") -> Y a-t-il des utilisateurs du Groupe sur les activités de la filiale ? | C27: Oui | E27: =IF(TRIM(B27)="","",IF(TRIM(C27)="",0,1)) -> 1 | F27: Non
B28: =IF(C27="Oui","Quel est le ratio ?","") -> Quel est le ratio ? | C28: NA | E28: =IF(TRIM(B28)="","",IF(TRIM(C28)="",0,1)) -> 1
B29: =IF(C2="Oui existant","Quels ont été les acquisitions de licences détaillées (nombre, date, coût) ?","") -> Quels ont été les acquisitions de licences détaillées (nombre, date, coût) ? | C29: NA | E29: =IF(TRIM(B29)="","",IF(TRIM(C29)="",0,1)) -> 1 | F29: Non
B30: =IF(C2="Oui existant","Quel est le nombre actuel de licences détenues par la filiale?",IF(C7="COTS","Combien de licences projettez-vous d'acquérir ?","")) -> Quel est le nombre actuel de licences détenues par la filiale? | C30: une licence par filiale | E30: =IF(TRIM(B30)="","",IF(TRIM(C30)="",0,1)) -> 1 | F30: Non
B31: =IF(C2="Oui existant","Quel type de licences (nominatives/partagées) ?",IF(C7="COTS","Est-ce que ce sera des licences nominatives ou partagées ?","")) -> Quel type de licences (nominatives/partagées) ? | C31: Partagées | E31: =IF(TRIM(B31)="","",IF(TRIM(C31)="",0,1)) -> 1 | F31: Non
B32: =IF(C2="Oui existant","Des licences supplémentaires sont-elles nécessaires pour l'utilisation de l'application (outil supplémentaire, interfaces, modules complémentaires, …) ? Par module / par utilisateur ?",IF(C7="COTS","Est-ce que vous projettez d'acquérir d'autres licences dans un second temps ? combien et quand ?","")) -> Des licences supplémentaires sont-elles nécessaires pour l'utilisation de l'application (outil supplémentaire, interfaces, modules complémentaires, …) ? Par module / par utilisateur ? | C32: OUI | D32: OUI | E32: =IF(TRIM(B32)="","",IF(TRIM(C32)="",0,1)) -> 1 | F32: Non
B33: =IF(C2="Oui existant","Quel est le coût du support éditeur ?",IF(C7="COTS","Quel sera le coût du support éditeur ?","")) -> Quel est le coût du support éditeur ? | C33: NA | E33: =IF(TRIM(B33)="","",IF(TRIM(C33)="",0,1)) -> 1 | F33: Non
B34: =IF(C2="Oui existant","Existe-t-il un contrat de support avec un fournisseur ou un partenaire ? Pouvez-vous le partager ?","") -> Existe-t-il un contrat de support avec un fournisseur ou un partenaire ? Pouvez-vous le partager ? | C34: Oui | E34: =IF(TRIM(B34)="","",IF(TRIM(C34)="",0,1)) -> 1 | F34: Pouvez-vous le partager?
B35: =IF(C2="Oui existant","Le contrat est-il global couvrant plusieurs filiales ou dédié à la filiale ?",IF(C7="COTS","Projettez-vous une acquisition individuelle ou groupe ?","")) -> Le contrat est-il global couvrant plusieurs filiales ou dédié à la filiale ? | C35: Global | E35: =IF(TRIM(B35)="","",IF(TRIM(C35)="",0,1)) -> 1 | F35: Non
B36: =IF(C2="Oui existant","Le contrat comprend-il un SLA formel ? Cela inclut-il un engagement de performance ?","") -> Le contrat comprend-il un SLA formel ? Cela inclut-il un engagement de performance ? | C36: Oui et non | E36: =IF(TRIM(B36)="","",IF(TRIM(C36)="",0,1)) -> 1 | F36: Pouvez-vous les partager?
B37: =IF(C2="Oui existant","Combien de ETP internes sont dédiés aux support (Niveaux 1, 2 et 3) de cette solution ? Veuillez décrire dans la colonne détail de quelle entité sont-ils (Holding ou pays), la répartition des principales activités, les compétences et les rôles",IF(AND(C7<>"Non prévu",C7<>""),"Combien de ETP internes projettez-vous de dédier aux support (Niveaux 1, 2 et 3) de cette solution ?","")) -> Combien de ETP internes sont dédiés aux support (Niveaux 1, 2 et 3) de cette solution ? Veuillez décrire dans la colonne détail de quelle entité sont-ils (Holding ou pays), la répartition des principales activités, les compétences et les rôles | C37: 1. Niveau 1 : o Nombre d'ETP : 4 o Répartition des Activités : Résolution des tickets de premier niveau, support de base aux utilisateurs, gestion des demandes simples et Analyse des incidents 2. Niveau 2 : o Nombre d'ETP : 5 o Entité : Holding o Répartition des Activités : Analyse des incidents plus complexes, gestion des escalades du niveau 1, résolution de problèmes techniques avancés. o Compétences : Expertise technique, capacité à résoudre des problèmes complexes. o Rôles : Technicien Support Niveau 2 3. Niveau 3 : o Nombre d'ETP : DEFINIR o Entité : PROVIDER o Répartition des Activités : Gestion des problèmes critiques, développement de solutions, coordination avec les équipes de développement. o Compétences : Expertise approfondie, compétences en développement et en gestion des incidents majeurs. o Rôles : Ingénieur Support Niveau 3 | D37: Niveau 1: Holding : ETP dédiés : 5 Niveau 2 : Filiale : ETP dédiés : 4 Niveau 3 : Nombre d'ETP : DEFINIR par IT GROUPE | E37: =IF(TRIM(B37)="","",IF(TRIM(C37)="",0,IF(TRIM(D37)="",0.5,1))) -> 1 | F37: Je n'ai pas compris
B38: =IF(C2="Oui existant","Combien de ETP internes sont dédiés aux changes opérés sur cette solution (incluant Dev, Config, Mise en prod) ? Veuillez décrire dans la col. détail de quelle entité sont-ils (Holding ou pays), la répartition des activités, les compétences et les rôles",IF(AND(C7<>"Non prévu",C7<>""),"Combien de ETP internes projettez-vous de dédier aux futurs changes sur cette solution (incluant Dev, Config, Mise en prod) ?","")) -> Combien de ETP internes sont dédiés aux changes opérés sur cette solution (incluant Dev, Config, Mise en prod) ? Veuillez décrire dans la col. détail de quelle entité sont-ils (Holding ou pays), la répartition des activités, les compétences et les rôles | C38: Holding : ETP dédiés : 5 Filiale : ETP dédiés : 1 | D38: Holding : ETP dédiés : 5 Filiale : ETP dédiés : 1 | E38: =IF(TRIM(B38)="","",IF(TRIM(C38)="",0,IF(TRIM(D38)="",0.5,1))) -> 1 | F38: Je n'ai pas compris
B39: =IF(C2="Oui existant","Qui administre cette solution et apporte le support aux utilisateurs l'IT Groupe, l'IT local ou les 2 ?",IF(AND(C7<>"Non prévu",C7<>""),"Qui va administrer cette solution et apporter le support aux utilisateurs: l'IT Groupe, l'IT local ou les 2 ?","")) -> Qui administre cette solution et apporte le support aux utilisateurs l'IT Groupe, l'IT local ou les 2 ? | C39: Les 2 | D39: IT local gère la créatiin des utilisateurs, les problèmes d'accès interne à l'application, la suppression des entrées erronées suite à la demande des CC, IT Groupe gère la disponibilité de l'application au niveau du Data Center, les sauvegardes, les problèmes de communication entre l'application et le core banking, les bugs | E39: =IF(TRIM(B39)="","",IF(TRIM(C39)="",0,1)) -> 1 | F39: Qui fait quoi?
B40: =IF(C39="Les 2","A quelle proportion chacun ? et existe-t-il un SLA interne entre Group IT et la filiale ? S'il existe, pouvez-vous le partager vous pouvez décrire dans la partie détails les responsabilités de chaque partie","") -> A quelle proportion chacun ? et existe-t-il un SLA interne entre Group IT et la filiale ? S'il existe, pouvez-vous le partager vous pouvez décrire dans la partie détails les responsabilités de chaque partie | C40: NON | D40: NON | E40: =IF(TRIM(B40)="","",IF(TRIM(C40)="",0,1)) -> 1 | F40: Pourquoi?
B41: =IF(C2="Oui existant","Avez-vous un historique des KPI pour la disponibilité et le support de cette application ? Si oui, pouvez-vous les partager","") -> Avez-vous un historique des KPI pour la disponibilité et le support de cette application ? Si oui, pouvez-vous les partager | C41: Non | D41: NON | E41: =IF(TRIM(B41)="","",IF(TRIM(C41)="",0,1)) -> 1 | F41: Pourquoi?
B42: =IF(C2="Oui existant","Existe-t-il un processus de suivi des contrats groupe et tiers ?","") -> Existe-t-il un processus de suivi des contrats groupe et tiers ? | C42: Non | E42: =IF(TRIM(B42)="","",IF(TRIM(C42)="",0,1)) -> 1 | F42: Pouvez-vous le partager?
B43: =IF(C2="Oui existant","L'application est-elle installée sur site ou utilisée sur le Cloud (SaaS) ?",IF(AND(C7<>"Non prévu",C7<>""),"La nouvelle solution sera-t-elle installée sur site ou utilisée sur le Cloud (SaaS) ?","")) -> L'application est-elle installée sur site ou utilisée sur le Cloud (SaaS) ? | C43: Cloud | E43: =IF(TRIM(B43)="","",IF(TRIM(C43)="",0,1)) -> 1 | F43: Non
B44: =IF(AND(C43="Cloud",C7="COTS"),"Est-ce entièrement SaaS ou Infra gérée par l'équipe locale ?","") -> Est-ce entièrement SaaS ou Infra gérée par l'équipe locale ? | C44: SaaS | E44: =IF(TRIM(B44)="","",IF(TRIM(C44)="",0,1)) -> 1 | F44: Non
B45: =IF(C2="Oui existant","S'agit-il d'une architecture Client/Serveur à 3 niveaux ? Décrivez s'il vous plait","") -> S'agit-il d'une architecture Client/Serveur à 3 niveaux ? Décrivez s'il vous plait | C45: Oui | D45: L'architecture client/serveur à deux niveaux | E45: =IF(TRIM(B45)="","",IF(TRIM(C45)="",0,IF(TRIM(D45)="",0.5,1))) -> 1 | F45: Non
B46: =IF(C43="On-site","Comment sont acquis les serveurs (achat/location/sous-traitance) ?","") | E46: =IF(TRIM(B46)="","",IF(TRIM(C46)="",0,1)) | F46: Non
B47: =IF(C2="Oui existant","Où sont installés les serveurs ?","") -> Où sont installés les serveurs ? | C47: La solution Reis Cloud est hébergée dans un data center Microsoft Azure, basé à l'Europe de l’Ouest. Le site principal du Datacenter Azure se trouve dans la ville d’Amsterdam. Les autres sites (de secours et de réplication) sont situés dans la même zone d'Amsterdam. | E47: =IF(TRIM(B47)="","",IF(TRIM(C47)="",0,1)) -> 1 | F47: Non
B48: =IF(C2="Oui existant","Sur quels systèmes (versions) cette application s'exécute-t-elle ?",IF(AND(C7<>"Non prévu",C7<>""),"Sur quels systèmes (versions) cette application sera-t-elle implémentée ?","")) -> Sur quels systèmes (versions) cette application s'exécute-t-elle ? | C48: NA | E48: =IF(TRIM(B48)="","",IF(TRIM(C48)="",0,1)) -> 1 | F48: Non
B49: =IF(C2="Oui existant","Sur quelle base de données cette application tourne-t-elle ?",IF(AND(C7<>"Non prévu",C7<>""),"Sur quelle base de données cette application tournera-t-elle ?","")) -> Sur quelle base de données cette application tourne-t-elle ? | C49: NA | E49: =IF(TRIM(B49)="","",IF(TRIM(C49)="",0,1)) -> 1 | F49: Non
B50: =IF(C2="Oui existant","Existe-t-il une architecture haute disponibilité (réplication) ?",IF(AND(C7<>"Non prévu",C7<>""),"Est-ce qu'il est prévu une architecture haute disponibilité (réplication) ?","")) -> Existe-t-il une architecture haute disponibilité (réplication) ? | C50: Non | E50: =IF(TRIM(B50)="","",IF(TRIM(C50)="",0,1)) -> 1 | F50: Non
B51: =IF(C50="Oui","Entièrement ou partiellement ? Actif-Actif ou Actif-Passif ?","") | E51: =IF(TRIM(B51)="","",IF(TRIM(C51)="",0,1))
B52: =IF(C2="Oui existant","Existe-t-il un plan de récupération pour cette application ?","") -> Existe-t-il un plan de récupération pour cette application ? | C52: Non | E52: =IF(TRIM(B52)="","",IF(TRIM(C52)="",0,1)) -> 1 | F52: Pouvez-vous le partager?
B53: =IF(C2="Oui existant","Qui gère les données de la base de données ?",IF(AND(C7<>"Non prévu",C7<>""),"Qui va gèrer les données de la base de données ?","")) -> Qui gère les données de la base de données ? | C53: NA | E53: =IF(TRIM(B53)="","",IF(TRIM(C53)="",0,1)) -> 1 | F53: Pourquoi?
B54: =IF(C2="Oui existant","Quelles sont les interfaces existantes de cette application ? Veuillez décrire et partager tout document d'architecture",IF(AND(C7<>"Non prévu",C7<>""),"Quelles sont les interfaces prévues ? Veuillez décrire et partager tout document d'architecture cible","")) -> Quelles sont les interfaces existantes de cette application ? Veuillez décrire et partager tout document d'architecture | C54: NA | D54: NA | E54: =IF(TRIM(B54)="","",IF(TRIM(C54)="",0,IF(TRIM(D54)="",0.5,1))) -> 1 | F54: Pourquoi?
B55: =IF(C2="Oui existant","L'application est-elle complètement en temps réel ou y'a-t-il des batchs la nuit ? Décrivez s'il vous plait",IF(AND(C7<>"Non prévu",C7<>""),"L'application sera-t-elle complètement en temps réel ou y'aura-t-il des batchs la nuit ? Décrivez s'il vous plait","")) -> L'application est-elle complètement en temps réel ou y'a-t-il des batchs la nuit ? Décrivez s'il vous plait | C55: L'appli est alimentée en data tous les jours à 07H30 | D55: NA | E55: =IF(TRIM(B55)="","",IF(TRIM(C55)="",0,IF(TRIM(D55)="",0.5,1))) -> 1 | F55: Non
B56: =IF(C2="Oui existant","Avez-vous connaissance d'un quelconque problème potentiel lié à la continuité de cette application (par exemple départ ou indisponibilité des ressources clés, fin de support, bug critique, ...), si oui lequel dans détails ?","") -> Avez-vous connaissance d'un quelconque problème potentiel lié à la continuité de cette application (par exemple départ ou indisponibilité des ressources clés, fin de support, bug critique, ...), si oui lequel dans détails ? | C56: Non | E56: =IF(TRIM(B56)="","",IF(TRIM(C56)="",0,1)) -> 1 | F56: Non
B57: =IF(C2="Oui existant","Est-ce que des sauvegardes sont réalisées régulièrement ?",IF(AND(C7<>"Non prévu",C7<>""),"Est-ce que des sauvegardes sont prévus dès l'implémentation ?","")) -> Est-ce que des sauvegardes sont réalisées régulièrement ? | C57: Oui | E57: =IF(TRIM(B57)="","",IF(TRIM(C57)="",0,1)) -> 1 | F57: Ce n'est pas contractualisé?
B58: =IF(C57="Oui","A quelle fréquence sont-elles exécutées?","") -> A quelle fréquence sont-elles exécutées? | C58: En cloud | E58: =IF(TRIM(B58)="","",IF(TRIM(C58)="",0,1)) -> 1
B59: =IF(C57="Oui","Avez-vous une politique de rétention en place ? Si oui, pouvez-vous me la partager?","") -> Avez-vous une politique de rétention en place ? Si oui, pouvez-vous me la partager? | C59: En cloud | E59: =IF(TRIM(B59)="","",IF(TRIM(C59)="",0,1)) -> 1
B60: =IF(C57="Oui","Quelle est la solution de sauvegarde/récupération utilisée ?","") -> Quelle est la solution de sauvegarde/récupération utilisée ? | C60: En cloud | E60: =IF(TRIM(B60)="","",IF(TRIM(C60)="",0,1)) -> 1
B61: =IF(C57="Oui","Quelle est la taille totale estimée des sauvegardes ?","") -> Quelle est la taille totale estimée des sauvegardes ? | C61: En cloud | E61: =IF(TRIM(B61)="","",IF(TRIM(C61)="",0,1)) -> 1
B62: =IF(C7="COTS","Est-ce que vous avez une autre solution de détection de fraude (autre que AML) ? Si oui, veuillez donner plus de détails dans la colonne D","") -> Est-ce que vous avez une autre solution de détection de fraude (autre que AML) ? Si oui, veuillez donner plus de détails dans la colonne D | E62: =IF(TRIM(B62)="","",IF(TRIM(C62)="",0,1)) -> 0
A123: Combien de ces demandes surviennent en moyenne par an ?

Sheet Collect
A1: Retour à la page d'accueil
B2: Collection - Outil de recouverement | C2: Oui existant | D2: Pourquoi vous n'utilisez pas le module de Flexcube? | F2: Nous utilisons actuellement l'application de recouvrement du CBS, mais elle ne couvre pas toutes les fonctionnalités d'une application de recouvrement.
B3: Veuillez répondre à toutes les questions et donner plus de détails (colonne D) lorsque nécessaire, un taux de remplissage est calculé dans le sommaire et devrait être à 100%
B4: Certaines questions peuvent en faire apparaitre de nouvelles auxquelles il faudra répondre, cela entre également dans le calcul du taux de remplissage
B6: Questions | C6: Réponses | D6: Détails | E6: Eval
B7: =IF(C2="Oui existant","COTS ou Développement interne? (Commercial Off-The-Shelf solution)","Vous prévoyez quel type de solution?: COTS ou Développement interne? (Commercial Off-The-Shelf solution)") -> COTS ou Développement interne? (Commercial Off-The-Shelf solution) | C7: Développement externalisé | D7: NA | E7: =IF(TRIM(B7)="","",IF(TRIM(C7)="",0,1)) -> 1 | G7: =IF(AND(TRIM(B7)<>"",TRIM(C7)<>""),IF(C7="COTS",5,IF(C7="Développement interne",3,IF(C7="Développement externalisé",5,0))),"") -> 5 | H7: =IF(AND(TRIM(B7)<>"",TRIM(C7)<>""),5,"") -> 5
B8: =IF(C7="COTS","Nom de l'éditeur","") | E8: =IF(TRIM(B8)="","",IF(TRIM(C8)="",0,1))
B9: =IF(C2="Oui existant","Nom de la solution",IF(AND(C7<>"Non prévu",C7<>""),"Nom de la solution (si déjà identifiée)","")) -> Nom de la solution | C9: Module : Collection | E9: =IF(TRIM(B9)="","",IF(TRIM(C9)="",0,1)) -> 1 | H9: =IF(AND(TRIM(B9)<>"",TRIM(C9)<>""),5,"") -> 5
B10: =IF(C2="Oui existant","Quelle est la version/release de l'application ?",IF(C7="COTS","Quelle est la version/release qui sera implémentée ?","")) -> Quelle est la version/release de l'application ? | C10: Version 14.7 | E10: =IF(TRIM(B10)="","",IF(TRIM(C10)="",0,1)) -> 1
B11: =IF(C2="Oui existant","Quelle est la dernière version de l'application ?",IF(C7="COTS","Quelle est la dernière version de cette nouvelle solution ?","")) -> Quelle est la dernière version de l'application ? | C11: Version 14.9 | E11: =IF(TRIM(B11)="","",IF(TRIM(C11)="",0,1)) -> 1
B12: =IF(C2="Oui existant","Etes-vous au courant d’une évolution majeure en cours sur cette application","") -> Etes-vous au courant d’une évolution majeure en cours sur cette application | C12: Non | E12: =IF(TRIM(B12)="","",IF(TRIM(C12)="",0,1)) -> 1
B13: =IF(C2="Oui existant","Qui contrôle les évolutions sur cette Application ?","") -> Qui contrôle les évolutions sur cette Application ? | C13: Oracle Corporation. | E13: =IF(TRIM(B13)="","",IF(TRIM(C13)="",0,1)) -> 1
B14: =IF(C2="Oui existant","Quelle est la criticité de cette application ? combien de temps peut-on supporter son indisponibilité (colonne détail) ?","Quelle est la criticité de ce besoin ?") -> Quelle est la criticité de cette application ? combien de temps peut-on supporter son indisponibilité (colonne détail) ? | C14: Critique | D14: NA | E14: =IF(TRIM(B14)="","",IF(TRIM(C14)="",0,1)) -> 1
B15: =IF(C7="COTS","Est-ce un module du CBS ou une solution séparée?","") | E15: =IF(TRIM(B15)="","",IF(TRIM(C15)="",0,1))
B16: =IF(C2="Oui existant","Quand l’application a-t-elle été implémentée ?",IF(AND(C7<>"Non prévu",C7<>""),"Quand l’application sera-t-elle implémentée ?","")) -> Quand l’application a-t-elle été implémentée ? | C16: 2024 | D16: 45387 | E16: =IF(TRIM(B16)="","",IF(TRIM(C16)="",0,1)) -> 1 | G16: =IF(AND(TRIM(B16)<>"",TRIM(C16)<>""),IF((2024-C16)<=5,10,IF((2024-C16)<=10,2,0)),"") -> 10 | H16: =IF(AND(TRIM(B16)<>"",TRIM(C16)<>""),10,"") -> 10
B17: =IF(C2="Oui existant","Qui l'a implémenté ?",IF(AND(C7<>"Non prévu",C7<>""),"Qui doit l'implémenter ?","")) -> Qui l'a implémenté ? | C17: JMR Infotech | E17: =IF(TRIM(B17)="","",IF(TRIM(C17)="",0,1)) -> 1
B18: =IF(C2="Oui existant","Quels sont les processus fonctionnels couverts ?",IF(AND(C7<>"Non prévu",C7<>""),"Quels sont les processus fonctionnels qui doivent être couverts ?","")) -> Quels sont les processus fonctionnels couverts ? | C18: Gestion des • Stratégies de • Actions de recouvrement • Négociations et règlements : • Calcul des pénalités | E18: =IF(TRIM(B18)="","",IF(TRIM(C18)="",0,1)) -> 1 | H18: =IF(AND(TRIM(B18)<>"",TRIM(C18)<>""),10,"") -> 10
B19: =IF(C2="Oui existant","Est-ce que la solution est integrée au CBS ?",IF(AND(C7<>"Non prévu",C7<>""),"Est-ce que la solution sera integrée au CBS ?","")) -> Est-ce que la solution est integrée au CBS ? | C19: Oui | E19: =IF(TRIM(B19)="","",IF(TRIM(C19)="",0,1)) -> 1 | G19: =IF(AND(TRIM(B19)<>"",TRIM(C19)<>""),IF(C19="Oui",20,0),"") -> 20 | H19: =IF(AND(TRIM(B19)<>"",TRIM(C19)<>""),20,"") -> 20
B20: =IF(C19="Oui",IF(C2="Oui existant","Comment et quels sont les processus et données qui transitent ?",IF(AND(C7<>"Non prévu",C7<>""),"Comment et quels seront les processus et données qui vont transiter ?","")),"") -> Comment et quels sont les processus et données qui transitent ? | C20: NON | E20: =IF(TRIM(B20)="","",IF(TRIM(C20)="",0,1)) -> 1 | I20: Très haut | J20: 0
B21: =IF(C2="Oui existant","Quel est le niveau de personnalisation de l’Application ?",IF(C7="COTS","Quel est le niveau de personnalisation prévu de l’Application ?","")) -> Quel est le niveau de personnalisation de l’Application ? | C21: Très haut | E21: =IF(TRIM(B21)="","",IF(TRIM(C21)="",0,1)) -> 1 | G21: =IF(AND(TRIM(B21)<>"",TRIM(C21)<>""),IF(ISNA(VLOOKUP(C21,I20:J24,2,0)),1,VLOOKUP(C21,I20:J24,2,0)),"") -> 0 | H21: =IF(AND(TRIM(B21)<>"",TRIM(C21)<>""),10,"") -> 10 | I21: Haut | J21: 2
B22: =IF(C2="Oui existant","Quelle(s) technologie(s) sous-jacente(s) ?","") -> Quelle(s) technologie(s) sous-jacente(s) ? | C22: NON | E22: =IF(TRIM(B22)="","",IF(TRIM(C22)="",0,1)) -> 1 | I22: Moyen | J22: 5
